Workbook
Name __Complete_Materials: Materials!$M$12
Name __Variance_Materials: Materials!$O$12
Name _Change_Order_Labor_Dollar_Est___Labor_Projection: 'Labor Projection'!$P$12
Name _Current_Labor_Dollar_Estimate__Labor_Projection: 'Labor Projection'!$Q$12
Name _Current_Labor_Dollar_Estimate__NTPLH: 'Labor Projection'!$Q$16
Name _Est____Hour__Labor_Projection: 'Labor Projection'!$V$12
Name _Est__Total_Labor__Labor_Projection: 'Labor Projection'!$T$12
Name _Est__Total_Labor__NTPLH: 'Labor Projection'!$T$16
Name _Est_Labor_to_Complete_Labor_Projection: 'Labor Projection'!$S$12
Name _Est_Labor_to_Complete_NTPLH: 'Labor Projection'!$S$16
Name _JTD____Hr__Labor_Projection: 'Labor Projection'!$W$12
Name _JTD_Labor_Cost__Labor_Projection: 'Labor Projection'!$R$12
Name _JTD_Labor_Cost__NTPLH: 'Labor Projection'!$R$16
Name _Original_Labor_Dollar_Est___Labor_Projection: 'Labor Projection'!$O$12
Name _TOTAL_LABOR_HOURS__ContractStatus: #REF!
Name _Under____Over____Labor_Projection: 'Labor Projection'!$X$12
Name _Under____Over___Labor_Projection: 'Labor Projection'!$U$12
Name _Under____Over__Labor_Projection: 'Labor Projection'!$N$12
Name _Under__Over_NTPLH: 'Labor Projection'!$U$16
Name ABC_NTPLH: 'Labor Projection'!$B$16
Name Actual_Composite_rate_dashboard: Sheet7!$V$5
Name Actual_Gross_Margin_dashboard: Sheet7!$J$5
Name Actual_Manhour_dashboard: Sheet7!$I$5
Name AR_Aged_Current_dashboard: Sheet7!$X$5
Name ARAged130days_dashboard: Sheet7!$Y$5
Name ARAged3160days_dashboard: Sheet7!$Z$5
Name ARAged6190days_dashboard: Sheet7!$AA$5
Name ARAgedover90days_dashboard: Sheet7!$AB$5
Name Base_Hrs_to_Complete_Labor_Projection: 'Labor Projection'!$I$12
Name Base_Hrs_to_Complete_NTPLH: 'Labor Projection'!$I$16
Name bid_day_Labor_Performance_Factor_dashboard: Sheet7!$M$5
Name Bid_day_Labor_Performance_Factor_Labor_Performance: 'Labor Performance'!$F$3
Name Change_Order_Hours_Estimate_Labor_Projection: 'Labor Projection'!$E$12
Name Change_Order_Hours_Estimate_NTPLH: 'Labor Projection'!$E$16
Name Change_Order_Labor_Dollar_Est__NTPLH: 'Labor Projection'!$P$16
Name Change_Orders_Estimate_Materials: Materials!$F$12
Name CO_Date_ContractStatus: #REF!
Name Composite_Rate_ContractStatus: #REF!
Name Composite_Rate_Variance_dashboard: Sheet7!$W$5
Name Cost_Type_Labor_Projection: 'Labor Projection'!$C$12
Name Cost_Type_Materials: Materials!$B$12
Name CostType1_Materials: Materials!$C$12
Name Current_Estimate_Materials: Materials!$G$12
Name Current_Labor_Hours_Estimate_Labor_Projection: 'Labor Projection'!$F$12
Name Current_Labor_Hours_Estimate_NTPLH: 'Labor Projection'!$F$16
Name Current_Labor_Performance_Factor_dashboard: Sheet7!$H$5
Name Department_dashboard: Sheet7!$C$5
Name Description_ContractStatus: #REF!
Name EOPeriodDate_dashboard: Sheet7!$E$5
Name EOPeriodDate_Labor_Performance: 'Labor Performance'!$C$3
Name Est____Complete_Labor_Projection: 'Labor Projection'!$H$12
Name Est____Complete_NTPLH: 'Labor Projection'!$H$16
Name Est____Hour_NTPLH: 'Labor Projection'!$V$16
Name Est_CompleteATYE_dashboard: Sheet7!$N$5
Name Estimated___Complete___YE_Block26: Summary!$J$42
Name Estimated___Complete___YE_Block28: Summary!$J$42
Name Estimated_Composite_Rate_dashboard: Sheet7!$U$5
Name Estimated_Future_Costs_Materials: Materials!$K$12
Name Estimated_Gross_Margin_dashboard: Sheet7!$G$5
Name Estimated_Manhours_dashboard: Sheet7!$F$5

Sheet Query
A1: WITH
A2: subqueryTable0 AS (
A3: SELECT DISTINCT
A4: table0.Company_Code AS Company_Code,
A5: table0.Job_Number AS Job_Number,
A6: table0.Phase_Code AS Phase_Code,
A7: table0.Cost_Type AS Cost_Type,
A8: table0.Description AS Description,
A9: table0.Phase_Job_Number AS Phase_Job_Number,
A10: table0.Cost_Center AS Cost_Center,
A11: table0.Status_Code AS Status_Code
A12: FROM
... A593: AND maintable.Phase_Job_Number = subqueryTable25.Job_Number)

Sheet Summary
H1: Job Name | J1: JOINT RESERVE BASE HANGAR
H9: Job No. | J9: 643700
H10: Project Manager | J10: J RAMOS
H11: Report Date | J11: 2026-01-07
H12: As of Date
F15: Revised Contract | G15: Notice to Proceed | H15: Pending | I15: Pending Contract | J15: Projected | K15: Variance | L15: Prior Month Variance
A16: Revenue | F16: {=#REF!} -> #REF! | G16: {=#REF!} -> #REF! | H16: {=#REF!} -> #REF! | I16: =F16+G16 -> #REF! | J16: {=#REF!} -> #REF! | K16: =ROUND(J16-I16,2) -> #REF! | L16: =DATA!B8-J16 -> #REF!
A18: Labor | F18: {=#REF!} -> #REF! | G18: {=#REF!} -> #REF! | H18: {=#REF!} -> #REF! | I18: =F18+G18 -> #REF! | J18: {='Labor Projection'!T10} -> 0 | K18: =ROUND(J18-I18,2) -> #REF! | L18: =DATA!C8-J18 -> 0
A19: Burden | F19: {=#REF!} -> #REF! | G19: {=#REF!} -> #REF! | H19: {=#REF!} -> #REF! | I19: =F19+G19 -> #REF! | J19: =('Labor Projection'!I10*'Labor Projection'!N1)+'Manpower Projection'!J16 -> #DIV/0! | K19: =ROUND(J19-I19,2) -> #DIV/0! | L19: =DATA!D8-J19 -> #DIV/0!
A20: Material / Subcontracts | F20: {=#REF!} -> #REF! | G20: {=#REF!} -> #REF! | H20: {=#REF!} -> #REF! | I20: =F20+G20 -> #REF! | J20: {=Materials!L3} -> 473279.63 | K20: =ROUND(J20-I20,2) -> #REF! | L20: =DATA!E8-J20 -> -473279.63
A21: DJE / Other | F21: {=#REF!} -> #REF! | G21: {=#REF!} -> #REF! | H21: {=#REF!} -> #REF! | I21: =F21+G21 -> #REF! | J21: {=Materials!L4} -> 29087.91 | K21: =ROUND(J21-I21,2) -> #REF! | L21: =DATA!F8-J21 -> -29087.91
A22: Total Cost | F22: =SUM(F18:F21) -> #REF! | G22: =SUM(G18:G21) -> #REF! | H22: =SUM(H18:H21) -> #REF! | I22: =SUM(I18:I21) -> #REF! | J22: =SUM(J18:J21) -> #DIV/0! | K22: =SUM(K18:K21) -> #REF! | L22: =SUM(L18:L21)-J22 -> #DIV/0!
A24: Profit | F24: =F16-F22 -> #REF! | G24: =G16-G22 -> #REF! | H24: =H16-H22 -> #REF! | I24: =I16-I22 -> #REF! | J24: =J16-J22 -> #REF! | K24: =K16-K22 -> #REF! | L24: =DATA!B8-SUM(DATA!C8:F8)-J24 -> #REF!
A25: Profit % on Cost | F25: =F24/F22 -> #REF! | G25: =G24/G22 -> #REF! | H25: =H24/H22 -> #REF! | I25: =I24/I22 -> #REF! | J25: =J24/J22 -> #REF! | K25: =ROUND(Summary!J25-Summary!I25,2) -> #REF! | L25: =DATA!G8-J25 -> #REF!
A26: Profit % on Rev | F26: =IF(F16=0,0,F24/F16) -> #REF! | G26: =IF(G16=0,0,G24/G16) -> #REF! | H26: =IF(H16=0,0,H24/H16) -> #REF! | I26: =ROUND(IF(I16=0,0,I24/I16),2) -> #REF! | J26: =ROUND(IF(J16=0,0,J24/J16),2) -> #REF! | K26: =IF(K16=0,0,K24/K16) -> #REF! | L26: =IF(L16=0,0,L24/L16) -> #REF!
A28: FINANCIAL AND OPERATIONAL DASHBOARD FOR THIS REPORTING PERIOD
A29: Over/ (Under) Billings | I29: Project Cash to Cost Position
A30: JTD Gross Billings $ | F30: None | I30: JTD Collected $ | J30: None
A31: JTD Revenue $ | F31: None | I31: JTD Cost $ | J31: =Materials!H10+'Manpower Projection'!K16 -> 24375.4
A32: Over/ (Under) Billing $ | F32: =F30-F31 -> #VALUE! | I32: Net Cash Position $ | J32: =J30-J31 -> #VALUE!
A33: As of Date: | F33: 2025-12-31 | I33: As of Date: | J33: 2025-12-31
A35: Composite Rate Analysis | I35: Labor Performance Factor | L35: Prior Month
A36: Composite Rate (Est.) | F36: =ROUND(#REF!,2) -> #REF! | I36: Earned MH's | J36: =ROUND('Labor Projection'!F10*'Labor Projection'!H10,2) -> #REF! | K36: =J36*F36 -> #REF! | L36: =J36-DATA!H8 -> #REF! | M36: =K36-(DATA!J8*DATA!H8) -> #REF!
A37: Composite Rate (Act.) | F37: =ROUND('Labor Projection'!R10/'Labor Projection'!G10,2) -> 51.69 | I37: Actual MH's | J37: =ROUND('Labor Projection'!G10,2) -> 290 | K37: =J37*F37 -> 14990.1 | L37: =J37-DATA!I8 -> 290 | M37: =K37-(DATA!K8*DATA!I8) -> 14990.1
A38: Composite Rate Var | F38: =F36-F37 -> #REF! | I38: Labor Performance Factor | J38: =J36/J37 -> #REF! | K38: =K36/K37 -> #REF! | L38: =L36/L37 -> #REF! | M38: =M36/M37 -> #REF!
A39: As of Date: | F39: 2025-12-31 | I39: As of Date: | J39: 2025-12-31
A41: A/R Aged Open Items | I41: Estimated % Complete @ YE value | J41: 0.03
A42: Current | F42: None
A43: 1-30 Days | F43: None | I43: Bid day Labor Performance Factor
A44: 31-60 Days | F44: None
A45: 61-90 Days | F45: None
A46: Over 90 Days | F46: None
A47: Last Billing Date | F47: NaT
A49: NOTES REGARDING SCHEDULE, JOB PROGRESS, CONCERNS:

Sheet Manpower Projection
F1: JOINT RESERVE BASE HANGAR
M3: Burden Cost | N3: Labor Cost | O3: Total Hours
J4: 9240.130000000 | M4: =SUM(#REF!) -> #REF! | N4: =SUM(#REF!) -> #REF! | O4: =SUM(#REF!) -> #REF!
F10: Projection Labor & Burden
F12: Job Projection
F13: Projection Labor Rate | I13: =I17/H17 -> #DIV/0!
F14: Projection L&B Rate | I14: =(I17+J17)/H17 -> #DIV/0!
F15: Week Ending: | H15: Total Hrs | I15: Labor Cost | J15: Burden Cost | K15: Total Cost | L15: Labor / Hr | M15: L&B / Hr
F16: Job to Date | H16: {=IF('Manpower Projection'!J4="None",'Manpower Projection'!O4,'Labor Projection'!G10)} -> 290 | I16: {=IF('Manpower Projection'!J4="None",'Manpower Projection'!N4,'Labor Projection'!R10)} -> 14989.17 | J16: =IF('Manpower Projection'!J4="None",'Manpower Projection'!M4,'Manpower Projection'!J4) -> 9240.130000000 | K16: =I16+J16 -> 24229.3 | L16: =ROUND(I16/H16,2) -> 51.69 | M16: =K16/H16 -> 83.54931
F17: Projection to Complete | H17: {=K25} -> 0 | I17: =H17*N25 -> 0 | J17: =(H17*O25)-I17 -> 0 | K17: =H17*I14 -> #DIV/0! | L17: =I17/H17 -> #DIV/0! | M17: =K17/H17 -> #DIV/0!
F19: Total Projection | H19: =H16+H17 -> 290 | I19: =I16+I17 -> 14989.17 | J19: =J16+J17 -> 9240.13 | K19: =K16+K17 -> #DIV/0! | L19: =I19/H19 -> 51.686793 | M19: =K19/H19 -> #DIV/0!
F20: Bid + Change Orders | H20: =#REF! -> #REF! | I20: =#REF! -> #REF! | J20: =#REF! -> #REF! | K20: =I20+J20 -> #REF! | L20: =I20/H20 -> #REF! | M20: =K20/H20 -> #REF! | O20: ='Manpower Projection'!H16 -> 290
F21: Variance | H21: =H19-H20 -> #REF! | I21: =I19-I20 -> #REF! | J21: =J19-J20 -> #REF! | K21: =K19-K20 -> #DIV/0! | L21: =L19-L20 -> #REF! | M21: =M19-M20 -> #DIV/0!
H24: Average Crew | I24: Ave Hrs | J24: Ave Days | K24: Total Hrs | L24: Labor Projection | M24: Delta | N24: Avg Composite Rate | O24: Avg L&B Rate
F25: Manpower Projection | H25: =AVERAGE('Manpower Projection'!H29:H5000) -> 4.5454545 | I25: =AVERAGE('Manpower Projection'!I29:I5000) -> 10 | J25: =AVERAGE('Manpower Projection'!J29:J5000) -> 4 | K25: =SUMIF('Manpower Projection'!G29:G5000,"",'Manpower Projection'!K29:K5000) -> 0 | L25: ='Labor Projection'!L10 -> 12624.476 | M25: =K25-L25 -> -12624.476 | N25: =N27/H27 -> 51.69 | O25: =O27/H27 -> 83.54931
F27: Grand Total | G27: - | H27: =SUBTOTAL(9,H29:H528) -> 50 | I27: =SUBTOTAL(9,I29:I528) -> 110 | J27: =SUBTOTAL(9,J29:J528) -> 44 | K27: =SUBTOTAL(9,K29:K528) -> 2000 | L27: - | M27: - | N27: =SUBTOTAL(9,N29:N528) -> 2584.5 | O27: =SUBTOTAL(9,O29:O528) -> 4177.4655
F28: Week ending: | G28: Actual Manpower | H28: Estimated Manpower | I28: Hours/Day | J28: Days/Week | K28: Total Hours | L28: Composite Rate | M28: L&B Rate | N28: Avg Composite Rate | O28: Avg L&B Rate
F29: 45968 | K29: =IFERROR('Manpower Projection'!H29*'Manpower Projection'!I29*'Manpower Projection'!J29,0) -> 0 | L29: {='Manpower Projection'!$L$16} -> 51.69 | M29: ='Manpower Projection'!$M$16 -> 83.54931 | N29: =IFERROR('Manpower Projection'!H29*'Manpower Projection'!L29,"") -> 0 | O29: =IFERROR('Manpower Projection'!M29*'Manpower Projection'!H29,"") -> 0
F30: 45975 | K30: =IFERROR('Manpower Projection'!H30*'Manpower Projection'!I30*'Manpower Projection'!J30,0) -> 0 | L30: {='Manpower Projection'!$L$16} -> 51.69 | M30: ='Manpower Projection'!$M$16 -> 83.54931 | N30: =IFERROR('Manpower Projection'!H30*'Manpower Projection'!L30,"") -> 0 | O30: =IFERROR('Manpower Projection'!M30*'Manpower Projection'!H30,"") -> 0
F31: 45982 | K31: =IFERROR('Manpower Projection'!H31*'Manpower Projection'!I31*'Manpower Projection'!J31,0) -> 0 | L31: {='Manpower Projection'!$L$16} -> 51.69 | M31: ='Manpower Projection'!$M$16 -> 83.54931 | N31: =IFERROR('Manpower Projection'!H31*'Manpower Projection'!L31,"") -> 0 | O31: =IFERROR('Manpower Projection'!M31*'Manpower Projection'!H31,"") -> 0
F32: 45989 | G32: 2 | H32: 2 | I32: 10 | J32: 4 | K32: =IFERROR('Manpower Projection'!H32*'Manpower Projection'!I32*'Manpower Projection'!J32,0) -> 80 | L32: {='Manpower Projection'!$L$16} -> 51.69 | M32: ='Manpower Projection'!$M$16 -> 83.54931 | N32: =IFERROR('Manpower Projection'!H32*'Manpower Projection'!L32,"") -> 103.38 | O32: =IFERROR('Manpower Projection'!M32*'Manpower Projection'!H32,"") -> 167.09862
F33: 45996 | G33: 2 | H33: 2 | I33: 10 | J33: 4 | K33: =IFERROR('Manpower Projection'!H33*'Manpower Projection'!I33*'Manpower Projection'!J33,0) -> 80 | L33: {='Manpower Projection'!$L$16} -> 51.69 | M33: ='Manpower Projection'!$M$16 -> 83.54931 | N33: =IFERROR('Manpower Projection'!H33*'Manpower Projection'!L33,"") -> 103.38 | O33: =IFERROR('Manpower Projection'!M33*'Manpower Projection'!H33,"") -> 167.09862
F34: 46003 | G34: 2 | H34: 2 | I34: 10 | J34: 4 | K34: =IFERROR('Manpower Projection'!H34*'Manpower Projection'!I34*'Manpower Projection'!J34,0) -> 80 | L34: {='Manpower Projection'!$L$16} -> 51.69 | M34: ='Manpower Projection'!$M$16 -> 83.54931 | N34: =IFERROR('Manpower Projection'!H34*'Manpower Projection'!L34,"") -> 103.38 | O34: =IFERROR('Manpower Projection'!M34*'Manpower Projection'!H34,"") -> 167.09862
F35: 46010 | G35: 2 | H35: 2 | I35: 10 | J35: 4 | K35: =IFERROR('Manpower Projection'!H35*'Manpower Projection'!I35*'Manpower Projection'!J35,0) -> 80 | L35: {='Manpower Projection'!$L$16} -> 51.69 | M35: ='Manpower Projection'!$M$16 -> 83.54931 | N35: =IFERROR('Manpower Projection'!H35*'Manpower Projection'!L35,"") -> 103.38 | O35: =IFERROR('Manpower Projection'!M35*'Manpower Projection'!H35,"") -> 167.09862
F36: 46017 | G36: 6 | H36: 6 | I36: 10 | J36: 4 | K36: =IFERROR('Manpower Projection'!H36*'Manpower Projection'!I36*'Manpower Projection'!J36,0) -> 240 | L36: {='Manpower Projection'!$L$16} -> 51.69 | M36: ='Manpower Projection'!$M$16 -> 83.54931 | N36: =IFERROR('Manpower Projection'!H36*'Manpower Projection'!L36,"") -> 310.14 | O36: =IFERROR('Manpower Projection'!M36*'Manpower Projection'!H36,"") -> 501.29586
F37: 46024 | G37: 6 | H37: 6 | I37: 10 | J37: 4 | K37: =IFERROR('Manpower Projection'!H37*'Manpower Projection'!I37*'Manpower Projection'!J37,0) -> 240 | L37: {='Manpower Projection'!$L$16} -> 51.69 | M37: ='Manpower Projection'!$M$16 -> 83.54931 | N37: =IFERROR('Manpower Projection'!H37*'Manpower Projection'!L37,"") -> 310.14 | O37: =IFERROR('Manpower Projection'!M37*'Manpower Projection'!H37,"") -> 501.29586
F38: 46031 | G38: 6 | H38: 6 | I38: 10 | J38: 4 | K38: =IFERROR('Manpower Projection'!H38*'Manpower Projection'!I38*'Manpower Projection'!J38,0) -> 240 | L38: {='Manpower Projection'!$L$16} -> 51.69 | M38: ='Manpower Projection'!$M$16 -> 83.54931 | N38: =IFERROR('Manpower Projection'!H38*'Manpower Projection'!L38,"") -> 310.14 | O38: =IFERROR('Manpower Projection'!M38*'Manpower Projection'!H38,"") -> 501.29586
F39: 46038 | G39: 6 | H39: 6 | I39: 10 | J39: 4 | K39: =IFERROR('Manpower Projection'!H39*'Manpower Projection'!I39*'Manpower Projection'!J39,0) -> 240 | L39: {='Manpower Projection'!$L$16} -> 51.69 | M39: ='Manpower Projection'!$M$16 -> 83.54931 | N39: =IFERROR('Manpower Projection'!H39*'Manpower Projection'!L39,"") -> 310.14 | O39: =IFERROR('Manpower Projection'!M39*'Manpower Projection'!H39,"") -> 501.29586
F40: 46045 | G40: 6 | H40: 6 | I40: 10 | J40: 4 | K40: =IFERROR('Manpower Projection'!H40*'Manpower Projection'!I40*'Manpower Projection'!J40,0) -> 240 | L40: {='Manpower Projection'!$L$16} -> 51.69 | M40: ='Manpower Projection'!$M$16 -> 83.54931 | N40: =IFERROR('Manpower Projection'!H40*'Manpower Projection'!L40,"") -> 310.14 | O40: =IFERROR('Manpower Projection'!M40*'Manpower Projection'!H40,"") -> 501.29586
F41: 46052 | G41: 6 | H41: 6 | I41: 10 | J41: 4 | K41: =IFERROR('Manpower Projection'!H41*'Manpower Projection'!I41*'Manpower Projection'!J41,0) -> 240 | L41: {='Manpower Projection'!$L$16} -> 51.69 | M41: ='Manpower Projection'!$M$16 -> 83.54931 | N41: =IFERROR('Manpower Projection'!H41*'Manpower Projection'!L41,"") -> 310.14 | O41: =IFERROR('Manpower Projection'!M41*'Manpower Projection'!H41,"") -> 501.29586
F42: 46059 | G42: 6 | H42: 6 | I42: 10 | J42: 4 | K42: =IFERROR('Manpower Projection'!H42*'Manpower Projection'!I42*'Manpower Projection'!J42,0) -> 240 | L42: {='Manpower Projection'!$L$16} -> 51.69 | M42: ='Manpower Projection'!$M$16 -> 83.54931 | N42: =IFERROR('Manpower Projection'!H42*'Manpower Projection'!L42,"") -> 310.14 | O42: =IFERROR('Manpower Projection'!M42*'Manpower Projection'!H42,"") -> 501.29586
F43: 46066 | K43: =IFERROR('Manpower Projection'!H43*'Manpower Projection'!I43*'Manpower Projection'!J43,0) -> 0 | L43: {='Manpower Projection'!$L$16} -> 51.69 | M43: ='Manpower Projection'!$M$16 -> 83.54931 | N43: =IFERROR('Manpower Projection'!H43*'Manpower Projection'!L43,"") -> 0 | O43: =IFERROR('Manpower Projection'!M43*'Manpower Projection'!H43,"") -> 0
F44: 46073 | K44: =IFERROR('Manpower Projection'!H44*'Manpower Projection'!I44*'Manpower Projection'!J44,0) -> 0 | L44: {='Manpower Projection'!$L$16} -> 51.69 | M44: ='Manpower Projection'!$M$16 -> 83.54931 | N44: =IFERROR('Manpower Projection'!H44*'Manpower Projection'!L44,"") -> 0 | O44: =IFERROR('Manpower Projection'!M44*'Manpower Projection'!H44,"") -> 0
F45: 46080 | K45: =IFERROR('Manpower Projection'!H45*'Manpower Projection'!I45*'Manpower Projection'!J45,0) -> 0 | L45: {='Manpower Projection'!$L$16} -> 51.69 | M45: ='Manpower Projection'!$M$16 -> 83.54931 | N45: =IFERROR('Manpower Projection'!H45*'Manpower Projection'!L45,"") -> 0 | O45: =IFERROR('Manpower Projection'!M45*'Manpower Projection'!H45,"") -> 0
F46: 46087 | K46: =IFERROR('Manpower Projection'!H46*'Manpower Projection'!I46*'Manpower Projection'!J46,0) -> 0 | L46: {='Manpower Projection'!$L$16} -> 51.69 | M46: ='Manpower Projection'!$M$16 -> 83.54931 | N46: =IFERROR('Manpower Projection'!H46*'Manpower Projection'!L46,"") -> 0 | O46: =IFERROR('Manpower Projection'!M46*'Manpower Projection'!H46,"") -> 0
F47: 46094 | K47: =IFERROR('Manpower Projection'!H47*'Manpower Projection'!I47*'Manpower Projection'!J47,0) -> 0 | L47: {='Manpower Projection'!$L$16} -> 51.69 | M47: ='Manpower Projection'!$M$16 -> 83.54931 | N47: =IFERROR('Manpower Projection'!H47*'Manpower Projection'!L47,"") -> 0 | O47: =IFERROR('Manpower Projection'!M47*'Manpower Projection'!H47,"") -> 0
F48: 46101 | K48: =IFERROR('Manpower Projection'!H48*'Manpower Projection'!I48*'Manpower Projection'!J48,0) -> 0 | L48: {='Manpower Projection'!$L$16} -> 51.69 | M48: ='Manpower Projection'!$M$16 -> 83.54931 | N48: =IFERROR('Manpower Projection'!H48*'Manpower Projection'!L48,"") -> 0 | O48: =IFERROR('Manpower Projection'!M48*'Manpower Projection'!H48,"") -> 0
F49: 46108 | K49: =IFERROR('Manpower Projection'!H49*'Manpower Projection'!I49*'Manpower Projection'!J49,0) -> 0 | L49: {='Manpower Projection'!$L$16} -> 51.69 | M49: ='Manpower Projection'!$M$16 -> 83.54931 | N49: =IFERROR('Manpower Projection'!H49*'Manpower Projection'!L49,"") -> 0 | O49: =IFERROR('Manpower Projection'!M49*'Manpower Projection'!H49,"") -> 0
F50: 46115 | K50: =IFERROR('Manpower Projection'!H50*'Manpower Projection'!I50*'Manpower Projection'!J50,0) -> 0 | L50: {='Manpower Projection'!$L$16} -> 51.69 | M50: ='Manpower Projection'!$M$16 -> 83.54931 | N50: =IFERROR('Manpower Projection'!H50*'Manpower Projection'!L50,"") -> 0 | O50: =IFERROR('Manpower Projection'!M50*'Manpower Projection'!H50,"") -> 0
F51: 46122 | K51: =IFERROR('Manpower Projection'!H51*'Manpower Projection'!I51*'Manpower Projection'!J51,0) -> 0 | L51: {='Manpower Projection'!$L$16} -> 51.69 | M51: ='Manpower Projection'!$M$16 -> 83.54931 | N51: =IFERROR('Manpower Projection'!H51*'Manpower Projection'!L51,"") -> 0 | O51: =IFERROR('Manpower Projection'!M51*'Manpower Projection'!H51,"") -> 0
F52: 46129 | K52: =IFERROR('Manpower Projection'!H52*'Manpower Projection'!I52*'Manpower Projection'!J52,0) -> 0 | L52: {='Manpower Projection'!$L$16} -> 51.69 | M52: ='Manpower Projection'!$M$16 -> 83.54931 | N52: =IFERROR('Manpower Projection'!H52*'Manpower Projection'!L52,"") -> 0 | O52: =IFERROR('Manpower Projection'!M52*'Manpower Projection'!H52,"") -> 0
F53: 46136 | K53: =IFERROR('Manpower Projection'!H53*'Manpower Projection'!I53*'Manpower Projection'!J53,0) -> 0 | L53: {='Manpower Projection'!$L$16} -> 51.69 | M53: ='Manpower Projection'!$M$16 -> 83.54931 | N53: =IFERROR('Manpower Projection'!H53*'Manpower Projection'!L53,"") -> 0 | O53: =IFERROR('Manpower Projection'!M53*'Manpower Projection'!H53,"") -> 0
F54: 46143 | K54: =IFERROR('Manpower Projection'!H54*'Manpower Projection'!I54*'Manpower Projection'!J54,0) -> 0 | L54: {='Manpower Projection'!$L$16} -> 51.69 | M54: ='Manpower Projection'!$M$16 -> 83.54931 | N54: =IFERROR('Manpower Projection'!H54*'Manpower Projection'!L54,"") -> 0 | O54: =IFERROR('Manpower Projection'!M54*'Manpower Projection'!H54,"") -> 0
... F89: 46388 | K89: =IFERROR('Manpower Projection'!H89*'Manpower Projection'!I89*'Manpower Projection'!J89,0) -> 0 | L89: {='Manpower Projection'!$L$16} -> 51.69 | M89: ='Manpower Projection'!$M$16 -> 83.54931 | N89: =IFERROR('Manpower Projection'!H89*'Manpower Projection'!L89,"") -> 0 | O89: =IFERROR('Manpower Projection'!M89*'Manpower Projection'!H89,"") -> 0
K90: =IFERROR('Manpower Projection'!H90*'Manpower Projection'!I90*'Manpower Projection'!J90,0) -> 0 | L90: {='Manpower Projection'!$L$16} -> 51.69 | M90: ='Manpower Projection'!$M$16 -> 83.54931 | N90: =IFERROR('Manpower Projection'!H90*'Manpower Projection'!L90,"") -> 0 | O90: =IFERROR('Manpower Projection'!M90*'Manpower Projection'!H90,"") -> 0
K91: =IFERROR('Manpower Projection'!H91*'Manpower Projection'!I91*'Manpower Projection'!J91,0) -> 0 | L91: {='Manpower Projection'!$L$16} -> 51.69 | M91: ='Manpower Projection'!$M$16 -> 83.54931 | N91: =IFERROR('Manpower Projection'!H91*'Manpower Projection'!L91,"") -> 0 | O91: =IFERROR('Manpower Projection'!M91*'Manpower Projection'!H91,"") -> 0
K92: =IFERROR('Manpower Projection'!H92*'Manpower Projection'!I92*'Manpower Projection'!J92,0) -> 0 | L92: {='Manpower Projection'!$L$16} -> 51.69 | M92: ='Manpower Projection'!$M$16 -> 83.54931 | N92: =IFERROR('Manpower Projection'!H92*'Manpower Projection'!L92,"") -> 0 | O92: =IFERROR('Manpower Projection'!M92*'Manpower Projection'!H92,"") -> 0
K93: =IFERROR('Manpower Projection'!H93*'Manpower Projection'!I93*'Manpower Projection'!J93,0) -> 0 | L93: {='Manpower Projection'!$L$16} -> 51.69 | M93: ='Manpower Projection'!$M$16 -> 83.54931 | N93: =IFERROR('Manpower Projection'!H93*'Manpower Projection'!L93,"") -> 0 | O93: =IFERROR('Manpower Projection'!M93*'Manpower Projection'!H93,"") -> 0
K94: =IFERROR('Manpower Projection'!H94*'Manpower Projection'!I94*'Manpower Projection'!J94,0) -> 0 | L94: {='Manpower Projection'!$L$16} -> 51.69 | M94: ='Manpower Projection'!$M$16 -> 83.54931 | N94: =IFERROR('Manpower Projection'!H94*'Manpower Projection'!L94,"") -> 0 | O94: =IFERROR('Manpower Projection'!M94*'Manpower Projection'!H94,"") -> 0
K95: =IFERROR('Manpower Projection'!H95*'Manpower Projection'!I95*'Manpower Projection'!J95,0) -> 0 | L95: {='Manpower Projection'!$L$16} -> 51.69 | M95: ='Manpower Projection'!$M$16 -> 83.54931 | N95: =IFERROR('Manpower Projection'!H95*'Manpower Projection'!L95,"") -> 0 | O95: =IFERROR('Manpower Projection'!M95*'Manpower Projection'!H95,"") -> 0
K96: =IFERROR('Manpower Projection'!H96*'Manpower Projection'!I96*'Manpower Projection'!J96,0) -> 0 | L96: {='Manpower Projection'!$L$16} -> 51.69 | M96: ='Manpower Projection'!$M$16 -> 83.54931 | N96: =IFERROR('Manpower Projection'!H96*'Manpower Projection'!L96,"") -> 0 | O96: =IFERROR('Manpower Projection'!M96*'Manpower Projection'!H96,"") -> 0
K97: =IFERROR('Manpower Projection'!H97*'Manpower Projection'!I97*'Manpower Projection'!J97,0) -> 0 | L97: {='Manpower Projection'!$L$16} -> 51.69 | M97: ='Manpower Projection'!$M$16 -> 83.54931 | N97: =IFERROR('Manpower Projection'!H97*'Manpower Projection'!L97,"") -> 0 | O97: =IFERROR('Manpower Projection'!M97*'Manpower Projection'!H97,"") -> 0
K98: =IFERROR('Manpower Projection'!H98*'Manpower Projection'!I98*'Manpower Projection'!J98,0) -> 0 | L98: {='Manpower Projection'!$L$16} -> 51.69 | M98: ='Manpower Projection'!$M$16 -> 83.54931 | N98: =IFERROR('Manpower Projection'!H98*'Manpower Projection'!L98,"") -> 0 | O98: =IFERROR('Manpower Projection'!M98*'Manpower Projection'!H98,"") -> 0
K99: =IFERROR('Manpower Projection'!H99*'Manpower Projection'!I99*'Manpower Projection'!J99,0) -> 0 | L99: {='Manpower Projection'!$L$16} -> 51.69 | M99: ='Manpower Projection'!$M$16 -> 83.54931 | N99: =IFERROR('Manpower Projection'!H99*'Manpower Projection'!L99,"") -> 0 | O99: =IFERROR('Manpower Projection'!M99*'Manpower Projection'!H99,"") -> 0
K100: =IFERROR('Manpower Projection'!H100*'Manpower Projection'!I100*'Manpower Projection'!J100,0) -> 0 | L100: {='Manpower Projection'!$L$16} -> 51.69 | M100: ='Manpower Projection'!$M$16 -> 83.54931 | N100: =IFERROR('Manpower Projection'!H100*'Manpower Projection'!L100,"") -> 0 | O100: =IFERROR('Manpower Projection'!M100*'Manpower Projection'!H100,"") -> 0
K101: =IFERROR('Manpower Projection'!H101*'Manpower Projection'!I101*'Manpower Projection'!J101,0) -> 0 | L101: {='Manpower Projection'!$L$16} -> 51.69 | M101: ='Manpower Projection'!$M$16 -> 83.54931 | N101: =IFERROR('Manpower Projection'!H101*'Manpower Projection'!L101,"") -> 0 | O101: =IFERROR('Manpower Projection'!M101*'Manpower Projection'!H101,"") -> 0
... K528: =IFERROR('Manpower Projection'!H528*'Manpower Projection'!I528*'Manpower Projection'!J528,0) -> 0 | L528: {='Manpower Projection'!$L$16} -> 51.69 | M528: ='Manpower Projection'!$M$16 -> 83.54931 | N528: =IFERROR('Manpower Projection'!H528*'Manpower Projection'!L528,"") -> 0 | O528: =IFERROR('Manpower Projection'!M528*'Manpower Projection'!H528,"") -> 0

Sheet Labor Projection
B1: JOINT RESERVE BASE HANGAR | H1: ='Manpower Projection'!M25 -> -12624.476 | I1: Projected Composite Rate: | K1: {='Manpower Projection'!I13} -> #DIV/0! | L1: Projected Burden Rate: | N1: ='Manpower Projection'!I14-'Manpower Projection'!I13 -> #DIV/0!
B2: Job to Date Labor
A3: Final | B3: 12 | C3: 2025 | D3: 2025-12-31
D10: =SUM(LaborProj[Original Hours Estimate])+SUM(NTPLH[Original Hours Estimate]) -> 12878 | E10: =SUM(LaborProj[Change Order Hours Estimate])+SUM(NTPLH[Change Order Hours Estimate]) -> 0 | F10: =SUM(LaborProj[Current Labor Hours Estimate])+SUM(NTPLH[Current Labor Hours Estimate]) -> #REF! | G10: =SUM(LaborProj[JTD Hours])+SUM(NTPLH[JTD Hours]) -> 290 | H10: =IFERROR(G10/M10,0) -> 0.022455422 | I10: =SUM(LaborProj[Base Hrs to Complete])+SUM(NTPLH[Base Hrs to Complete]) -> 12624.476 | K10: =SUM(LaborProj[Productivity Hours])+SUM(NTPLH[Productivity Hours]) -> 0 | L10: =SUM(LaborProj[Projected Hrs to Complete])+SUM(NTPLH[Projected Hrs to Complete]) -> 12624.476 | M10: =SUM(LaborProj[Total Hrs])+SUM(NTPLH[Total Hrs]) -> 12914.476 | N10: =SUM(LaborProj[(Under) / Over ])+SUM(NTPLH[(Under) / Over]) -> 36.475796 | O10: =SUM(LaborProj[ Original Labor Dollar Est. ])+SUM(NTPLH[Original Labor Dollar Est.]) -> 508684 | P10: =SUM(LaborProj[ Change Order Labor Dollar Est. ])+SUM(NTPLH[Change Order Labor Dollar Est.]) -> 0 | Q10: =SUM(LaborProj[[ Current Labor Dollar Estimate ]])+SUM(NTPLH[[ Current Labor Dollar Estimate ]]) -> #REF! | R10: =SUM(LaborProj[[ JTD Labor Cost ]])+SUM(NTPLH[[ JTD Labor Cost ]]) -> 14989.17 | S10: =SUM(LaborProj[[ Est Labor to Complete]])+SUM(NTPLH[[ Est Labor to Complete]]) -> 0 | T10: =SUM(LaborProj[ Est. Total Labor ])+SUM(NTPLH[ Est. Total Labor ]) -> 0 | U10: =SUM(LaborProj[(Under) / Over ])+SUM(NTPLH[(Under)/Over]) -> 0 | V10: =SUM(LaborProj[ Est. $/Hour ])+SUM(NTPLH[Est. $/Hour]) -> 790.00852 | W10: =SUM(LaborProj[ JTD $/ Hr ])+SUM(NTPLH[JTD $/ Hr]) -> 211.51135 | X10: =SUM(LaborProj[(Under) / Over ])+SUM(NTPLH[(Under) / Over2]) -> -578.49716
B11: Phase | C11: Cost Type | D11: Original Hours Estimate | E11: Change Order Hours Estimate | F11: Current Labor Hours Estimate | G11: JTD Hours | H11: Est. % Complete | I11: Base Hrs to Complete | J11: Productivity Factor | K11: Productivity Hours | L11: Projected Hrs to Complete | M11: Total Hrs | N11: (Under) / Over | O11: Original Labor Dollar Est. | P11: Change Order Labor Dollar Est. | Q11: Current Labor Dollar Estimate | R11: JTD Labor Cost | S11: Est Labor to Complete | T11: Est. Total Labor | U11: (Under) / Over | V11: Est. $/Hour | W11: JTD $/ Hr | X11: (Under) / Over | Y11: CostType | Z11: PhaseCenter
B12: 00300321 - PROJECT ENGINEER | C12: L | D12: 0 | E12: =IFERROR('Labor Projection'!F12-'Labor Projection'!D12,"") -> 0 | F12: 0 | G12: 16 | I12: =IFERROR(IF('Labor Projection'!H12=0,'Labor Projection'!F12,(('Labor Projection'!G12/'Labor Projection'!H12)-'Labor Projection'!G12)),"") -> 0 | K12: =IFERROR('Labor Projection'!I12*'Labor Projection'!J12,"") -> 0 | L12: =IFERROR('Labor Projection'!I12+'Labor Projection'!K12,"") -> 0 | M12: =IFERROR('Labor Projection'!L12+'Labor Projection'!G12,"") -> 16 | N12: =IFERROR('Labor Projection'!M12-'Labor Projection'!F12,"") -> 16 | O12: 0 | P12: =IFERROR('Labor Projection'!Q12-'Labor Projection'!O12,"") -> 0 | Q12: 0 | R12: 901.6 | S12: =IFERROR('Labor Projection'!L12*'Labor Projection'!$K$1,"") | T12: =IFERROR('Labor Projection'!R12+'Labor Projection'!S12,"") | U12: =IFERROR('Labor Projection'!T12-'Labor Projection'!Q12,"") | V12: =IFERROR(IF('Labor Projection'!D12=0,0,'Labor Projection'!O12/'Labor Projection'!D12),"") -> 0 | W12: =IFERROR(IF('Labor Projection'!G12=0,0,'Labor Projection'!R12/'Labor Projection'!G12),"") -> 56.35 | X12: =IFERROR('Labor Projection'!W12-'Labor Projection'!V12,"") -> 56.35 | Y12: L | Z12: 0050301000
B13: 00300321 - PROJECT ENGINEER | C13: LA | D13: 0 | E13: =IFERROR('Labor Projection'!F13-'Labor Projection'!D13,"") -> 0 | F13: 0 | I13: =IFERROR(IF('Labor Projection'!H13=0,'Labor Projection'!F13,(('Labor Projection'!G13/'Labor Projection'!H13)-'Labor Projection'!G13)),"") -> 0 | K13: =IFERROR('Labor Projection'!I13*'Labor Projection'!J13,"") -> 0 | L13: =IFERROR('Labor Projection'!I13+'Labor Projection'!K13,"") -> 0 | M13: =IFERROR('Labor Projection'!L13+'Labor Projection'!G13,"") -> 0 | N13: =IFERROR('Labor Projection'!M13-'Labor Projection'!F13,"") -> 0 | O13: 0 | P13: =IFERROR('Labor Projection'!Q13-'Labor Projection'!O13,"") -> 0 | Q13: 0 | S13: =IFERROR('Labor Projection'!L13*'Labor Projection'!$K$1,"") | T13: =IFERROR('Labor Projection'!R13+'Labor Projection'!S13,"") | U13: =IFERROR('Labor Projection'!T13-'Labor Projection'!Q13,"") | V13: =IFERROR(IF('Labor Projection'!D13=0,0,'Labor Projection'!O13/'Labor Projection'!D13),"") -> 0 | W13: =IFERROR(IF('Labor Projection'!G13=0,0,'Labor Projection'!R13/'Labor Projection'!G13),"") -> 0 | X13: =IFERROR('Labor Projection'!W13-'Labor Projection'!V13,"") -> 0 | Y13: LA | Z13: 0050301000
B14: 00300321 - PROJECT ENGINEER | C14: LB | D14: 0 | E14: =IFERROR('Labor Projection'!F14-'Labor Projection'!D14,"") -> 0 | F14: 0 | I14: =IFERROR(IF('Labor Projection'!H14=0,'Labor Projection'!F14,(('Labor Projection'!G14/'Labor Projection'!H14)-'Labor Projection'!G14)),"") -> 0 | K14: =IFERROR('Labor Projection'!I14*'Labor Projection'!J14,"") -> 0 | L14: =IFERROR('Labor Projection'!I14+'Labor Projection'!K14,"") -> 0 | M14: =IFERROR('Labor Projection'!L14+'Labor Projection'!G14,"") -> 0 | N14: =IFERROR('Labor Projection'!M14-'Labor Projection'!F14,"") -> 0 | O14: 0 | P14: =IFERROR('Labor Projection'!Q14-'Labor Projection'!O14,"") -> 0 | Q14: 0 | S14: =IFERROR('Labor Projection'!L14*'Labor Projection'!$K$1,"") | T14: =IFERROR('Labor Projection'!R14+'Labor Projection'!S14,"") | U14: =IFERROR('Labor Projection'!T14-'Labor Projection'!Q14,"") | V14: =IFERROR(IF('Labor Projection'!D14=0,0,'Labor Projection'!O14/'Labor Projection'!D14),"") -> 0 | W14: =IFERROR(IF('Labor Projection'!G14=0,0,'Labor Projection'!R14/'Labor Projection'!G14),"") -> 0 | X14: =IFERROR('Labor Projection'!W14-'Labor Projection'!V14,"") -> 0 | Y14: LB | Z14: 0050301000
B15: 00300321 - PROJECT ENGINEER | C15: LD | D15: 0 | E15: =IFERROR('Labor Projection'!F15-'Labor Projection'!D15,"") -> 0 | F15: 0 | I15: =IFERROR(IF('Labor Projection'!H15=0,'Labor Projection'!F15,(('Labor Projection'!G15/'Labor Projection'!H15)-'Labor Projection'!G15)),"") -> 0 | K15: =IFERROR('Labor Projection'!I15*'Labor Projection'!J15,"") -> 0 | L15: =IFERROR('Labor Projection'!I15+'Labor Projection'!K15,"") -> 0 | M15: =IFERROR('Labor Projection'!L15+'Labor Projection'!G15,"") -> 0 | N15: =IFERROR('Labor Projection'!M15-'Labor Projection'!F15,"") -> 0 | O15: 0 | P15: =IFERROR('Labor Projection'!Q15-'Labor Projection'!O15,"") -> 0 | Q15: 0 | S15: =IFERROR('Labor Projection'!L15*'Labor Projection'!$K$1,"") | T15: =IFERROR('Labor Projection'!R15+'Labor Projection'!S15,"") | U15: =IFERROR('Labor Projection'!T15-'Labor Projection'!Q15,"") | V15: =IFERROR(IF('Labor Projection'!D15=0,0,'Labor Projection'!O15/'Labor Projection'!D15),"") -> 0 | W15: =IFERROR(IF('Labor Projection'!G15=0,0,'Labor Projection'!R15/'Labor Projection'!G15),"") -> 0 | X15: =IFERROR('Labor Projection'!W15-'Labor Projection'!V15,"") -> 0 | Y15: LD | Z15: 0050301000
B16: 00300321 - PROJECT ENGINEER | C16: LM | D16: 0 | E16: =IFERROR('Labor Projection'!F16-'Labor Projection'!D16,"") -> 0 | F16: 0 | I16: =IFERROR(IF('Labor Projection'!H16=0,'Labor Projection'!F16,(('Labor Projection'!G16/'Labor Projection'!H16)-'Labor Projection'!G16)),"") -> 0 | K16: =IFERROR('Labor Projection'!I16*'Labor Projection'!J16,"") -> 0 | L16: =IFERROR('Labor Projection'!I16+'Labor Projection'!K16,"") -> 0 | M16: =IFERROR('Labor Projection'!L16+'Labor Projection'!G16,"") -> 0 | N16: =IFERROR('Labor Projection'!M16-'Labor Projection'!F16,"") -> 0 | O16: 0 | P16: =IFERROR('Labor Projection'!Q16-'Labor Projection'!O16,"") -> 0 | Q16: 0 | S16: =IFERROR('Labor Projection'!L16*'Labor Projection'!$K$1,"") | T16: =IFERROR('Labor Projection'!R16+'Labor Projection'!S16,"") | U16: =IFERROR('Labor Projection'!T16-'Labor Projection'!Q16,"") | V16: =IFERROR(IF('Labor Projection'!D16=0,0,'Labor Projection'!O16/'Labor Projection'!D16),"") -> 0 | W16: =IFERROR(IF('Labor Projection'!G16=0,0,'Labor Projection'!R16/'Labor Projection'!G16),"") -> 0 | X16: =IFERROR('Labor Projection'!W16-'Labor Projection'!V16,"") -> 0 | Y16: LM | Z16: 0050301000
B17: 00400000 - ALL LABOR | C17: L | D17: 0 | E17: =IFERROR('Labor Projection'!F17-'Labor Projection'!D17,"") -> 0 | F17: 0 | I17: =IFERROR(IF('Labor Projection'!H17=0,'Labor Projection'!F17,(('Labor Projection'!G17/'Labor Projection'!H17)-'Labor Projection'!G17)),"") -> 0 | K17: =IFERROR('Labor Projection'!I17*'Labor Projection'!J17,"") -> 0 | L17: =IFERROR('Labor Projection'!I17+'Labor Projection'!K17,"") -> 0 | M17: =IFERROR('Labor Projection'!L17+'Labor Projection'!G17,"") -> 0 | N17: =IFERROR('Labor Projection'!M17-'Labor Projection'!F17,"") -> 0 | O17: 0 | P17: =IFERROR('Labor Projection'!Q17-'Labor Projection'!O17,"") -> 0 | Q17: 0 | S17: =IFERROR('Labor Projection'!L17*'Labor Projection'!$K$1,"") | T17: =IFERROR('Labor Projection'!R17+'Labor Projection'!S17,"") | U17: =IFERROR('Labor Projection'!T17-'Labor Projection'!Q17,"") | V17: =IFERROR(IF('Labor Projection'!D17=0,0,'Labor Projection'!O17/'Labor Projection'!D17),"") -> 0 | W17: =IFERROR(IF('Labor Projection'!G17=0,0,'Labor Projection'!R17/'Labor Projection'!G17),"") -> 0 | X17: =IFERROR('Labor Projection'!W17-'Labor Projection'!V17,"") -> 0 | Y17: L | Z17: 0050301000
B18: 00400000 - ALL LABOR | C18: LA | D18: 0 | E18: =IFERROR('Labor Projection'!F18-'Labor Projection'!D18,"") -> 0 | F18: 0 | I18: =IFERROR(IF('Labor Projection'!H18=0,'Labor Projection'!F18,(('Labor Projection'!G18/'Labor Projection'!H18)-'Labor Projection'!G18)),"") -> 0 | K18: =IFERROR('Labor Projection'!I18*'Labor Projection'!J18,"") -> 0 | L18: =IFERROR('Labor Projection'!I18+'Labor Projection'!K18,"") -> 0 | M18: =IFERROR('Labor Projection'!L18+'Labor Projection'!G18,"") -> 0 | N18: =IFERROR('Labor Projection'!M18-'Labor Projection'!F18,"") -> 0 | O18: 0 | P18: =IFERROR('Labor Projection'!Q18-'Labor Projection'!O18,"") -> 0 | Q18: 0 | S18: =IFERROR('Labor Projection'!L18*'Labor Projection'!$K$1,"") | T18: =IFERROR('Labor Projection'!R18+'Labor Projection'!S18,"") | U18: =IFERROR('Labor Projection'!T18-'Labor Projection'!Q18,"") | V18: =IFERROR(IF('Labor Projection'!D18=0,0,'Labor Projection'!O18/'Labor Projection'!D18),"") -> 0 | W18: =IFERROR(IF('Labor Projection'!G18=0,0,'Labor Projection'!R18/'Labor Projection'!G18),"") -> 0 | X18: =IFERROR('Labor Projection'!W18-'Labor Projection'!V18,"") -> 0 | Y18: LA | Z18: 0050301000
B19: 00400000 - ALL LABOR | C19: LB | D19: 0 | E19: =IFERROR('Labor Projection'!F19-'Labor Projection'!D19,"") -> 0 | F19: 0 | I19: =IFERROR(IF('Labor Projection'!H19=0,'Labor Projection'!F19,(('Labor Projection'!G19/'Labor Projection'!H19)-'Labor Projection'!G19)),"") -> 0 | K19: =IFERROR('Labor Projection'!I19*'Labor Projection'!J19,"") -> 0 | L19: =IFERROR('Labor Projection'!I19+'Labor Projection'!K19,"") -> 0 | M19: =IFERROR('Labor Projection'!L19+'Labor Projection'!G19,"") -> 0 | N19: =IFERROR('Labor Projection'!M19-'Labor Projection'!F19,"") -> 0 | O19: 0 | P19: =IFERROR('Labor Projection'!Q19-'Labor Projection'!O19,"") -> 0 | Q19: 0 | S19: =IFERROR('Labor Projection'!L19*'Labor Projection'!$K$1,"") | T19: =IFERROR('Labor Projection'!R19+'Labor Projection'!S19,"") | U19: =IFERROR('Labor Projection'!T19-'Labor Projection'!Q19,"") | V19: =IFERROR(IF('Labor Projection'!D19=0,0,'Labor Projection'!O19/'Labor Projection'!D19),"") -> 0 | W19: =IFERROR(IF('Labor Projection'!G19=0,0,'Labor Projection'!R19/'Labor Projection'!G19),"") -> 0 | X19: =IFERROR('Labor Projection'!W19-'Labor Projection'!V19,"") -> 0 | Y19: LB | Z19: 0050301000
B20: 00400000 - ALL LABOR | C20: LD | D20: 0 | E20: =IFERROR('Labor Projection'!F20-'Labor Projection'!D20,"") -> 0 | F20: 0 | I20: =IFERROR(IF('Labor Projection'!H20=0,'Labor Projection'!F20,(('Labor Projection'!G20/'Labor Projection'!H20)-'Labor Projection'!G20)),"") -> 0 | K20: =IFERROR('Labor Projection'!I20*'Labor Projection'!J20,"") -> 0 | L20: =IFERROR('Labor Projection'!I20+'Labor Projection'!K20,"") -> 0 | M20: =IFERROR('Labor Projection'!L20+'Labor Projection'!G20,"") -> 0 | N20: =IFERROR('Labor Projection'!M20-'Labor Projection'!F20,"") -> 0 | O20: 0 | P20: =IFERROR('Labor Projection'!Q20-'Labor Projection'!O20,"") -> 0 | Q20: 0 | S20: =IFERROR('Labor Projection'!L20*'Labor Projection'!$K$1,"") | T20: =IFERROR('Labor Projection'!R20+'Labor Projection'!S20,"") | U20: =IFERROR('Labor Projection'!T20-'Labor Projection'!Q20,"") | V20: =IFERROR(IF('Labor Projection'!D20=0,0,'Labor Projection'!O20/'Labor Projection'!D20),"") -> 0 | W20: =IFERROR(IF('Labor Projection'!G20=0,0,'Labor Projection'!R20/'Labor Projection'!G20),"") -> 0 | X20: =IFERROR('Labor Projection'!W20-'Labor Projection'!V20,"") -> 0 | Y20: LD | Z20: 0050301000
B21: 00400000 - ALL LABOR | C21: LM | D21: 0 | E21: =IFERROR('Labor Projection'!F21-'Labor Projection'!D21,"") -> 0 | F21: 0 | I21: =IFERROR(IF('Labor Projection'!H21=0,'Labor Projection'!F21,(('Labor Projection'!G21/'Labor Projection'!H21)-'Labor Projection'!G21)),"") -> 0 | K21: =IFERROR('Labor Projection'!I21*'Labor Projection'!J21,"") -> 0 | L21: =IFERROR('Labor Projection'!I21+'Labor Projection'!K21,"") -> 0 | M21: =IFERROR('Labor Projection'!L21+'Labor Projection'!G21,"") -> 0 | N21: =IFERROR('Labor Projection'!M21-'Labor Projection'!F21,"") -> 0 | O21: 0 | P21: =IFERROR('Labor Projection'!Q21-'Labor Projection'!O21,"") -> 0 | Q21: 0 | S21: =IFERROR('Labor Projection'!L21*'Labor Projection'!$K$1,"") | T21: =IFERROR('Labor Projection'!R21+'Labor Projection'!S21,"") | U21: =IFERROR('Labor Projection'!T21-'Labor Projection'!Q21,"") | V21: =IFERROR(IF('Labor Projection'!D21=0,0,'Labor Projection'!O21/'Labor Projection'!D21),"") -> 0 | W21: =IFERROR(IF('Labor Projection'!G21=0,0,'Labor Projection'!R21/'Labor Projection'!G21),"") -> 0 | X21: =IFERROR('Labor Projection'!W21-'Labor Projection'!V21,"") -> 0 | Y21: LM | Z21: 0050301000
B22: 00400401 - LIGHT FIXTURES | C22: L | D22: 752 | E22: =IFERROR('Labor Projection'!F22-'Labor Projection'!D22,"") -> 0 | F22: 752 | I22: =IFERROR(IF('Labor Projection'!H22=0,'Labor Projection'!F22,(('Labor Projection'!G22/'Labor Projection'!H22)-'Labor Projection'!G22)),"") -> 752 | K22: =IFERROR('Labor Projection'!I22*'Labor Projection'!J22,"") -> 0 | L22: =IFERROR('Labor Projection'!I22+'Labor Projection'!K22,"") -> 752 | M22: =IFERROR('Labor Projection'!L22+'Labor Projection'!G22,"") -> 752 | N22: =IFERROR('Labor Projection'!M22-'Labor Projection'!F22,"") -> 0 | O22: 29704 | P22: =IFERROR('Labor Projection'!Q22-'Labor Projection'!O22,"") -> 0 | Q22: 29704 | S22: =IFERROR('Labor Projection'!L22*'Labor Projection'!$K$1,"") | T22: =IFERROR('Labor Projection'!R22+'Labor Projection'!S22,"") | U22: =IFERROR('Labor Projection'!T22-'Labor Projection'!Q22,"") | V22: =IFERROR(IF('Labor Projection'!D22=0,0,'Labor Projection'!O22/'Labor Projection'!D22),"") -> 39.5 | W22: =IFERROR(IF('Labor Projection'!G22=0,0,'Labor Projection'!R22/'Labor Projection'!G22),"") -> 0 | X22: =IFERROR('Labor Projection'!W22-'Labor Projection'!V22,"") -> -39.5 | Y22: L | Z22: 0050301000
B23: 00400403 - BW- LIGHTING- ABOVE CEILI | C23: L | D23: 2600 | E23: =IFERROR('Labor Projection'!F23-'Labor Projection'!D23,"") -> 0 | F23: 2600 | I23: =IFERROR(IF('Labor Projection'!H23=0,'Labor Projection'!F23,(('Labor Projection'!G23/'Labor Projection'!H23)-'Labor Projection'!G23)),"") -> 2600 | K23: =IFERROR('Labor Projection'!I23*'Labor Projection'!J23,"") -> 0 | L23: =IFERROR('Labor Projection'!I23+'Labor Projection'!K23,"") -> 2600 | M23: =IFERROR('Labor Projection'!L23+'Labor Projection'!G23,"") -> 2600 | N23: =IFERROR('Labor Projection'!M23-'Labor Projection'!F23,"") -> 0 | O23: 102700 | P23: =IFERROR('Labor Projection'!Q23-'Labor Projection'!O23,"") -> 0 | Q23: 102700 | S23: =IFERROR('Labor Projection'!L23*'Labor Projection'!$K$1,"") | T23: =IFERROR('Labor Projection'!R23+'Labor Projection'!S23,"") | U23: =IFERROR('Labor Projection'!T23-'Labor Projection'!Q23,"") | V23: =IFERROR(IF('Labor Projection'!D23=0,0,'Labor Projection'!O23/'Labor Projection'!D23),"") -> 39.5 | W23: =IFERROR(IF('Labor Projection'!G23=0,0,'Labor Projection'!R23/'Labor Projection'!G23),"") -> 0 | X23: =IFERROR('Labor Projection'!W23-'Labor Projection'!V23,"") -> -39.5 | Y23: L | Z23: 0050301000
B24: 00400404 - WIRING DEVICES- LIGHTING | C24: L | D24: 229 | E24: =IFERROR('Labor Projection'!F24-'Labor Projection'!D24,"") -> 0 | F24: 229 | I24: =IFERROR(IF('Labor Projection'!H24=0,'Labor Projection'!F24,(('Labor Projection'!G24/'Labor Projection'!H24)-'Labor Projection'!G24)),"") -> 229 | K24: =IFERROR('Labor Projection'!I24*'Labor Projection'!J24,"") -> 0 | L24: =IFERROR('Labor Projection'!I24+'Labor Projection'!K24,"") -> 229 | M24: =IFERROR('Labor Projection'!L24+'Labor Projection'!G24,"") -> 229 | N24: =IFERROR('Labor Projection'!M24-'Labor Projection'!F24,"") -> 0 | O24: 9046 | P24: =IFERROR('Labor Projection'!Q24-'Labor Projection'!O24,"") -> 0 | Q24: 9046 | S24: =IFERROR('Labor Projection'!L24*'Labor Projection'!$K$1,"") | T24: =IFERROR('Labor Projection'!R24+'Labor Projection'!S24,"") | U24: =IFERROR('Labor Projection'!T24-'Labor Projection'!Q24,"") | V24: =IFERROR(IF('Labor Projection'!D24=0,0,'Labor Projection'!O24/'Labor Projection'!D24),"") -> 39.502183 | W24: =IFERROR(IF('Labor Projection'!G24=0,0,'Labor Projection'!R24/'Labor Projection'!G24),"") -> 0 | X24: =IFERROR('Labor Projection'!W24-'Labor Projection'!V24,"") -> -39.502183 | Y24: L | Z24: 0050301000
... B26: 00400408 - GEAR | C26: L | D26: 331 | E26: =IFERROR('Labor Projection'!F26-'Labor Projection'!D26,"") -> 0 | F26: 331 | I26: =IFERROR(IF('Labor Projection'!H26=0,'Labor Projection'!F26,(('Labor Projection'!G26/'Labor Projection'!H26)-'Labor Projection'!G26)),"") -> 331 | K26: =IFERROR('Labor Projection'!I26*'Labor Projection'!J26,"") -> 0 | L26: =IFERROR('Labor Projection'!I26+'Labor Projection'!K26,"") -> 331 | M26: =IFERROR('Labor Projection'!L26+'Labor Projection'!G26,"") -> 331 | N26: =IFERROR('Labor Projection'!M26-'Labor Projection'!F26,"") -> 0 | O26: 13075 | P26: =IFERROR('Labor Projection'!Q26-'Labor Projection'!O26,"") -> 0 | Q26: 13075 | S26: =IFERROR('Labor Projection'!L26*'Labor Projection'!$K$1,"") | T26: =IFERROR('Labor Projection'!R26+'Labor Projection'!S26,"") | U26: =IFERROR('Labor Projection'!T26-'Labor Projection'!Q26,"") | V26: =IFERROR(IF('Labor Projection'!D26=0,0,'Labor Projection'!O26/'Labor Projection'!D26),"") -> 39.501511 | W26: =IFERROR(IF('Labor Projection'!G26=0,0,'Labor Projection'!R26/'Labor Projection'!G26),"") -> 0 | X26: =IFERROR('Labor Projection'!W26-'Labor Projection'!V26,"") -> -39.501511 | Y26: L | Z26: 0050301000
B27: 00400409 - TEMPORARY | C27: L | D27: 360 | E27: =IFERROR('Labor Projection'!F27-'Labor Projection'!D27,"") -> 0 | F27: 360 | G27: 131 | H27: 0.36 | I27: =IFERROR(IF('Labor Projection'!H27=0,'Labor Projection'!F27,(('Labor Projection'!G27/'Labor Projection'!H27)-'Labor Projection'!G27)),"") -> 232.88889 | K27: =IFERROR('Labor Projection'!I27*'Labor Projection'!J27,"") -> 0 | L27: =IFERROR('Labor Projection'!I27+'Labor Projection'!K27,"") -> 232.88889 | M27: =IFERROR('Labor Projection'!L27+'Labor Projection'!G27,"") -> 363.88889 | N27: =IFERROR('Labor Projection'!M27-'Labor Projection'!F27,"") -> 3.8888889 | O27: 14220 | P27: =IFERROR('Labor Projection'!Q27-'Labor Projection'!O27,"") -> 0 | Q27: 14220 | R27: 6609.13 | S27: =IFERROR('Labor Projection'!L27*'Labor Projection'!$K$1,"") | T27: =IFERROR('Labor Projection'!R27+'Labor Projection'!S27,"") | U27: =IFERROR('Labor Projection'!T27-'Labor Projection'!Q27,"") | V27: =IFERROR(IF('Labor Projection'!D27=0,0,'Labor Projection'!O27/'Labor Projection'!D27),"") -> 39.5 | W27: =IFERROR(IF('Labor Projection'!G27=0,0,'Labor Projection'!R27/'Labor Projection'!G27),"") -> 50.451374 | X27: =IFERROR('Labor Projection'!W27-'Labor Projection'!V27,"") -> 10.951374 | Y27: L | Z27: 0050301000
B28: 00400413 - FIRE ALARM | C28: L | D28: 496 | E28: =IFERROR('Labor Projection'!F28-'Labor Projection'!D28,"") -> 0 | F28: 496 | I28: =IFERROR(IF('Labor Projection'!H28=0,'Labor Projection'!F28,(('Labor Projection'!G28/'Labor Projection'!H28)-'Labor Projection'!G28)),"") -> 496 | K28: =IFERROR('Labor Projection'!I28*'Labor Projection'!J28,"") -> 0 | L28: =IFERROR('Labor Projection'!I28+'Labor Projection'!K28,"") -> 496 | M28: =IFERROR('Labor Projection'!L28+'Labor Projection'!G28,"") -> 496 | N28: =IFERROR('Labor Projection'!M28-'Labor Projection'!F28,"") -> 0 | O28: 19592 | P28: =IFERROR('Labor Projection'!Q28-'Labor Projection'!O28,"") -> 0 | Q28: 19592 | S28: =IFERROR('Labor Projection'!L28*'Labor Projection'!$K$1,"") | T28: =IFERROR('Labor Projection'!R28+'Labor Projection'!S28,"") | U28: =IFERROR('Labor Projection'!T28-'Labor Projection'!Q28,"") | V28: =IFERROR(IF('Labor Projection'!D28=0,0,'Labor Projection'!O28/'Labor Projection'!D28),"") -> 39.5 | W28: =IFERROR(IF('Labor Projection'!G28=0,0,'Labor Projection'!R28/'Labor Projection'!G28),"") -> 0 | X28: =IFERROR('Labor Projection'!W28-'Labor Projection'!V28,"") -> -39.5 | Y28: L | Z28: 0050301000
B29: 00400416 - DEMO | C29: L | D29: 180 | E29: =IFERROR('Labor Projection'!F29-'Labor Projection'!D29,"") -> 0 | F29: 180 | G29: 80 | H29: 0.443 | I29: =IFERROR(IF('Labor Projection'!H29=0,'Labor Projection'!F29,(('Labor Projection'!G29/'Labor Projection'!H29)-'Labor Projection'!G29)),"") -> 100.58691 | K29: =IFERROR('Labor Projection'!I29*'Labor Projection'!J29,"") -> 0 | L29: =IFERROR('Labor Projection'!I29+'Labor Projection'!K29,"") -> 100.58691 | M29: =IFERROR('Labor Projection'!L29+'Labor Projection'!G29,"") -> 180.58691 | N29: =IFERROR('Labor Projection'!M29-'Labor Projection'!F29,"") -> 0.58690745 | O29: 7110 | P29: =IFERROR('Labor Projection'!Q29-'Labor Projection'!O29,"") -> 0 | Q29: 7110 | R29: 4149.23 | S29: =IFERROR('Labor Projection'!L29*'Labor Projection'!$K$1,"") | T29: =IFERROR('Labor Projection'!R29+'Labor Projection'!S29,"") | U29: =IFERROR('Labor Projection'!T29-'Labor Projection'!Q29,"") | V29: =IFERROR(IF('Labor Projection'!D29=0,0,'Labor Projection'!O29/'Labor Projection'!D29),"") -> 39.5 | W29: =IFERROR(IF('Labor Projection'!G29=0,0,'Labor Projection'!R29/'Labor Projection'!G29),"") -> 51.865375 | X29: =IFERROR('Labor Projection'!W29-'Labor Projection'!V29,"") -> 12.365375 | Y29: L | Z29: 0050301000
B30: 00400417 - GROUNDING | C30: L | D30: 269 | E30: =IFERROR('Labor Projection'!F30-'Labor Projection'!D30,"") -> 0 | F30: 269 | I30: =IFERROR(IF('Labor Projection'!H30=0,'Labor Projection'!F30,(('Labor Projection'!G30/'Labor Projection'!H30)-'Labor Projection'!G30)),"") -> 269 | K30: =IFERROR('Labor Projection'!I30*'Labor Projection'!J30,"") -> 0 | L30: =IFERROR('Labor Projection'!I30+'Labor Projection'!K30,"") -> 269 | M30: =IFERROR('Labor Projection'!L30+'Labor Projection'!G30,"") -> 269 | N30: =IFERROR('Labor Projection'!M30-'Labor Projection'!F30,"") -> 0 | O30: 10626 | P30: =IFERROR('Labor Projection'!Q30-'Labor Projection'!O30,"") -> 0 | Q30: 10626 | S30: =IFERROR('Labor Projection'!L30*'Labor Projection'!$K$1,"") | T30: =IFERROR('Labor Projection'!R30+'Labor Projection'!S30,"") | U30: =IFERROR('Labor Projection'!T30-'Labor Projection'!Q30,"") | V30: =IFERROR(IF('Labor Projection'!D30=0,0,'Labor Projection'!O30/'Labor Projection'!D30),"") -> 39.501859 | W30: =IFERROR(IF('Labor Projection'!G30=0,0,'Labor Projection'!R30/'Labor Projection'!G30),"") -> 0 | X30: =IFERROR('Labor Projection'!W30-'Labor Projection'!V30,"") -> -39.501859 | Y30: L | Z30: 0050301000
B31: 00400418 - TECHNOLOGIES | C31: L | D31: 358 | E31: =IFERROR('Labor Projection'!F31-'Labor Projection'!D31,"") -> 0 | F31: 358 | I31: =IFERROR(IF('Labor Projection'!H31=0,'Labor Projection'!F31,(('Labor Projection'!G31/'Labor Projection'!H31)-'Labor Projection'!G31)),"") -> 358 | K31: =IFERROR('Labor Projection'!I31*'Labor Projection'!J31,"") -> 0 | L31: =IFERROR('Labor Projection'!I31+'Labor Projection'!K31,"") -> 358 | M31: =IFERROR('Labor Projection'!L31+'Labor Projection'!G31,"") -> 358 | N31: =IFERROR('Labor Projection'!M31-'Labor Projection'!F31,"") -> 0 | O31: 14141 | P31: =IFERROR('Labor Projection'!Q31-'Labor Projection'!O31,"") -> 0 | Q31: 14141 | S31: =IFERROR('Labor Projection'!L31*'Labor Projection'!$K$1,"") | T31: =IFERROR('Labor Projection'!R31+'Labor Projection'!S31,"") | U31: =IFERROR('Labor Projection'!T31-'Labor Projection'!Q31,"") | V31: =IFERROR(IF('Labor Projection'!D31=0,0,'Labor Projection'!O31/'Labor Projection'!D31),"") -> 39.5 | W31: =IFERROR(IF('Labor Projection'!G31=0,0,'Labor Projection'!R31/'Labor Projection'!G31),"") -> 0 | X31: =IFERROR('Labor Projection'!W31-'Labor Projection'!V31,"") -> -39.5 | Y31: L | Z31: 0050301000
B32: 00400419 - SUPERVISION | C32: L | D32: 1484 | E32: =IFERROR('Labor Projection'!F32-'Labor Projection'!D32,"") -> 0 | F32: 1484 | G32: 63 | H32: 0.042 | I32: =IFERROR(IF('Labor Projection'!H32=0,'Labor Projection'!F32,(('Labor Projection'!G32/'Labor Projection'!H32)-'Labor Projection'!G32)),"") -> 1437 | K32: =IFERROR('Labor Projection'!I32*'Labor Projection'!J32,"") -> 0 | L32: =IFERROR('Labor Projection'!I32+'Labor Projection'!K32,"") -> 1437 | M32: =IFERROR('Labor Projection'!L32+'Labor Projection'!G32,"") -> 1500 | N32: =IFERROR('Labor Projection'!M32-'Labor Projection'!F32,"") -> 16 | O32: 58618 | P32: =IFERROR('Labor Projection'!Q32-'Labor Projection'!O32,"") -> 0 | Q32: 58618 | R32: 3329.21 | S32: =IFERROR('Labor Projection'!L32*'Labor Projection'!$K$1,"") | T32: =IFERROR('Labor Projection'!R32+'Labor Projection'!S32,"") | U32: =IFERROR('Labor Projection'!T32-'Labor Projection'!Q32,"") | V32: =IFERROR(IF('Labor Projection'!D32=0,0,'Labor Projection'!O32/'Labor Projection'!D32),"") -> 39.5 | W32: =IFERROR(IF('Labor Projection'!G32=0,0,'Labor Projection'!R32/'Labor Projection'!G32),"") -> 52.844603 | X32: =IFERROR('Labor Projection'!W32-'Labor Projection'!V32,"") -> 13.344603 | Y32: L | Z32: 0050301000
B33: 00400420 - GENERATOR | C33: L | D33: 180 | E33: =IFERROR('Labor Projection'!F33-'Labor Projection'!D33,"") -> 0 | F33: 180 | I33: =IFERROR(IF('Labor Projection'!H33=0,'Labor Projection'!F33,(('Labor Projection'!G33/'Labor Projection'!H33)-'Labor Projection'!G33)),"") -> 180 | K33: =IFERROR('Labor Projection'!I33*'Labor Projection'!J33,"") -> 0 | L33: =IFERROR('Labor Projection'!I33+'Labor Projection'!K33,"") -> 180 | M33: =IFERROR('Labor Projection'!L33+'Labor Projection'!G33,"") -> 180 | N33: =IFERROR('Labor Projection'!M33-'Labor Projection'!F33,"") -> 0 | O33: 7110 | P33: =IFERROR('Labor Projection'!Q33-'Labor Projection'!O33,"") -> 0 | Q33: 7110 | S33: =IFERROR('Labor Projection'!L33*'Labor Projection'!$K$1,"") | T33: =IFERROR('Labor Projection'!R33+'Labor Projection'!S33,"") | U33: =IFERROR('Labor Projection'!T33-'Labor Projection'!Q33,"") | V33: =IFERROR(IF('Labor Projection'!D33=0,0,'Labor Projection'!O33/'Labor Projection'!D33),"") -> 39.5 | W33: =IFERROR(IF('Labor Projection'!G33=0,0,'Labor Projection'!R33/'Labor Projection'!G33),"") -> 0 | X33: =IFERROR('Labor Projection'!W33-'Labor Projection'!V33,"") -> -39.5 | Y33: L | Z33: 0050301000
B34: 00400421 - UG DISTIBUTION/DB | C34: L | D34: 400 | E34: =IFERROR('Labor Projection'!F34-'Labor Projection'!D34,"") -> 0 | F34: 400 | I34: =IFERROR(IF('Labor Projection'!H34=0,'Labor Projection'!F34,(('Labor Projection'!G34/'Labor Projection'!H34)-'Labor Projection'!G34)),"") -> 400 | K34: =IFERROR('Labor Projection'!I34*'Labor Projection'!J34,"") -> 0 | L34: =IFERROR('Labor Projection'!I34+'Labor Projection'!K34,"") -> 400 | M34: =IFERROR('Labor Projection'!L34+'Labor Projection'!G34,"") -> 400 | N34: =IFERROR('Labor Projection'!M34-'Labor Projection'!F34,"") -> 0 | O34: 15800 | P34: =IFERROR('Labor Projection'!Q34-'Labor Projection'!O34,"") -> 0 | Q34: 15800 | S34: =IFERROR('Labor Projection'!L34*'Labor Projection'!$K$1,"") | T34: =IFERROR('Labor Projection'!R34+'Labor Projection'!S34,"") | U34: =IFERROR('Labor Projection'!T34-'Labor Projection'!Q34,"") | V34: =IFERROR(IF('Labor Projection'!D34=0,0,'Labor Projection'!O34/'Labor Projection'!D34),"") -> 39.5 | W34: =IFERROR(IF('Labor Projection'!G34=0,0,'Labor Projection'!R34/'Labor Projection'!G34),"") -> 0 | X34: =IFERROR('Labor Projection'!W34-'Labor Projection'!V34,"") -> -39.5 | Y34: L | Z34: 0050301000
B35: 00400422 - MV CABLE | C35: L | D35: 360 | E35: =IFERROR('Labor Projection'!F35-'Labor Projection'!D35,"") -> 0 | F35: 360 | I35: =IFERROR(IF('Labor Projection'!H35=0,'Labor Projection'!F35,(('Labor Projection'!G35/'Labor Projection'!H35)-'Labor Projection'!G35)),"") -> 360 | K35: =IFERROR('Labor Projection'!I35*'Labor Projection'!J35,"") -> 0 | L35: =IFERROR('Labor Projection'!I35+'Labor Projection'!K35,"") -> 360 | M35: =IFERROR('Labor Projection'!L35+'Labor Projection'!G35,"") -> 360 | N35: =IFERROR('Labor Projection'!M35-'Labor Projection'!F35,"") -> 0 | O35: 14220 | P35: =IFERROR('Labor Projection'!Q35-'Labor Projection'!O35,"") -> 0 | Q35: 14220 | S35: =IFERROR('Labor Projection'!L35*'Labor Projection'!$K$1,"") | T35: =IFERROR('Labor Projection'!R35+'Labor Projection'!S35,"") | U35: =IFERROR('Labor Projection'!T35-'Labor Projection'!Q35,"") | V35: =IFERROR(IF('Labor Projection'!D35=0,0,'Labor Projection'!O35/'Labor Projection'!D35),"") -> 39.5 | W35: =IFERROR(IF('Labor Projection'!G35=0,0,'Labor Projection'!R35/'Labor Projection'!G35),"") -> 0 | X35: =IFERROR('Labor Projection'!W35-'Labor Projection'!V35,"") -> -39.5 | Y35: L | Z35: 0050301000
B36: 00400423 - MV TERMINATIONS | C36: L | D36: 88 | E36: =IFERROR('Labor Projection'!F36-'Labor Projection'!D36,"") -> 0 | F36: 88 | I36: =IFERROR(IF('Labor Projection'!H36=0,'Labor Projection'!F36,(('Labor Projection'!G36/'Labor Projection'!H36)-'Labor Projection'!G36)),"") -> 88 | K36: =IFERROR('Labor Projection'!I36*'Labor Projection'!J36,"") -> 0 | L36: =IFERROR('Labor Projection'!I36+'Labor Projection'!K36,"") -> 88 | M36: =IFERROR('Labor Projection'!L36+'Labor Projection'!G36,"") -> 88 | N36: =IFERROR('Labor Projection'!M36-'Labor Projection'!F36,"") -> 0 | O36: 3476 | P36: =IFERROR('Labor Projection'!Q36-'Labor Projection'!O36,"") -> 0 | Q36: 3476 | S36: =IFERROR('Labor Projection'!L36*'Labor Projection'!$K$1,"") | T36: =IFERROR('Labor Projection'!R36+'Labor Projection'!S36,"") | U36: =IFERROR('Labor Projection'!T36-'Labor Projection'!Q36,"") | V36: =IFERROR(IF('Labor Projection'!D36=0,0,'Labor Projection'!O36/'Labor Projection'!D36),"") -> 39.5 | W36: =IFERROR(IF('Labor Projection'!G36=0,0,'Labor Projection'!R36/'Labor Projection'!G36),"") -> 0 | X36: =IFERROR('Labor Projection'!W36-'Labor Projection'!V36,"") -> -39.5 | Y36: L | Z36: 0050301000
B37: 00400424 - START UP & COMMISIONING | C37: L | D37: 80 | E37: =IFERROR('Labor Projection'!F37-'Labor Projection'!D37,"") -> 0 | F37: 80 | I37: =IFERROR(IF('Labor Projection'!H37=0,'Labor Projection'!F37,(('Labor Projection'!G37/'Labor Projection'!H37)-'Labor Projection'!G37)),"") -> 80 | K37: =IFERROR('Labor Projection'!I37*'Labor Projection'!J37,"") -> 0 | L37: =IFERROR('Labor Projection'!I37+'Labor Projection'!K37,"") -> 80 | M37: =IFERROR('Labor Projection'!L37+'Labor Projection'!G37,"") -> 80 | N37: =IFERROR('Labor Projection'!M37-'Labor Projection'!F37,"") -> 0 | O37: 3160 | P37: =IFERROR('Labor Projection'!Q37-'Labor Projection'!O37,"") -> 0 | Q37: 3160 | S37: =IFERROR('Labor Projection'!L37*'Labor Projection'!$K$1,"") | T37: =IFERROR('Labor Projection'!R37+'Labor Projection'!S37,"") | U37: =IFERROR('Labor Projection'!T37-'Labor Projection'!Q37,"") | V37: =IFERROR(IF('Labor Projection'!D37=0,0,'Labor Projection'!O37/'Labor Projection'!D37),"") -> 39.5 | W37: =IFERROR(IF('Labor Projection'!G37=0,0,'Labor Projection'!R37/'Labor Projection'!G37),"") -> 0 | X37: =IFERROR('Labor Projection'!W37-'Labor Projection'!V37,"") -> -39.5 | Y37: L | Z37: 0050301000
B38: 00400425 - PUNCHLIST | C38: L | D38: 120 | E38: =IFERROR('Labor Projection'!F38-'Labor Projection'!D38,"") -> 0 | F38: 120 | I38: =IFERROR(IF('Labor Projection'!H38=0,'Labor Projection'!F38,(('Labor Projection'!G38/'Labor Projection'!H38)-'Labor Projection'!G38)),"") -> 120 | K38: =IFERROR('Labor Projection'!I38*'Labor Projection'!J38,"") -> 0 | L38: =IFERROR('Labor Projection'!I38+'Labor Projection'!K38,"") -> 120 | M38: =IFERROR('Labor Projection'!L38+'Labor Projection'!G38,"") -> 120 | N38: =IFERROR('Labor Projection'!M38-'Labor Projection'!F38,"") -> 0 | O38: 4740 | P38: =IFERROR('Labor Projection'!Q38-'Labor Projection'!O38,"") -> 0 | Q38: 4740 | S38: =IFERROR('Labor Projection'!L38*'Labor Projection'!$K$1,"") | T38: =IFERROR('Labor Projection'!R38+'Labor Projection'!S38,"") | U38: =IFERROR('Labor Projection'!T38-'Labor Projection'!Q38,"") | V38: =IFERROR(IF('Labor Projection'!D38=0,0,'Labor Projection'!O38/'Labor Projection'!D38),"") -> 39.5 | W38: =IFERROR(IF('Labor Projection'!G38=0,0,'Labor Projection'!R38/'Labor Projection'!G38),"") -> 0 | X38: =IFERROR('Labor Projection'!W38-'Labor Projection'!V38,"") -> -39.5 | Y38: L | Z38: 0050301000
B39: 00401402 - BW- POWER- HOMERUNS | C39: L | D39: 641 | E39: =IFERROR('Labor Projection'!F39-'Labor Projection'!D39,"") -> 0 | F39: 641 | I39: =IFERROR(IF('Labor Projection'!H39=0,'Labor Projection'!F39,(('Labor Projection'!G39/'Labor Projection'!H39)-'Labor Projection'!G39)),"") -> 641 | K39: =IFERROR('Labor Projection'!I39*'Labor Projection'!J39,"") -> 0 | L39: =IFERROR('Labor Projection'!I39+'Labor Projection'!K39,"") -> 641 | M39: =IFERROR('Labor Projection'!L39+'Labor Projection'!G39,"") -> 641 | N39: =IFERROR('Labor Projection'!M39-'Labor Projection'!F39,"") -> 0 | O39: 25320 | P39: =IFERROR('Labor Projection'!Q39-'Labor Projection'!O39,"") -> 0 | Q39: 25320 | S39: =IFERROR('Labor Projection'!L39*'Labor Projection'!$K$1,"") | T39: =IFERROR('Labor Projection'!R39+'Labor Projection'!S39,"") | U39: =IFERROR('Labor Projection'!T39-'Labor Projection'!Q39,"") | V39: =IFERROR(IF('Labor Projection'!D39=0,0,'Labor Projection'!O39/'Labor Projection'!D39),"") -> 39.50078 | W39: =IFERROR(IF('Labor Projection'!G39=0,0,'Labor Projection'!R39/'Labor Projection'!G39),"") -> 0 | X39: =IFERROR('Labor Projection'!W39-'Labor Projection'!V39,"") -> -39.50078 | Y39: L | Z39: 0050301000
B40: 00401403 - BW- POWER- ABOVE CEILING | C40: L | D40: 2093 | E40: =IFERROR('Labor Projection'!F40-'Labor Projection'!D40,"") -> 0 | F40: 2093 | I40: =IFERROR(IF('Labor Projection'!H40=0,'Labor Projection'!F40,(('Labor Projection'!G40/'Labor Projection'!H40)-'Labor Projection'!G40)),"") -> 2093 | K40: =IFERROR('Labor Projection'!I40*'Labor Projection'!J40,"") -> 0 | L40: =IFERROR('Labor Projection'!I40+'Labor Projection'!K40,"") -> 2093 | M40: =IFERROR('Labor Projection'!L40+'Labor Projection'!G40,"") -> 2093 | N40: =IFERROR('Labor Projection'!M40-'Labor Projection'!F40,"") -> 0 | O40: 82674 | P40: =IFERROR('Labor Projection'!Q40-'Labor Projection'!O40,"") -> 0 | Q40: 82674 | S40: =IFERROR('Labor Projection'!L40*'Labor Projection'!$K$1,"") | T40: =IFERROR('Labor Projection'!R40+'Labor Projection'!S40,"") | U40: =IFERROR('Labor Projection'!T40-'Labor Projection'!Q40,"") | V40: =IFERROR(IF('Labor Projection'!D40=0,0,'Labor Projection'!O40/'Labor Projection'!D40),"") -> 39.500239 | W40: =IFERROR(IF('Labor Projection'!G40=0,0,'Labor Projection'!R40/'Labor Projection'!G40),"") -> 0 | X40: =IFERROR('Labor Projection'!W40-'Labor Projection'!V40,"") -> -39.500239 | Y40: L | Z40: 0050301000
B41: 00401404 - WIRING DEVICES- POWER | C41: L | D41: 257 | E41: =IFERROR('Labor Projection'!F41-'Labor Projection'!D41,"") -> 0 | F41: 257 | I41: =IFERROR(IF('Labor Projection'!H41=0,'Labor Projection'!F41,(('Labor Projection'!G41/'Labor Projection'!H41)-'Labor Projection'!G41)),"") -> 257 | K41: =IFERROR('Labor Projection'!I41*'Labor Projection'!J41,"") -> 0 | L41: =IFERROR('Labor Projection'!I41+'Labor Projection'!K41,"") -> 257 | M41: =IFERROR('Labor Projection'!L41+'Labor Projection'!G41,"") -> 257 | N41: =IFERROR('Labor Projection'!M41-'Labor Projection'!F41,"") -> 0 | O41: 10152 | P41: =IFERROR('Labor Projection'!Q41-'Labor Projection'!O41,"") -> 0 | Q41: 10152 | S41: =IFERROR('Labor Projection'!L41*'Labor Projection'!$K$1,"") | T41: =IFERROR('Labor Projection'!R41+'Labor Projection'!S41,"") | U41: =IFERROR('Labor Projection'!T41-'Labor Projection'!Q41,"") | V41: =IFERROR(IF('Labor Projection'!D41=0,0,'Labor Projection'!O41/'Labor Projection'!D41),"") -> 39.501946 | W41: =IFERROR(IF('Labor Projection'!G41=0,0,'Labor Projection'!R41/'Labor Projection'!G41),"") -> 0 | X41: =IFERROR('Labor Projection'!W41-'Labor Projection'!V41,"") -> -39.501946 | Y41: L | Z41: 0050301000
B42: 00405450 - ENGRAVING TAGS | C42: L | D42: 0 | E42: =IFERROR('Labor Projection'!F42-'Labor Projection'!D42,"") -> 0 | F42: 0 | I42: =IFERROR(IF('Labor Projection'!H42=0,'Labor Projection'!F42,(('Labor Projection'!G42/'Labor Projection'!H42)-'Labor Projection'!G42)),"") -> 0 | K42: =IFERROR('Labor Projection'!I42*'Labor Projection'!J42,"") -> 0 | L42: =IFERROR('Labor Projection'!I42+'Labor Projection'!K42,"") -> 0 | M42: =IFERROR('Labor Projection'!L42+'Labor Projection'!G42,"") -> 0 | N42: =IFERROR('Labor Projection'!M42-'Labor Projection'!F42,"") -> 0 | O42: 0 | P42: =IFERROR('Labor Projection'!Q42-'Labor Projection'!O42,"") -> 0 | Q42: 0 | S42: =IFERROR('Labor Projection'!L42*'Labor Projection'!$K$1,"") | T42: =IFERROR('Labor Projection'!R42+'Labor Projection'!S42,"") | U42: =IFERROR('Labor Projection'!T42-'Labor Projection'!Q42,"") | V42: =IFERROR(IF('Labor Projection'!D42=0,0,'Labor Projection'!O42/'Labor Projection'!D42),"") -> 0 | W42: =IFERROR(IF('Labor Projection'!G42=0,0,'Labor Projection'!R42/'Labor Projection'!G42),"") -> 0 | X42: =IFERROR('Labor Projection'!W42-'Labor Projection'!V42,"") -> 0 | Y42: L | Z42: 0050301000
B43: 00405450 - ENGRAVING TAGS | C43: LA | D43: 0 | E43: =IFERROR('Labor Projection'!F43-'Labor Projection'!D43,"") -> 0 | F43: 0 | I43: =IFERROR(IF('Labor Projection'!H43=0,'Labor Projection'!F43,(('Labor Projection'!G43/'Labor Projection'!H43)-'Labor Projection'!G43)),"") -> 0 | K43: =IFERROR('Labor Projection'!I43*'Labor Projection'!J43,"") -> 0 | L43: =IFERROR('Labor Projection'!I43+'Labor Projection'!K43,"") -> 0 | M43: =IFERROR('Labor Projection'!L43+'Labor Projection'!G43,"") -> 0 | N43: =IFERROR('Labor Projection'!M43-'Labor Projection'!F43,"") -> 0 | O43: 0 | P43: =IFERROR('Labor Projection'!Q43-'Labor Projection'!O43,"") -> 0 | Q43: 0 | S43: =IFERROR('Labor Projection'!L43*'Labor Projection'!$K$1,"") | T43: =IFERROR('Labor Projection'!R43+'Labor Projection'!S43,"") | U43: =IFERROR('Labor Projection'!T43-'Labor Projection'!Q43,"") | V43: =IFERROR(IF('Labor Projection'!D43=0,0,'Labor Projection'!O43/'Labor Projection'!D43),"") -> 0 | W43: =IFERROR(IF('Labor Projection'!G43=0,0,'Labor Projection'!R43/'Labor Projection'!G43),"") -> 0 | X43: =IFERROR('Labor Projection'!W43-'Labor Projection'!V43,"") -> 0 | Y43: LA | Z43: 0050301000
B44: 00405450 - ENGRAVING TAGS | C44: LB | D44: 0 | E44: =IFERROR('Labor Projection'!F44-'Labor Projection'!D44,"") -> 0 | F44: 0 | I44: =IFERROR(IF('Labor Projection'!H44=0,'Labor Projection'!F44,(('Labor Projection'!G44/'Labor Projection'!H44)-'Labor Projection'!G44)),"") -> 0 | K44: =IFERROR('Labor Projection'!I44*'Labor Projection'!J44,"") -> 0 | L44: =IFERROR('Labor Projection'!I44+'Labor Projection'!K44,"") -> 0 | M44: =IFERROR('Labor Projection'!L44+'Labor Projection'!G44,"") -> 0 | N44: =IFERROR('Labor Projection'!M44-'Labor Projection'!F44,"") -> 0 | O44: 0 | P44: =IFERROR('Labor Projection'!Q44-'Labor Projection'!O44,"") -> 0 | Q44: 0 | S44: =IFERROR('Labor Projection'!L44*'Labor Projection'!$K$1,"") | T44: =IFERROR('Labor Projection'!R44+'Labor Projection'!S44,"") | U44: =IFERROR('Labor Projection'!T44-'Labor Projection'!Q44,"") | V44: =IFERROR(IF('Labor Projection'!D44=0,0,'Labor Projection'!O44/'Labor Projection'!D44),"") -> 0 | W44: =IFERROR(IF('Labor Projection'!G44=0,0,'Labor Projection'!R44/'Labor Projection'!G44),"") -> 0 | X44: =IFERROR('Labor Projection'!W44-'Labor Projection'!V44,"") -> 0 | Y44: LB | Z44: 0050301000
... B46: 00405450 - ENGRAVING TAGS | C46: LM | D46: 0 | E46: =IFERROR('Labor Projection'!F46-'Labor Projection'!D46,"") -> 0 | F46: 0 | I46: =IFERROR(IF('Labor Projection'!H46=0,'Labor Projection'!F46,(('Labor Projection'!G46/'Labor Projection'!H46)-'Labor Projection'!G46)),"") -> 0 | K46: =IFERROR('Labor Projection'!I46*'Labor Projection'!J46,"") -> 0 | L46: =IFERROR('Labor Projection'!I46+'Labor Projection'!K46,"") -> 0 | M46: =IFERROR('Labor Projection'!L46+'Labor Projection'!G46,"") -> 0 | N46: =IFERROR('Labor Projection'!M46-'Labor Projection'!F46,"") -> 0 | O46: 0 | P46: =IFERROR('Labor Projection'!Q46-'Labor Projection'!O46,"") -> 0 | Q46: 0 | S46: =IFERROR('Labor Projection'!L46*'Labor Projection'!$K$1,"") | T46: =IFERROR('Labor Projection'!R46+'Labor Projection'!S46,"") | U46: =IFERROR('Labor Projection'!T46-'Labor Projection'!Q46,"") | V46: =IFERROR(IF('Labor Projection'!D46=0,0,'Labor Projection'!O46/'Labor Projection'!D46),"") -> 0 | W46: =IFERROR(IF('Labor Projection'!G46=0,0,'Labor Projection'!R46/'Labor Projection'!G46),"") -> 0 | X46: =IFERROR('Labor Projection'!W46-'Labor Projection'!V46,"") -> 0 | Y46: LM | Z46: 0050301000
B51: ABC | C51: Pseudo Cost Type | D51: Original Hours Estimate | E51: Change Order Hours Estimate | F51: Current Labor Hours Estimate | G51: JTD Hours | H51: Est. % Complete | I51: Base Hrs to Complete | J51: Productivity Factor | K51: Productivity Hours | L51: Projected Hrs to Complete | M51: Total Hrs | N51: (Under) / Over | O51: Original Labor Dollar Est. | P51: Change Order Labor Dollar Est. | Q51: Current Labor Dollar Estimate | R51: JTD Labor Cost | S51: Est Labor to Complete | T51: Est. Total Labor | U51: (Under)/Over | V51: Est. $/Hour | W51: JTD $/ Hr | X51: (Under) / Over2
B52: NOTICE TO PROCEED LABOR HOURS | F52: {=#REF!} -> #REF! | I52: =IFERROR(IF('Labor Projection'!H52=0,'Labor Projection'!F52,('Labor Projection'!G52/'Labor Projection'!H52)-'Labor Projection'!G52),"") | K52: =IFERROR('Labor Projection'!I52*'Labor Projection'!J52,"") | L52: =IFERROR('Labor Projection'!I52+'Labor Projection'!K52,"") | M52: =IFERROR('Labor Projection'!G52+'Labor Projection'!L52,"") | N52: =IFERROR('Labor Projection'!M52-'Labor Projection'!F52,"") | Q52: =#REF! -> #REF! | R52: =IFERROR(IF('Labor Projection'!F52=0,0,('Labor Projection'!Q52/'Labor Projection'!F52)*'Labor Projection'!G52),"") | S52: =IFERROR(IF('Labor Projection'!F52=0,0,('Labor Projection'!Q52/'Labor Projection'!F52)*'Labor Projection'!L52),"") | T52: =IFERROR('Labor Projection'!R52+'Labor Projection'!S52,"") | U52: =IFERROR('Labor Projection'!T52-'Labor Projection'!Q52,"")

Sheet Materials
B1: JOINT RESERVE BASE HANGAR
B2: Material, Subcontract, Other & Tax
D3: Materials / Subcontracts | E3: =SUMIF(C12:C1000,"M",E12:E1000)+SUMIF(C12:C1000,"S",E12:E1000) -> 1043578 | F3: =SUMIF(C12:C1000,"M",F12:F1000)+SUMIF(C12:C1000,"S",F12:F1000) -> 0 | G3: =SUMIF(C12:C1000,"M",G12:G1000)+SUMIF(C12:C1000,"S",G12:G1000) -> 1043578 | H3: =SUMIF(C12:C1000,"M",H12:H1000)+SUMIF(C12:C1000,"S",H12:H1000) -> 146.1 | I3: =SUMIF(C12:C1000,"M",I12:I1000)+SUMIF(C12:C1000,"S",I12:I1000) -> 429478.63 | J3: =SUMIF(C12:C1000,"M",J12:J1000)+SUMIF(C12:C1000,"S",J12:J1000) -> 429624.73 | K3: =SUMIF(C12:C1000,"M",K12:K1000)+SUMIF(C12:C1000,"S",K12:K1000) -> 43654.9 | L3: =SUMIF(C12:C1000,"M",L12:L1000)+SUMIF(C12:C1000,"S",L12:L1000) -> 473279.63 | M3: =IF(L3=0,0,H3/L3) -> 0.000308697 | N3: =G3-L3 -> 570298.37 | O3: =IF(G3=0,0,N3/G3) -> 0.5464837
D4: DJE / Others | E4: =SUMIF(C12:C1000,"E",E12:E1000)+SUMIF(C12:C1000,"O",E12:E1000)+SUMIF(C12:C1000,"T",E12:E1000) -> 383140 | F4: =SUMIF(C12:C1000,"E",F12:F1000)+SUMIF(C12:C1000,"O",F12:F1000)+SUMIF(C12:C1000,"T",F12:F1000) -> 0 | G4: =SUMIF(C12:C1000,"E",G12:G1000)+SUMIF(C12:C1000,"O",G12:G1000)+SUMIF(C12:C1000,"T",G12:G1000) -> 383140 | H4: =SUMIF(C12:C1000,"E",H12:H1000)+SUMIF(C12:C1000,"O",H12:H1000)+SUMIF(C12:C1000,"T",H12:H1000) -> 0 | I4: =SUMIF(C12:C1000,"E",I12:I1000)+SUMIF(C12:C1000,"O",I12:I1000)+SUMIF(C12:C1000,"T",I12:I1000) -> 29087.91 | J4: =SUMIF(C12:C1000,"E",J12:J1000)+SUMIF(C12:C1000,"O",J12:J1000)+SUMIF(C12:C1000,"T",J12:J1000) -> 29087.91 | K4: =SUMIF(C12:C1000,"E",K12:K1000)+SUMIF(C12:C1000,"O",K12:K1000)+SUMIF(C12:C1000,"T",K12:K1000) -> 0 | L4: =SUMIF(C12:C1000,"E",L12:L1000)+SUMIF(C12:C1000,"O",L12:L1000)+SUMIF(C12:C1000,"T",L12:L1000) -> 29087.91 | M4: =IF(L4=0,0,H4/L4) -> 0 | N4: =G4-L4 -> 354052.09 | O4: =IF(G4=0,0,N4/G4) -> 0.92408021
D6: Summary Sheet Comparison
D7: Materials / Subcontracts | N7: =Summary!K20 -> #REF! | O7: =N3-N7 -> #REF!
D8: DJE / Others | N8: =Summary!K21 -> #REF! | O8: =N4-N8 -> #REF!
B10: Grand Total | C10: - | D10: - | E10: =SUBTOTAL(9,E12:E14,E16:E69,E71:E91,E93:E113,E115) -> 1426718 | F10: =SUBTOTAL(9,F12:F14,F16:F69,F71:F91,F93:F113,F115) -> 0 | G10: =SUBTOTAL(9,G12:G14,G16:G69,G71:G91,G93:G113,G115) -> 1426718 | H10: =SUBTOTAL(9,H12:H14,H16:H69,H71:H91,H93:H113,H115) -> 146.1 | I10: =SUBTOTAL(9,I12:I14,I16:I69,I71:I91,I93:I113,I115) -> 458566.54 | J10: =SUBTOTAL(9,J12:J14,J16:J69,J71:J91,J93:J113,J115) -> 458712.64 | K10: =SUBTOTAL(9,K12:K14,K16:K69,K71:K91,K93:K113,K115) -> 43654.9 | L10: =SUBTOTAL(9,L12:L14,L16:L69,L71:L91,L93:L113,L115) -> 502367.54 | M10: - | N10: =SUBTOTAL(9,N12:N14,N16:N69,N71:N91,N93:N113,N115) -> 924350.46 | O10: - | P10: - | Q10: -
B11: Cost Type | C11: CostType1 | D11: Phase | E11: Original Estimate | F11: Change Orders Estimate | G11: Current Estimate | H11: JTD | I11: Open | J11: JTD + Open | K11: Estimated Future Costs | L11: Projected Cost | M11: % Complete | N11: Variance | O11: % Variance | P11: PhaseCenter | Q11: ProjectStatus
B12: E | C12: E | D12: 00300306 - EQUIPMENT RENTAL | E12: 96900 | F12: =IFERROR(Materials!G12-Materials!E12,"") -> 0 | G12: 96900 | I12: 26643.75 | J12: =IFERROR(Materials!H12+Materials!I12,"") -> 26643.75 | L12: =IFERROR(Materials!J12+Materials!K12,"") -> 26643.75 | M12: =IFERROR(IF(Materials!L12=0,0,Materials!H12/Materials!L12),"") -> 0 | N12: =IFERROR(Materials!G12-Materials!L12,"") -> 70256.25 | O12: =IFERROR(IF(Materials!G12=0,0,Materials!N12/Materials!G12),"") -> 0.7250387 | P12: 0050301000 | Q12: A
B13: E | C13: E | D13: 00300312 - STORAGE & SHEDS | E13: 5000 | F13: =IFERROR(Materials!G13-Materials!E13,"") -> 0 | G13: 5000 | J13: =IFERROR(Materials!H13+Materials!I13,"") -> 0 | L13: =IFERROR(Materials!J13+Materials!K13,"") -> 0 | M13: =IFERROR(IF(Materials!L13=0,0,Materials!H13/Materials!L13),"") -> 0 | N13: =IFERROR(Materials!G13-Materials!L13,"") -> 5000 | O13: =IFERROR(IF(Materials!G13=0,0,Materials!N13/Materials!G13),"") -> 1 | P13: 0050301000 | Q13: A
B14: E | C14: E | D14: 00300327 - OFFSITE STORAGE | E14: 0 | F14: =IFERROR(Materials!G14-Materials!E14,"") -> 0 | G14: 0 | J14: =IFERROR(Materials!H14+Materials!I14,"") -> 0 | L14: =IFERROR(Materials!J14+Materials!K14,"") -> 0 | M14: =IFERROR(IF(Materials!L14=0,0,Materials!H14/Materials!L14),"") -> 0 | N14: =IFERROR(Materials!G14-Materials!L14,"") -> 0 | O14: =IFERROR(IF(Materials!G14=0,0,Materials!N14/Materials!G14),"") -> 0 | P14: 0050301000 | Q14: A
B15: Subtotal of E | C15: - | D15: - | E15: =SUBTOTAL(9,E12:E14) -> 101900 | F15: =SUBTOTAL(9,F12:F14) -> 0 | G15: =SUBTOTAL(9,G12:G14) -> 101900 | H15: =SUBTOTAL(9,H12:H14) -> 0 | I15: =SUBTOTAL(9,I12:I14) -> 26643.75 | J15: =SUBTOTAL(9,J12:J14) -> 26643.75 | K15: =SUBTOTAL(9,K12:K14) -> 0 | L15: =SUBTOTAL(9,L12:L14) -> 26643.75 | M15: - | N15: =SUBTOTAL(9,N12:N14) -> 75256.25 | O15: - | P15: - | Q15: -
B16: M | C16: M | D16: 00100000 - MISC MATERIALS | E16: 0 | F16: =IFERROR(Materials!G16-Materials!E16,"") -> 0 | G16: 0 | J16: =IFERROR(Materials!H16+Materials!I16,"") -> 0 | L16: =IFERROR(Materials!J16+Materials!K16,"") -> 0 | M16: =IFERROR(IF(Materials!L16=0,0,Materials!H16/Materials!L16),"") -> 0 | N16: =IFERROR(Materials!G16-Materials!L16,"") -> 0 | O16: =IFERROR(IF(Materials!G16=0,0,Materials!N16/Materials!G16),"") -> 0 | P16: 0050301000 | Q16: A
B17: M | C17: M | D17: 00100010 - GALVANIZED CONDUIT & FITT | E17: 4228 | F17: =IFERROR(Materials!G17-Materials!E17,"") -> 0 | G17: 4228 | J17: =IFERROR(Materials!H17+Materials!I17,"") -> 0 | L17: =IFERROR(Materials!J17+Materials!K17,"") -> 0 | M17: =IFERROR(IF(Materials!L17=0,0,Materials!H17/Materials!L17),"") -> 0 | N17: =IFERROR(Materials!G17-Materials!L17,"") -> 4228 | O17: =IFERROR(IF(Materials!G17=0,0,Materials!N17/Materials!G17),"") -> 1 | P17: 0050301000 | Q17: A
B18: M | C18: M | D18: 00100020 - EMT CONDUIT & FITTINGS | E18: 52019 | F18: =IFERROR(Materials!G18-Materials!E18,"") -> 0 | G18: 52019 | J18: =IFERROR(Materials!H18+Materials!I18,"") -> 0 | L18: =IFERROR(Materials!J18+Materials!K18,"") -> 0 | M18: =IFERROR(IF(Materials!L18=0,0,Materials!H18/Materials!L18),"") -> 0 | N18: =IFERROR(Materials!G18-Materials!L18,"") -> 52019 | O18: =IFERROR(IF(Materials!G18=0,0,Materials!N18/Materials!G18),"") -> 1 | P18: 0050301000 | Q18: A
B19: M | C19: M | D19: 00100030 - PVC CONDUIT & FITTTINGS | E19: 2982 | F19: =IFERROR(Materials!G19-Materials!E19,"") -> 0 | G19: 2982 | J19: =IFERROR(Materials!H19+Materials!I19,"") -> 0 | L19: =IFERROR(Materials!J19+Materials!K19,"") -> 0 | M19: =IFERROR(IF(Materials!L19=0,0,Materials!H19/Materials!L19),"") -> 0 | N19: =IFERROR(Materials!G19-Materials!L19,"") -> 2982 | O19: =IFERROR(IF(Materials!G19=0,0,Materials!N19/Materials!G19),"") -> 1 | P19: 0050301000 | Q19: A
B20: M | C20: M | D20: 00100040 - FIBERGLASS | E20: 0 | F20: =IFERROR(Materials!G20-Materials!E20,"") -> 0 | G20: 0 | J20: =IFERROR(Materials!H20+Materials!I20,"") -> 0 | L20: =IFERROR(Materials!J20+Materials!K20,"") -> 0 | M20: =IFERROR(IF(Materials!L20=0,0,Materials!H20/Materials!L20),"") -> 0 | N20: =IFERROR(Materials!G20-Materials!L20,"") -> 0 | O20: =IFERROR(IF(Materials!G20=0,0,Materials!N20/Materials!G20),"") -> 0 | P20: 0050301000 | Q20: A
B21: M | C21: M | D21: 00100050 - PVC COATED CONDUIT & FITT | E21: 0 | F21: =IFERROR(Materials!G21-Materials!E21,"") -> 0 | G21: 0 | J21: =IFERROR(Materials!H21+Materials!I21,"") -> 0 | L21: =IFERROR(Materials!J21+Materials!K21,"") -> 0 | M21: =IFERROR(IF(Materials!L21=0,0,Materials!H21/Materials!L21),"") -> 0 | N21: =IFERROR(Materials!G21-Materials!L21,"") -> 0 | O21: =IFERROR(IF(Materials!G21=0,0,Materials!N21/Materials!G21),"") -> 0 | P21: 0050301000 | Q21: A
B22: M | C22: M | D22: 00100060 - IMC CONDUIT & FITTINGS | E22: 0 | F22: =IFERROR(Materials!G22-Materials!E22,"") -> 0 | G22: 0 | J22: =IFERROR(Materials!H22+Materials!I22,"") -> 0 | L22: =IFERROR(Materials!J22+Materials!K22,"") -> 0 | M22: =IFERROR(IF(Materials!L22=0,0,Materials!H22/Materials!L22),"") -> 0 | N22: =IFERROR(Materials!G22-Materials!L22,"") -> 0 | O22: =IFERROR(IF(Materials!G22=0,0,Materials!N22/Materials!G22),"") -> 0 | P22: 0050301000 | Q22: A
B23: M | C23: M | D23: 00100070 - ALUMINUM CONDUIT,FITTING | E23: 0 | F23: =IFERROR(Materials!G23-Materials!E23,"") -> 0 | G23: 0 | J23: =IFERROR(Materials!H23+Materials!I23,"") -> 0 | L23: =IFERROR(Materials!J23+Materials!K23,"") -> 0 | M23: =IFERROR(IF(Materials!L23=0,0,Materials!H23/Materials!L23),"") -> 0 | N23: =IFERROR(Materials!G23-Materials!L23,"") -> 0 | O23: =IFERROR(IF(Materials!G23=0,0,Materials!N23/Materials!G23),"") -> 0 | P23: 0050301000 | Q23: A
B24: M | C24: M | D24: 00100100 - MATERIALS | E24: 0 | F24: =IFERROR(Materials!G24-Materials!E24,"") -> 0 | G24: 0 | J24: =IFERROR(Materials!H24+Materials!I24,"") -> 0 | L24: =IFERROR(Materials!J24+Materials!K24,"") -> 0 | M24: =IFERROR(IF(Materials!L24=0,0,Materials!H24/Materials!L24),"") -> 0 | N24: =IFERROR(Materials!G24-Materials!L24,"") -> 0 | O24: =IFERROR(IF(Materials!G24=0,0,Materials!N24/Materials!G24),"") -> 0 | P24: 0050301000 | Q24: A
B25: M | C25: M | D25: 00100130 - SUPPORTS | E25: 43801 | F25: =IFERROR(Materials!G25-Materials!E25,"") -> 0 | G25: 43801 | H25: 146.1 | I25: 0 | J25: =IFERROR(Materials!H25+Materials!I25,"") -> 146.1 | K25: 43654.9 | L25: =IFERROR(Materials!J25+Materials!K25,"") -> 43801 | M25: =IFERROR(IF(Materials!L25=0,0,Materials!H25/Materials!L25),"") -> 0.0033355403 | N25: =IFERROR(Materials!G25-Materials!L25,"") -> 0 | O25: =IFERROR(IF(Materials!G25=0,0,Materials!N25/Materials!G25),"") -> 0 | P25: 0050301000 | Q25: A
B26: M | C26: M | D26: 00100140 - FLEXIBLE CONDUIT & FITTIN | E26: 666 | F26: =IFERROR(Materials!G26-Materials!E26,"") -> 0 | G26: 666 | J26: =IFERROR(Materials!H26+Materials!I26,"") -> 0 | L26: =IFERROR(Materials!J26+Materials!K26,"") -> 0 | M26: =IFERROR(IF(Materials!L26=0,0,Materials!H26/Materials!L26),"") -> 0 | N26: =IFERROR(Materials!G26-Materials!L26,"") -> 666 | O26: =IFERROR(IF(Materials!G26=0,0,Materials!N26/Materials!G26),"") -> 1 | P26: 0050301000 | Q26: A
B27: M | C27: M | D27: 00100170 - GROUNDING | E27: 14476 | F27: =IFERROR(Materials!G27-Materials!E27,"") -> 0 | G27: 14476 | J27: =IFERROR(Materials!H27+Materials!I27,"") -> 0 | L27: =IFERROR(Materials!J27+Materials!K27,"") -> 0 | M27: =IFERROR(IF(Materials!L27=0,0,Materials!H27/Materials!L27),"") -> 0 | N27: =IFERROR(Materials!G27-Materials!L27,"") -> 14476 | O27: =IFERROR(IF(Materials!G27=0,0,Materials!N27/Materials!G27),"") -> 1 | P27: 0050301000 | Q27: A
B28: M | C28: M | D28: 00100180 - FIXTURES & LAMPS & PARTS | E28: 0 | F28: =IFERROR(Materials!G28-Materials!E28,"") -> 0 | G28: 0 | J28: =IFERROR(Materials!H28+Materials!I28,"") -> 0 | L28: =IFERROR(Materials!J28+Materials!K28,"") -> 0 | M28: =IFERROR(IF(Materials!L28=0,0,Materials!H28/Materials!L28),"") -> 0 | N28: =IFERROR(Materials!G28-Materials!L28,"") -> 0 | O28: =IFERROR(IF(Materials!G28=0,0,Materials!N28/Materials!G28),"") -> 0 | P28: 0050301000 | Q28: A
B29: M | C29: M | D29: 00100210 - WIRING DEVICES & WALL PLA | E29: 1429 | F29: =IFERROR(Materials!G29-Materials!E29,"") -> 0 | G29: 1429 | J29: =IFERROR(Materials!H29+Materials!I29,"") -> 0 | L29: =IFERROR(Materials!J29+Materials!K29,"") -> 0 | M29: =IFERROR(IF(Materials!L29=0,0,Materials!H29/Materials!L29),"") -> 0 | N29: =IFERROR(Materials!G29-Materials!L29,"") -> 1429 | O29: =IFERROR(IF(Materials!G29=0,0,Materials!N29/Materials!G29),"") -> 1 | P29: 0050301000 | Q29: A
B30: M | C30: M | D30: 00100230 - BOXES & FITTINGS | E30: 10483 | F30: =IFERROR(Materials!G30-Materials!E30,"") -> 0 | G30: 10483 | I30: 226.3 | J30: =IFERROR(Materials!H30+Materials!I30,"") -> 226.3 | L30: =IFERROR(Materials!J30+Materials!K30,"") -> 226.3 | M30: =IFERROR(IF(Materials!L30=0,0,Materials!H30/Materials!L30),"") -> 0 | N30: =IFERROR(Materials!G30-Materials!L30,"") -> 10256.7 | O30: =IFERROR(IF(Materials!G30=0,0,Materials!N30/Materials!G30),"") -> 0.97841267 | P30: 0050301000 | Q30: A
B31: M | C31: M | D31: 00100290 - LOW VOLTAGE WIRING CABLE | E31: 0 | F31: =IFERROR(Materials!G31-Materials!E31,"") -> 0 | G31: 0 | J31: =IFERROR(Materials!H31+Materials!I31,"") -> 0 | L31: =IFERROR(Materials!J31+Materials!K31,"") -> 0 | M31: =IFERROR(IF(Materials!L31=0,0,Materials!H31/Materials!L31),"") -> 0 | N31: =IFERROR(Materials!G31-Materials!L31,"") -> 0 | O31: =IFERROR(IF(Materials!G31=0,0,Materials!N31/Materials!G31),"") -> 0 | P31: 0050301000 | Q31: A
B32: M | C32: M | D32: 00100310 - COPPER WIRE | E32: 155925 | F32: =IFERROR(Materials!G32-Materials!E32,"") -> 0 | G32: 155925 | J32: =IFERROR(Materials!H32+Materials!I32,"") -> 0 | L32: =IFERROR(Materials!J32+Materials!K32,"") -> 0 | M32: =IFERROR(IF(Materials!L32=0,0,Materials!H32/Materials!L32),"") -> 0 | N32: =IFERROR(Materials!G32-Materials!L32,"") -> 155925 | O32: =IFERROR(IF(Materials!G32=0,0,Materials!N32/Materials!G32),"") -> 1 | P32: 0050301000 | Q32: A
B33: M | C33: M | D33: 00100350 - ALUMINUM WIRE | E33: 0 | F33: =IFERROR(Materials!G33-Materials!E33,"") -> 0 | G33: 0 | J33: =IFERROR(Materials!H33+Materials!I33,"") -> 0 | L33: =IFERROR(Materials!J33+Materials!K33,"") -> 0 | M33: =IFERROR(IF(Materials!L33=0,0,Materials!H33/Materials!L33),"") -> 0 | N33: =IFERROR(Materials!G33-Materials!L33,"") -> 0 | O33: =IFERROR(IF(Materials!G33=0,0,Materials!N33/Materials!G33),"") -> 0 | P33: 0050301000 | Q33: A
B34: M | C34: M | D34: 00100370 - MC CABLE & FITTINGS | E34: 6961 | F34: =IFERROR(Materials!G34-Materials!E34,"") -> 0 | G34: 6961 | J34: =IFERROR(Materials!H34+Materials!I34,"") -> 0 | L34: =IFERROR(Materials!J34+Materials!K34,"") -> 0 | M34: =IFERROR(IF(Materials!L34=0,0,Materials!H34/Materials!L34),"") -> 0 | N34: =IFERROR(Materials!G34-Materials!L34,"") -> 6961 | O34: =IFERROR(IF(Materials!G34=0,0,Materials!N34/Materials!G34),"") -> 1 | P34: 0050301000 | Q34: A
B35: M | C35: M | D35: 00100390 - PORTABLE CORD & FITTINGS | E35: 0 | F35: =IFERROR(Materials!G35-Materials!E35,"") -> 0 | G35: 0 | J35: =IFERROR(Materials!H35+Materials!I35,"") -> 0 | L35: =IFERROR(Materials!J35+Materials!K35,"") -> 0 | M35: =IFERROR(IF(Materials!L35=0,0,Materials!H35/Materials!L35),"") -> 0 | N35: =IFERROR(Materials!G35-Materials!L35,"") -> 0 | O35: =IFERROR(IF(Materials!G35=0,0,Materials!N35/Materials!G35),"") -> 0 | P35: 0050301000 | Q35: A
B36: M | C36: M | D36: 00100420 - WIRE TERMINATIONS | E36: 1305 | F36: =IFERROR(Materials!G36-Materials!E36,"") -> 0 | G36: 1305 | I36: 3719.89 | J36: =IFERROR(Materials!H36+Materials!I36,"") -> 3719.89 | L36: =IFERROR(Materials!J36+Materials!K36,"") -> 3719.89 | M36: =IFERROR(IF(Materials!L36=0,0,Materials!H36/Materials!L36),"") -> 0 | N36: =IFERROR(Materials!G36-Materials!L36,"") -> -2414.89 | O36: =IFERROR(IF(Materials!G36=0,0,Materials!N36/Materials!G36),"") -> -1.8504904 | P36: 0050301000 | Q36: A
B37: M | C37: M | D37: 00100430 - SWITCHGEAR | E37: 4667 | F37: =IFERROR(Materials!G37-Materials!E37,"") -> 0 | G37: 4667 | I37: 1653.44 | J37: =IFERROR(Materials!H37+Materials!I37,"") -> 1653.44 | L37: =IFERROR(Materials!J37+Materials!K37,"") -> 1653.44 | M37: =IFERROR(IF(Materials!L37=0,0,Materials!H37/Materials!L37),"") -> 0 | N37: =IFERROR(Materials!G37-Materials!L37,"") -> 3013.56 | O37: =IFERROR(IF(Materials!G37=0,0,Materials!N37/Materials!G37),"") -> 0.64571673 | P37: 0050301000 | Q37: A
B38: M | C38: M | D38: 00100470 - CONCRETE & ACCESSORIES | E38: 0 | F38: =IFERROR(Materials!G38-Materials!E38,"") -> 0 | G38: 0 | J38: =IFERROR(Materials!H38+Materials!I38,"") -> 0 | L38: =IFERROR(Materials!J38+Materials!K38,"") -> 0 | M38: =IFERROR(IF(Materials!L38=0,0,Materials!H38/Materials!L38),"") -> 0 | N38: =IFERROR(Materials!G38-Materials!L38,"") -> 0 | O38: =IFERROR(IF(Materials!G38=0,0,Materials!N38/Materials!G38),"") -> 0 | P38: 0050301000 | Q38: A
B39: M | C39: M | D39: 00100490 - FIREPROOFING | E39: 0 | F39: =IFERROR(Materials!G39-Materials!E39,"") -> 0 | G39: 0 | J39: =IFERROR(Materials!H39+Materials!I39,"") -> 0 | L39: =IFERROR(Materials!J39+Materials!K39,"") -> 0 | M39: =IFERROR(IF(Materials!L39=0,0,Materials!H39/Materials!L39),"") -> 0 | N39: =IFERROR(Materials!G39-Materials!L39,"") -> 0 | O39: =IFERROR(IF(Materials!G39=0,0,Materials!N39/Materials!G39),"") -> 0 | P39: 0050301000 | Q39: A
B40: M | C40: M | D40: 00100510 - SURFACE & UNDERFLOOR RACE | E40: 0 | F40: =IFERROR(Materials!G40-Materials!E40,"") -> 0 | G40: 0 | J40: =IFERROR(Materials!H40+Materials!I40,"") -> 0 | L40: =IFERROR(Materials!J40+Materials!K40,"") -> 0 | M40: =IFERROR(IF(Materials!L40=0,0,Materials!H40/Materials!L40),"") -> 0 | N40: =IFERROR(Materials!G40-Materials!L40,"") -> 0 | O40: =IFERROR(IF(Materials!G40=0,0,Materials!N40/Materials!G40),"") -> 0 | P40: 0050301000 | Q40: A
B41: M | C41: M | D41: 00100550 - GUTTER & GUTTER FITTINGS | E41: 0 | F41: =IFERROR(Materials!G41-Materials!E41,"") -> 0 | G41: 0 | J41: =IFERROR(Materials!H41+Materials!I41,"") -> 0 | L41: =IFERROR(Materials!J41+Materials!K41,"") -> 0 | M41: =IFERROR(IF(Materials!L41=0,0,Materials!H41/Materials!L41),"") -> 0 | N41: =IFERROR(Materials!G41-Materials!L41,"") -> 0 | O41: =IFERROR(IF(Materials!G41=0,0,Materials!N41/Materials!G41),"") -> 0 | P41: 0050301000 | Q41: A
B42: M | C42: M | D42: 00100560 - CABLE TRAY | E42: 0 | F42: =IFERROR(Materials!G42-Materials!E42,"") -> 0 | G42: 0 | J42: =IFERROR(Materials!H42+Materials!I42,"") -> 0 | L42: =IFERROR(Materials!J42+Materials!K42,"") -> 0 | M42: =IFERROR(IF(Materials!L42=0,0,Materials!H42/Materials!L42),"") -> 0 | N42: =IFERROR(Materials!G42-Materials!L42,"") -> 0 | O42: =IFERROR(IF(Materials!G42=0,0,Materials!N42/Materials!G42),"") -> 0 | P42: 0050301000 | Q42: A
B43: M | C43: M | D43: 00100580 - SPECIAL & LV SYSTEMS | E43: 0 | F43: =IFERROR(Materials!G43-Materials!E43,"") -> 0 | G43: 0 | J43: =IFERROR(Materials!H43+Materials!I43,"") -> 0 | L43: =IFERROR(Materials!J43+Materials!K43,"") -> 0 | M43: =IFERROR(IF(Materials!L43=0,0,Materials!H43/Materials!L43),"") -> 0 | N43: =IFERROR(Materials!G43-Materials!L43,"") -> 0 | O43: =IFERROR(IF(Materials!G43=0,0,Materials!N43/Materials!G43),"") -> 0 | P43: 0050301000 | Q43: A
B44: M | C44: M | D44: 00100600 - FIREALARM | E44: 0 | F44: =IFERROR(Materials!G44-Materials!E44,"") -> 0 | G44: 0 | J44: =IFERROR(Materials!H44+Materials!I44,"") -> 0 | L44: =IFERROR(Materials!J44+Materials!K44,"") -> 0 | M44: =IFERROR(IF(Materials!L44=0,0,Materials!H44/Materials!L44),"") -> 0 | N44: =IFERROR(Materials!G44-Materials!L44,"") -> 0 | O44: =IFERROR(IF(Materials!G44=0,0,Materials!N44/Materials!G44),"") -> 0 | P44: 0050301000 | Q44: A
B45: M | C45: M | D45: 00100610 - NURSE CALL | E45: 0 | F45: =IFERROR(Materials!G45-Materials!E45,"") -> 0 | G45: 0 | J45: =IFERROR(Materials!H45+Materials!I45,"") -> 0 | L45: =IFERROR(Materials!J45+Materials!K45,"") -> 0 | M45: =IFERROR(IF(Materials!L45=0,0,Materials!H45/Materials!L45),"") -> 0 | N45: =IFERROR(Materials!G45-Materials!L45,"") -> 0 | O45: =IFERROR(IF(Materials!G45=0,0,Materials!N45/Materials!G45),"") -> 0 | P45: 0050301000 | Q45: A
B46: M | C46: M | D46: 00100620 - LIGHTNING PROTECTION | E46: 0 | F46: =IFERROR(Materials!G46-Materials!E46,"") -> 0 | G46: 0 | J46: =IFERROR(Materials!H46+Materials!I46,"") -> 0 | L46: =IFERROR(Materials!J46+Materials!K46,"") -> 0 | M46: =IFERROR(IF(Materials!L46=0,0,Materials!H46/Materials!L46),"") -> 0 | N46: =IFERROR(Materials!G46-Materials!L46,"") -> 0 | O46: =IFERROR(IF(Materials!G46=0,0,Materials!N46/Materials!G46),"") -> 0 | P46: 0050301000 | Q46: A
B47: M | C47: M | D47: 00100630 - TEMPERATURE CONTROLS | E47: 0 | F47: =IFERROR(Materials!G47-Materials!E47,"") -> 0 | G47: 0 | J47: =IFERROR(Materials!H47+Materials!I47,"") -> 0 | L47: =IFERROR(Materials!J47+Materials!K47,"") -> 0 | M47: =IFERROR(IF(Materials!L47=0,0,Materials!H47/Materials!L47),"") -> 0 | N47: =IFERROR(Materials!G47-Materials!L47,"") -> 0 | O47: =IFERROR(IF(Materials!G47=0,0,Materials!N47/Materials!G47),"") -> 0 | P47: 0050301000 | Q47: A
B48: M | C48: M | D48: 00100640 - LOW VOLTAGE SYSTEMS | E48: 0 | F48: =IFERROR(Materials!G48-Materials!E48,"") -> 0 | G48: 0 | J48: =IFERROR(Materials!H48+Materials!I48,"") -> 0 | L48: =IFERROR(Materials!J48+Materials!K48,"") -> 0 | M48: =IFERROR(IF(Materials!L48=0,0,Materials!H48/Materials!L48),"") -> 0 | N48: =IFERROR(Materials!G48-Materials!L48,"") -> 0 | O48: =IFERROR(IF(Materials!G48=0,0,Materials!N48/Materials!G48),"") -> 0 | P48: 0050301000 | Q48: A
B49: M | C49: M | D49: 00100710 - DEMOLITION | E49: 0 | F49: =IFERROR(Materials!G49-Materials!E49,"") -> 0 | G49: 0 | J49: =IFERROR(Materials!H49+Materials!I49,"") -> 0 | L49: =IFERROR(Materials!J49+Materials!K49,"") -> 0 | M49: =IFERROR(IF(Materials!L49=0,0,Materials!H49/Materials!L49),"") -> 0 | N49: =IFERROR(Materials!G49-Materials!L49,"") -> 0 | O49: =IFERROR(IF(Materials!G49=0,0,Materials!N49/Materials!G49),"") -> 0 | P49: 0050301000 | Q49: A
... B59: M | C59: M | D59: 00200202 - GEAR | E59: 180000 | F59: =IFERROR(Materials!G59-Materials!E59,"") -> -120000 | G59: 60000 | J59: =IFERROR(Materials!H59+Materials!I59,"") -> 0 | L59: =IFERROR(Materials!J59+Materials!K59,"") -> 0 | M59: =IFERROR(IF(Materials!L59=0,0,Materials!H59/Materials!L59),"") -> 0 | N59: =IFERROR(Materials!G59-Materials!L59,"") -> 60000 | O59: =IFERROR(IF(Materials!G59=0,0,Materials!N59/Materials!G59),"") -> 1 | P59: 0050301000 | Q59: A
B60: M | C60: M | D60: 00200205 - GENERATOR | E60: 0 | F60: =IFERROR(Materials!G60-Materials!E60,"") -> 120000 | G60: 120000 | I60: 120000 | J60: =IFERROR(Materials!H60+Materials!I60,"") -> 120000 | L60: =IFERROR(Materials!J60+Materials!K60,"") -> 120000 | M60: =IFERROR(IF(Materials!L60=0,0,Materials!H60/Materials!L60),"") -> 0 | N60: =IFERROR(Materials!G60-Materials!L60,"") -> 0 | O60: =IFERROR(IF(Materials!G60=0,0,Materials!N60/Materials!G60),"") -> 0 | P60: 0050301000 | Q60: A
B61: M | C61: M | D61: 00200206 - ATS | E61: 0 | F61: =IFERROR(Materials!G61-Materials!E61,"") -> 0 | G61: 0 | J61: =IFERROR(Materials!H61+Materials!I61,"") -> 0 | L61: =IFERROR(Materials!J61+Materials!K61,"") -> 0 | M61: =IFERROR(IF(Materials!L61=0,0,Materials!H61/Materials!L61),"") -> 0 | N61: =IFERROR(Materials!G61-Materials!L61,"") -> 0 | O61: =IFERROR(IF(Materials!G61=0,0,Materials!N61/Materials!G61),"") -> 0 | P61: 0050301000 | Q61: A
B62: M | C62: M | D62: 00200207 - UPS | E62: 0 | F62: =IFERROR(Materials!G62-Materials!E62,"") -> 0 | G62: 0 | J62: =IFERROR(Materials!H62+Materials!I62,"") -> 0 | L62: =IFERROR(Materials!J62+Materials!K62,"") -> 0 | M62: =IFERROR(IF(Materials!L62=0,0,Materials!H62/Materials!L62),"") -> 0 | N62: =IFERROR(Materials!G62-Materials!L62,"") -> 0 | O62: =IFERROR(IF(Materials!G62=0,0,Materials!N62/Materials!G62),"") -> 0 | P62: 0050301000 | Q62: A
B63: M | C63: M | D63: 00200208 - PDU | E63: 0 | F63: =IFERROR(Materials!G63-Materials!E63,"") -> 0 | G63: 0 | J63: =IFERROR(Materials!H63+Materials!I63,"") -> 0 | L63: =IFERROR(Materials!J63+Materials!K63,"") -> 0 | M63: =IFERROR(IF(Materials!L63=0,0,Materials!H63/Materials!L63),"") -> 0 | N63: =IFERROR(Materials!G63-Materials!L63,"") -> 0 | O63: =IFERROR(IF(Materials!G63=0,0,Materials!N63/Materials!G63),"") -> 0 | P63: 0050301000 | Q63: A
B64: M | C64: M | D64: 00200210 - MANHOLES | E64: 2825 | F64: =IFERROR(Materials!G64-Materials!E64,"") -> 0 | G64: 2825 | J64: =IFERROR(Materials!H64+Materials!I64,"") -> 0 | L64: =IFERROR(Materials!J64+Materials!K64,"") -> 0 | M64: =IFERROR(IF(Materials!L64=0,0,Materials!H64/Materials!L64),"") -> 0 | N64: =IFERROR(Materials!G64-Materials!L64,"") -> 2825 | O64: =IFERROR(IF(Materials!G64=0,0,Materials!N64/Materials!G64),"") -> 1 | P64: 0050301000 | Q64: A
B65: M | C65: M | D65: 00200220 - MEDIUM VOLTAGE | E65: 5726 | F65: =IFERROR(Materials!G65-Materials!E65,"") -> 0 | G65: 5726 | J65: =IFERROR(Materials!H65+Materials!I65,"") -> 0 | L65: =IFERROR(Materials!J65+Materials!K65,"") -> 0 | M65: =IFERROR(IF(Materials!L65=0,0,Materials!H65/Materials!L65),"") -> 0 | N65: =IFERROR(Materials!G65-Materials!L65,"") -> 5726 | O65: =IFERROR(IF(Materials!G65=0,0,Materials!N65/Materials!G65),"") -> 1 | P65: 0050301000 | Q65: A
B66: M | C66: M | D66: 00200221 - CABLE TRAY | E66: 0 | F66: =IFERROR(Materials!G66-Materials!E66,"") -> 0 | G66: 0 | J66: =IFERROR(Materials!H66+Materials!I66,"") -> 0 | L66: =IFERROR(Materials!J66+Materials!K66,"") -> 0 | M66: =IFERROR(IF(Materials!L66=0,0,Materials!H66/Materials!L66),"") -> 0 | N66: =IFERROR(Materials!G66-Materials!L66,"") -> 0 | O66: =IFERROR(IF(Materials!G66=0,0,Materials!N66/Materials!G66),"") -> 0 | P66: 0050301000 | Q66: A
B67: M | C67: M | D67: 00200223 - VEHICLE CHARGER | E67: 10000 | F67: =IFERROR(Materials!G67-Materials!E67,"") -> 0 | G67: 10000 | J67: =IFERROR(Materials!H67+Materials!I67,"") -> 0 | L67: =IFERROR(Materials!J67+Materials!K67,"") -> 0 | M67: =IFERROR(IF(Materials!L67=0,0,Materials!H67/Materials!L67),"") -> 0 | N67: =IFERROR(Materials!G67-Materials!L67,"") -> 10000 | O67: =IFERROR(IF(Materials!G67=0,0,Materials!N67/Materials!G67),"") -> 1 | P67: 0050301000 | Q67: A
B68: M | C68: M | D68: 00300318 - FREIGHT CHARGES | E68: 0 | F68: =IFERROR(Materials!G68-Materials!E68,"") -> 0 | G68: 0 | J68: =IFERROR(Materials!H68+Materials!I68,"") -> 0 | L68: =IFERROR(Materials!J68+Materials!K68,"") -> 0 | M68: =IFERROR(IF(Materials!L68=0,0,Materials!H68/Materials!L68),"") -> 0 | N68: =IFERROR(Materials!G68-Materials!L68,"") -> 0 | O68: =IFERROR(IF(Materials!G68=0,0,Materials!N68/Materials!G68),"") -> 0 | P68: 0050301000 | Q68: A
B69: M | C69: M | D69: 00400450 - PREFAB | E69: 0 | F69: =IFERROR(Materials!G69-Materials!E69,"") -> 0 | G69: 0 | J69: =IFERROR(Materials!H69+Materials!I69,"") -> 0 | L69: =IFERROR(Materials!J69+Materials!K69,"") -> 0 | M69: =IFERROR(IF(Materials!L69=0,0,Materials!H69/Materials!L69),"") -> 0 | N69: =IFERROR(Materials!G69-Materials!L69,"") -> 0 | O69: =IFERROR(IF(Materials!G69=0,0,Materials!N69/Materials!G69),"") -> 0 | P69: 0050301000 | Q69: A
B70: Subtotal of M | C70: - | D70: - | E70: =SUBTOTAL(9,E16:E69) -> 631618 | F70: =SUBTOTAL(9,F16:F69) -> 0 | G70: =SUBTOTAL(9,G16:G69) -> 631618 | H70: =SUBTOTAL(9,H16:H69) -> 146.1 | I70: =SUBTOTAL(9,I16:I69) -> 125599.63 | J70: =SUBTOTAL(9,J16:J69) -> 125745.73 | K70: =SUBTOTAL(9,K16:K69) -> 43654.9 | L70: =SUBTOTAL(9,L16:L69) -> 169400.63 | M70: - | N70: =SUBTOTAL(9,N16:N69) -> 462217.37 | O70: - | P70: - | Q70: -
B71: O | C71: O | D71: 00100000 - MISC MATERIALS | E71: 0 | F71: =IFERROR(Materials!G71-Materials!E71,"") -> 0 | G71: 0 | J71: =IFERROR(Materials!H71+Materials!I71,"") -> 0 | L71: =IFERROR(Materials!J71+Materials!K71,"") -> 0 | M71: =IFERROR(IF(Materials!L71=0,0,Materials!H71/Materials!L71),"") -> 0 | N71: =IFERROR(Materials!G71-Materials!L71,"") -> 0 | O71: =IFERROR(IF(Materials!G71=0,0,Materials!N71/Materials!G71),"") -> 0 | P71: 0050301000 | Q71: A
B72: O | C72: O | D72: 00300301 - PERMITS | E72: 1200 | F72: =IFERROR(Materials!G72-Materials!E72,"") -> 0 | G72: 1200 | J72: =IFERROR(Materials!H72+Materials!I72,"") -> 0 | L72: =IFERROR(Materials!J72+Materials!K72,"") -> 0 | M72: =IFERROR(IF(Materials!L72=0,0,Materials!H72/Materials!L72),"") -> 0 | N72: =IFERROR(Materials!G72-Materials!L72,"") -> 1200 | O72: =IFERROR(IF(Materials!G72=0,0,Materials!N72/Materials!G72),"") -> 1 | P72: 0050301000 | Q72: A
B73: O | C73: O | D73: 00300302 - UTILITY CHARGES | E73: 0 | F73: =IFERROR(Materials!G73-Materials!E73,"") -> 0 | G73: 0 | J73: =IFERROR(Materials!H73+Materials!I73,"") -> 0 | L73: =IFERROR(Materials!J73+Materials!K73,"") -> 0 | M73: =IFERROR(IF(Materials!L73=0,0,Materials!H73/Materials!L73),"") -> 0 | N73: =IFERROR(Materials!G73-Materials!L73,"") -> 0 | O73: =IFERROR(IF(Materials!G73=0,0,Materials!N73/Materials!G73),"") -> 0 | P73: 0050301000 | Q73: A
B74: O | C74: O | D74: 00300303 - SPECIAL INSURANCE | E74: 0 | F74: =IFERROR(Materials!G74-Materials!E74,"") -> 0 | G74: 0 | J74: =IFERROR(Materials!H74+Materials!I74,"") -> 0 | L74: =IFERROR(Materials!J74+Materials!K74,"") -> 0 | M74: =IFERROR(IF(Materials!L74=0,0,Materials!H74/Materials!L74),"") -> 0 | N74: =IFERROR(Materials!G74-Materials!L74,"") -> 0 | O74: =IFERROR(IF(Materials!G74=0,0,Materials!N74/Materials!G74),"") -> 0 | P74: 0050301000 | Q74: A
B75: O | C75: O | D75: 00300305 - EXPENDABLES TOOLS/REPAIRS | E75: 39722 | F75: =IFERROR(Materials!G75-Materials!E75,"") -> 0 | G75: 39722 | I75: 2444.16 | J75: =IFERROR(Materials!H75+Materials!I75,"") -> 2444.16 | L75: =IFERROR(Materials!J75+Materials!K75,"") -> 2444.16 | M75: =IFERROR(IF(Materials!L75=0,0,Materials!H75/Materials!L75),"") -> 0 | N75: =IFERROR(Materials!G75-Materials!L75,"") -> 37277.84 | O75: =IFERROR(IF(Materials!G75=0,0,Materials!N75/Materials!G75),"") -> 0.93846836 | P75: 0050301000 | Q75: A
B76: O | C76: O | D76: 00300307 - TOOL EXPENSE | E76: 10000 | F76: =IFERROR(Materials!G76-Materials!E76,"") -> 0 | G76: 10000 | J76: =IFERROR(Materials!H76+Materials!I76,"") -> 0 | L76: =IFERROR(Materials!J76+Materials!K76,"") -> 0 | M76: =IFERROR(IF(Materials!L76=0,0,Materials!H76/Materials!L76),"") -> 0 | N76: =IFERROR(Materials!G76-Materials!L76,"") -> 10000 | O76: =IFERROR(IF(Materials!G76=0,0,Materials!N76/Materials!G76),"") -> 1 | P76: 0050301000 | Q76: A
B77: O | C77: O | D77: 00300314 - TELEPHONE & CELL PH & IT | E77: 0 | F77: =IFERROR(Materials!G77-Materials!E77,"") -> 0 | G77: 0 | J77: =IFERROR(Materials!H77+Materials!I77,"") -> 0 | L77: =IFERROR(Materials!J77+Materials!K77,"") -> 0 | M77: =IFERROR(IF(Materials!L77=0,0,Materials!H77/Materials!L77),"") -> 0 | N77: =IFERROR(Materials!G77-Materials!L77,"") -> 0 | O77: =IFERROR(IF(Materials!G77=0,0,Materials!N77/Materials!G77),"") -> 0 | P77: 0050301000 | Q77: A
B78: O | C78: O | D78: 00300315 - AS BUILT DRAWINGS | E78: 500 | F78: =IFERROR(Materials!G78-Materials!E78,"") -> 0 | G78: 500 | J78: =IFERROR(Materials!H78+Materials!I78,"") -> 0 | L78: =IFERROR(Materials!J78+Materials!K78,"") -> 0 | M78: =IFERROR(IF(Materials!L78=0,0,Materials!H78/Materials!L78),"") -> 0 | N78: =IFERROR(Materials!G78-Materials!L78,"") -> 500 | O78: =IFERROR(IF(Materials!G78=0,0,Materials!N78/Materials!G78),"") -> 1 | P78: 0050301000 | Q78: A
B79: O | C79: O | D79: 00300316 - VEHICLE EXPENSE | E79: 0 | F79: =IFERROR(Materials!G79-Materials!E79,"") -> 0 | G79: 0 | J79: =IFERROR(Materials!H79+Materials!I79,"") -> 0 | L79: =IFERROR(Materials!J79+Materials!K79,"") -> 0 | M79: =IFERROR(IF(Materials!L79=0,0,Materials!H79/Materials!L79),"") -> 0 | N79: =IFERROR(Materials!G79-Materials!L79,"") -> 0 | O79: =IFERROR(IF(Materials!G79=0,0,Materials!N79/Materials!G79),"") -> 0 | P79: 0050301000 | Q79: A
B80: O | C80: O | D80: 00300317 - TRAVEL EXPENSE | E80: 0 | F80: =IFERROR(Materials!G80-Materials!E80,"") -> 0 | G80: 0 | J80: =IFERROR(Materials!H80+Materials!I80,"") -> 0 | L80: =IFERROR(Materials!J80+Materials!K80,"") -> 0 | M80: =IFERROR(IF(Materials!L80=0,0,Materials!H80/Materials!L80),"") -> 0 | N80: =IFERROR(Materials!G80-Materials!L80,"") -> 0 | O80: =IFERROR(IF(Materials!G80=0,0,Materials!N80/Materials!G80),"") -> 0 | P80: 0050301000 | Q80: A
B81: O | C81: O | D81: 00300319 - FIELD OFFICE | E81: 0 | F81: =IFERROR(Materials!G81-Materials!E81,"") -> 0 | G81: 0 | J81: =IFERROR(Materials!H81+Materials!I81,"") -> 0 | L81: =IFERROR(Materials!J81+Materials!K81,"") -> 0 | M81: =IFERROR(IF(Materials!L81=0,0,Materials!H81/Materials!L81),"") -> 0 | N81: =IFERROR(Materials!G81-Materials!L81,"") -> 0 | O81: =IFERROR(IF(Materials!G81=0,0,Materials!N81/Materials!G81),"") -> 0 | P81: 0050301000 | Q81: A
B82: O | C82: O | D82: 00300320 - PM | E82: 54770 | F82: =IFERROR(Materials!G82-Materials!E82,"") -> 0 | G82: 54770 | J82: =IFERROR(Materials!H82+Materials!I82,"") -> 0 | L82: =IFERROR(Materials!J82+Materials!K82,"") -> 0 | M82: =IFERROR(IF(Materials!L82=0,0,Materials!H82/Materials!L82),"") -> 0 | N82: =IFERROR(Materials!G82-Materials!L82,"") -> 54770 | O82: =IFERROR(IF(Materials!G82=0,0,Materials!N82/Materials!G82),"") -> 1 | P82: 0050301000 | Q82: A
B83: O | C83: O | D83: 00300322 - CADD | E83: 0 | F83: =IFERROR(Materials!G83-Materials!E83,"") -> 0 | G83: 0 | J83: =IFERROR(Materials!H83+Materials!I83,"") -> 0 | L83: =IFERROR(Materials!J83+Materials!K83,"") -> 0 | M83: =IFERROR(IF(Materials!L83=0,0,Materials!H83/Materials!L83),"") -> 0 | N83: =IFERROR(Materials!G83-Materials!L83,"") -> 0 | O83: =IFERROR(IF(Materials!G83=0,0,Materials!N83/Materials!G83),"") -> 0 | P83: 0050301000 | Q83: A
B84: O | C84: O | D84: 00300323 - BOND EXPENSE | E84: 39948 | F84: =IFERROR(Materials!G84-Materials!E84,"") -> 0 | G84: 39948 | J84: =IFERROR(Materials!H84+Materials!I84,"") -> 0 | L84: =IFERROR(Materials!J84+Materials!K84,"") -> 0 | M84: =IFERROR(IF(Materials!L84=0,0,Materials!H84/Materials!L84),"") -> 0 | N84: =IFERROR(Materials!G84-Materials!L84,"") -> 39948 | O84: =IFERROR(IF(Materials!G84=0,0,Materials!N84/Materials!G84),"") -> 1 | P84: 0050301000 | Q84: A
B85: O | C85: O | D85: 00300324 - ENTERTAINMENT | E85: 1800 | F85: =IFERROR(Materials!G85-Materials!E85,"") -> 0 | G85: 1800 | J85: =IFERROR(Materials!H85+Materials!I85,"") -> 0 | L85: =IFERROR(Materials!J85+Materials!K85,"") -> 0 | M85: =IFERROR(IF(Materials!L85=0,0,Materials!H85/Materials!L85),"") -> 0 | N85: =IFERROR(Materials!G85-Materials!L85,"") -> 1800 | O85: =IFERROR(IF(Materials!G85=0,0,Materials!N85/Materials!G85),"") -> 1 | P85: 0050301000 | Q85: A
B86: O | C86: O | D86: 00300325 - LEGAL | E86: 0 | F86: =IFERROR(Materials!G86-Materials!E86,"") -> 0 | G86: 0 | J86: =IFERROR(Materials!H86+Materials!I86,"") -> 0 | L86: =IFERROR(Materials!J86+Materials!K86,"") -> 0 | M86: =IFERROR(IF(Materials!L86=0,0,Materials!H86/Materials!L86),"") -> 0 | N86: =IFERROR(Materials!G86-Materials!L86,"") -> 0 | O86: =IFERROR(IF(Materials!G86=0,0,Materials!N86/Materials!G86),"") -> 0 | P86: 0050301000 | Q86: A
B87: O | C87: O | D87: 00300328 - SAFETY DRUG TESTING | E87: 3300 | F87: =IFERROR(Materials!G87-Materials!E87,"") -> 0 | G87: 3300 | J87: =IFERROR(Materials!H87+Materials!I87,"") -> 0 | L87: =IFERROR(Materials!J87+Materials!K87,"") -> 0 | M87: =IFERROR(IF(Materials!L87=0,0,Materials!H87/Materials!L87),"") -> 0 | N87: =IFERROR(Materials!G87-Materials!L87,"") -> 3300 | O87: =IFERROR(IF(Materials!G87=0,0,Materials!N87/Materials!G87),"") -> 1 | P87: 0050301000 | Q87: A
... B91: O | C91: O | D91: 00400450 - PREFAB | E91: 0 | F91: =IFERROR(Materials!G91-Materials!E91,"") -> 0 | G91: 0 | J91: =IFERROR(Materials!H91+Materials!I91,"") -> 0 | L91: =IFERROR(Materials!J91+Materials!K91,"") -> 0 | M91: =IFERROR(IF(Materials!L91=0,0,Materials!H91/Materials!L91),"") -> 0 | N91: =IFERROR(Materials!G91-Materials!L91,"") -> 0 | O91: =IFERROR(IF(Materials!G91=0,0,Materials!N91/Materials!G91),"") -> 0 | P91: 0050301000 | Q91: A
B92: Subtotal of O | C92: - | D92: - | E92: =SUBTOTAL(9,E71:E91) -> 281240 | F92: =SUBTOTAL(9,F71:F91) -> 0 | G92: =SUBTOTAL(9,G71:G91) -> 281240 | H92: =SUBTOTAL(9,H71:H91) -> 0 | I92: =SUBTOTAL(9,I71:I91) -> 2444.16 | J92: =SUBTOTAL(9,J71:J91) -> 2444.16 | K92: =SUBTOTAL(9,K71:K91) -> 0 | L92: =SUBTOTAL(9,L71:L91) -> 2444.16 | M92: - | N92: =SUBTOTAL(9,N71:N91) -> 278795.84 | O92: - | P92: - | Q92: -
B93: S | C93: S | D93: 00200203 - FIRE ALARM SUB CONTRACT | E93: 203000 | F93: =IFERROR(Materials!G93-Materials!E93,"") -> 0 | G93: 203000 | I93: 203879 | J93: =IFERROR(Materials!H93+Materials!I93,"") -> 203879 | L93: =IFERROR(Materials!J93+Materials!K93,"") -> 203879 | M93: =IFERROR(IF(Materials!L93=0,0,Materials!H93/Materials!L93),"") -> 0 | N93: =IFERROR(Materials!G93-Materials!L93,"") -> -879 | O93: =IFERROR(IF(Materials!G93=0,0,Materials!N93/Materials!G93),"") -> -0.0043300493 | P93: 0050301000 | Q93: A
B94: S | C94: S | D94: 00200204 - LIGHTNING PROTECTION | E94: 95900 | F94: =IFERROR(Materials!G94-Materials!E94,"") -> 0 | G94: 95900 | I94: 95900 | J94: =IFERROR(Materials!H94+Materials!I94,"") -> 95900 | L94: =IFERROR(Materials!J94+Materials!K94,"") -> 95900 | M94: =IFERROR(IF(Materials!L94=0,0,Materials!H94/Materials!L94),"") -> 0 | N94: =IFERROR(Materials!G94-Materials!L94,"") -> 0 | O94: =IFERROR(IF(Materials!G94=0,0,Materials!N94/Materials!G94),"") -> 0 | P94: 0050301000 | Q94: A
B95: S | C95: S | D95: 00200209 - TESTING | E95: 0 | F95: =IFERROR(Materials!G95-Materials!E95,"") -> 0 | G95: 0 | J95: =IFERROR(Materials!H95+Materials!I95,"") -> 0 | L95: =IFERROR(Materials!J95+Materials!K95,"") -> 0 | M95: =IFERROR(IF(Materials!L95=0,0,Materials!H95/Materials!L95),"") -> 0 | N95: =IFERROR(Materials!G95-Materials!L95,"") -> 0 | O95: =IFERROR(IF(Materials!G95=0,0,Materials!N95/Materials!G95),"") -> 0 | P95: 0050301000 | Q95: A
B96: S | C96: S | D96: 00200211 - DITCHING | E96: 39000 | F96: =IFERROR(Materials!G96-Materials!E96,"") -> 0 | G96: 39000 | J96: =IFERROR(Materials!H96+Materials!I96,"") -> 0 | L96: =IFERROR(Materials!J96+Materials!K96,"") -> 0 | M96: =IFERROR(IF(Materials!L96=0,0,Materials!H96/Materials!L96),"") -> 0 | N96: =IFERROR(Materials!G96-Materials!L96,"") -> 39000 | O96: =IFERROR(IF(Materials!G96=0,0,Materials!N96/Materials!G96),"") -> 1 | P96: 0050301000 | Q96: A
B97: S | C97: S | D97: 00200212 - CRANE | E97: 4086 | F97: =IFERROR(Materials!G97-Materials!E97,"") -> 0 | G97: 4086 | J97: =IFERROR(Materials!H97+Materials!I97,"") -> 0 | L97: =IFERROR(Materials!J97+Materials!K97,"") -> 0 | M97: =IFERROR(IF(Materials!L97=0,0,Materials!H97/Materials!L97),"") -> 0 | N97: =IFERROR(Materials!G97-Materials!L97,"") -> 4086 | O97: =IFERROR(IF(Materials!G97=0,0,Materials!N97/Materials!G97),"") -> 1 | P97: 0050301000 | Q97: A
B98: S | C98: S | D98: 00200213 - RIGGING/MOVERS | E98: 0 | F98: =IFERROR(Materials!G98-Materials!E98,"") -> 0 | G98: 0 | J98: =IFERROR(Materials!H98+Materials!I98,"") -> 0 | L98: =IFERROR(Materials!J98+Materials!K98,"") -> 0 | M98: =IFERROR(IF(Materials!L98=0,0,Materials!H98/Materials!L98),"") -> 0 | N98: =IFERROR(Materials!G98-Materials!L98,"") -> 0 | O98: =IFERROR(IF(Materials!G98=0,0,Materials!N98/Materials!G98),"") -> 0 | P98: 0050301000 | Q98: A
B99: S | C99: S | D99: 00200214 - TELE/DATA | E99: 0 | F99: =IFERROR(Materials!G99-Materials!E99,"") -> 0 | G99: 0 | J99: =IFERROR(Materials!H99+Materials!I99,"") -> 0 | L99: =IFERROR(Materials!J99+Materials!K99,"") -> 0 | M99: =IFERROR(IF(Materials!L99=0,0,Materials!H99/Materials!L99),"") -> 0 | N99: =IFERROR(Materials!G99-Materials!L99,"") -> 0 | O99: =IFERROR(IF(Materials!G99=0,0,Materials!N99/Materials!G99),"") -> 0 | P99: 0050301000 | Q99: A
B100: S | C100: S | D100: 00200215 - SECURITY/CCTV | E100: 0 | F100: =IFERROR(Materials!G100-Materials!E100,"") -> 0 | G100: 0 | J100: =IFERROR(Materials!H100+Materials!I100,"") -> 0 | L100: =IFERROR(Materials!J100+Materials!K100,"") -> 0 | M100: =IFERROR(IF(Materials!L100=0,0,Materials!H100/Materials!L100),"") -> 0 | N100: =IFERROR(Materials!G100-Materials!L100,"") -> 0 | O100: =IFERROR(IF(Materials!G100=0,0,Materials!N100/Materials!G100),"") -> 0 | P100: 0050301000 | Q100: A
B101: S | C101: S | D101: 00200216 - NURSE CALL | E101: 0 | F101: =IFERROR(Materials!G101-Materials!E101,"") -> 0 | G101: 0 | J101: =IFERROR(Materials!H101+Materials!I101,"") -> 0 | L101: =IFERROR(Materials!J101+Materials!K101,"") -> 0 | M101: =IFERROR(IF(Materials!L101=0,0,Materials!H101/Materials!L101),"") -> 0 | N101: =IFERROR(Materials!G101-Materials!L101,"") -> 0 | O101: =IFERROR(IF(Materials!G101=0,0,Materials!N101/Materials!G101),"") -> 0 | P101: 0050301000 | Q101: A
B102: S | C102: S | D102: 00200217 - A/V | E102: 0 | F102: =IFERROR(Materials!G102-Materials!E102,"") -> 0 | G102: 0 | J102: =IFERROR(Materials!H102+Materials!I102,"") -> 0 | L102: =IFERROR(Materials!J102+Materials!K102,"") -> 0 | M102: =IFERROR(IF(Materials!L102=0,0,Materials!H102/Materials!L102),"") -> 0 | N102: =IFERROR(Materials!G102-Materials!L102,"") -> 0 | O102: =IFERROR(IF(Materials!G102=0,0,Materials!N102/Materials!G102),"") -> 0 | P102: 0050301000 | Q102: A
B103: S | C103: S | D103: 00200218 - CONTROLS | E103: 0 | F103: =IFERROR(Materials!G103-Materials!E103,"") -> 0 | G103: 0 | J103: =IFERROR(Materials!H103+Materials!I103,"") -> 0 | L103: =IFERROR(Materials!J103+Materials!K103,"") -> 0 | M103: =IFERROR(IF(Materials!L103=0,0,Materials!H103/Materials!L103),"") -> 0 | N103: =IFERROR(Materials!G103-Materials!L103,"") -> 0 | O103: =IFERROR(IF(Materials!G103=0,0,Materials!N103/Materials!G103),"") -> 0 | P103: 0050301000 | Q103: A
B104: S | C104: S | D104: 00200222 - SOLAR | E104: 52974 | F104: =IFERROR(Materials!G104-Materials!E104,"") -> 0 | G104: 52974 | J104: =IFERROR(Materials!H104+Materials!I104,"") -> 0 | L104: =IFERROR(Materials!J104+Materials!K104,"") -> 0 | M104: =IFERROR(IF(Materials!L104=0,0,Materials!H104/Materials!L104),"") -> 0 | N104: =IFERROR(Materials!G104-Materials!L104,"") -> 52974 | O104: =IFERROR(IF(Materials!G104=0,0,Materials!N104/Materials!G104),"") -> 1 | P104: 0050301000 | Q104: A
B105: S | C105: S | D105: 00200224 - SCANNING & CORING | E105: 5500 | F105: =IFERROR(Materials!G105-Materials!E105,"") -> 0 | G105: 5500 | J105: =IFERROR(Materials!H105+Materials!I105,"") -> 0 | L105: =IFERROR(Materials!J105+Materials!K105,"") -> 0 | M105: =IFERROR(IF(Materials!L105=0,0,Materials!H105/Materials!L105),"") -> 0 | N105: =IFERROR(Materials!G105-Materials!L105,"") -> 5500 | O105: =IFERROR(IF(Materials!G105=0,0,Materials!N105/Materials!G105),"") -> 1 | P105: 0050301000 | Q105: A
B106: S | C106: S | D106: 00200225 - HYDROVAC | E106: 6500 | F106: =IFERROR(Materials!G106-Materials!E106,"") -> 0 | G106: 6500 | J106: =IFERROR(Materials!H106+Materials!I106,"") -> 0 | L106: =IFERROR(Materials!J106+Materials!K106,"") -> 0 | M106: =IFERROR(IF(Materials!L106=0,0,Materials!H106/Materials!L106),"") -> 0 | N106: =IFERROR(Materials!G106-Materials!L106,"") -> 6500 | O106: =IFERROR(IF(Materials!G106=0,0,Materials!N106/Materials!G106),"") -> 1 | P106: 0050301000 | Q106: A
B107: S | C107: S | D107: 00200226 - CABLE TESTING | E107: 5000 | F107: =IFERROR(Materials!G107-Materials!E107,"") -> 0 | G107: 5000 | I107: 4100 | J107: =IFERROR(Materials!H107+Materials!I107,"") -> 4100 | L107: =IFERROR(Materials!J107+Materials!K107,"") -> 4100 | M107: =IFERROR(IF(Materials!L107=0,0,Materials!H107/Materials!L107),"") -> 0 | N107: =IFERROR(Materials!G107-Materials!L107,"") -> 900 | O107: =IFERROR(IF(Materials!G107=0,0,Materials!N107/Materials!G107),"") -> 0.18 | P107: 0050301000 | Q107: A
B108: S | C108: S | D108: 00300308 - TRENCHING SUBCONTRACTOR | E108: 0 | F108: =IFERROR(Materials!G108-Materials!E108,"") -> 0 | G108: 0 | J108: =IFERROR(Materials!H108+Materials!I108,"") -> 0 | L108: =IFERROR(Materials!J108+Materials!K108,"") -> 0 | M108: =IFERROR(IF(Materials!L108=0,0,Materials!H108/Materials!L108),"") -> 0 | N108: =IFERROR(Materials!G108-Materials!L108,"") -> 0 | O108: =IFERROR(IF(Materials!G108=0,0,Materials!N108/Materials!G108),"") -> 0 | P108: 0050301000 | Q108: A
B109: S | C109: S | D109: 00300309 - TESTING SERVICES | E109: 0 | F109: =IFERROR(Materials!G109-Materials!E109,"") -> 0 | G109: 0 | J109: =IFERROR(Materials!H109+Materials!I109,"") -> 0 | L109: =IFERROR(Materials!J109+Materials!K109,"") -> 0 | M109: =IFERROR(IF(Materials!L109=0,0,Materials!H109/Materials!L109),"") -> 0 | N109: =IFERROR(Materials!G109-Materials!L109,"") -> 0 | O109: =IFERROR(IF(Materials!G109=0,0,Materials!N109/Materials!G109),"") -> 0 | P109: 0050301000 | Q109: A
B110: S | C110: S | D110: 00300310 - CRANE | E110: 0 | F110: =IFERROR(Materials!G110-Materials!E110,"") -> 0 | G110: 0 | J110: =IFERROR(Materials!H110+Materials!I110,"") -> 0 | L110: =IFERROR(Materials!J110+Materials!K110,"") -> 0 | M110: =IFERROR(IF(Materials!L110=0,0,Materials!H110/Materials!L110),"") -> 0 | N110: =IFERROR(Materials!G110-Materials!L110,"") -> 0 | O110: =IFERROR(IF(Materials!G110=0,0,Materials!N110/Materials!G110),"") -> 0 | P110: 0050301000 | Q110: A
B111: S | C111: S | D111: 00300311 - CABLE TEST | E111: 0 | F111: =IFERROR(Materials!G111-Materials!E111,"") -> 0 | G111: 0 | J111: =IFERROR(Materials!H111+Materials!I111,"") -> 0 | L111: =IFERROR(Materials!J111+Materials!K111,"") -> 0 | M111: =IFERROR(IF(Materials!L111=0,0,Materials!H111/Materials!L111),"") -> 0 | N111: =IFERROR(Materials!G111-Materials!L111,"") -> 0 | O111: =IFERROR(IF(Materials!G111=0,0,Materials!N111/Materials!G111),"") -> 0 | P111: 0050301000 | Q111: A
B112: S | C112: S | D112: 00300326 - CONTRACT LABOR | E112: 0 | F112: =IFERROR(Materials!G112-Materials!E112,"") -> 0 | G112: 0 | J112: =IFERROR(Materials!H112+Materials!I112,"") -> 0 | L112: =IFERROR(Materials!J112+Materials!K112,"") -> 0 | M112: =IFERROR(IF(Materials!L112=0,0,Materials!H112/Materials!L112),"") -> 0 | N112: =IFERROR(Materials!G112-Materials!L112,"") -> 0 | O112: =IFERROR(IF(Materials!G112=0,0,Materials!N112/Materials!G112),"") -> 0 | P112: 0050301000 | Q112: A
B113: S | C113: S | D113: 00300399 - MISC SUBCONTRACTOR SVCS | E113: 0 | F113: =IFERROR(Materials!G113-Materials!E113,"") -> 0 | G113: 0 | J113: =IFERROR(Materials!H113+Materials!I113,"") -> 0 | L113: =IFERROR(Materials!J113+Materials!K113,"") -> 0 | M113: =IFERROR(IF(Materials!L113=0,0,Materials!H113/Materials!L113),"") -> 0 | N113: =IFERROR(Materials!G113-Materials!L113,"") -> 0 | O113: =IFERROR(IF(Materials!G113=0,0,Materials!N113/Materials!G113),"") -> 0 | P113: 0050301000 | Q113: A
B114: Subtotal of S | C114: - | D114: - | E114: =SUBTOTAL(9,E93:E113) -> 411960 | F114: =SUBTOTAL(9,F93:F113) -> 0 | G114: =SUBTOTAL(9,G93:G113) -> 411960 | H114: =SUBTOTAL(9,H93:H113) -> 0 | I114: =SUBTOTAL(9,I93:I113) -> 303879 | J114: =SUBTOTAL(9,J93:J113) -> 303879 | K114: =SUBTOTAL(9,K93:K113) -> 0 | L114: =SUBTOTAL(9,L93:L113) -> 303879 | M114: - | N114: =SUBTOTAL(9,N93:N113) -> 108081 | O114: - | P114: - | Q114: -
...

Sheet DATA
B7: VarRevenue | C7: VarLabor | D7: VarBurden | E7: VarMatSub | F7: VarDJEOthers | G7: VarProfitPercOnCost | H7: EarnedMHs | I7: ActualMHs | J7: CompositeRateEst | K7: CompositeRateAct

Sheet Sheet7
A1: ='Labor Projection'!D3 -> 2025-12-31
B4: Job | C4: Department | D4: Project Manager | E4: EOPeriodDate | F4: Estimated Manhours | G4: Estimated Gross Margin | H4: Current Labor Performance Factor | I4: Actual Manhour | J4: Actual Gross Margin | K4: Labor performance factorr | L4: Labor Performance Factor cost | M4: bid day Labor Performance Factor | N4: Est%CompleteATYE | O4: JTD Billings | P4: JTD Revenue | Q4: overunderbilling | R4: JTD collected | S4: JTD Cost | T4: Net Cash Position | U4: Estimated Composite Rate | V4: Actual Composite rate | W4: Composite Rate Variance | X4: AR Aged Current | Y4: ARAged130days | Z4: ARAged3160days | AA4: ARAged6190days | AB4: ARAgedover90days
B5: =IFERROR(Summary!$J$9,"0") -> 643700 | C5: =IFERROR(Summary!$O$13,"0") -> 0 | D5: =IFERROR(Summary!$J$10,"0") -> J RAMOS | E5: =IFERROR(Sheet7!$A$1,0) -> 2025-12-31 | F5: =IFERROR(IF(Summary!$J$36="none",0,Summary!$J$36),0) -> 0 | G5: =IFERROR(IF(Summary!$K$36="none",0,Summary!$K$36),0) -> 0 | H5: =IFERROR(IF(Summary!$J$38="none",0,Summary!$J$38),0) -> 0 | I5: =IFERROR(IF(Summary!$J$37="none",0,Summary!$J$37),0) -> 290 | J5: =IFERROR(IF(Summary!$K$37="none",0,Summary!$K$37),0) -> 14990.1 | K5: =IFERROR(IF(Summary!$J$38="none",0,Summary!$J$38),0) -> 0 | L5: =IFERROR(IF(Summary!$K$38="none",0,Summary!$K$38),0) -> 0 | M5: =IFERROR(IF(Summary!$J$43="none",0,Summary!$J$43),0) -> 0 | N5: =IFERROR(IF(Summary!$J$41="none",0,Summary!$J$41),0) -> 0.03 | O5: =IFERROR(IF(Summary!$F$30="none",0,Summary!$F$30),0) -> 0 | P5: =IFERROR(IF(Summary!$F$31="none",0,Summary!$F$31),0) -> 0 | Q5: =IFERROR(IF(Summary!$F$32="none",0,Summary!$F$32),0) -> 0 | R5: =IFERROR(IF(Summary!$J$30="none",0,Summary!$J$30),0) -> 0 | S5: =IFERROR(IF(Summary!$J$31="none",0,Summary!$J$31),0) -> 24375.4 | T5: =IFERROR(IF(Summary!$J$32="none",0,Summary!$J$32),0) -> 0 | U5: =IFERROR(IF(Summary!$F$36="none",0,Summary!$F$36),0) -> 0 | V5: =IFERROR(IF(Summary!$F$37="none",0,Summary!$F$37),0) -> 51.69 | W5: =IFERROR(IF(Summary!$F$38="none",0,Summary!$F$38),0) -> 0 | X5: =IFERROR(IF(Summary!$F$42="none",0,Summary!$F$42),0) -> 0 | Y5: =IFERROR(IF(Summary!$F$43="none",0,Summary!$F$43),0) -> 0 | Z5: =IFERROR(IF(Summary!$F$44="none",0,Summary!$F$44),0) -> 0 | AA5: =IFERROR(IF(Summary!$F$45="none",0,Summary!$F$45),0) -> 0 | AB5: =IFERROR(IF(Summary!$F$46="none",0,Summary!$F$46),0) -> 0

Sheet Labor Performance
B2: ProjectUniqueID | C2: EOPeriodDate | D2: Labor_Performance_Factor | E2: Labor_Performance_Cost | F2: Bid_day_Labor_Performance_Factor
