Workbook
Name __Complete___YE_Block5: Divisions!$V$16
Name __Complete___YE_Block6: Divisions!$V$16
Name __Complete___YE_Block8: Divisions!$V$16
Name __Complete___YE_Division: Divisions!$V$16
Name __Complete___YE_WIP_ProjectManager: 'Project Managers'!$X$12
Name __Complete_Block5: Divisions!$Q$16
Name __Complete_Block6: Divisions!$Q$16
Name __Complete_Block8: Divisions!$Q$16
Name __Complete_Division: Divisions!$Q$16
Name __Complete_WIP_ProjectManager: 'Project Managers'!$Q$12
Name _CY1_Estimated__Cost__Block8: Divisions!$AD$16
Name _CY1_Estimated__Cost__Division: Divisions!$AD$16
Name _CY1_Estimated__Cost__WIP_ProjectManager: 'Project Managers'!$AG$12
Name _Estimated__Cost__Block5: Divisions!$AD$16
Name _Estimated__Cost__Block6: Divisions!$AD$16
Name _Under__Billing_Block5: Divisions!$O$16
Name _Under__Billing_Block6: Divisions!$O$16
Name _Under__Billing_Block8: Divisions!$O$16
Name _Under__Billing_Division: Divisions!$O$16
Name _Under__Billing_WIP_ProjectManager: 'Project Managers'!$O$12
Name Backlog_Block5: Divisions!$P$16
Name Backlog_Block6: Divisions!$P$16
Name Backlog_Block8: Divisions!$P$16
Name Backlog_Division: Divisions!$P$16
Name Backlog_WIP_ProjectManager: 'Project Managers'!$P$12
Name Billed_Amount_Block5: Divisions!$M$16
Name Billed_Amount_Block6: Divisions!$M$16
Name Billed_Amount_Block8: Divisions!$M$16
Name Billed_Amount_Division: Divisions!$M$16
Name Billed_Amount_WIP_ProjectManager: 'Project Managers'!$M$12
Name Comments_Block5: Divisions!$AO$16
Name Comments_Block6: Divisions!$AO$16
Name Comments_Block8: Divisions!$AO$16
Name Comments_Division: Divisions!$AO$16
Name Comments_WIP_ProjectManager: 'Project Managers'!$AR$12
Name Contract__Amount_Block5: Divisions!$AC$16
Name Contract__Amount_Block6: Divisions!$AC$16
Name Contract_Amount____Block5: Divisions!$AH$16
Name Contract_Amount____Block6: Divisions!$AH$16
Name Contract_Amount__Block5: Divisions!$X$16
Name Contract_Amount__Block6: Divisions!$X$16
Name Cost_to_Date_Block5: Divisions!$J$16
Name Cost_to_Date_Block6: Divisions!$J$16
Name Cost_to_Date_Block8: Divisions!$J$16
Name Cost_to_Date_Division: Divisions!$J$16
Name Cost_to_Date_WIP_ProjectManager: 'Project Managers'!$J$12
Name Current_Contract_Amount_Block5: Divisions!$E$16
Name Current_Contract_Amount_Block6: Divisions!$E$16
Name Current_Contract_Amount_Block8: Divisions!$E$16
Name Current_Contract_Amount_Division: Divisions!$E$16
Name Current_Contract_Amount_WIP_ProjectManager: 'Project Managers'!$E$12
Name CY_Contract_Amount__Block8: Divisions!$X$16
Name CY_Contract_Amount__Division: Divisions!$X$16
Name CY_Contract_Amount__WIP_ProjectManager: 'Project Managers'!$AA$12
Name CY_Estimated_Cost_Block8: Divisions!$Y$16
Name CY_Estimated_Cost_Division: Divisions!$Y$16
Name CY_Estimated_Cost_WIP_ProjectManager: 'Project Managers'!$AB$12
Name CY_GM_____Block8: Divisions!$AA$16
Name CY_GM_____Division: Divisions!$AA$16
Name CY_GM_____WIP_ProjectManager: 'Project Managers'!$AD$12

Sheet Query
A1: WITH subqueryTable0 AS (
A2: SELECT
A3: MAX(table0.CorporateFilter__custom) AS CorporateFilter__custom,
A4: MAX(table0.project_manager) AS Project_Manager__custom,
A5: MAX(table0.project_manager) AS projectmanager__standard,
A6: SUM(table0.GM) AS EStimatedGMPct__custom,
A7: '2025-12-31' AS EOPeriodDate,
A8: table0.New_Job_Number AS ProjectUniqueID
A9: FROM
A10: PHASE_MASTER AS table0
A11: WHERE
A12: (
... A181: ProjectUniqueID

Sheet Project Managers
E7: Estimated | Y7: =YEAR(Divisions!H4) -> 2025 | AE7: =Y7+1 -> 2026 | AJ7: =AE7+1 -> 2027
B8: {=B11} -> Project Manager | C8: {=C11} -> Job Number | D8: {=D11} -> Description | E8: {=E11} -> Current Contract Amount | F8: {=F11} -> Estimated Cost | G8: {=G11} -> Gross Margin | H8: {=H11} -> GM% | I8: {=I11} -> JTD Earned Revenue | ... Y8: {=Y11} -> Prior Period Revised % Complete @ YE | Z8: Revised % Complete @ YE | AA8: Contract Amount | AB8: Estimated Cost | AC8: Gross Margin | AD8: GM % | AE8: Revised % Complete @ YE | AF8: Contract Amount | AG8: Estimated Cost | AH8: Gross Margin | AI8: GM % | AJ8: Revised % Complete @ YE | AK8: Contract Amount | AL8: Estimated Cost | AM8: Gross Margin | AN8: GM % | AO8: Gross Margin | AP8: GM % | AQ8: {=AP11} -> pmestimatedgmpercentage__custom | AR8: {=AR11} -> Comments
B11: Project Manager | C11: Job Number | D11: Description | E11: Current Contract Amount | F11: Estimated Cost | G11: Gross Margin | H11: GM% | I11: JTD Earned Revenue | J11: Cost to Date | K11: Gross Margin to Date | L11: GM % | M11: Billed Amount | N11: Over Billing | O11: (Under) Billing | P11: Backlog | Q11: % Complete | R11: PM Estimated GM % | S11: Prior Period Revised PM Estimated GM % | T11: Revised PM Estimated GM % | U11: Potential Profit | V11: Prior Period Revised Potential Profit | W11: Revised Potential Profit | X11: % Complete @ YE | Y11: Prior Period Revised % Complete @ YE | Z11: Revised % Complete @ YE | AA11: CY Contract Amount | AB11: CY Estimated Cost | AC11: CY Gross Margin | AD11: CY GM % | AE11: RevisedCY1 % Complete | AF11: CY1 Contract Amount | AG11: CY1 Estimated Cost | AH11: CY1 Gross Margin | AI11: CY1GM% | AJ11: CY2 Revised % Complete @ YE | AK11: CY2 Contract Amount | AL11: CY2 Estimated Cost | AM11: CY2 Gross Margin | AN11: CY2 GM % | AO11: estimatedgmpercentage__custom | AP11: pmestimatedgmpercentage__custom | AQ11: percentagecompleteatye__custom | AR11: Comments | AS11: EStimatedGMPct | BT11: Comments
B12: B LIU | C12: 719500 | D12: SWITCH RR NAP 4 | E12: 20845819 | F12: =IFERROR('Project Managers'!E12*(1-'Project Managers'!H12),0) -> 16885113 | G12: =IFERROR('Project Managers'!E12-'Project Managers'!F12,0) -> 3960705.6 | H12: {=IF(ISBLANK('Project Managers'!AO12),'Project Managers'!R12,'Project Managers'!AO12)} -> 0.19 | I12: 20845819 | J12: 16381247 | K12: =IFERROR('Project Managers'!I12-'Project Managers'!J12,0) -> 4464572.5 | L12: =IFERROR('Project Managers'!K12/'Project Managers'!I12,0) -> 0.21417112 | M12: 20845819 | N12: =IFERROR(IF('Project Managers'!M12-'Project Managers'!I12>0,'Project Managers'!M12-'Project Managers'!I12,0),0) -> 0 | O12: =IFERROR(IF('Project Managers'!M12-'Project Managers'!I12<0,'Project Managers'!M12-'Project Managers'!I12,0),0) -> 0 | P12: =IFERROR('Project Managers'!E12-'Project Managers'!I12,0) -> 0 | Q12: =IFERROR(ROUND('Project Managers'!I12/'Project Managers'!E12,4),0) -> 1 | R12: {=IF(ISBLANK('Project Managers'!AP12),IF('Project Managers'!I12<>0,('Project Managers'!I12-'Project Managers'!J12)/'Project Managers'!I12,'Project Managers'!AS12),'Project Managers'!AP12)} -> 0.21 | S12: 0.2149 | T12: 0.2142 | U12: =IFERROR(-('Project Managers'!I12-('Project Managers'!J12/(1-'Project Managers'!R12))),0) -> -110063.92 | V12: -690.43765 | W12: =IFERROR(-('Project Managers'!I12-('Project Managers'!J12/(1-'Project Managers'!T12))),0) -> 766.02709 | X12: =IFERROR(IF('Project Managers'!AQ12="",1,'Project Managers'!AQ12),0) -> 1 | Y12: 1 | Z12: 1 | AA12: =IFERROR(IF('Project Managers'!Z12='Project Managers'!Q12,0,(('Project Managers'!Z12*'Project Managers'!E12)-'Project Managers'!I12)),0) -> 0 | AB12: =IFERROR(IF('Project Managers'!Z12='Project Managers'!Q12,0,('Project Managers'!AA12-('Project Managers'!AA12*'Project Managers'!L12))),0) -> 0 | AC12: =IFERROR('Project Managers'!AA12-'Project Managers'!AB12,0) -> 0 | AD12: =IFERROR('Project Managers'!AC12/'Project Managers'!AA12,0) -> 0 | AE12: =IFERROR(IF('Project Managers'!Z12<1,1,0),0) -> 0 | AF12: =IFERROR(IF('Project Managers'!AE12=0,0,('Project Managers'!AE12*'Project Managers'!E12)-'Project Managers'!I12-'Project Managers'!AA12),0) -> 0 | AG12: =IFERROR(IF('Project Managers'!AE12='Project Managers'!V12,0,('Project Managers'!AF12-('Project Managers'!AF12*'Project Managers'!L12))),0) -> 0 | AH12: =IFERROR('Project Managers'!AF12-'Project Managers'!AG12,0) -> 0 | AI12: =IFERROR('Project Managers'!AH12/'Project Managers'!AF12,0) -> 0 | AK12: =IFERROR(IF('Project Managers'!AJ12=0,0,('Project Managers'!AJ12*'Project Managers'!E12)-'Project Managers'!I12-'Project Managers'!AA12-'Project Managers'!AF12),0) -> 0 | AL12: =IFERROR(IF('Project Managers'!AJ12='Project Managers'!V12,0,('Project Managers'!AK12-('Project Managers'!AK12*'Project Managers'!L12))),0) -> 0 | AM12: =IFERROR('Project Managers'!AK12-'Project Managers'!AL12,0) -> 0 | AN12: =IFERROR('Project Managers'!AM12/'Project Managers'!AK12,0) -> 0 | AO12: 0.19 | AP12: 0.21
B13: B LIU | C13: 722320 | D13: SPACEX DIRECT WORK | E13: 128026.07 | F13: =IFERROR('Project Managers'!E13*(1-'Project Managers'!H13),0) -> 106193.44 | G13: =IFERROR('Project Managers'!E13-'Project Managers'!F13,0) -> 21832.631 | H13: {=IF(ISBLANK('Project Managers'!AO13),'Project Managers'!R13,'Project Managers'!AO13)} -> 0.1705327 | I13: 124814.07 | J13: 103529.19 | K13: =IFERROR('Project Managers'!I13-'Project Managers'!J13,0) -> 21284.88 | L13: =IFERROR('Project Managers'!K13/'Project Managers'!I13,0) -> 0.1705327 | M13: 124814.07 | N13: =IFERROR(IF('Project Managers'!M13-'Project Managers'!I13>0,'Project Managers'!M13-'Project Managers'!I13,0),0) -> 0 | O13: =IFERROR(IF('Project Managers'!M13-'Project Managers'!I13<0,'Project Managers'!M13-'Project Managers'!I13,0),0) -> 0 | P13: =IFERROR('Project Managers'!E13-'Project Managers'!I13,0) -> 3212 | Q13: =IFERROR(ROUND('Project Managers'!I13/'Project Managers'!E13,4),0) -> 0.9749 | R13: =IF(ISBLANK('Project Managers'!AP13),IF('Project Managers'!I13<>0,('Project Managers'!I13-'Project Managers'!J13)/'Project Managers'!I13,'Project Managers'!AS13),'Project Managers'!AP13) -> 0.1705327 | S13: 0.15 | T13: 0.15 | U13: =IFERROR(-('Project Managers'!I13-('Project Managers'!J13/(1-'Project Managers'!R13))),0) -> 0 | V13: -3850.67 | W13: =IFERROR(-('Project Managers'!I13-('Project Managers'!J13/(1-'Project Managers'!T13))),0) -> -3015.0229 | X13: =IFERROR(IF('Project Managers'!AQ13="",1,'Project Managers'!AQ13),0) -> 1 | Y13: 1 | Z13: 1 | AA13: =IFERROR(IF('Project Managers'!Z13='Project Managers'!Q13,0,(('Project Managers'!Z13*'Project Managers'!E13)-'Project Managers'!I13)),0) -> 3212 | AB13: =IFERROR(IF('Project Managers'!Z13='Project Managers'!Q13,0,('Project Managers'!AA13-('Project Managers'!AA13*'Project Managers'!L13))),0) -> 2664.249 | AC13: =IFERROR('Project Managers'!AA13-'Project Managers'!AB13,0) -> 547.75102 | AD13: =IFERROR('Project Managers'!AC13/'Project Managers'!AA13,0) -> 0.1705327 | AE13: =IFERROR(IF('Project Managers'!Z13<1,1,0),0) -> 0 | AF13: =IFERROR(IF('Project Managers'!AE13=0,0,('Project Managers'!AE13*'Project Managers'!E13)-'Project Managers'!I13-'Project Managers'!AA13),0) -> 0 | AG13: =IFERROR(IF('Project Managers'!AE13='Project Managers'!V13,0,('Project Managers'!AF13-('Project Managers'!AF13*'Project Managers'!L13))),0) -> 0 | AH13: =IFERROR('Project Managers'!AF13-'Project Managers'!AG13,0) -> 0 | AI13: =IFERROR('Project Managers'!AH13/'Project Managers'!AF13,0) -> 0 | AK13: =IFERROR(IF('Project Managers'!AJ13=0,0,('Project Managers'!AJ13*'Project Managers'!E13)-'Project Managers'!I13-'Project Managers'!AA13-'Project Managers'!AF13),0) -> 0 | AL13: =IFERROR(IF('Project Managers'!AJ13='Project Managers'!V13,0,('Project Managers'!AK13-('Project Managers'!AK13*'Project Managers'!L13))),0) -> 0 | AM13: =IFERROR('Project Managers'!AK13-'Project Managers'!AL13,0) -> 0 | AN13: =IFERROR('Project Managers'!AM13/'Project Managers'!AK13,0) -> 0 | AS13: 0.15
B14: Subtotal of B LIU | C14: - | D14: - | E14: =SUBTOTAL(9,E12:E13) -> 20973845 | F14: =SUBTOTAL(9,F12:F13) -> 16991307 | G14: =SUBTOTAL(9,G12:G13) -> 3982538.2 | H14: {=IF(ISBLANK('Project Managers'!AO14),'Project Managers'!R14,'Project Managers'!AO14)} -> - | I14: =SUBTOTAL(9,I12:I13) -> 20970633 | J14: =SUBTOTAL(9,J12:J13) -> 16484776 | K14: =SUBTOTAL(9,K12:K13) -> 4485857.4 | L14: =IFERROR('Project Managers'!K14/'Project Managers'!I14,0) -> 0.21391139 | M14: =SUBTOTAL(9,M12:M13) -> 20970633 | N14: =SUBTOTAL(9,N12:N13) -> 0 | O14: =SUBTOTAL(9,O12:O13) -> 0 | P14: =SUBTOTAL(9,P12:P13) -> 3212 | Q14: =IFERROR(ROUND('Project Managers'!I14/'Project Managers'!E14,4),0) -> 0.9998 | R14: - | S14: - | T14: - | U14: =SUBTOTAL(9,U12:U13) -> -110063.92 | V14: =SUBTOTAL(9,V12:V13) -> -4541.1077 | W14: =SUBTOTAL(9,W12:W13) -> -2248.9959 | X14: - | Y14: - | Z14: - | AA14: =SUBTOTAL(9,AA12:AA13) -> 3212 | AB14: =SUBTOTAL(9,AB12:AB13) -> 2664.249 | AC14: =IFERROR('Project Managers'!AA14-'Project Managers'!AB14,0) -> 547.75102 | AD14: =IFERROR('Project Managers'!AC14/'Project Managers'!AA14,0) -> 0.1705327 | AE14: =IFERROR(IF('Project Managers'!Z14<1,1,0),0) -> 0 | AF14: =SUBTOTAL(9,AF12:AF13) -> 0 | AG14: =SUBTOTAL(9,AG12:AG13) -> 0 | AH14: =SUBTOTAL(9,AH12:AH13) -> 0 | AI14: =IFERROR('Project Managers'!AH14/'Project Managers'!AF14,0) -> 0 | AJ14: - | AK14: =SUBTOTAL(9,AK12:AK13) -> 0 | AL14: =SUBTOTAL(9,AL12:AL13) -> 0 | AM14: =SUBTOTAL(9,AM12:AM13) -> 0 | AN14: =IFERROR('Project Managers'!AM14/'Project Managers'!AK14,0) -> 0 | AO14: - | AP14: - | AQ14: - | AR14: - | AS14: -
B15: B ONTIVEROS | C15: 722210 | D15: LIBERTY HILL HS #2 | E15: 11473198 | F15: =IFERROR('Project Managers'!E15*(1-'Project Managers'!H15),0) -> 9522754.3 | G15: =IFERROR('Project Managers'!E15-'Project Managers'!F15,0) -> 1950443.7 | H15: {=IF(ISBLANK('Project Managers'!AO15),'Project Managers'!R15,'Project Managers'!AO15)} -> 0.17 | I15: 10565813 | J15: 8976901.2 | K15: =IFERROR('Project Managers'!I15-'Project Managers'!J15,0) -> 1588911.5 | L15: =IFERROR('Project Managers'!K15/'Project Managers'!I15,0) -> 0.15038233 | M15: 10673409 | N15: =IFERROR(IF('Project Managers'!M15-'Project Managers'!I15>0,'Project Managers'!M15-'Project Managers'!I15,0),0) -> 107596.05 | O15: =IFERROR(IF('Project Managers'!M15-'Project Managers'!I15<0,'Project Managers'!M15-'Project Managers'!I15,0),0) -> 0 | P15: =IFERROR('Project Managers'!E15-'Project Managers'!I15,0) -> 907385.3 | Q15: =IFERROR(ROUND('Project Managers'!I15/'Project Managers'!E15,4),0) -> 0.9209 | R15: {=IF(ISBLANK('Project Managers'!AP15),IF('Project Managers'!I15<>0,('Project Managers'!I15-'Project Managers'!J15)/'Project Managers'!I15,'Project Managers'!AS15),'Project Managers'!AP15)} -> 0.19 | S15: 0.15 | T15: 0.15 | U15: =IFERROR(-('Project Managers'!I15-('Project Managers'!J15/(1-'Project Managers'!R15))),0) -> 516781.36 | V15: -4632.4106 | W15: =IFERROR(-('Project Managers'!I15-('Project Managers'!J15/(1-'Project Managers'!T15))),0) -> -4752.4765 | X15: =IFERROR(IF('Project Managers'!AQ15="",1,'Project Managers'!AQ15),0) -> 1 | Y15: 0.9898 | Z15: 0.87 | AA15: =IFERROR(IF('Project Managers'!Z15='Project Managers'!Q15,0,(('Project Managers'!Z15*'Project Managers'!E15)-'Project Managers'!I15)),0) -> -584130.44 | AB15: =IFERROR(IF('Project Managers'!Z15='Project Managers'!Q15,0,('Project Managers'!AA15-('Project Managers'!AA15*'Project Managers'!L15))),0) -> -496287.54 | AC15: =IFERROR('Project Managers'!AA15-'Project Managers'!AB15,0) -> -87842.895 | AD15: =IFERROR('Project Managers'!AC15/'Project Managers'!AA15,0) -> 0.15038233 | AE15: =IFERROR(IF('Project Managers'!Z15<1,1,0),0) -> 1 | AF15: =IFERROR(IF('Project Managers'!AE15=0,0,('Project Managers'!AE15*'Project Managers'!E15)-'Project Managers'!I15-'Project Managers'!AA15),0) -> 1491515.7 | AG15: =IFERROR(IF('Project Managers'!AE15='Project Managers'!V15,0,('Project Managers'!AF15-('Project Managers'!AF15*'Project Managers'!L15))),0) -> 1267218.1 | AH15: =IFERROR('Project Managers'!AF15-'Project Managers'!AG15,0) -> 224297.61 | AI15: =IFERROR('Project Managers'!AH15/'Project Managers'!AF15,0) -> 0.15038233 | AK15: =IFERROR(IF('Project Managers'!AJ15=0,0,('Project Managers'!AJ15*'Project Managers'!E15)-'Project Managers'!I15-'Project Managers'!AA15-'Project Managers'!AF15),0) -> 0 | AL15: =IFERROR(IF('Project Managers'!AJ15='Project Managers'!V15,0,('Project Managers'!AK15-('Project Managers'!AK15*'Project Managers'!L15))),0) -> 0 | AM15: =IFERROR('Project Managers'!AK15-'Project Managers'!AL15,0) -> 0 | AN15: =IFERROR('Project Managers'!AM15/'Project Managers'!AK15,0) -> 0 | AO15: 0.17 | AP15: 0.19 | AS15: 0.3
B16: B ONTIVEROS | C16: 722450 | D16: VALERO AUSTIN PAC OFFICE | E16: 404338.1 | F16: =IFERROR('Project Managers'!E16*(1-'Project Managers'!H16),0) -> 337510.95 | G16: =IFERROR('Project Managers'!E16-'Project Managers'!F16,0) -> 66827.152 | H16: {=IF(ISBLANK('Project Managers'!AO16),'Project Managers'!R16,'Project Managers'!AO16)} -> 0.16527543 | I16: 395116.39 | J16: 329813.36 | K16: =IFERROR('Project Managers'!I16-'Project Managers'!J16,0) -> 65303.03 | L16: =IFERROR('Project Managers'!K16/'Project Managers'!I16,0) -> 0.16527543 | M16: 404338.1 | N16: =IFERROR(IF('Project Managers'!M16-'Project Managers'!I16>0,'Project Managers'!M16-'Project Managers'!I16,0),0) -> 9221.71 | O16: =IFERROR(IF('Project Managers'!M16-'Project Managers'!I16<0,'Project Managers'!M16-'Project Managers'!I16,0),0) -> 0 | P16: =IFERROR('Project Managers'!E16-'Project Managers'!I16,0) -> 9221.71 | Q16: =IFERROR(ROUND('Project Managers'!I16/'Project Managers'!E16,4),0) -> 0.9772 | R16: =IF(ISBLANK('Project Managers'!AP16),IF('Project Managers'!I16<>0,('Project Managers'!I16-'Project Managers'!J16)/'Project Managers'!I16,'Project Managers'!AS16),'Project Managers'!AP16) -> 0.16527543 | S16: 0.17 | T16: 0.17 | U16: =IFERROR(-('Project Managers'!I16-('Project Managers'!J16/(1-'Project Managers'!R16))),0) -> 0 | V16: 9254.1282 | W16: =IFERROR(-('Project Managers'!I16-('Project Managers'!J16/(1-'Project Managers'!T16))),0) -> 2249.104 | X16: =IFERROR(IF('Project Managers'!AQ16="",1,'Project Managers'!AQ16),0) -> 1 | Y16: 1 | Z16: 1 | AA16: =IFERROR(IF('Project Managers'!Z16='Project Managers'!Q16,0,(('Project Managers'!Z16*'Project Managers'!E16)-'Project Managers'!I16)),0) -> 9221.71 | AB16: =IFERROR(IF('Project Managers'!Z16='Project Managers'!Q16,0,('Project Managers'!AA16-('Project Managers'!AA16*'Project Managers'!L16))),0) -> 7697.5879 | AC16: =IFERROR('Project Managers'!AA16-'Project Managers'!AB16,0) -> 1524.1221 | AD16: =IFERROR('Project Managers'!AC16/'Project Managers'!AA16,0) -> 0.16527543 | AE16: =IFERROR(IF('Project Managers'!Z16<1,1,0),0) -> 0 | AF16: =IFERROR(IF('Project Managers'!AE16=0,0,('Project Managers'!AE16*'Project Managers'!E16)-'Project Managers'!I16-'Project Managers'!AA16),0) -> 0 | AG16: =IFERROR(IF('Project Managers'!AE16='Project Managers'!V16,0,('Project Managers'!AF16-('Project Managers'!AF16*'Project Managers'!L16))),0) -> 0 | AH16: =IFERROR('Project Managers'!AF16-'Project Managers'!AG16,0) -> 0 | AI16: =IFERROR('Project Managers'!AH16/'Project Managers'!AF16,0) -> 0 | AK16: =IFERROR(IF('Project Managers'!AJ16=0,0,('Project Managers'!AJ16*'Project Managers'!E16)-'Project Managers'!I16-'Project Managers'!AA16-'Project Managers'!AF16),0) -> 0 | AL16: =IFERROR(IF('Project Managers'!AJ16='Project Managers'!V16,0,('Project Managers'!AK16-('Project Managers'!AK16*'Project Managers'!L16))),0) -> 0 | AM16: =IFERROR('Project Managers'!AK16-'Project Managers'!AL16,0) -> 0 | AN16: =IFERROR('Project Managers'!AM16/'Project Managers'!AK16,0) -> 0
B17: B ONTIVEROS | C17: 722500 | D17: CORR OSP ADMIN & REC | E17: 9526861 | F17: =IFERROR('Project Managers'!E17*(1-'Project Managers'!H17),0) -> 7906107.9 | G17: =IFERROR('Project Managers'!E17-'Project Managers'!F17,0) -> 1620753.1 | H17: {=IF(ISBLANK('Project Managers'!AO17),'Project Managers'!R17,'Project Managers'!AO17)} -> 0.17012456 | I17: 233598.07 | J17: 193857.3 | K17: =IFERROR('Project Managers'!I17-'Project Managers'!J17,0) -> 39740.77 | L17: =IFERROR('Project Managers'!K17/'Project Managers'!I17,0) -> 0.17012456 | M17: 268250 | N17: =IFERROR(IF('Project Managers'!M17-'Project Managers'!I17>0,'Project Managers'!M17-'Project Managers'!I17,0),0) -> 34651.93 | O17: =IFERROR(IF('Project Managers'!M17-'Project Managers'!I17<0,'Project Managers'!M17-'Project Managers'!I17,0),0) -> 0 | P17: =IFERROR('Project Managers'!E17-'Project Managers'!I17,0) -> 9293262.9 | Q17: =IFERROR(ROUND('Project Managers'!I17/'Project Managers'!E17,4),0) -> 0.0245 | R17: =IF(ISBLANK('Project Managers'!AP17),IF('Project Managers'!I17<>0,('Project Managers'!I17-'Project Managers'!J17)/'Project Managers'!I17,'Project Managers'!AS17),'Project Managers'!AP17) -> 0.17012456 | S17: 0.15 | T17: 0.17 | U17: =IFERROR(-('Project Managers'!I17-('Project Managers'!J17/(1-'Project Managers'!R17))),0) -> 0 | V17: -2771.5918 | W17: =IFERROR(-('Project Managers'!I17-('Project Managers'!J17/(1-'Project Managers'!T17))),0) -> -35.057952 | X17: =IFERROR(IF('Project Managers'!AQ17="",1,'Project Managers'!AQ17),0) -> 1 | Y17: 0.1111 | Z17: 0.05 | AA17: =IFERROR(IF('Project Managers'!Z17='Project Managers'!Q17,0,(('Project Managers'!Z17*'Project Managers'!E17)-'Project Managers'!I17)),0) -> 242744.98 | AB17: =IFERROR(IF('Project Managers'!Z17='Project Managers'!Q17,0,('Project Managers'!AA17-('Project Managers'!AA17*'Project Managers'!L17))),0) -> 201448.1 | AC17: =IFERROR('Project Managers'!AA17-'Project Managers'!AB17,0) -> 41296.884 | AD17: =IFERROR('Project Managers'!AC17/'Project Managers'!AA17,0) -> 0.17012456 | AE17: =IFERROR(IF('Project Managers'!Z17<1,1,0),0) -> 1 | AF17: =IFERROR(IF('Project Managers'!AE17=0,0,('Project Managers'!AE17*'Project Managers'!E17)-'Project Managers'!I17-'Project Managers'!AA17),0) -> 9050517.9 | AG17: =IFERROR(IF('Project Managers'!AE17='Project Managers'!V17,0,('Project Managers'!AF17-('Project Managers'!AF17*'Project Managers'!L17))),0) -> 7510802.5 | AH17: =IFERROR('Project Managers'!AF17-'Project Managers'!AG17,0) -> 1539715.4 | AI17: =IFERROR('Project Managers'!AH17/'Project Managers'!AF17,0) -> 0.17012456 | AJ17: 1 | AK17: =IFERROR(IF('Project Managers'!AJ17=0,0,('Project Managers'!AJ17*'Project Managers'!E17)-'Project Managers'!I17-'Project Managers'!AA17-'Project Managers'!AF17),0) -> 0 | AL17: =IFERROR(IF('Project Managers'!AJ17='Project Managers'!V17,0,('Project Managers'!AK17-('Project Managers'!AK17*'Project Managers'!L17))),0) -> 0 | AM17: =IFERROR('Project Managers'!AK17-'Project Managers'!AL17,0) -> 0 | AN17: =IFERROR('Project Managers'!AM17/'Project Managers'!AK17,0) -> 0 | AS17: 0.17
B18: Subtotal of B ONTIVEROS | C18: - | D18: - | E18: =SUBTOTAL(9,E15:E17) -> 21404397 | F18: =SUBTOTAL(9,F15:F17) -> 17766373 | G18: =SUBTOTAL(9,G15:G17) -> 3638023.9 | H18: {=IF(ISBLANK('Project Managers'!AO18),'Project Managers'!R18,'Project Managers'!AO18)} -> - | I18: =SUBTOTAL(9,I15:I17) -> 11194527 | J18: =SUBTOTAL(9,J15:J17) -> 9500571.8 | K18: =SUBTOTAL(9,K15:K17) -> 1693955.3 | L18: =IFERROR('Project Managers'!K18/'Project Managers'!I18,0) -> 0.15131995 | M18: =SUBTOTAL(9,M15:M17) -> 11345997 | N18: =SUBTOTAL(9,N15:N17) -> 151469.69 | O18: =SUBTOTAL(9,O15:O17) -> 0 | P18: =SUBTOTAL(9,P15:P17) -> 10209870 | Q18: =IFERROR(ROUND('Project Managers'!I18/'Project Managers'!E18,4),0) -> 0.523 | R18: - | S18: - | T18: - | U18: =SUBTOTAL(9,U15:U17) -> 516781.36 | V18: =SUBTOTAL(9,V15:V17) -> 1850.1258 | W18: =SUBTOTAL(9,W15:W17) -> -2538.4304 | X18: - | Y18: - | Z18: - | AA18: =SUBTOTAL(9,AA15:AA17) -> -332163.75 | AB18: =SUBTOTAL(9,AB15:AB17) -> -287141.86 | AC18: =IFERROR('Project Managers'!AA18-'Project Managers'!AB18,0) -> -45021.889 | AD18: =IFERROR('Project Managers'!AC18/'Project Managers'!AA18,0) -> 0.13554125 | AE18: =IFERROR(IF('Project Managers'!Z18<1,1,0),0) -> 0 | AF18: =SUBTOTAL(9,AF15:AF17) -> 10542034 | AG18: =SUBTOTAL(9,AG15:AG17) -> 8778020.7 | AH18: =SUBTOTAL(9,AH15:AH17) -> 1764013 | AI18: =IFERROR('Project Managers'!AH18/'Project Managers'!AF18,0) -> 0.16733138 | AJ18: - | AK18: =SUBTOTAL(9,AK15:AK17) -> 0 | AL18: =SUBTOTAL(9,AL15:AL17) -> 0 | AM18: =SUBTOTAL(9,AM15:AM17) -> 0 | AN18: =IFERROR('Project Managers'!AM18/'Project Managers'!AK18,0) -> 0 | AO18: - | AP18: - | AQ18: - | AR18: - | AS18: -
B19: D CASTANEDA | C19: 722400 | D19: WILCO JUVENILE JUSTICE | E19: 10936332 | F19: =IFERROR('Project Managers'!E19*(1-'Project Managers'!H19),0) -> 8858428.7 | G19: =IFERROR('Project Managers'!E19-'Project Managers'!F19,0) -> 2077903 | H19: {=IF(ISBLANK('Project Managers'!AO19),'Project Managers'!R19,'Project Managers'!AO19)} -> 0.19 | I19: 2811002.6 | J19: 2342502.2 | K19: =IFERROR('Project Managers'!I19-'Project Managers'!J19,0) -> 468500.46 | L19: =IFERROR('Project Managers'!K19/'Project Managers'!I19,0) -> 0.16666667 | M19: 3561220.1 | N19: =IFERROR(IF('Project Managers'!M19-'Project Managers'!I19>0,'Project Managers'!M19-'Project Managers'!I19,0),0) -> 750217.48 | O19: =IFERROR(IF('Project Managers'!M19-'Project Managers'!I19<0,'Project Managers'!M19-'Project Managers'!I19,0),0) -> 0 | P19: =IFERROR('Project Managers'!E19-'Project Managers'!I19,0) -> 8125329.1 | Q19: =IFERROR(ROUND('Project Managers'!I19/'Project Managers'!E19,4),0) -> 0.257 | R19: {=IF(ISBLANK('Project Managers'!AP19),IF('Project Managers'!I19<>0,('Project Managers'!I19-'Project Managers'!J19)/'Project Managers'!I19,'Project Managers'!AS19),'Project Managers'!AP19)} -> 0.18 | S19: 0.17 | T19: 0.18 | U19: =IFERROR(-('Project Managers'!I19-('Project Managers'!J19/(1-'Project Managers'!R19))),0) -> 45707.338 | V19: 9491.6304 | W19: =IFERROR(-('Project Managers'!I19-('Project Managers'!J19/(1-'Project Managers'!T19))),0) -> 45707.338 | X19: =IFERROR(IF('Project Managers'!AQ19="",1,'Project Managers'!AQ19),0) -> 1 | Y19: 0.3337 | Z19: 0.26 | AA19: =IFERROR(IF('Project Managers'!Z19='Project Managers'!Q19,0,(('Project Managers'!Z19*'Project Managers'!E19)-'Project Managers'!I19)),0) -> 32443.6 | AB19: =IFERROR(IF('Project Managers'!Z19='Project Managers'!Q19,0,('Project Managers'!AA19-('Project Managers'!AA19*'Project Managers'!L19))),0) -> 27036.333 | AC19: =IFERROR('Project Managers'!AA19-'Project Managers'!AB19,0) -> 5407.2668 | AD19: =IFERROR('Project Managers'!AC19/'Project Managers'!AA19,0) -> 0.16666667 | AE19: =IFERROR(IF('Project Managers'!Z19<1,1,0),0) -> 1 | AF19: =IFERROR(IF('Project Managers'!AE19=0,0,('Project Managers'!AE19*'Project Managers'!E19)-'Project Managers'!I19-'Project Managers'!AA19),0) -> 8092885.5 | AG19: =IFERROR(IF('Project Managers'!AE19='Project Managers'!V19,0,('Project Managers'!AF19-('Project Managers'!AF19*'Project Managers'!L19))),0) -> 6744071.2 | AH19: =IFERROR('Project Managers'!AF19-'Project Managers'!AG19,0) -> 1348814.3 | AI19: =IFERROR('Project Managers'!AH19/'Project Managers'!AF19,0) -> 0.16666667 | AJ19: 1 | AK19: =IFERROR(IF('Project Managers'!AJ19=0,0,('Project Managers'!AJ19*'Project Managers'!E19)-'Project Managers'!I19-'Project Managers'!AA19-'Project Managers'!AF19),0) -> 0 | AL19: =IFERROR(IF('Project Managers'!AJ19='Project Managers'!V19,0,('Project Managers'!AK19-('Project Managers'!AK19*'Project Managers'!L19))),0) -> 0 | AM19: =IFERROR('Project Managers'!AK19-'Project Managers'!AL19,0) -> 0 | AN19: =IFERROR('Project Managers'!AM19/'Project Managers'!AK19,0) -> 0 | AO19: 0.19 | AP19: 0.18 | AS19: 0.167
B20: D CASTANEDA | C20: 722520 | D20: SPACE X CLEANROOM-HODESS | E20: 8053000 | F20: =IFERROR('Project Managers'!E20*(1-'Project Managers'!H20),0) -> 6682987.7 | G20: =IFERROR('Project Managers'!E20-'Project Managers'!F20,0) -> 1370012.3 | H20: {=IF(ISBLANK('Project Managers'!AO20),'Project Managers'!R20,'Project Managers'!AO20)} -> 0.17012447 | I20: 886097.52 | J20: 735350.65 | K20: =IFERROR('Project Managers'!I20-'Project Managers'!J20,0) -> 150746.87 | L20: =IFERROR('Project Managers'!K20/'Project Managers'!I20,0) -> 0.17012447 | M20: 1670850 | N20: =IFERROR(IF('Project Managers'!M20-'Project Managers'!I20>0,'Project Managers'!M20-'Project Managers'!I20,0),0) -> 784752.48 | O20: =IFERROR(IF('Project Managers'!M20-'Project Managers'!I20<0,'Project Managers'!M20-'Project Managers'!I20,0),0) -> 0 | P20: =IFERROR('Project Managers'!E20-'Project Managers'!I20,0) -> 7166902.5 | Q20: =IFERROR(ROUND('Project Managers'!I20/'Project Managers'!E20,4),0) -> 0.11 | R20: =IF(ISBLANK('Project Managers'!AP20),IF('Project Managers'!I20<>0,('Project Managers'!I20-'Project Managers'!J20)/'Project Managers'!I20,'Project Managers'!AS20),'Project Managers'!AP20) -> 0.17012447 | S20: 0.15 | T20: 0.2 | U20: =IFERROR(-('Project Managers'!I20-('Project Managers'!J20/(1-'Project Managers'!R20))),0) -> 0 | V20: 3675.7847 | W20: =IFERROR(-('Project Managers'!I20-('Project Managers'!J20/(1-'Project Managers'!T20))),0) -> 33090.792 | X20: =IFERROR(IF('Project Managers'!AQ20="",1,'Project Managers'!AQ20),0) -> 1 | Y20: 0.2159 | Z20: 0.25 | AA20: =IFERROR(IF('Project Managers'!Z20='Project Managers'!Q20,0,(('Project Managers'!Z20*'Project Managers'!E20)-'Project Managers'!I20)),0) -> 1127152.5 | AB20: =IFERROR(IF('Project Managers'!Z20='Project Managers'!Q20,0,('Project Managers'!AA20-('Project Managers'!AA20*'Project Managers'!L20))),0) -> 935396.26 | AC20: =IFERROR('Project Managers'!AA20-'Project Managers'!AB20,0) -> 191756.22 | AD20: =IFERROR('Project Managers'!AC20/'Project Managers'!AA20,0) -> 0.17012447 | AE20: =IFERROR(IF('Project Managers'!Z20<1,1,0),0) -> 1 | AF20: =IFERROR(IF('Project Managers'!AE20=0,0,('Project Managers'!AE20*'Project Managers'!E20)-'Project Managers'!I20-'Project Managers'!AA20),0) -> 6039750 | AG20: =IFERROR(IF('Project Managers'!AE20='Project Managers'!V20,0,('Project Managers'!AF20-('Project Managers'!AF20*'Project Managers'!L20))),0) -> 5012240.7 | AH20: =IFERROR('Project Managers'!AF20-'Project Managers'!AG20,0) -> 1027509.3 | AI20: =IFERROR('Project Managers'!AH20/'Project Managers'!AF20,0) -> 0.17012447 | AK20: =IFERROR(IF('Project Managers'!AJ20=0,0,('Project Managers'!AJ20*'Project Managers'!E20)-'Project Managers'!I20-'Project Managers'!AA20-'Project Managers'!AF20),0) -> 0 | AL20: =IFERROR(IF('Project Managers'!AJ20='Project Managers'!V20,0,('Project Managers'!AK20-('Project Managers'!AK20*'Project Managers'!L20))),0) -> 0 | AM20: =IFERROR('Project Managers'!AK20-'Project Managers'!AL20,0) -> 0 | AN20: =IFERROR('Project Managers'!AM20/'Project Managers'!AK20,0) -> 0 | AS20: 0.17
B21: Subtotal of D CASTANEDA | C21: - | D21: - | E21: =SUBTOTAL(9,E19:E20) -> 18989332 | F21: =SUBTOTAL(9,F19:F20) -> 15541416 | G21: =SUBTOTAL(9,G19:G20) -> 3447915.4 | H21: {=IF(ISBLANK('Project Managers'!AO21),'Project Managers'!R21,'Project Managers'!AO21)} -> - | I21: =SUBTOTAL(9,I19:I20) -> 3697100.2 | J21: =SUBTOTAL(9,J19:J20) -> 3077852.8 | K21: =SUBTOTAL(9,K19:K20) -> 619247.33 | L21: =IFERROR('Project Managers'!K21/'Project Managers'!I21,0) -> 0.16749542 | M21: =SUBTOTAL(9,M19:M20) -> 5232070.1 | N21: =SUBTOTAL(9,N19:N20) -> 1534970 | O21: =SUBTOTAL(9,O19:O20) -> 0 | P21: =SUBTOTAL(9,P19:P20) -> 15292232 | Q21: =IFERROR(ROUND('Project Managers'!I21/'Project Managers'!E21,4),0) -> 0.1947 | R21: - | S21: - | T21: - | U21: =SUBTOTAL(9,U19:U20) -> 45707.338 | V21: =SUBTOTAL(9,V19:V20) -> 13167.415 | W21: =SUBTOTAL(9,W19:W20) -> 78798.13 | X21: - | Y21: - | Z21: - | AA21: =SUBTOTAL(9,AA19:AA20) -> 1159596.1 | AB21: =SUBTOTAL(9,AB19:AB20) -> 962432.6 | AC21: =IFERROR('Project Managers'!AA21-'Project Managers'!AB21,0) -> 197163.48 | AD21: =IFERROR('Project Managers'!AC21/'Project Managers'!AA21,0) -> 0.17002773 | AE21: =IFERROR(IF('Project Managers'!Z21<1,1,0),0) -> 0 | AF21: =SUBTOTAL(9,AF19:AF20) -> 14132635 | AG21: =SUBTOTAL(9,AG19:AG20) -> 11756312 | AH21: =SUBTOTAL(9,AH19:AH20) -> 2376323.6 | AI21: =IFERROR('Project Managers'!AH21/'Project Managers'!AF21,0) -> 0.1681444 | AJ21: - | AK21: =SUBTOTAL(9,AK19:AK20) -> 0 | AL21: =SUBTOTAL(9,AL19:AL20) -> 0 | AM21: =SUBTOTAL(9,AM19:AM20) -> 0 | AN21: =IFERROR('Project Managers'!AM21/'Project Managers'!AK21,0) -> 0 | AO21: - | AP21: - | AQ21: - | AR21: - | AS21: -
B22: K HERNANDEZ | C22: 710045 | D22: ZILKER BARTON SPRINGS BAT | E22: 1484896.8 | F22: =IFERROR('Project Managers'!E22*(1-'Project Managers'!H22),0) -> 1158219.5 | G22: =IFERROR('Project Managers'!E22-'Project Managers'!F22,0) -> 326677.3 | H22: {=IF(ISBLANK('Project Managers'!AO22),'Project Managers'!R22,'Project Managers'!AO22)} -> 0.22 | I22: 1484896.8 | J22: 1465800.4 | K22: =IFERROR('Project Managers'!I22-'Project Managers'!J22,0) -> 19096.46 | L22: =IFERROR('Project Managers'!K22/'Project Managers'!I22,0) -> 0.012860463 | M22: 1484896.8 | N22: =IFERROR(IF('Project Managers'!M22-'Project Managers'!I22>0,'Project Managers'!M22-'Project Managers'!I22,0),0) -> 0 | O22: =IFERROR(IF('Project Managers'!M22-'Project Managers'!I22<0,'Project Managers'!M22-'Project Managers'!I22,0),0) -> 0 | P22: =IFERROR('Project Managers'!E22-'Project Managers'!I22,0) -> 0 | Q22: =IFERROR(ROUND('Project Managers'!I22/'Project Managers'!E22,4),0) -> 1 | R22: {=IF(ISBLANK('Project Managers'!AP22),IF('Project Managers'!I22<>0,('Project Managers'!I22-'Project Managers'!J22)/'Project Managers'!I22,'Project Managers'!AS22),'Project Managers'!AP22)} -> 0.05 | S22: 0.018 | T22: 0.01 | U22: =IFERROR(-('Project Managers'!I22-('Project Managers'!J22/(1-'Project Managers'!R22))),0) -> 58050.927 | V22: 6070.7358 | W22: =IFERROR(-('Project Managers'!I22-('Project Managers'!J22/(1-'Project Managers'!T22))),0) -> -4290.3959 | X22: =IFERROR(IF('Project Managers'!AQ22="",1,'Project Managers'!AQ22),0) -> 1 | Y22: 1 | Z22: 1 | AA22: =IFERROR(IF('Project Managers'!Z22='Project Managers'!Q22,0,(('Project Managers'!Z22*'Project Managers'!E22)-'Project Managers'!I22)),0) -> 0 | AB22: =IFERROR(IF('Project Managers'!Z22='Project Managers'!Q22,0,('Project Managers'!AA22-('Project Managers'!AA22*'Project Managers'!L22))),0) -> 0 | AC22: =IFERROR('Project Managers'!AA22-'Project Managers'!AB22,0) -> 0 | AD22: =IFERROR('Project Managers'!AC22/'Project Managers'!AA22,0) -> 0 | AE22: =IFERROR(IF('Project Managers'!Z22<1,1,0),0) -> 0 | AF22: =IFERROR(IF('Project Managers'!AE22=0,0,('Project Managers'!AE22*'Project Managers'!E22)-'Project Managers'!I22-'Project Managers'!AA22),0) -> 0 | AG22: =IFERROR(IF('Project Managers'!AE22='Project Managers'!V22,0,('Project Managers'!AF22-('Project Managers'!AF22*'Project Managers'!L22))),0) -> 0 | AH22: =IFERROR('Project Managers'!AF22-'Project Managers'!AG22,0) -> 0 | AI22: =IFERROR('Project Managers'!AH22/'Project Managers'!AF22,0) -> 0 | AK22: =IFERROR(IF('Project Managers'!AJ22=0,0,('Project Managers'!AJ22*'Project Managers'!E22)-'Project Managers'!I22-'Project Managers'!AA22-'Project Managers'!AF22),0) -> 0 | AL22: =IFERROR(IF('Project Managers'!AJ22='Project Managers'!V22,0,('Project Managers'!AK22-('Project Managers'!AK22*'Project Managers'!L22))),0) -> 0 | AM22: =IFERROR('Project Managers'!AK22-'Project Managers'!AL22,0) -> 0 | AN22: =IFERROR('Project Managers'!AM22/'Project Managers'!AK22,0) -> 0 | AO22: 0.22 | AP22: 0.05 | AS22: 0.06
B23: K HERNANDEZ | C23: 718000 | D23: TFC PARK 35 | E23: 4093979.3 | F23: =IFERROR('Project Managers'!E23*(1-'Project Managers'!H23),0) -> 3398002.8 | G23: =IFERROR('Project Managers'!E23-'Project Managers'!F23,0) -> 695976.48 | H23: {=IF(ISBLANK('Project Managers'!AO23),'Project Managers'!R23,'Project Managers'!AO23)} -> 0.17 | I23: 4093633.3 | J23: 3313579.7 | K23: =IFERROR('Project Managers'!I23-'Project Managers'!J23,0) -> 780053.59 | L23: =IFERROR('Project Managers'!K23/'Project Managers'!I23,0) -> 0.19055287 | M23: 4093633.3 | N23: =IFERROR(IF('Project Managers'!M23-'Project Managers'!I23>0,'Project Managers'!M23-'Project Managers'!I23,0),0) -> 0 | O23: =IFERROR(IF('Project Managers'!M23-'Project Managers'!I23<0,'Project Managers'!M23-'Project Managers'!I23,0),0) -> 0 | P23: =IFERROR('Project Managers'!E23-'Project Managers'!I23,0) -> 346 | Q23: =IFERROR(ROUND('Project Managers'!I23/'Project Managers'!E23,4),0) -> 0.9999 | R23: {=IF(ISBLANK('Project Managers'!AP23),IF('Project Managers'!I23<>0,('Project Managers'!I23-'Project Managers'!J23)/'Project Managers'!I23,'Project Managers'!AS23),'Project Managers'!AP23)} -> 0.19 | S23: 0.19 | T23: 0.19 | U23: =IFERROR(-('Project Managers'!I23-('Project Managers'!J23/(1-'Project Managers'!R23))),0) -> -2794.1472 | V23: -5913.4805 | W23: =IFERROR(-('Project Managers'!I23-('Project Managers'!J23/(1-'Project Managers'!T23))),0) -> -2794.1472 | X23: =IFERROR(IF('Project Managers'!AQ23="",1,'Project Managers'!AQ23),0) -> 1 | Y23: 1 | Z23: 1 | AA23: =IFERROR(IF('Project Managers'!Z23='Project Managers'!Q23,0,(('Project Managers'!Z23*'Project Managers'!E23)-'Project Managers'!I23)),0) -> 346 | AB23: =IFERROR(IF('Project Managers'!Z23='Project Managers'!Q23,0,('Project Managers'!AA23-('Project Managers'!AA23*'Project Managers'!L23))),0) -> 280.06871 | AC23: =IFERROR('Project Managers'!AA23-'Project Managers'!AB23,0) -> 65.931294 | AD23: =IFERROR('Project Managers'!AC23/'Project Managers'!AA23,0) -> 0.19055287 | AE23: =IFERROR(IF('Project Managers'!Z23<1,1,0),0) -> 0 | AF23: =IFERROR(IF('Project Managers'!AE23=0,0,('Project Managers'!AE23*'Project Managers'!E23)-'Project Managers'!I23-'Project Managers'!AA23),0) -> 0 | AG23: =IFERROR(IF('Project Managers'!AE23='Project Managers'!V23,0,('Project Managers'!AF23-('Project Managers'!AF23*'Project Managers'!L23))),0) -> 0 | AH23: =IFERROR('Project Managers'!AF23-'Project Managers'!AG23,0) -> 0 | AI23: =IFERROR('Project Managers'!AH23/'Project Managers'!AF23,0) -> 0 | AK23: =IFERROR(IF('Project Managers'!AJ23=0,0,('Project Managers'!AJ23*'Project Managers'!E23)-'Project Managers'!I23-'Project Managers'!AA23-'Project Managers'!AF23),0) -> 0 | AL23: =IFERROR(IF('Project Managers'!AJ23='Project Managers'!V23,0,('Project Managers'!AK23-('Project Managers'!AK23*'Project Managers'!L23))),0) -> 0 | AM23: =IFERROR('Project Managers'!AK23-'Project Managers'!AL23,0) -> 0 | AN23: =IFERROR('Project Managers'!AM23/'Project Managers'!AK23,0) -> 0 | AO23: 0.17 | AP23: 0.19 | AS23: 0.22
B24: K HERNANDEZ | C24: 720900 | D24: TFC GMP4 - BP4- DHNP RENO | E24: 7230488.5 | F24: =IFERROR('Project Managers'!E24*(1-'Project Managers'!H24),0) -> 6001305.5 | G24: =IFERROR('Project Managers'!E24-'Project Managers'!F24,0) -> 1229183.1 | H24: {=IF(ISBLANK('Project Managers'!AO24),'Project Managers'!R24,'Project Managers'!AO24)} -> 0.17 | I24: 5396691.7 | J24: 4063773.8 | K24: =IFERROR('Project Managers'!I24-'Project Managers'!J24,0) -> 1332917.9 | L24: =IFERROR('Project Managers'!K24/'Project Managers'!I24,0) -> 0.24698797 | M24: 6079333.9 | N24: =IFERROR(IF('Project Managers'!M24-'Project Managers'!I24>0,'Project Managers'!M24-'Project Managers'!I24,0),0) -> 682642.21 | O24: =IFERROR(IF('Project Managers'!M24-'Project Managers'!I24<0,'Project Managers'!M24-'Project Managers'!I24,0),0) -> 0 | P24: =IFERROR('Project Managers'!E24-'Project Managers'!I24,0) -> 1833796.8 | Q24: =IFERROR(ROUND('Project Managers'!I24/'Project Managers'!E24,4),0) -> 0.7464 | R24: {=IF(ISBLANK('Project Managers'!AP24),IF('Project Managers'!I24<>0,('Project Managers'!I24-'Project Managers'!J24)/'Project Managers'!I24,'Project Managers'!AS24),'Project Managers'!AP24)} -> 0.33 | S24: 0.26 | T24: 0.25 | U24: =IFERROR(-('Project Managers'!I24-('Project Managers'!J24/(1-'Project Managers'!R24))),0) -> 668642.31 | V24: 346109.89 | W24: =IFERROR(-('Project Managers'!I24-('Project Managers'!J24/(1-'Project Managers'!T24))),0) -> 21673.353 | X24: =IFERROR(IF('Project Managers'!AQ24="",1,'Project Managers'!AQ24),0) -> 1 | Y24: 0.971 | Z24: 0.95 | AA24: =IFERROR(IF('Project Managers'!Z24='Project Managers'!Q24,0,(('Project Managers'!Z24*'Project Managers'!E24)-'Project Managers'!I24)),0) -> 1472272.4 | AB24: =IFERROR(IF('Project Managers'!Z24='Project Managers'!Q24,0,('Project Managers'!AA24-('Project Managers'!AA24*'Project Managers'!L24))),0) -> 1108638.8 | AC24: =IFERROR('Project Managers'!AA24-'Project Managers'!AB24,0) -> 363633.57 | AD24: =IFERROR('Project Managers'!AC24/'Project Managers'!AA24,0) -> 0.24698797 | AE24: =IFERROR(IF('Project Managers'!Z24<1,1,0),0) -> 1 | AF24: =IFERROR(IF('Project Managers'!AE24=0,0,('Project Managers'!AE24*'Project Managers'!E24)-'Project Managers'!I24-'Project Managers'!AA24),0) -> 361524.43 | AG24: =IFERROR(IF('Project Managers'!AE24='Project Managers'!V24,0,('Project Managers'!AF24-('Project Managers'!AF24*'Project Managers'!L24))),0) -> 272232.24 | AH24: =IFERROR('Project Managers'!AF24-'Project Managers'!AG24,0) -> 89292.183 | AI24: =IFERROR('Project Managers'!AH24/'Project Managers'!AF24,0) -> 0.24698797 | AK24: =IFERROR(IF('Project Managers'!AJ24=0,0,('Project Managers'!AJ24*'Project Managers'!E24)-'Project Managers'!I24-'Project Managers'!AA24-'Project Managers'!AF24),0) -> 0 | AL24: =IFERROR(IF('Project Managers'!AJ24='Project Managers'!V24,0,('Project Managers'!AK24-('Project Managers'!AK24*'Project Managers'!L24))),0) -> 0 | AM24: =IFERROR('Project Managers'!AK24-'Project Managers'!AL24,0) -> 0 | AN24: =IFERROR('Project Managers'!AM24/'Project Managers'!AK24,0) -> 0 | AO24: 0.17 | AP24: 0.33 | AS24: 0.241
B25: K HERNANDEZ | C25: 722420 | D25: UT MAIN BLDG RESTORATION | E25: 3751721 | F25: =IFERROR('Project Managers'!E25*(1-'Project Managers'!H25),0) -> 3100595.9 | G25: =IFERROR('Project Managers'!E25-'Project Managers'!F25,0) -> 651125.11 | H25: {=IF(ISBLANK('Project Managers'!AO25),'Project Managers'!R25,'Project Managers'!AO25)} -> 0.17355371 | I25: 1327737.1 | J25: 1097303.4 | K25: =IFERROR('Project Managers'!I25-'Project Managers'!J25,0) -> 230433.7 | L25: =IFERROR('Project Managers'!K25/'Project Managers'!I25,0) -> 0.17355371 | M25: 1172929 | N25: =IFERROR(IF('Project Managers'!M25-'Project Managers'!I25>0,'Project Managers'!M25-'Project Managers'!I25,0),0) -> 0 | O25: =IFERROR(IF('Project Managers'!M25-'Project Managers'!I25<0,'Project Managers'!M25-'Project Managers'!I25,0),0) -> -154808.07 | P25: =IFERROR('Project Managers'!E25-'Project Managers'!I25,0) -> 2423983.9 | Q25: =IFERROR(ROUND('Project Managers'!I25/'Project Managers'!E25,4),0) -> 0.3539 | R25: =IF(ISBLANK('Project Managers'!AP25),IF('Project Managers'!I25<>0,('Project Managers'!I25-'Project Managers'!J25)/'Project Managers'!I25,'Project Managers'!AS25),'Project Managers'!AP25) -> 0.17355371 | S25: 0.17 | T25: 0.17 | U25: =IFERROR(-('Project Managers'!I25-('Project Managers'!J25/(1-'Project Managers'!R25))),0) -> 0 | V25: -5191.8275 | W25: =IFERROR(-('Project Managers'!I25-('Project Managers'!J25/(1-'Project Managers'!T25))),0) -> -5684.817 | X25: =IFERROR(IF('Project Managers'!AQ25="",1,'Project Managers'!AQ25),0) -> 1 | Y25: 0.5262 | Z25: 0.4 | AA25: =IFERROR(IF('Project Managers'!Z25='Project Managers'!Q25,0,(('Project Managers'!Z25*'Project Managers'!E25)-'Project Managers'!I25)),0) -> 172951.33 | AB25: =IFERROR(IF('Project Managers'!Z25='Project Managers'!Q25,0,('Project Managers'!AA25-('Project Managers'!AA25*'Project Managers'!L25))),0) -> 142934.98 | AC25: =IFERROR('Project Managers'!AA25-'Project Managers'!AB25,0) -> 30016.346 | AD25: =IFERROR('Project Managers'!AC25/'Project Managers'!AA25,0) -> 0.17355371 | AE25: =IFERROR(IF('Project Managers'!Z25<1,1,0),0) -> 1 | AF25: =IFERROR(IF('Project Managers'!AE25=0,0,('Project Managers'!AE25*'Project Managers'!E25)-'Project Managers'!I25-'Project Managers'!AA25),0) -> 2251032.6 | AG25: =IFERROR(IF('Project Managers'!AE25='Project Managers'!V25,0,('Project Managers'!AF25-('Project Managers'!AF25*'Project Managers'!L25))),0) -> 1860357.5 | AH25: =IFERROR('Project Managers'!AF25-'Project Managers'!AG25,0) -> 390675.07 | AI25: =IFERROR('Project Managers'!AH25/'Project Managers'!AF25,0) -> 0.17355371 | AK25: =IFERROR(IF('Project Managers'!AJ25=0,0,('Project Managers'!AJ25*'Project Managers'!E25)-'Project Managers'!I25-'Project Managers'!AA25-'Project Managers'!AF25),0) -> 0 | AL25: =IFERROR(IF('Project Managers'!AJ25='Project Managers'!V25,0,('Project Managers'!AK25-('Project Managers'!AK25*'Project Managers'!L25))),0) -> 0 | AM25: =IFERROR('Project Managers'!AK25-'Project Managers'!AL25,0) -> 0 | AN25: =IFERROR('Project Managers'!AM25/'Project Managers'!AK25,0) -> 0 | AS25: 0.174
B26: Subtotal of K HERNANDEZ | C26: - | D26: - | E26: =SUBTOTAL(9,E22:E25) -> 16561086 | F26: =SUBTOTAL(9,F22:F25) -> 13658124 | G26: =SUBTOTAL(9,G22:G25) -> 2902961.9 | H26: {=IF(ISBLANK('Project Managers'!AO26),'Project Managers'!R26,'Project Managers'!AO26)} -> - | I26: =SUBTOTAL(9,I22:I25) -> 12302959 | J26: =SUBTOTAL(9,J22:J25) -> 9940457.2 | K26: =SUBTOTAL(9,K22:K25) -> 2362501.7 | L26: =IFERROR('Project Managers'!K26/'Project Managers'!I26,0) -> 0.19202711 | M26: =SUBTOTAL(9,M22:M25) -> 12830793 | N26: =SUBTOTAL(9,N22:N25) -> 682642.21 | O26: =SUBTOTAL(9,O22:O25) -> -154808.07 | P26: =SUBTOTAL(9,P22:P25) -> 4258126.8 | Q26: =IFERROR(ROUND('Project Managers'!I26/'Project Managers'!E26,4),0) -> 0.7429 | R26: - | S26: - | T26: - | U26: =SUBTOTAL(9,U22:U25) -> 723899.09 | V26: =SUBTOTAL(9,V22:V25) -> 341075.32 | W26: =SUBTOTAL(9,W22:W25) -> 8903.9933 | X26: - | Y26: - | Z26: - | AA26: =SUBTOTAL(9,AA22:AA25) -> 1645569.7 | AB26: =SUBTOTAL(9,AB22:AB25) -> 1251853.9 | AC26: =IFERROR('Project Managers'!AA26-'Project Managers'!AB26,0) -> 393715.85 | AD26: =IFERROR('Project Managers'!AC26/'Project Managers'!AA26,0) -> 0.23925807 | AE26: =IFERROR(IF('Project Managers'!Z26<1,1,0),0) -> 0 | AF26: =SUBTOTAL(9,AF22:AF25) -> 2612557 | AG26: =SUBTOTAL(9,AG22:AG25) -> 2132589.8 | AH26: =SUBTOTAL(9,AH22:AH25) -> 479967.25 | AI26: =IFERROR('Project Managers'!AH26/'Project Managers'!AF26,0) -> 0.18371551 | AJ26: - | AK26: =SUBTOTAL(9,AK22:AK25) -> 0 | AL26: =SUBTOTAL(9,AL22:AL25) -> 0 | AM26: =SUBTOTAL(9,AM22:AM25) -> 0 | AN26: =IFERROR('Project Managers'!AM26/'Project Managers'!AK26,0) -> 0 | AO26: - | AP26: - | AQ26: - | AR26: - | AS26: -
B27: M CASELLA | C27: 722280 | D27: HUTTO 1 INITIAL IMPROV | E27: 13617357 | F27: =IFERROR('Project Managers'!E27*(1-'Project Managers'!H27),0) -> 11438580 | G27: =IFERROR('Project Managers'!E27-'Project Managers'!F27,0) -> 2178777.1 | H27: {=IF(ISBLANK('Project Managers'!AO27),'Project Managers'!R27,'Project Managers'!AO27)} -> 0.16 | I27: 13617357 | J27: 12370710 | K27: =IFERROR('Project Managers'!I27-'Project Managers'!J27,0) -> 1246647.3 | L27: =IFERROR('Project Managers'!K27/'Project Managers'!I27,0) -> 0.091548405 | M27: 13617357 | N27: =IFERROR(IF('Project Managers'!M27-'Project Managers'!I27>0,'Project Managers'!M27-'Project Managers'!I27,0),0) -> 0 | O27: =IFERROR(IF('Project Managers'!M27-'Project Managers'!I27<0,'Project Managers'!M27-'Project Managers'!I27,0),0) -> 0 | P27: =IFERROR('Project Managers'!E27-'Project Managers'!I27,0) -> 0 | Q27: =IFERROR(ROUND('Project Managers'!I27/'Project Managers'!E27,4),0) -> 1 | R27: {=IF(ISBLANK('Project Managers'!AP27),IF('Project Managers'!I27<>0,('Project Managers'!I27-'Project Managers'!J27)/'Project Managers'!I27,'Project Managers'!AS27),'Project Managers'!AP27)} -> 0.23 | S27: 0.09 | T27: 0.085 | U27: =IFERROR(-('Project Managers'!I27-('Project Managers'!J27/(1-'Project Managers'!R27))),0) -> 2448499.7 | V27: -143371.43 | W27: =IFERROR(-('Project Managers'!I27-('Project Managers'!J27/(1-'Project Managers'!T27))),0) -> -97455.699 | X27: =IFERROR(IF('Project Managers'!AQ27="",1,'Project Managers'!AQ27),0) -> 1 | Y27: 1 | Z27: 1 | AA27: =IFERROR(IF('Project Managers'!Z27='Project Managers'!Q27,0,(('Project Managers'!Z27*'Project Managers'!E27)-'Project Managers'!I27)),0) -> 0 | AB27: =IFERROR(IF('Project Managers'!Z27='Project Managers'!Q27,0,('Project Managers'!AA27-('Project Managers'!AA27*'Project Managers'!L27))),0) -> 0 | AC27: =IFERROR('Project Managers'!AA27-'Project Managers'!AB27,0) -> 0 | AD27: =IFERROR('Project Managers'!AC27/'Project Managers'!AA27,0) -> 0 | AE27: =IFERROR(IF('Project Managers'!Z27<1,1,0),0) -> 0 | AF27: =IFERROR(IF('Project Managers'!AE27=0,0,('Project Managers'!AE27*'Project Managers'!E27)-'Project Managers'!I27-'Project Managers'!AA27),0) -> 0 | AG27: =IFERROR(IF('Project Managers'!AE27='Project Managers'!V27,0,('Project Managers'!AF27-('Project Managers'!AF27*'Project Managers'!L27))),0) -> 0 | AH27: =IFERROR('Project Managers'!AF27-'Project Managers'!AG27,0) -> 0 | AI27: =IFERROR('Project Managers'!AH27/'Project Managers'!AF27,0) -> 0 | AK27: =IFERROR(IF('Project Managers'!AJ27=0,0,('Project Managers'!AJ27*'Project Managers'!E27)-'Project Managers'!I27-'Project Managers'!AA27-'Project Managers'!AF27),0) -> 0 | AL27: =IFERROR(IF('Project Managers'!AJ27='Project Managers'!V27,0,('Project Managers'!AK27-('Project Managers'!AK27*'Project Managers'!L27))),0) -> 0 | AM27: =IFERROR('Project Managers'!AK27-'Project Managers'!AL27,0) -> 0 | AN27: =IFERROR('Project Managers'!AM27/'Project Managers'!AK27,0) -> 0 | AO27: 0.16 | AP27: 0.23 | AS27: 0.1
B28: M CASELLA | C28: 722340 | D28: DEL VALLE LIBRARY | E28: 1188326 | F28: =IFERROR('Project Managers'!E28*(1-'Project Managers'!H28),0) -> 986310.58 | G28: =IFERROR('Project Managers'!E28-'Project Managers'!F28,0) -> 202015.42 | H28: {=IF(ISBLANK('Project Managers'!AO28),'Project Managers'!R28,'Project Managers'!AO28)} -> 0.17 | I28: 364066.55 | J28: 316579.52 | K28: =IFERROR('Project Managers'!I28-'Project Managers'!J28,0) -> 47487.03 | L28: =IFERROR('Project Managers'!K28/'Project Managers'!I28,0) -> 0.13043503 | M28: 259600 | N28: =IFERROR(IF('Project Managers'!M28-'Project Managers'!I28>0,'Project Managers'!M28-'Project Managers'!I28,0),0) -> 0 | O28: =IFERROR(IF('Project Managers'!M28-'Project Managers'!I28<0,'Project Managers'!M28-'Project Managers'!I28,0),0) -> -104466.55 | P28: =IFERROR('Project Managers'!E28-'Project Managers'!I28,0) -> 824259.45 | Q28: =IFERROR(ROUND('Project Managers'!I28/'Project Managers'!E28,4),0) -> 0.3064 | R28: {=IF(ISBLANK('Project Managers'!AP28),IF('Project Managers'!I28<>0,('Project Managers'!I28-'Project Managers'!J28)/'Project Managers'!I28,'Project Managers'!AS28),'Project Managers'!AP28)} -> 0.18 | S28: 0.12 | T28: 0.13 | U28: =IFERROR(-('Project Managers'!I28-('Project Managers'!J28/(1-'Project Managers'!R28))),0) -> 22006.035 | V28: -3314.9436 | W28: =IFERROR(-('Project Managers'!I28-('Project Managers'!J28/(1-'Project Managers'!T28))),0) -> -182.04425 | X28: =IFERROR(IF('Project Managers'!AQ28="",1,'Project Managers'!AQ28),0) -> 1 | Y28: 0.4647 | Z28: 0.3 | AA28: =IFERROR(IF('Project Managers'!Z28='Project Managers'!Q28,0,(('Project Managers'!Z28*'Project Managers'!E28)-'Project Managers'!I28)),0) -> -7568.75 | AB28: =IFERROR(IF('Project Managers'!Z28='Project Managers'!Q28,0,('Project Managers'!AA28-('Project Managers'!AA28*'Project Managers'!L28))),0) -> -6581.5199 | AC28: =IFERROR('Project Managers'!AA28-'Project Managers'!AB28,0) -> -987.2301 | AD28: =IFERROR('Project Managers'!AC28/'Project Managers'!AA28,0) -> 0.13043503 | AE28: =IFERROR(IF('Project Managers'!Z28<1,1,0),0) -> 1 | AF28: =IFERROR(IF('Project Managers'!AE28=0,0,('Project Managers'!AE28*'Project Managers'!E28)-'Project Managers'!I28-'Project Managers'!AA28),0) -> 831828.2 | AG28: =IFERROR(IF('Project Managers'!AE28='Project Managers'!V28,0,('Project Managers'!AF28-('Project Managers'!AF28*'Project Managers'!L28))),0) -> 723328.67 | AH28: =IFERROR('Project Managers'!AF28-'Project Managers'!AG28,0) -> 108499.53 | AI28: =IFERROR('Project Managers'!AH28/'Project Managers'!AF28,0) -> 0.13043503 | AK28: =IFERROR(IF('Project Managers'!AJ28=0,0,('Project Managers'!AJ28*'Project Managers'!E28)-'Project Managers'!I28-'Project Managers'!AA28-'Project Managers'!AF28),0) -> 0 | AL28: =IFERROR(IF('Project Managers'!AJ28='Project Managers'!V28,0,('Project Managers'!AK28-('Project Managers'!AK28*'Project Managers'!L28))),0) -> 0 | AM28: =IFERROR('Project Managers'!AK28-'Project Managers'!AL28,0) -> 0 | AN28: =IFERROR('Project Managers'!AM28/'Project Managers'!AK28,0) -> 0 | AO28: 0.17 | AP28: 0.18 | AS28: 0.13
B29: M CASELLA | C29: 722470 | D29: TSTC HUTTO | E29: 585596.97 | F29: =IFERROR('Project Managers'!E29*(1-'Project Managers'!H29),0) -> 485972.57 | G29: =IFERROR('Project Managers'!E29-'Project Managers'!F29,0) -> 99624.395 | H29: {=IF(ISBLANK('Project Managers'!AO29),'Project Managers'!R29,'Project Managers'!AO29)} -> 0.17012451 | I29: 177100 | J29: 146970.95 | K29: =IFERROR('Project Managers'!I29-'Project Managers'!J29,0) -> 30129.05 | L29: =IFERROR('Project Managers'!K29/'Project Managers'!I29,0) -> 0.17012451 | M29: 398194.97 | N29: =IFERROR(IF('Project Managers'!M29-'Project Managers'!I29>0,'Project Managers'!M29-'Project Managers'!I29,0),0) -> 221094.97 | O29: =IFERROR(IF('Project Managers'!M29-'Project Managers'!I29<0,'Project Managers'!M29-'Project Managers'!I29,0),0) -> 0 | P29: =IFERROR('Project Managers'!E29-'Project Managers'!I29,0) -> 408496.97 | Q29: =IFERROR(ROUND('Project Managers'!I29/'Project Managers'!E29,4),0) -> 0.3024 | R29: =IF(ISBLANK('Project Managers'!AP29),IF('Project Managers'!I29<>0,('Project Managers'!I29-'Project Managers'!J29)/'Project Managers'!I29,'Project Managers'!AS29),'Project Managers'!AP29) -> 0.17012451 | S29: 0.17 | T29: 0.17 | U29: =IFERROR(-('Project Managers'!I29-('Project Managers'!J29/(1-'Project Managers'!R29))),0) -> 0 | V29: -25.994337 | W29: =IFERROR(-('Project Managers'!I29-('Project Managers'!J29/(1-'Project Managers'!T29))),0) -> -26.566265 | X29: =IFERROR(IF('Project Managers'!AQ29="",1,'Project Managers'!AQ29),0) -> 1 | Y29: 0.648 | Z29: 0.9 | AA29: =IFERROR(IF('Project Managers'!Z29='Project Managers'!Q29,0,(('Project Managers'!Z29*'Project Managers'!E29)-'Project Managers'!I29)),0) -> 349937.27 | AB29: =IFERROR(IF('Project Managers'!Z29='Project Managers'!Q29,0,('Project Managers'!AA29-('Project Managers'!AA29*'Project Managers'!L29))),0) -> 290404.37 | AC29: =IFERROR('Project Managers'!AA29-'Project Managers'!AB29,0) -> 59532.906 | AD29: =IFERROR('Project Managers'!AC29/'Project Managers'!AA29,0) -> 0.17012451 | AE29: =IFERROR(IF('Project Managers'!Z29<1,1,0),0) -> 1 | AF29: =IFERROR(IF('Project Managers'!AE29=0,0,('Project Managers'!AE29*'Project Managers'!E29)-'Project Managers'!I29-'Project Managers'!AA29),0) -> 58559.697 | AG29: =IFERROR(IF('Project Managers'!AE29='Project Managers'!V29,0,('Project Managers'!AF29-('Project Managers'!AF29*'Project Managers'!L29))),0) -> 48597.257 | AH29: =IFERROR('Project Managers'!AF29-'Project Managers'!AG29,0) -> 9962.4395 | AI29: =IFERROR('Project Managers'!AH29/'Project Managers'!AF29,0) -> 0.17012451 | AK29: =IFERROR(IF('Project Managers'!AJ29=0,0,('Project Managers'!AJ29*'Project Managers'!E29)-'Project Managers'!I29-'Project Managers'!AA29-'Project Managers'!AF29),0) -> 0 | AL29: =IFERROR(IF('Project Managers'!AJ29='Project Managers'!V29,0,('Project Managers'!AK29-('Project Managers'!AK29*'Project Managers'!L29))),0) -> 0 | AM29: =IFERROR('Project Managers'!AK29-'Project Managers'!AL29,0) -> 0 | AN29: =IFERROR('Project Managers'!AM29/'Project Managers'!AK29,0) -> 0 | AS29: 0.17
B30: Subtotal of M CASELLA | C30: - | D30: - | E30: =SUBTOTAL(9,E27:E29) -> 15391280 | F30: =SUBTOTAL(9,F27:F29) -> 12910863 | G30: =SUBTOTAL(9,G27:G29) -> 2480416.9 | H30: {=IF(ISBLANK('Project Managers'!AO30),'Project Managers'!R30,'Project Managers'!AO30)} -> - | I30: =SUBTOTAL(9,I27:I29) -> 14158524 | J30: =SUBTOTAL(9,J27:J29) -> 12834260 | K30: =SUBTOTAL(9,K27:K29) -> 1324263.4 | L30: =IFERROR('Project Managers'!K30/'Project Managers'!I30,0) -> 0.093531178 | M30: =SUBTOTAL(9,M27:M29) -> 14275152 | N30: =SUBTOTAL(9,N27:N29) -> 221094.97 | O30: =SUBTOTAL(9,O27:O29) -> -104466.55 | P30: =SUBTOTAL(9,P27:P29) -> 1232756.4 | Q30: =IFERROR(ROUND('Project Managers'!I30/'Project Managers'!E30,4),0) -> 0.9199 | R30: - | S30: - | T30: - | U30: =SUBTOTAL(9,U27:U29) -> 2470505.8 | V30: =SUBTOTAL(9,V27:V29) -> -146712.37 | W30: =SUBTOTAL(9,W27:W29) -> -97664.31 | X30: - | Y30: - | Z30: - | AA30: =SUBTOTAL(9,AA27:AA29) -> 342368.52 | AB30: =SUBTOTAL(9,AB27:AB29) -> 283822.85 | AC30: =IFERROR('Project Managers'!AA30-'Project Managers'!AB30,0) -> 58545.676 | AD30: =IFERROR('Project Managers'!AC30/'Project Managers'!AA30,0) -> 0.17100192 | AE30: =IFERROR(IF('Project Managers'!Z30<1,1,0),0) -> 0 | AF30: =SUBTOTAL(9,AF27:AF29) -> 890387.9 | AG30: =SUBTOTAL(9,AG27:AG29) -> 771925.92 | AH30: =SUBTOTAL(9,AH27:AH29) -> 118461.97 | AI30: =IFERROR('Project Managers'!AH30/'Project Managers'!AF30,0) -> 0.13304535 | AJ30: - | AK30: =SUBTOTAL(9,AK27:AK29) -> 0 | AL30: =SUBTOTAL(9,AL27:AL29) -> 0 | AM30: =SUBTOTAL(9,AM27:AM29) -> 0 | AN30: =IFERROR('Project Managers'!AM30/'Project Managers'!AK30,0) -> 0 | AO30: - | AP30: - | AQ30: - | AR30: - | AS30: -
B31: T FERGUSON | C31: 718100 | D31: TESLA 2022 PLASTIC FEEDER | E31: 898831.39 | F31: =IFERROR('Project Managers'!E31*(1-'Project Managers'!H31),0) -> 728053.43 | G31: =IFERROR('Project Managers'!E31-'Project Managers'!F31,0) -> 170777.96 | H31: {=IF(ISBLANK('Project Managers'!AO31),'Project Managers'!R31,'Project Managers'!AO31)} -> 0.19 | I31: 898831.39 | J31: 744578.07 | K31: =IFERROR('Project Managers'!I31-'Project Managers'!J31,0) -> 154253.32 | L31: =IFERROR('Project Managers'!K31/'Project Managers'!I31,0) -> 0.17161541 | M31: 898831.39 | N31: =IFERROR(IF('Project Managers'!M31-'Project Managers'!I31>0,'Project Managers'!M31-'Project Managers'!I31,0),0) -> 0 | O31: =IFERROR(IF('Project Managers'!M31-'Project Managers'!I31<0,'Project Managers'!M31-'Project Managers'!I31,0),0) -> 0 | P31: =IFERROR('Project Managers'!E31-'Project Managers'!I31,0) -> 0 | Q31: =IFERROR(ROUND('Project Managers'!I31/'Project Managers'!E31,4),0) -> 1 | R31: {=IF(ISBLANK('Project Managers'!AP31),IF('Project Managers'!I31<>0,('Project Managers'!I31-'Project Managers'!J31)/'Project Managers'!I31,'Project Managers'!AS31),'Project Managers'!AP31)} -> 0.17 | S31: 0.08 | T31: 0.07 | U31: =IFERROR(-('Project Managers'!I31-('Project Managers'!J31/(1-'Project Managers'!R31))),0) -> -1749.378 | V31: -89507.401 | W31: =IFERROR(-('Project Managers'!I31-('Project Managers'!J31/(1-'Project Managers'!T31))),0) -> -98209.809 | X31: =IFERROR(IF('Project Managers'!AQ31="",1,'Project Managers'!AQ31),0) -> 1 | Y31: 1 | Z31: 1 | AA31: =IFERROR(IF('Project Managers'!Z31='Project Managers'!Q31,0,(('Project Managers'!Z31*'Project Managers'!E31)-'Project Managers'!I31)),0) -> 0 | AB31: =IFERROR(IF('Project Managers'!Z31='Project Managers'!Q31,0,('Project Managers'!AA31-('Project Managers'!AA31*'Project Managers'!L31))),0) -> 0 | AC31: =IFERROR('Project Managers'!AA31-'Project Managers'!AB31,0) -> 0 | AD31: =IFERROR('Project Managers'!AC31/'Project Managers'!AA31,0) -> 0 | AE31: =IFERROR(IF('Project Managers'!Z31<1,1,0),0) -> 0 | AF31: =IFERROR(IF('Project Managers'!AE31=0,0,('Project Managers'!AE31*'Project Managers'!E31)-'Project Managers'!I31-'Project Managers'!AA31),0) -> 0 | AG31: =IFERROR(IF('Project Managers'!AE31='Project Managers'!V31,0,('Project Managers'!AF31-('Project Managers'!AF31*'Project Managers'!L31))),0) -> 0 | AH31: =IFERROR('Project Managers'!AF31-'Project Managers'!AG31,0) -> 0 | AI31: =IFERROR('Project Managers'!AH31/'Project Managers'!AF31,0) -> 0 | AK31: =IFERROR(IF('Project Managers'!AJ31=0,0,('Project Managers'!AJ31*'Project Managers'!E31)-'Project Managers'!I31-'Project Managers'!AA31-'Project Managers'!AF31),0) -> 0 | AL31: =IFERROR(IF('Project Managers'!AJ31='Project Managers'!V31,0,('Project Managers'!AK31-('Project Managers'!AK31*'Project Managers'!L31))),0) -> 0 | AM31: =IFERROR('Project Managers'!AK31-'Project Managers'!AL31,0) -> 0 | AN31: =IFERROR('Project Managers'!AM31/'Project Managers'!AK31,0) -> 0 | AO31: 0.19 | AP31: 0.17
B32: T FERGUSON | C32: 719900 | D32: BLOCKER LANE D14 | E32: 10000 | F32: =IFERROR('Project Managers'!E32*(1-'Project Managers'!H32),0) -> 10000 | G32: =IFERROR('Project Managers'!E32-'Project Managers'!F32,0) -> 0 | H32: {=IF(ISBLANK('Project Managers'!AO32),'Project Managers'!R32,'Project Managers'!AO32)} -> 0 | I32: 6910.28 | J32: 6910.28 | K32: =IFERROR('Project Managers'!I32-'Project Managers'!J32,0) -> 0 | L32: =IFERROR('Project Managers'!K32/'Project Managers'!I32,0) -> 0 | N32: =IFERROR(IF('Project Managers'!M32-'Project Managers'!I32>0,'Project Managers'!M32-'Project Managers'!I32,0),0) -> 0 | O32: =IFERROR(IF('Project Managers'!M32-'Project Managers'!I32<0,'Project Managers'!M32-'Project Managers'!I32,0),0) -> -6910.28 | P32: =IFERROR('Project Managers'!E32-'Project Managers'!I32,0) -> 3089.72 | Q32: =IFERROR(ROUND('Project Managers'!I32/'Project Managers'!E32,4),0) -> 0.691 | R32: {=IF(ISBLANK('Project Managers'!AP32),IF('Project Managers'!I32<>0,('Project Managers'!I32-'Project Managers'!J32)/'Project Managers'!I32,'Project Managers'!AS32),'Project Managers'!AP32)} -> 0 | S32: 0.17 | T32: 0.17 | U32: =IFERROR(-('Project Managers'!I32-('Project Managers'!J32/(1-'Project Managers'!R32))),0) -> 0 | V32: 1415.3586 | W32: =IFERROR(-('Project Managers'!I32-('Project Managers'!J32/(1-'Project Managers'!T32))),0) -> 1415.3586 | X32: =IFERROR(IF('Project Managers'!AQ32="",1,'Project Managers'!AQ32),0) -> 1 | Y32: 1 | Z32: 1 | AA32: =IFERROR(IF('Project Managers'!Z32='Project Managers'!Q32,0,(('Project Managers'!Z32*'Project Managers'!E32)-'Project Managers'!I32)),0) -> 3089.72 | AB32: =IFERROR(IF('Project Managers'!Z32='Project Managers'!Q32,0,('Project Managers'!AA32-('Project Managers'!AA32*'Project Managers'!L32))),0) -> 3089.72 | AC32: =IFERROR('Project Managers'!AA32-'Project Managers'!AB32,0) -> 0 | AD32: =IFERROR('Project Managers'!AC32/'Project Managers'!AA32,0) -> 0 | AE32: =IFERROR(IF('Project Managers'!Z32<1,1,0),0) -> 0 | AF32: =IFERROR(IF('Project Managers'!AE32=0,0,('Project Managers'!AE32*'Project Managers'!E32)-'Project Managers'!I32-'Project Managers'!AA32),0) -> 0 | AG32: =IFERROR(IF('Project Managers'!AE32='Project Managers'!V32,0,('Project Managers'!AF32-('Project Managers'!AF32*'Project Managers'!L32))),0) -> 0 | AH32: =IFERROR('Project Managers'!AF32-'Project Managers'!AG32,0) -> 0 | AI32: =IFERROR('Project Managers'!AH32/'Project Managers'!AF32,0) -> 0 | AK32: =IFERROR(IF('Project Managers'!AJ32=0,0,('Project Managers'!AJ32*'Project Managers'!E32)-'Project Managers'!I32-'Project Managers'!AA32-'Project Managers'!AF32),0) -> 0 | AL32: =IFERROR(IF('Project Managers'!AJ32='Project Managers'!V32,0,('Project Managers'!AK32-('Project Managers'!AK32*'Project Managers'!L32))),0) -> 0 | AM32: =IFERROR('Project Managers'!AK32-'Project Managers'!AL32,0) -> 0 | AN32: =IFERROR('Project Managers'!AM32/'Project Managers'!AK32,0) -> 0 | AO32: 0 | AP32: 0
B33: T FERGUSON | C33: 720500 | D33: UTFC4 | E33: 972890 | F33: =IFERROR('Project Managers'!E33*(1-'Project Managers'!H33),0) -> 865872.1 | G33: =IFERROR('Project Managers'!E33-'Project Managers'!F33,0) -> 107017.9 | H33: {=IF(ISBLANK('Project Managers'!AO33),'Project Managers'!R33,'Project Managers'!AO33)} -> 0.11 | I33: 972890 | J33: 847449.19 | K33: =IFERROR('Project Managers'!I33-'Project Managers'!J33,0) -> 125440.81 | L33: =IFERROR('Project Managers'!K33/'Project Managers'!I33,0) -> 0.12893627 | M33: 972890 | N33: =IFERROR(IF('Project Managers'!M33-'Project Managers'!I33>0,'Project Managers'!M33-'Project Managers'!I33,0),0) -> 0 | O33: =IFERROR(IF('Project Managers'!M33-'Project Managers'!I33<0,'Project Managers'!M33-'Project Managers'!I33,0),0) -> 0 | P33: =IFERROR('Project Managers'!E33-'Project Managers'!I33,0) -> 0 | Q33: =IFERROR(ROUND('Project Managers'!I33/'Project Managers'!E33,4),0) -> 1 | R33: {=IF(ISBLANK('Project Managers'!AP33),IF('Project Managers'!I33<>0,('Project Managers'!I33-'Project Managers'!J33)/'Project Managers'!I33,'Project Managers'!AS33),'Project Managers'!AP33)} -> 0.12 | S33: 0.13 | T33: 0.13 | U33: =IFERROR(-('Project Managers'!I33-('Project Managers'!J33/(1-'Project Managers'!R33))),0) -> -9879.5568 | V33: -487.0154 | W33: =IFERROR(-('Project Managers'!I33-('Project Managers'!J33/(1-'Project Managers'!T33))),0) -> 1189.5287 | X33: =IFERROR(IF('Project Managers'!AQ33="",1,'Project Managers'!AQ33),0) -> 1 | Y33: 1 | Z33: 1 | AA33: =IFERROR(IF('Project Managers'!Z33='Project Managers'!Q33,0,(('Project Managers'!Z33*'Project Managers'!E33)-'Project Managers'!I33)),0) -> 0 | AB33: =IFERROR(IF('Project Managers'!Z33='Project Managers'!Q33,0,('Project Managers'!AA33-('Project Managers'!AA33*'Project Managers'!L33))),0) -> 0 | AC33: =IFERROR('Project Managers'!AA33-'Project Managers'!AB33,0) -> 0 | AD33: =IFERROR('Project Managers'!AC33/'Project Managers'!AA33,0) -> 0 | AE33: =IFERROR(IF('Project Managers'!Z33<1,1,0),0) -> 0 | AF33: =IFERROR(IF('Project Managers'!AE33=0,0,('Project Managers'!AE33*'Project Managers'!E33)-'Project Managers'!I33-'Project Managers'!AA33),0) -> 0 | AG33: =IFERROR(IF('Project Managers'!AE33='Project Managers'!V33,0,('Project Managers'!AF33-('Project Managers'!AF33*'Project Managers'!L33))),0) -> 0 | AH33: =IFERROR('Project Managers'!AF33-'Project Managers'!AG33,0) -> 0 | AI33: =IFERROR('Project Managers'!AH33/'Project Managers'!AF33,0) -> 0 | AK33: =IFERROR(IF('Project Managers'!AJ33=0,0,('Project Managers'!AJ33*'Project Managers'!E33)-'Project Managers'!I33-'Project Managers'!AA33-'Project Managers'!AF33),0) -> 0 | AL33: =IFERROR(IF('Project Managers'!AJ33='Project Managers'!V33,0,('Project Managers'!AK33-('Project Managers'!AK33*'Project Managers'!L33))),0) -> 0 | AM33: =IFERROR('Project Managers'!AK33-'Project Managers'!AL33,0) -> 0 | AN33: =IFERROR('Project Managers'!AM33/'Project Managers'!AK33,0) -> 0 | AO33: 0.11 | AP33: 0.12 | AS33: 0.13
B34: T FERGUSON | C34: 722200 | D34: TITO'S BLOCKER LN W7 | E34: 10801639 | F34: =IFERROR('Project Managers'!E34*(1-'Project Managers'!H34),0) -> 8857344 | G34: =IFERROR('Project Managers'!E34-'Project Managers'!F34,0) -> 1944295 | H34: {=IF(ISBLANK('Project Managers'!AO34),'Project Managers'!R34,'Project Managers'!AO34)} -> 0.18 | I34: 10200547 | J34: 6443807.6 | K34: =IFERROR('Project Managers'!I34-'Project Managers'!J34,0) -> 3756739.8 | L34: =IFERROR('Project Managers'!K34/'Project Managers'!I34,0) -> 0.36828806 | M34: 10801639 | N34: =IFERROR(IF('Project Managers'!M34-'Project Managers'!I34>0,'Project Managers'!M34-'Project Managers'!I34,0),0) -> 601091.62 | O34: =IFERROR(IF('Project Managers'!M34-'Project Managers'!I34<0,'Project Managers'!M34-'Project Managers'!I34,0),0) -> 0 | P34: =IFERROR('Project Managers'!E34-'Project Managers'!I34,0) -> 601091.62 | Q34: =IFERROR(ROUND('Project Managers'!I34/'Project Managers'!E34,4),0) -> 0.9444 | R34: {=IF(ISBLANK('Project Managers'!AP34),IF('Project Managers'!I34<>0,('Project Managers'!I34-'Project Managers'!J34)/'Project Managers'!I34,'Project Managers'!AS34),'Project Managers'!AP34)} -> 0.36 | S34: 0.36 | T34: 0.39 | U34: =IFERROR(-('Project Managers'!I34-('Project Managers'!J34/(1-'Project Managers'!R34))),0) -> -132098.05 | V34: 150995.02 | W34: =IFERROR(-('Project Managers'!I34-('Project Managers'!J34/(1-'Project Managers'!T34))),0) -> 363071.59 | X34: =IFERROR(IF('Project Managers'!AQ34="",1,'Project Managers'!AQ34),0) -> 1 | Y34: 0.9983 | Z34: 0.98 | AA34: =IFERROR(IF('Project Managers'!Z34='Project Managers'!Q34,0,(('Project Managers'!Z34*'Project Managers'!E34)-'Project Managers'!I34)),0) -> 385058.84 | AB34: =IFERROR(IF('Project Managers'!Z34='Project Managers'!Q34,0,('Project Managers'!AA34-('Project Managers'!AA34*'Project Managers'!L34))),0) -> 243246.27 | AC34: =IFERROR('Project Managers'!AA34-'Project Managers'!AB34,0) -> 141812.57 | AD34: =IFERROR('Project Managers'!AC34/'Project Managers'!AA34,0) -> 0.36828806 | AE34: =IFERROR(IF('Project Managers'!Z34<1,1,0),0) -> 1 | AF34: =IFERROR(IF('Project Managers'!AE34=0,0,('Project Managers'!AE34*'Project Managers'!E34)-'Project Managers'!I34-'Project Managers'!AA34),0) -> 216032.78 | AG34: =IFERROR(IF('Project Managers'!AE34='Project Managers'!V34,0,('Project Managers'!AF34-('Project Managers'!AF34*'Project Managers'!L34))),0) -> 136470.49 | AH34: =IFERROR('Project Managers'!AF34-'Project Managers'!AG34,0) -> 79562.294 | AI34: =IFERROR('Project Managers'!AH34/'Project Managers'!AF34,0) -> 0.36828806 | AK34: =IFERROR(IF('Project Managers'!AJ34=0,0,('Project Managers'!AJ34*'Project Managers'!E34)-'Project Managers'!I34-'Project Managers'!AA34-'Project Managers'!AF34),0) -> 0 | AL34: =IFERROR(IF('Project Managers'!AJ34='Project Managers'!V34,0,('Project Managers'!AK34-('Project Managers'!AK34*'Project Managers'!L34))),0) -> 0 | AM34: =IFERROR('Project Managers'!AK34-'Project Managers'!AL34,0) -> 0 | AN34: =IFERROR('Project Managers'!AM34/'Project Managers'!AK34,0) -> 0 | AO34: 0.18 | AP34: 0.36
B35: T FERGUSON | C35: 722201 | D35: TITOS D16 | E35: 540613 | F35: =IFERROR('Project Managers'!E35*(1-'Project Managers'!H35),0) -> 432490.35 | G35: =IFERROR('Project Managers'!E35-'Project Managers'!F35,0) -> 108122.65 | H35: {=IF(ISBLANK('Project Managers'!AO35),'Project Managers'!R35,'Project Managers'!AO35)} -> 0.20000009 | I35: 536266.36 | J35: 429013.04 | K35: =IFERROR('Project Managers'!I35-'Project Managers'!J35,0) -> 107253.32 | L35: =IFERROR('Project Managers'!K35/'Project Managers'!I35,0) -> 0.20000009 | M35: 540613 | N35: =IFERROR(IF('Project Managers'!M35-'Project Managers'!I35>0,'Project Managers'!M35-'Project Managers'!I35,0),0) -> 4346.64 | O35: =IFERROR(IF('Project Managers'!M35-'Project Managers'!I35<0,'Project Managers'!M35-'Project Managers'!I35,0),0) -> 0 | P35: =IFERROR('Project Managers'!E35-'Project Managers'!I35,0) -> 4346.64 | Q35: =IFERROR(ROUND('Project Managers'!I35/'Project Managers'!E35,4),0) -> 0.992 | R35: =IF(ISBLANK('Project Managers'!AP35),IF('Project Managers'!I35<>0,('Project Managers'!I35-'Project Managers'!J35)/'Project Managers'!I35,'Project Managers'!AS35),'Project Managers'!AP35) -> 0.20000009 | S35: 0.17 | T35: 0.2 | U35: =IFERROR(-('Project Managers'!I35-('Project Managers'!J35/(1-'Project Managers'!R35))),0) -> 0 | V35: 2008.2646 | W35: =IFERROR(-('Project Managers'!I35-('Project Managers'!J35/(1-'Project Managers'!T35))),0) -> -0.06 | X35: =IFERROR(IF('Project Managers'!AQ35="",1,'Project Managers'!AQ35),0) -> 1 | Y35: 0.9812 | Z35: 0.95 | AA35: =IFERROR(IF('Project Managers'!Z35='Project Managers'!Q35,0,(('Project Managers'!Z35*'Project Managers'!E35)-'Project Managers'!I35)),0) -> -22684.01 | AB35: =IFERROR(IF('Project Managers'!Z35='Project Managers'!Q35,0,('Project Managers'!AA35-('Project Managers'!AA35*'Project Managers'!L35))),0) -> -18147.206 | AC35: =IFERROR('Project Managers'!AA35-'Project Managers'!AB35,0) -> -4536.804 | AD35: =IFERROR('Project Managers'!AC35/'Project Managers'!AA35,0) -> 0.20000009 | AE35: =IFERROR(IF('Project Managers'!Z35<1,1,0),0) -> 1 | AF35: =IFERROR(IF('Project Managers'!AE35=0,0,('Project Managers'!AE35*'Project Managers'!E35)-'Project Managers'!I35-'Project Managers'!AA35),0) -> 27030.65 | AG35: =IFERROR(IF('Project Managers'!AE35='Project Managers'!V35,0,('Project Managers'!AF35-('Project Managers'!AF35*'Project Managers'!L35))),0) -> 21624.518 | AH35: =IFERROR('Project Managers'!AF35-'Project Managers'!AG35,0) -> 5406.1324 | AI35: =IFERROR('Project Managers'!AH35/'Project Managers'!AF35,0) -> 0.20000009 | AK35: =IFERROR(IF('Project Managers'!AJ35=0,0,('Project Managers'!AJ35*'Project Managers'!E35)-'Project Managers'!I35-'Project Managers'!AA35-'Project Managers'!AF35),0) -> 0 | AL35: =IFERROR(IF('Project Managers'!AJ35='Project Managers'!V35,0,('Project Managers'!AK35-('Project Managers'!AK35*'Project Managers'!L35))),0) -> 0 | AM35: =IFERROR('Project Managers'!AK35-'Project Managers'!AL35,0) -> 0 | AN35: =IFERROR('Project Managers'!AM35/'Project Managers'!AK35,0) -> 0 | AS35: 0.2
B36: T FERGUSON | C36: 722202 | D36: TITOS D17 | E36: 540613 | F36: =IFERROR('Project Managers'!E36*(1-'Project Managers'!H36),0) -> 432490.26 | G36: =IFERROR('Project Managers'!E36-'Project Managers'!F36,0) -> 108122.74 | H36: {=IF(ISBLANK('Project Managers'!AO36),'Project Managers'!R36,'Project Managers'!AO36)} -> 0.20000026 | I36: 264539.26 | J36: 211631.34 | K36: =IFERROR('Project Managers'!I36-'Project Managers'!J36,0) -> 52907.92 | L36: =IFERROR('Project Managers'!K36/'Project Managers'!I36,0) -> 0.20000026 | M36: 540613 | N36: =IFERROR(IF('Project Managers'!M36-'Project Managers'!I36>0,'Project Managers'!M36-'Project Managers'!I36,0),0) -> 276073.74 | O36: =IFERROR(IF('Project Managers'!M36-'Project Managers'!I36<0,'Project Managers'!M36-'Project Managers'!I36,0),0) -> 0 | P36: =IFERROR('Project Managers'!E36-'Project Managers'!I36,0) -> 276073.74 | Q36: =IFERROR(ROUND('Project Managers'!I36/'Project Managers'!E36,4),0) -> 0.4893 | R36: =IF(ISBLANK('Project Managers'!AP36),IF('Project Managers'!I36<>0,('Project Managers'!I36-'Project Managers'!J36)/'Project Managers'!I36,'Project Managers'!AS36),'Project Managers'!AP36) -> 0.20000026 | S36: 0.17 | T36: 0.2 | U36: =IFERROR(-('Project Managers'!I36-('Project Managers'!J36/(1-'Project Managers'!R36))),0) -> 0 | V36: 979.57217 | W36: =IFERROR(-('Project Managers'!I36-('Project Managers'!J36/(1-'Project Managers'!T36))),0) -> -0.085 | X36: =IFERROR(IF('Project Managers'!AQ36="",1,'Project Managers'!AQ36),0) -> 1 | Y36: 0.8628 | Z36: 0.95 | AA36: =IFERROR(IF('Project Managers'!Z36='Project Managers'!Q36,0,(('Project Managers'!Z36*'Project Managers'!E36)-'Project Managers'!I36)),0) -> 249043.09 | AB36: =IFERROR(IF('Project Managers'!Z36='Project Managers'!Q36,0,('Project Managers'!AA36-('Project Managers'!AA36*'Project Managers'!L36))),0) -> 199234.41 | AC36: =IFERROR('Project Managers'!AA36-'Project Managers'!AB36,0) -> 49808.682 | AD36: =IFERROR('Project Managers'!AC36/'Project Managers'!AA36,0) -> 0.20000026 | AE36: =IFERROR(IF('Project Managers'!Z36<1,1,0),0) -> 1 | AF36: =IFERROR(IF('Project Managers'!AE36=0,0,('Project Managers'!AE36*'Project Managers'!E36)-'Project Managers'!I36-'Project Managers'!AA36),0) -> 27030.65 | AG36: =IFERROR(IF('Project Managers'!AE36='Project Managers'!V36,0,('Project Managers'!AF36-('Project Managers'!AF36*'Project Managers'!L36))),0) -> 21624.513 | AH36: =IFERROR('Project Managers'!AF36-'Project Managers'!AG36,0) -> 5406.1369 | AI36: =IFERROR('Project Managers'!AH36/'Project Managers'!AF36,0) -> 0.20000026 | AK36: =IFERROR(IF('Project Managers'!AJ36=0,0,('Project Managers'!AJ36*'Project Managers'!E36)-'Project Managers'!I36-'Project Managers'!AA36-'Project Managers'!AF36),0) -> 0 | AL36: =IFERROR(IF('Project Managers'!AJ36='Project Managers'!V36,0,('Project Managers'!AK36-('Project Managers'!AK36*'Project Managers'!L36))),0) -> 0 | AM36: =IFERROR('Project Managers'!AK36-'Project Managers'!AL36,0) -> 0 | AN36: =IFERROR('Project Managers'!AM36/'Project Managers'!AK36,0) -> 0 | AS36: 0.2
B37: T FERGUSON | C37: 722203 | D37: TITOS D18 | E37: 540613 | F37: =IFERROR('Project Managers'!E37*(1-'Project Managers'!H37),0) -> 432490.38 | G37: =IFERROR('Project Managers'!E37-'Project Managers'!F37,0) -> 108122.62 | H37: {=IF(ISBLANK('Project Managers'!AO37),'Project Managers'!R37,'Project Managers'!AO37)} -> 0.20000004 | I37: 529491.34 | J37: 423593.05 | K37: =IFERROR('Project Managers'!I37-'Project Managers'!J37,0) -> 105898.29 | L37: =IFERROR('Project Managers'!K37/'Project Managers'!I37,0) -> 0.20000004 | M37: 540613 | N37: =IFERROR(IF('Project Managers'!M37-'Project Managers'!I37>0,'Project Managers'!M37-'Project Managers'!I37,0),0) -> 11121.66 | O37: =IFERROR(IF('Project Managers'!M37-'Project Managers'!I37<0,'Project Managers'!M37-'Project Managers'!I37,0),0) -> 0 | P37: =IFERROR('Project Managers'!E37-'Project Managers'!I37,0) -> 11121.66 | Q37: =IFERROR(ROUND('Project Managers'!I37/'Project Managers'!E37,4),0) -> 0.9794 | R37: =IF(ISBLANK('Project Managers'!AP37),IF('Project Managers'!I37<>0,('Project Managers'!I37-'Project Managers'!J37)/'Project Managers'!I37,'Project Managers'!AS37),'Project Managers'!AP37) -> 0.20000004 | S37: 0.17 | T37: 0.2 | U37: =IFERROR(-('Project Managers'!I37-('Project Managers'!J37/(1-'Project Managers'!R37))),0) -> 0 | V37: 2003.3175 | W37: =IFERROR(-('Project Managers'!I37-('Project Managers'!J37/(1-'Project Managers'!T37))),0) -> -0.0275 | X37: =IFERROR(IF('Project Managers'!AQ37="",1,'Project Managers'!AQ37),0) -> 1 | Y37: 0.9807 | Z37: 0.95 | AA37: =IFERROR(IF('Project Managers'!Z37='Project Managers'!Q37,0,(('Project Managers'!Z37*'Project Managers'!E37)-'Project Managers'!I37)),0) -> -15908.99 | AB37: =IFERROR(IF('Project Managers'!Z37='Project Managers'!Q37,0,('Project Managers'!AA37-('Project Managers'!AA37*'Project Managers'!L37))),0) -> -12727.191 | AC37: =IFERROR('Project Managers'!AA37-'Project Managers'!AB37,0) -> -3181.7987 | AD37: =IFERROR('Project Managers'!AC37/'Project Managers'!AA37,0) -> 0.20000004 | AE37: =IFERROR(IF('Project Managers'!Z37<1,1,0),0) -> 1 | AF37: =IFERROR(IF('Project Managers'!AE37=0,0,('Project Managers'!AE37*'Project Managers'!E37)-'Project Managers'!I37-'Project Managers'!AA37),0) -> 27030.65 | AG37: =IFERROR(IF('Project Managers'!AE37='Project Managers'!V37,0,('Project Managers'!AF37-('Project Managers'!AF37*'Project Managers'!L37))),0) -> 21624.519 | AH37: =IFERROR('Project Managers'!AF37-'Project Managers'!AG37,0) -> 5406.1311 | AI37: =IFERROR('Project Managers'!AH37/'Project Managers'!AF37,0) -> 0.20000004 | AK37: =IFERROR(IF('Project Managers'!AJ37=0,0,('Project Managers'!AJ37*'Project Managers'!E37)-'Project Managers'!I37-'Project Managers'!AA37-'Project Managers'!AF37),0) -> 0 | AL37: =IFERROR(IF('Project Managers'!AJ37='Project Managers'!V37,0,('Project Managers'!AK37-('Project Managers'!AK37*'Project Managers'!L37))),0) -> 0 | AM37: =IFERROR('Project Managers'!AK37-'Project Managers'!AL37,0) -> 0 | AN37: =IFERROR('Project Managers'!AM37/'Project Managers'!AK37,0) -> 0 | AS37: 0.2
B38: T FERGUSON | C38: 722204 | D38: TITOS D19 | E38: 540613 | F38: =IFERROR('Project Managers'!E38*(1-'Project Managers'!H38),0) -> 432490.36 | G38: =IFERROR('Project Managers'!E38-'Project Managers'!F38,0) -> 108122.64 | H38: {=IF(ISBLANK('Project Managers'!AO38),'Project Managers'!R38,'Project Managers'!AO38)} -> 0.20000007 | I38: 511281.68 | J38: 409025.31 | K38: =IFERROR('Project Managers'!I38-'Project Managers'!J38,0) -> 102256.37 | L38: =IFERROR('Project Managers'!K38/'Project Managers'!I38,0) -> 0.20000007 | M38: 540613 | N38: =IFERROR(IF('Project Managers'!M38-'Project Managers'!I38>0,'Project Managers'!M38-'Project Managers'!I38,0),0) -> 29331.32 | O38: =IFERROR(IF('Project Managers'!M38-'Project Managers'!I38<0,'Project Managers'!M38-'Project Managers'!I38,0),0) -> 0 | P38: =IFERROR('Project Managers'!E38-'Project Managers'!I38,0) -> 29331.32 | Q38: =IFERROR(ROUND('Project Managers'!I38/'Project Managers'!E38,4),0) -> 0.9457 | R38: =IF(ISBLANK('Project Managers'!AP38),IF('Project Managers'!I38<>0,('Project Managers'!I38-'Project Managers'!J38)/'Project Managers'!I38,'Project Managers'!AS38),'Project Managers'!AP38) -> 0.20000007 | S38: 0.17 | T38: 0.2 | U38: =IFERROR(-('Project Managers'!I38-('Project Managers'!J38/(1-'Project Managers'!R38))),0) -> -5.8207661e-11 | V38: 1919.9359 | W38: =IFERROR(-('Project Managers'!I38-('Project Managers'!J38/(1-'Project Managers'!T38))),0) -> -0.0425 | X38: =IFERROR(IF('Project Managers'!AQ38="",1,'Project Managers'!AQ38),0) -> 1 | Y38: 0.9711 | Z38: 0.95 | AA38: =IFERROR(IF('Project Managers'!Z38='Project Managers'!Q38,0,(('Project Managers'!Z38*'Project Managers'!E38)-'Project Managers'!I38)),0) -> 2300.67 | AB38: =IFERROR(IF('Project Managers'!Z38='Project Managers'!Q38,0,('Project Managers'!AA38-('Project Managers'!AA38*'Project Managers'!L38))),0) -> 1840.5358 | AC38: =IFERROR('Project Managers'!AA38-'Project Managers'!AB38,0) -> 460.13415 | AD38: =IFERROR('Project Managers'!AC38/'Project Managers'!AA38,0) -> 0.20000007 | AE38: =IFERROR(IF('Project Managers'!Z38<1,1,0),0) -> 1 | AF38: =IFERROR(IF('Project Managers'!AE38=0,0,('Project Managers'!AE38*'Project Managers'!E38)-'Project Managers'!I38-'Project Managers'!AA38),0) -> 27030.65 | AG38: =IFERROR(IF('Project Managers'!AE38='Project Managers'!V38,0,('Project Managers'!AF38-('Project Managers'!AF38*'Project Managers'!L38))),0) -> 21624.518 | AH38: =IFERROR('Project Managers'!AF38-'Project Managers'!AG38,0) -> 5406.1318 | AI38: =IFERROR('Project Managers'!AH38/'Project Managers'!AF38,0) -> 0.20000007 | AK38: =IFERROR(IF('Project Managers'!AJ38=0,0,('Project Managers'!AJ38*'Project Managers'!E38)-'Project Managers'!I38-'Project Managers'!AA38-'Project Managers'!AF38),0) -> 0 | AL38: =IFERROR(IF('Project Managers'!AJ38='Project Managers'!V38,0,('Project Managers'!AK38-('Project Managers'!AK38*'Project Managers'!L38))),0) -> 0 | AM38: =IFERROR('Project Managers'!AK38-'Project Managers'!AL38,0) -> 0 | AN38: =IFERROR('Project Managers'!AM38/'Project Managers'!AK38,0) -> 0 | AS38: 0.2
B39: T FERGUSON | C39: 722205 | D39: NEW COMPRESSOR BLDG | E39: 97115 | F39: =IFERROR('Project Managers'!E39*(1-'Project Managers'!H39),0) -> 63102.676 | G39: =IFERROR('Project Managers'!E39-'Project Managers'!F39,0) -> 34012.324 | H39: {=IF(ISBLANK('Project Managers'!AO39),'Project Managers'!R39,'Project Managers'!AO39)} -> 0.35022729 | I39: 71722.08 | J39: 46603.05 | K39: =IFERROR('Project Managers'!I39-'Project Managers'!J39,0) -> 25119.03 | L39: =IFERROR('Project Managers'!K39/'Project Managers'!I39,0) -> 0.35022729 | M39: 97115 | N39: =IFERROR(IF('Project Managers'!M39-'Project Managers'!I39>0,'Project Managers'!M39-'Project Managers'!I39,0),0) -> 25392.92 | O39: =IFERROR(IF('Project Managers'!M39-'Project Managers'!I39<0,'Project Managers'!M39-'Project Managers'!I39,0),0) -> 0 | P39: =IFERROR('Project Managers'!E39-'Project Managers'!I39,0) -> 25392.92 | Q39: =IFERROR(ROUND('Project Managers'!I39/'Project Managers'!E39,4),0) -> 0.7385 | R39: =IF(ISBLANK('Project Managers'!AP39),IF('Project Managers'!I39<>0,('Project Managers'!I39-'Project Managers'!J39)/'Project Managers'!I39,'Project Managers'!AS39),'Project Managers'!AP39) -> 0.35022729 | S39: 0.15 | T39: 0.35 | U39: =IFERROR(-('Project Managers'!I39-('Project Managers'!J39/(1-'Project Managers'!R39))),0) -> 0 | V39: -3426.7324 | W39: =IFERROR(-('Project Managers'!I39-('Project Managers'!J39/(1-'Project Managers'!T39))),0) -> -25.08 | X39: =IFERROR(IF('Project Managers'!AQ39="",1,'Project Managers'!AQ39),0) -> 1 | Y39: 1 | Z39: 1 | AA39: =IFERROR(IF('Project Managers'!Z39='Project Managers'!Q39,0,(('Project Managers'!Z39*'Project Managers'!E39)-'Project Managers'!I39)),0) -> 25392.92 | AB39: =IFERROR(IF('Project Managers'!Z39='Project Managers'!Q39,0,('Project Managers'!AA39-('Project Managers'!AA39*'Project Managers'!L39))),0) -> 16499.626 | AC39: =IFERROR('Project Managers'!AA39-'Project Managers'!AB39,0) -> 8893.2937 | AD39: =IFERROR('Project Managers'!AC39/'Project Managers'!AA39,0) -> 0.35022729 | AE39: =IFERROR(IF('Project Managers'!Z39<1,1,0),0) -> 0 | AF39: =IFERROR(IF('Project Managers'!AE39=0,0,('Project Managers'!AE39*'Project Managers'!E39)-'Project Managers'!I39-'Project Managers'!AA39),0) -> 0 | AG39: =IFERROR(IF('Project Managers'!AE39='Project Managers'!V39,0,('Project Managers'!AF39-('Project Managers'!AF39*'Project Managers'!L39))),0) -> 0 | AH39: =IFERROR('Project Managers'!AF39-'Project Managers'!AG39,0) -> 0 | AI39: =IFERROR('Project Managers'!AH39/'Project Managers'!AF39,0) -> 0 | AK39: =IFERROR(IF('Project Managers'!AJ39=0,0,('Project Managers'!AJ39*'Project Managers'!E39)-'Project Managers'!I39-'Project Managers'!AA39-'Project Managers'!AF39),0) -> 0 | AL39: =IFERROR(IF('Project Managers'!AJ39='Project Managers'!V39,0,('Project Managers'!AK39-('Project Managers'!AK39*'Project Managers'!L39))),0) -> 0 | AM39: =IFERROR('Project Managers'!AK39-'Project Managers'!AL39,0) -> 0 | AN39: =IFERROR('Project Managers'!AM39/'Project Managers'!AK39,0) -> 0 | AS39: 0.35
B40: T FERGUSON | C40: 722206 | D40: TITOS GUARD HOUSE 6 | E40: 101940 | F40: =IFERROR('Project Managers'!E40*(1-'Project Managers'!H40),0) -> 99235.31 | G40: =IFERROR('Project Managers'!E40-'Project Managers'!F40,0) -> 2704.69 | H40: {=IF(ISBLANK('Project Managers'!AO40),'Project Managers'!R40,'Project Managers'!AO40)} -> 0.026532176 | I40: 101940 | J40: 99235.31 | K40: =IFERROR('Project Managers'!I40-'Project Managers'!J40,0) -> 2704.69 | L40: =IFERROR('Project Managers'!K40/'Project Managers'!I40,0) -> 0.026532176 | M40: 101940 | N40: =IFERROR(IF('Project Managers'!M40-'Project Managers'!I40>0,'Project Managers'!M40-'Project Managers'!I40,0),0) -> 0 | O40: =IFERROR(IF('Project Managers'!M40-'Project Managers'!I40<0,'Project Managers'!M40-'Project Managers'!I40,0),0) -> 0 | P40: =IFERROR('Project Managers'!E40-'Project Managers'!I40,0) -> 0 | Q40: =IFERROR(ROUND('Project Managers'!I40/'Project Managers'!E40,4),0) -> 1 | R40: =IF(ISBLANK('Project Managers'!AP40),IF('Project Managers'!I40<>0,('Project Managers'!I40-'Project Managers'!J40)/'Project Managers'!I40,'Project Managers'!AS40),'Project Managers'!AP40) -> 0.026532176 | S40: 0.15 | T40: 0.0265 | U40: =IFERROR(-('Project Managers'!I40-('Project Managers'!J40/(1-'Project Managers'!R40))),0) -> 0 | V40: -2333.9465 | W40: =IFERROR(-('Project Managers'!I40-('Project Managers'!J40/(1-'Project Managers'!T40))),0) -> -3.3692861 | X40: =IFERROR(IF('Project Managers'!AQ40="",1,'Project Managers'!AQ40),0) -> 1 | Y40: 1 | Z40: 1 | AA40: =IFERROR(IF('Project Managers'!Z40='Project Managers'!Q40,0,(('Project Managers'!Z40*'Project Managers'!E40)-'Project Managers'!I40)),0) -> 0 | AB40: =IFERROR(IF('Project Managers'!Z40='Project Managers'!Q40,0,('Project Managers'!AA40-('Project Managers'!AA40*'Project Managers'!L40))),0) -> 0 | AC40: =IFERROR('Project Managers'!AA40-'Project Managers'!AB40,0) -> 0 | AD40: =IFERROR('Project Managers'!AC40/'Project Managers'!AA40,0) -> 0 | AE40: =IFERROR(IF('Project Managers'!Z40<1,1,0),0) -> 0 | AF40: =IFERROR(IF('Project Managers'!AE40=0,0,('Project Managers'!AE40*'Project Managers'!E40)-'Project Managers'!I40-'Project Managers'!AA40),0) -> 0 | AG40: =IFERROR(IF('Project Managers'!AE40='Project Managers'!V40,0,('Project Managers'!AF40-('Project Managers'!AF40*'Project Managers'!L40))),0) -> 0 | AH40: =IFERROR('Project Managers'!AF40-'Project Managers'!AG40,0) -> 0 | AI40: =IFERROR('Project Managers'!AH40/'Project Managers'!AF40,0) -> 0 | AK40: =IFERROR(IF('Project Managers'!AJ40=0,0,('Project Managers'!AJ40*'Project Managers'!E40)-'Project Managers'!I40-'Project Managers'!AA40-'Project Managers'!AF40),0) -> 0 | AL40: =IFERROR(IF('Project Managers'!AJ40='Project Managers'!V40,0,('Project Managers'!AK40-('Project Managers'!AK40*'Project Managers'!L40))),0) -> 0 | AM40: =IFERROR('Project Managers'!AK40-'Project Managers'!AL40,0) -> 0 | AN40: =IFERROR('Project Managers'!AM40/'Project Managers'!AK40,0) -> 0 | AS40: 0.167
B41: T FERGUSON | C41: 722207 | D41: TITOS DUNNAGE AREA DA-1 | E41: 223936.85 | F41: =IFERROR('Project Managers'!E41*(1-'Project Managers'!H41),0) -> 186614.06 | G41: =IFERROR('Project Managers'!E41-'Project Managers'!F41,0) -> 37322.786 | H41: {=IF(ISBLANK('Project Managers'!AO41),'Project Managers'!R41,'Project Managers'!AO41)} -> 0.16666657 | I41: 186692.87 | J41: 155577.41 | K41: =IFERROR('Project Managers'!I41-'Project Managers'!J41,0) -> 31115.46 | L41: =IFERROR('Project Managers'!K41/'Project Managers'!I41,0) -> 0.16666657 | M41: 223936.85 | N41: =IFERROR(IF('Project Managers'!M41-'Project Managers'!I41>0,'Project Managers'!M41-'Project Managers'!I41,0),0) -> 37243.98 | O41: =IFERROR(IF('Project Managers'!M41-'Project Managers'!I41<0,'Project Managers'!M41-'Project Managers'!I41,0),0) -> 0 | P41: =IFERROR('Project Managers'!E41-'Project Managers'!I41,0) -> 37243.98 | Q41: =IFERROR(ROUND('Project Managers'!I41/'Project Managers'!E41,4),0) -> 0.8337 | R41: =IF(ISBLANK('Project Managers'!AP41),IF('Project Managers'!I41<>0,('Project Managers'!I41-'Project Managers'!J41)/'Project Managers'!I41,'Project Managers'!AS41),'Project Managers'!AP41) -> 0.16666657 | S41: 0.2 | T41: 0.2 | U41: =IFERROR(-('Project Managers'!I41-('Project Managers'!J41/(1-'Project Managers'!R41))),0) -> 0 | V41: 7778.8925 | W41: =IFERROR(-('Project Managers'!I41-('Project Managers'!J41/(1-'Project Managers'!T41))),0) -> 7778.8925 | X41: =IFERROR(IF('Project Managers'!AQ41="",1,'Project Managers'!AQ41),0) -> 1 | Y41: 1 | Z41: 1 | AA41: =IFERROR(IF('Project Managers'!Z41='Project Managers'!Q41,0,(('Project Managers'!Z41*'Project Managers'!E41)-'Project Managers'!I41)),0) -> 37243.98 | AB41: =IFERROR(IF('Project Managers'!Z41='Project Managers'!Q41,0,('Project Managers'!AA41-('Project Managers'!AA41*'Project Managers'!L41))),0) -> 31036.654 | AC41: =IFERROR('Project Managers'!AA41-'Project Managers'!AB41,0) -> 6207.3263 | AD41: =IFERROR('Project Managers'!AC41/'Project Managers'!AA41,0) -> 0.16666657 | AE41: =IFERROR(IF('Project Managers'!Z41<1,1,0),0) -> 0 | AF41: =IFERROR(IF('Project Managers'!AE41=0,0,('Project Managers'!AE41*'Project Managers'!E41)-'Project Managers'!I41-'Project Managers'!AA41),0) -> 0 | AG41: =IFERROR(IF('Project Managers'!AE41='Project Managers'!V41,0,('Project Managers'!AF41-('Project Managers'!AF41*'Project Managers'!L41))),0) -> 0 | AH41: =IFERROR('Project Managers'!AF41-'Project Managers'!AG41,0) -> 0 | AI41: =IFERROR('Project Managers'!AH41/'Project Managers'!AF41,0) -> 0 | AK41: =IFERROR(IF('Project Managers'!AJ41=0,0,('Project Managers'!AJ41*'Project Managers'!E41)-'Project Managers'!I41-'Project Managers'!AA41-'Project Managers'!AF41),0) -> 0 | AL41: =IFERROR(IF('Project Managers'!AJ41='Project Managers'!V41,0,('Project Managers'!AK41-('Project Managers'!AK41*'Project Managers'!L41))),0) -> 0 | AM41: =IFERROR('Project Managers'!AK41-'Project Managers'!AL41,0) -> 0 | AN41: =IFERROR('Project Managers'!AM41/'Project Managers'!AK41,0) -> 0 | AS41: 0.167
B42: T FERGUSON | C42: 722208 | D42: TITOS AT VAULT EXPANSION | E42: 155587 | F42: =IFERROR('Project Managers'!E42*(1-'Project Managers'!H42),0) -> 124469.48 | G42: =IFERROR('Project Managers'!E42-'Project Managers'!F42,0) -> 31117.517 | H42: {=IF(ISBLANK('Project Managers'!AO42),'Project Managers'!R42,'Project Managers'!AO42)} -> 0.20000075 | I42: 29248.64 | J42: 23398.89 | K42: =IFERROR('Project Managers'!I42-'Project Managers'!J42,0) -> 5849.75 | L42: =IFERROR('Project Managers'!K42/'Project Managers'!I42,0) -> 0.20000075 | M42: 29762 | N42: =IFERROR(IF('Project Managers'!M42-'Project Managers'!I42>0,'Project Managers'!M42-'Project Managers'!I42,0),0) -> 513.36 | O42: =IFERROR(IF('Project Managers'!M42-'Project Managers'!I42<0,'Project Managers'!M42-'Project Managers'!I42,0),0) -> 0 | P42: =IFERROR('Project Managers'!E42-'Project Managers'!I42,0) -> 126338.36 | Q42: =IFERROR(ROUND('Project Managers'!I42/'Project Managers'!E42,4),0) -> 0.188 | R42: =IF(ISBLANK('Project Managers'!AP42),IF('Project Managers'!I42<>0,('Project Managers'!I42-'Project Managers'!J42)/'Project Managers'!I42,'Project Managers'!AS42),'Project Managers'!AP42) -> 0.20000075 | S42: 0.2 | T42: 0.2 | U42: =IFERROR(-('Project Managers'!I42-('Project Managers'!J42/(1-'Project Managers'!R42))),0) -> -3.6379788e-12 | V42: -0.0225 | W42: =IFERROR(-('Project Managers'!I42-('Project Managers'!J42/(1-'Project Managers'!T42))),0) -> -0.0275 | X42: =IFERROR(IF('Project Managers'!AQ42="",1,'Project Managers'!AQ42),0) -> 1 | Y42: 0.317 | Z42: 0.2 | AA42: =IFERROR(IF('Project Managers'!Z42='Project Managers'!Q42,0,(('Project Managers'!Z42*'Project Managers'!E42)-'Project Managers'!I42)),0) -> 1868.76 | AB42: =IFERROR(IF('Project Managers'!Z42='Project Managers'!Q42,0,('Project Managers'!AA42-('Project Managers'!AA42*'Project Managers'!L42))),0) -> 1495.0066 | AC42: =IFERROR('Project Managers'!AA42-'Project Managers'!AB42,0) -> 373.75341 | AD42: =IFERROR('Project Managers'!AC42/'Project Managers'!AA42,0) -> 0.20000075 | AE42: =IFERROR(IF('Project Managers'!Z42<1,1,0),0) -> 1 | AF42: =IFERROR(IF('Project Managers'!AE42=0,0,('Project Managers'!AE42*'Project Managers'!E42)-'Project Managers'!I42-'Project Managers'!AA42),0) -> 124469.6 | AG42: =IFERROR(IF('Project Managers'!AE42='Project Managers'!V42,0,('Project Managers'!AF42-('Project Managers'!AF42*'Project Managers'!L42))),0) -> 99575.586 | AH42: =IFERROR('Project Managers'!AF42-'Project Managers'!AG42,0) -> 24894.014 | AI42: =IFERROR('Project Managers'!AH42/'Project Managers'!AF42,0) -> 0.20000075 | AK42: =IFERROR(IF('Project Managers'!AJ42=0,0,('Project Managers'!AJ42*'Project Managers'!E42)-'Project Managers'!I42-'Project Managers'!AA42-'Project Managers'!AF42),0) -> 0 | AL42: =IFERROR(IF('Project Managers'!AJ42='Project Managers'!V42,0,('Project Managers'!AK42-('Project Managers'!AK42*'Project Managers'!L42))),0) -> 0 | AM42: =IFERROR('Project Managers'!AK42-'Project Managers'!AL42,0) -> 0 | AN42: =IFERROR('Project Managers'!AM42/'Project Managers'!AK42,0) -> 0 | AS42: 0.2
B43: T FERGUSON | C43: 722330 | D43: WILCO HQ | E43: 8047533.5 | F43: =IFERROR('Project Managers'!E43*(1-'Project Managers'!H43),0) -> 6679452.8 | G43: =IFERROR('Project Managers'!E43-'Project Managers'!F43,0) -> 1368080.7 | H43: {=IF(ISBLANK('Project Managers'!AO43),'Project Managers'!R43,'Project Managers'!AO43)} -> 0.17 | I43: 6563125 | J43: 5446576.6 | K43: =IFERROR('Project Managers'!I43-'Project Managers'!J43,0) -> 1116548.3 | L43: =IFERROR('Project Managers'!K43/'Project Managers'!I43,0) -> 0.1701245 | M43: 6409924.4 | N43: =IFERROR(IF('Project Managers'!M43-'Project Managers'!I43>0,'Project Managers'!M43-'Project Managers'!I43,0),0) -> 0 | O43: =IFERROR(IF('Project Managers'!M43-'Project Managers'!I43<0,'Project Managers'!M43-'Project Managers'!I43,0),0) -> -153200.51 | P43: =IFERROR('Project Managers'!E43-'Project Managers'!I43,0) -> 1484408.5 | Q43: =IFERROR(ROUND('Project Managers'!I43/'Project Managers'!E43,4),0) -> 0.8155 | R43: {=IF(ISBLANK('Project Managers'!AP43),IF('Project Managers'!I43<>0,('Project Managers'!I43-'Project Managers'!J43)/'Project Managers'!I43,'Project Managers'!AS43),'Project Managers'!AP43)} -> 0.22 | S43: 0.21 | T43: 0.2 | U43: =IFERROR(-('Project Managers'!I43-('Project Managers'!J43/(1-'Project Managers'!R43))),0) -> 419665.6 | V43: 71486.018 | W43: =IFERROR(-('Project Managers'!I43-('Project Managers'!J43/(1-'Project Managers'!T43))),0) -> 245095.84 | X43: =IFERROR(IF('Project Managers'!AQ43="",1,'Project Managers'!AQ43),0) -> 1 | Y43: 0.8956 | Z43: 0.9 | AA43: =IFERROR(IF('Project Managers'!Z43='Project Managers'!Q43,0,(('Project Managers'!Z43*'Project Managers'!E43)-'Project Managers'!I43)),0) -> 679655.19 | AB43: =IFERROR(IF('Project Managers'!Z43='Project Managers'!Q43,0,('Project Managers'!AA43-('Project Managers'!AA43*'Project Managers'!L43))),0) -> 564029.19 | AC43: =IFERROR('Project Managers'!AA43-'Project Managers'!AB43,0) -> 115626 | AD43: =IFERROR('Project Managers'!AC43/'Project Managers'!AA43,0) -> 0.1701245 | AE43: =IFERROR(IF('Project Managers'!Z43<1,1,0),0) -> 1 | AF43: =IFERROR(IF('Project Managers'!AE43=0,0,('Project Managers'!AE43*'Project Managers'!E43)-'Project Managers'!I43-'Project Managers'!AA43),0) -> 804753.35 | AG43: =IFERROR(IF('Project Managers'!AE43='Project Managers'!V43,0,('Project Managers'!AF43-('Project Managers'!AF43*'Project Managers'!L43))),0) -> 667845.09 | AH43: =IFERROR('Project Managers'!AF43-'Project Managers'!AG43,0) -> 136908.26 | AI43: =IFERROR('Project Managers'!AH43/'Project Managers'!AF43,0) -> 0.1701245 | AK43: =IFERROR(IF('Project Managers'!AJ43=0,0,('Project Managers'!AJ43*'Project Managers'!E43)-'Project Managers'!I43-'Project Managers'!AA43-'Project Managers'!AF43),0) -> 0 | AL43: =IFERROR(IF('Project Managers'!AJ43='Project Managers'!V43,0,('Project Managers'!AK43-('Project Managers'!AK43*'Project Managers'!L43))),0) -> 0 | AM43: =IFERROR('Project Managers'!AK43-'Project Managers'!AL43,0) -> 0 | AN43: =IFERROR('Project Managers'!AM43/'Project Managers'!AK43,0) -> 0 | AO43: 0.17 | AP43: 0.22 | AS43: 0.17
B44: T FERGUSON | C44: 722460 | D44: TITOS BACK OF LINE IMPROV | E44: 161110 | F44: =IFERROR('Project Managers'!E44*(1-'Project Managers'!H44),0) -> 128887.93 | G44: =IFERROR('Project Managers'!E44-'Project Managers'!F44,0) -> 32222.069 | H44: {=IF(ISBLANK('Project Managers'!AO44),'Project Managers'!R44,'Project Managers'!AO44)} -> 0.20000043 | I44: 102807.23 | J44: 82245.74 | K44: =IFERROR('Project Managers'!I44-'Project Managers'!J44,0) -> 20561.49 | L44: =IFERROR('Project Managers'!K44/'Project Managers'!I44,0) -> 0.20000043 | M44: 155528 | N44: =IFERROR(IF('Project Managers'!M44-'Project Managers'!I44>0,'Project Managers'!M44-'Project Managers'!I44,0),0) -> 52720.77 | O44: =IFERROR(IF('Project Managers'!M44-'Project Managers'!I44<0,'Project Managers'!M44-'Project Managers'!I44,0),0) -> 0 | P44: =IFERROR('Project Managers'!E44-'Project Managers'!I44,0) -> 58302.77 | Q44: =IFERROR(ROUND('Project Managers'!I44/'Project Managers'!E44,4),0) -> 0.6381 | R44: =IF(ISBLANK('Project Managers'!AP44),IF('Project Managers'!I44<>0,('Project Managers'!I44-'Project Managers'!J44)/'Project Managers'!I44,'Project Managers'!AS44),'Project Managers'!AP44) -> 0.20000043 | S44: 0.2 | T44: 0.22 | U44: =IFERROR(-('Project Managers'!I44-('Project Managers'!J44/(1-'Project Managers'!R44))),0) -> 0 | V44: -0.055 | W44: =IFERROR(-('Project Managers'!I44-('Project Managers'!J44/(1-'Project Managers'!T44))),0) -> 2636.0264 | X44: =IFERROR(IF('Project Managers'!AQ44="",1,'Project Managers'!AQ44),0) -> 1 | Y44: 0.9631 | Z44: 0.8 | AA44: =IFERROR(IF('Project Managers'!Z44='Project Managers'!Q44,0,(('Project Managers'!Z44*'Project Managers'!E44)-'Project Managers'!I44)),0) -> 26080.77 | AB44: =IFERROR(IF('Project Managers'!Z44='Project Managers'!Q44,0,('Project Managers'!AA44-('Project Managers'!AA44*'Project Managers'!L44))),0) -> 20864.605 | AC44: =IFERROR('Project Managers'!AA44-'Project Managers'!AB44,0) -> 5216.1652 | AD44: =IFERROR('Project Managers'!AC44/'Project Managers'!AA44,0) -> 0.20000043 | AE44: =IFERROR(IF('Project Managers'!Z44<1,1,0),0) -> 1 | AF44: =IFERROR(IF('Project Managers'!AE44=0,0,('Project Managers'!AE44*'Project Managers'!E44)-'Project Managers'!I44-'Project Managers'!AA44),0) -> 32222 | AG44: =IFERROR(IF('Project Managers'!AE44='Project Managers'!V44,0,('Project Managers'!AF44-('Project Managers'!AF44*'Project Managers'!L44))),0) -> 25777.586 | AH44: =IFERROR('Project Managers'!AF44-'Project Managers'!AG44,0) -> 6444.4138 | AI44: =IFERROR('Project Managers'!AH44/'Project Managers'!AF44,0) -> 0.20000043 | AK44: =IFERROR(IF('Project Managers'!AJ44=0,0,('Project Managers'!AJ44*'Project Managers'!E44)-'Project Managers'!I44-'Project Managers'!AA44-'Project Managers'!AF44),0) -> 0 | AL44: =IFERROR(IF('Project Managers'!AJ44='Project Managers'!V44,0,('Project Managers'!AK44-('Project Managers'!AK44*'Project Managers'!L44))),0) -> 0 | AM44: =IFERROR('Project Managers'!AK44-'Project Managers'!AL44,0) -> 0 | AN44: =IFERROR('Project Managers'!AM44/'Project Managers'!AK44,0) -> 0 | AS44: 0.2
B45: T FERGUSON | C45: 722480 | D45: TITOS D 14 PWR / SECURITY | E45: 70972.07 | F45: =IFERROR('Project Managers'!E45*(1-'Project Managers'!H45),0) -> 71113.38 | G45: =IFERROR('Project Managers'!E45-'Project Managers'!F45,0) -> -141.31 | H45: {=IF(ISBLANK('Project Managers'!AO45),'Project Managers'!R45,'Project Managers'!AO45)} -> -0.0019910649 | I45: 70972.07 | J45: 71113.38 | K45: =IFERROR('Project Managers'!I45-'Project Managers'!J45,0) -> -141.31 | L45: =IFERROR('Project Managers'!K45/'Project Managers'!I45,0) -> -0.0019910649 | M45: 70972.07 | N45: =IFERROR(IF('Project Managers'!M45-'Project Managers'!I45>0,'Project Managers'!M45-'Project Managers'!I45,0),0) -> 0 | O45: =IFERROR(IF('Project Managers'!M45-'Project Managers'!I45<0,'Project Managers'!M45-'Project Managers'!I45,0),0) -> 0 | P45: =IFERROR('Project Managers'!E45-'Project Managers'!I45,0) -> 0 | Q45: =IFERROR(ROUND('Project Managers'!I45/'Project Managers'!E45,4),0) -> 1 | R45: =IF(ISBLANK('Project Managers'!AP45),IF('Project Managers'!I45<>0,('Project Managers'!I45-'Project Managers'!J45)/'Project Managers'!I45,'Project Managers'!AS45),'Project Managers'!AP45) -> -0.0019910649 | S45: 0.25 | T45: 0 | U45: =IFERROR(-('Project Managers'!I45-('Project Managers'!J45/(1-'Project Managers'!R45))),0) -> 0 | V45: 19975.103 | W45: =IFERROR(-('Project Managers'!I45-('Project Managers'!J45/(1-'Project Managers'!T45))),0) -> 141.31 | X45: =IFERROR(IF('Project Managers'!AQ45="",1,'Project Managers'!AQ45),0) -> 1 | Y45: 1 | Z45: 1 | AA45: =IFERROR(IF('Project Managers'!Z45='Project Managers'!Q45,0,(('Project Managers'!Z45*'Project Managers'!E45)-'Project Managers'!I45)),0) -> 0 | AB45: =IFERROR(IF('Project Managers'!Z45='Project Managers'!Q45,0,('Project Managers'!AA45-('Project Managers'!AA45*'Project Managers'!L45))),0) -> 0 | AC45: =IFERROR('Project Managers'!AA45-'Project Managers'!AB45,0) -> 0 | AD45: =IFERROR('Project Managers'!AC45/'Project Managers'!AA45,0) -> 0 | AE45: =IFERROR(IF('Project Managers'!Z45<1,1,0),0) -> 0 | AF45: =IFERROR(IF('Project Managers'!AE45=0,0,('Project Managers'!AE45*'Project Managers'!E45)-'Project Managers'!I45-'Project Managers'!AA45),0) -> 0 | AG45: =IFERROR(IF('Project Managers'!AE45='Project Managers'!V45,0,('Project Managers'!AF45-('Project Managers'!AF45*'Project Managers'!L45))),0) -> 0 | AH45: =IFERROR('Project Managers'!AF45-'Project Managers'!AG45,0) -> 0 | AI45: =IFERROR('Project Managers'!AH45/'Project Managers'!AF45,0) -> 0 | AK45: =IFERROR(IF('Project Managers'!AJ45=0,0,('Project Managers'!AJ45*'Project Managers'!E45)-'Project Managers'!I45-'Project Managers'!AA45-'Project Managers'!AF45),0) -> 0 | AL45: =IFERROR(IF('Project Managers'!AJ45='Project Managers'!V45,0,('Project Managers'!AK45-('Project Managers'!AK45*'Project Managers'!L45))),0) -> 0 | AM45: =IFERROR('Project Managers'!AK45-'Project Managers'!AL45,0) -> 0 | AN45: =IFERROR('Project Managers'!AM45/'Project Managers'!AK45,0) -> 0
B46: T FERGUSON | C46: 722510 | D46: D2&D3 FA CONDUITS | E46: 22500 | F46: =IFERROR('Project Managers'!E46*(1-'Project Managers'!H46),0) -> 17999.957 | G46: =IFERROR('Project Managers'!E46-'Project Managers'!F46,0) -> 4500.0431 | H46: {=IF(ISBLANK('Project Managers'!AO46),'Project Managers'!R46,'Project Managers'!AO46)} -> 0.20000191 | I46: 9406.26 | J46: 7524.99 | K46: =IFERROR('Project Managers'!I46-'Project Managers'!J46,0) -> 1881.27 | L46: =IFERROR('Project Managers'!K46/'Project Managers'!I46,0) -> 0.20000191 | M46: 22500 | N46: =IFERROR(IF('Project Managers'!M46-'Project Managers'!I46>0,'Project Managers'!M46-'Project Managers'!I46,0),0) -> 13093.74 | O46: =IFERROR(IF('Project Managers'!M46-'Project Managers'!I46<0,'Project Managers'!M46-'Project Managers'!I46,0),0) -> 0 | P46: =IFERROR('Project Managers'!E46-'Project Managers'!I46,0) -> 13093.74 | Q46: =IFERROR(ROUND('Project Managers'!I46/'Project Managers'!E46,4),0) -> 0.4181 | R46: =IF(ISBLANK('Project Managers'!AP46),IF('Project Managers'!I46<>0,('Project Managers'!I46-'Project Managers'!J46)/'Project Managers'!I46,'Project Managers'!AS46),'Project Managers'!AP46) -> 0.20000191 | S46: 0.2 | T46: 0.3 | U46: =IFERROR(-('Project Managers'!I46-('Project Managers'!J46/(1-'Project Managers'!R46))),0) -> 0 | V46: -0.01 | W46: =IFERROR(-('Project Managers'!I46-('Project Managers'!J46/(1-'Project Managers'!T46))),0) -> 1343.7257 | X46: =IFERROR(IF('Project Managers'!AQ46="",1,'Project Managers'!AQ46),0) -> 1 | Y46: 0.6342 | Z46: 0.5 | AA46: =IFERROR(IF('Project Managers'!Z46='Project Managers'!Q46,0,(('Project Managers'!Z46*'Project Managers'!E46)-'Project Managers'!I46)),0) -> 1843.74 | AB46: =IFERROR(IF('Project Managers'!Z46='Project Managers'!Q46,0,('Project Managers'!AA46-('Project Managers'!AA46*'Project Managers'!L46))),0) -> 1474.9885 | AC46: =IFERROR('Project Managers'!AA46-'Project Managers'!AB46,0) -> 368.75153 | AD46: =IFERROR('Project Managers'!AC46/'Project Managers'!AA46,0) -> 0.20000191 | AE46: =IFERROR(IF('Project Managers'!Z46<1,1,0),0) -> 1 | AF46: =IFERROR(IF('Project Managers'!AE46=0,0,('Project Managers'!AE46*'Project Managers'!E46)-'Project Managers'!I46-'Project Managers'!AA46),0) -> 11250 | AG46: =IFERROR(IF('Project Managers'!AE46='Project Managers'!V46,0,('Project Managers'!AF46-('Project Managers'!AF46*'Project Managers'!L46))),0) -> 8999.9785 | AH46: =IFERROR('Project Managers'!AF46-'Project Managers'!AG46,0) -> 2250.0215 | AI46: =IFERROR('Project Managers'!AH46/'Project Managers'!AF46,0) -> 0.20000191 | AK46: =IFERROR(IF('Project Managers'!AJ46=0,0,('Project Managers'!AJ46*'Project Managers'!E46)-'Project Managers'!I46-'Project Managers'!AA46-'Project Managers'!AF46),0) -> 0 | AL46: =IFERROR(IF('Project Managers'!AJ46='Project Managers'!V46,0,('Project Managers'!AK46-('Project Managers'!AK46*'Project Managers'!L46))),0) -> 0 | AM46: =IFERROR('Project Managers'!AK46-'Project Managers'!AL46,0) -> 0 | AN46: =IFERROR('Project Managers'!AM46/'Project Managers'!AK46,0) -> 0 | AS46: 0.2
B47: T FERGUSON | C47: 722530 | D47: W7 B-VAULTS | E47: 70673.08 | F47: =IFERROR('Project Managers'!E47*(1-'Project Managers'!H47),0) -> 56538.453 | G47: =IFERROR('Project Managers'!E47-'Project Managers'!F47,0) -> 14134.627 | H47: {=IF(ISBLANK('Project Managers'!AO47),'Project Managers'!R47,'Project Managers'!AO47)} -> 0.20000015 | I47: 66973.35 | J47: 53578.67 | K47: =IFERROR('Project Managers'!I47-'Project Managers'!J47,0) -> 13394.68 | L47: =IFERROR('Project Managers'!K47/'Project Managers'!I47,0) -> 0.20000015 | M47: 37427.44 | N47: =IFERROR(IF('Project Managers'!M47-'Project Managers'!I47>0,'Project Managers'!M47-'Project Managers'!I47,0),0) -> 0 | O47: =IFERROR(IF('Project Managers'!M47-'Project Managers'!I47<0,'Project Managers'!M47-'Project Managers'!I47,0),0) -> -29545.91 | P47: =IFERROR('Project Managers'!E47-'Project Managers'!I47,0) -> 3699.73 | Q47: =IFERROR(ROUND('Project Managers'!I47/'Project Managers'!E47,4),0) -> 0.9477 | R47: =IF(ISBLANK('Project Managers'!AP47),IF('Project Managers'!I47<>0,('Project Managers'!I47-'Project Managers'!J47)/'Project Managers'!I47,'Project Managers'!AS47),'Project Managers'!AP47) -> 0.20000015 | S47: 0.2 | T47: 0.2 | U47: =IFERROR(-('Project Managers'!I47-('Project Managers'!J47/(1-'Project Managers'!R47))),0) -> 0 | V47: -0.0075 | W47: =IFERROR(-('Project Managers'!I47-('Project Managers'!J47/(1-'Project Managers'!T47))),0) -> -0.0125 | X47: =IFERROR(IF('Project Managers'!AQ47="",1,'Project Managers'!AQ47),0) -> 1 | Y47: 0.4977 | Z47: 1 | AA47: =IFERROR(IF('Project Managers'!Z47='Project Managers'!Q47,0,(('Project Managers'!Z47*'Project Managers'!E47)-'Project Managers'!I47)),0) -> 3699.73 | AB47: =IFERROR(IF('Project Managers'!Z47='Project Managers'!Q47,0,('Project Managers'!AA47-('Project Managers'!AA47*'Project Managers'!L47))),0) -> 2959.7834 | AC47: =IFERROR('Project Managers'!AA47-'Project Managers'!AB47,0) -> 739.94655 | AD47: =IFERROR('Project Managers'!AC47/'Project Managers'!AA47,0) -> 0.20000015 | AE47: =IFERROR(IF('Project Managers'!Z47<1,1,0),0) -> 0 | AF47: =IFERROR(IF('Project Managers'!AE47=0,0,('Project Managers'!AE47*'Project Managers'!E47)-'Project Managers'!I47-'Project Managers'!AA47),0) -> 0 | AG47: =IFERROR(IF('Project Managers'!AE47='Project Managers'!V47,0,('Project Managers'!AF47-('Project Managers'!AF47*'Project Managers'!L47))),0) -> 0 | AH47: =IFERROR('Project Managers'!AF47-'Project Managers'!AG47,0) -> 0 | AI47: =IFERROR('Project Managers'!AH47/'Project Managers'!AF47,0) -> 0 | AK47: =IFERROR(IF('Project Managers'!AJ47=0,0,('Project Managers'!AJ47*'Project Managers'!E47)-'Project Managers'!I47-'Project Managers'!AA47-'Project Managers'!AF47),0) -> 0 | AL47: =IFERROR(IF('Project Managers'!AJ47='Project Managers'!V47,0,('Project Managers'!AK47-('Project Managers'!AK47*'Project Managers'!L47))),0) -> 0 | AM47: =IFERROR('Project Managers'!AK47-'Project Managers'!AL47,0) -> 0 | AN47: =IFERROR('Project Managers'!AM47/'Project Managers'!AK47,0) -> 0 | AS47: 0.2
B48: T FERGUSON | C48: 722540 | D48: TITOS GOLF CART CHARGERS | E48: 846 | F48: =IFERROR('Project Managers'!E48*(1-'Project Managers'!H48),0) -> 761.4 | G48: =IFERROR('Project Managers'!E48-'Project Managers'!F48,0) -> 84.6 | H48: {=IF(ISBLANK('Project Managers'!AO48),'Project Managers'!R48,'Project Managers'!AO48)} -> 0.1 | K48: =IFERROR('Project Managers'!I48-'Project Managers'!J48,0) -> 0 | L48: =IFERROR('Project Managers'!K48/'Project Managers'!I48,0) -> 0 | M48: 846 | N48: =IFERROR(IF('Project Managers'!M48-'Project Managers'!I48>0,'Project Managers'!M48-'Project Managers'!I48,0),0) -> 846 | O48: =IFERROR(IF('Project Managers'!M48-'Project Managers'!I48<0,'Project Managers'!M48-'Project Managers'!I48,0),0) -> 0 | P48: =IFERROR('Project Managers'!E48-'Project Managers'!I48,0) -> 846 | Q48: =IFERROR(ROUND('Project Managers'!I48/'Project Managers'!E48,4),0) -> 0 | R48: {=IF(ISBLANK('Project Managers'!AP48),IF('Project Managers'!I48<>0,('Project Managers'!I48-'Project Managers'!J48)/'Project Managers'!I48,'Project Managers'!AS48),'Project Managers'!AP48)} -> 0.1 | S48: 0.1 | T48: 0.25 | U48: =IFERROR(-('Project Managers'!I48-('Project Managers'!J48/(1-'Project Managers'!R48))),0) -> 0 | V48: 0 | W48: =IFERROR(-('Project Managers'!I48-('Project Managers'!J48/(1-'Project Managers'!T48))),0) -> 0 | X48: =IFERROR(IF('Project Managers'!AQ48="",1,'Project Managers'!AQ48),0) -> 1 | Y48: 0.15 | Z48: 1 | AA48: =IFERROR(IF('Project Managers'!Z48='Project Managers'!Q48,0,(('Project Managers'!Z48*'Project Managers'!E48)-'Project Managers'!I48)),0) -> 846 | AB48: =IFERROR(IF('Project Managers'!Z48='Project Managers'!Q48,0,('Project Managers'!AA48-('Project Managers'!AA48*'Project Managers'!L48))),0) -> 846 | AC48: =IFERROR('Project Managers'!AA48-'Project Managers'!AB48,0) -> 0 | AD48: =IFERROR('Project Managers'!AC48/'Project Managers'!AA48,0) -> 0 | AE48: =IFERROR(IF('Project Managers'!Z48<1,1,0),0) -> 0 | AF48: =IFERROR(IF('Project Managers'!AE48=0,0,('Project Managers'!AE48*'Project Managers'!E48)-'Project Managers'!I48-'Project Managers'!AA48),0) -> 0 | AG48: =IFERROR(IF('Project Managers'!AE48='Project Managers'!V48,0,('Project Managers'!AF48-('Project Managers'!AF48*'Project Managers'!L48))),0) -> 0 | AH48: =IFERROR('Project Managers'!AF48-'Project Managers'!AG48,0) -> 0 | AI48: =IFERROR('Project Managers'!AH48/'Project Managers'!AF48,0) -> 0 | AK48: =IFERROR(IF('Project Managers'!AJ48=0,0,('Project Managers'!AJ48*'Project Managers'!E48)-'Project Managers'!I48-'Project Managers'!AA48-'Project Managers'!AF48),0) -> 0 | AL48: =IFERROR(IF('Project Managers'!AJ48='Project Managers'!V48,0,('Project Managers'!AK48-('Project Managers'!AK48*'Project Managers'!L48))),0) -> 0 | AM48: =IFERROR('Project Managers'!AK48-'Project Managers'!AL48,0) -> 0 | AN48: =IFERROR('Project Managers'!AM48/'Project Managers'!AK48,0) -> 0 | AS48: 0.1
B49: T FERGUSON | C49: 722550 | D49: W2 MDF ROOM | E49: 2574 | F49: =IFERROR('Project Managers'!E49*(1-'Project Managers'!H49),0) -> 2059.1945 | G49: =IFERROR('Project Managers'!E49-'Project Managers'!F49,0) -> 514.80547 | H49: {=IF(ISBLANK('Project Managers'!AO49),'Project Managers'!R49,'Project Managers'!AO49)} -> 0.20000212 | I49: 1883.73 | J49: 1506.98 | K49: =IFERROR('Project Managers'!I49-'Project Managers'!J49,0) -> 376.75 | L49: =IFERROR('Project Managers'!K49/'Project Managers'!I49,0) -> 0.20000212 | M49: 2574 | N49: =IFERROR(IF('Project Managers'!M49-'Project Managers'!I49>0,'Project Managers'!M49-'Project Managers'!I49,0),0) -> 690.27 | O49: =IFERROR(IF('Project Managers'!M49-'Project Managers'!I49<0,'Project Managers'!M49-'Project Managers'!I49,0),0) -> 0 | P49: =IFERROR('Project Managers'!E49-'Project Managers'!I49,0) -> 690.27 | Q49: =IFERROR(ROUND('Project Managers'!I49/'Project Managers'!E49,4),0) -> 0.7318 | R49: =IF(ISBLANK('Project Managers'!AP49),IF('Project Managers'!I49<>0,('Project Managers'!I49-'Project Managers'!J49)/'Project Managers'!I49,'Project Managers'!AS49),'Project Managers'!AP49) -> 0.20000212 | S49: 0.2 | T49: 0.2 | U49: =IFERROR(-('Project Managers'!I49-('Project Managers'!J49/(1-'Project Managers'!R49))),0) -> 0 | V49: 0 | W49: =IFERROR(-('Project Managers'!I49-('Project Managers'!J49/(1-'Project Managers'!T49))),0) -> -0.005 | X49: =IFERROR(IF('Project Managers'!AQ49="",1,'Project Managers'!AQ49),0) -> 1 | Y49: 0.3548 | Z49: 1 | AA49: =IFERROR(IF('Project Managers'!Z49='Project Managers'!Q49,0,(('Project Managers'!Z49*'Project Managers'!E49)-'Project Managers'!I49)),0) -> 690.27 | AB49: =IFERROR(IF('Project Managers'!Z49='Project Managers'!Q49,0,('Project Managers'!AA49-('Project Managers'!AA49*'Project Managers'!L49))),0) -> 552.21453 | AC49: =IFERROR('Project Managers'!AA49-'Project Managers'!AB49,0) -> 138.05547 | AD49: =IFERROR('Project Managers'!AC49/'Project Managers'!AA49,0) -> 0.20000212 | AE49: =IFERROR(IF('Project Managers'!Z49<1,1,0),0) -> 0 | AF49: =IFERROR(IF('Project Managers'!AE49=0,0,('Project Managers'!AE49*'Project Managers'!E49)-'Project Managers'!I49-'Project Managers'!AA49),0) -> 0 | AG49: =IFERROR(IF('Project Managers'!AE49='Project Managers'!V49,0,('Project Managers'!AF49-('Project Managers'!AF49*'Project Managers'!L49))),0) -> 0 | AH49: =IFERROR('Project Managers'!AF49-'Project Managers'!AG49,0) -> 0 | AI49: =IFERROR('Project Managers'!AH49/'Project Managers'!AF49,0) -> 0 | AK49: =IFERROR(IF('Project Managers'!AJ49=0,0,('Project Managers'!AJ49*'Project Managers'!E49)-'Project Managers'!I49-'Project Managers'!AA49-'Project Managers'!AF49),0) -> 0 | AL49: =IFERROR(IF('Project Managers'!AJ49='Project Managers'!V49,0,('Project Managers'!AK49-('Project Managers'!AK49*'Project Managers'!L49))),0) -> 0 | AM49: =IFERROR('Project Managers'!AK49-'Project Managers'!AL49,0) -> 0 | AN49: =IFERROR('Project Managers'!AM49/'Project Managers'!AK49,0) -> 0 | AS49: 0.2
B50: T FERGUSON | C50: 722560 | D50: PROJECT COSMOS | E50: 1212523 | F50: =IFERROR('Project Managers'!E50*(1-'Project Managers'!H50),0) -> 1212523 | G50: =IFERROR('Project Managers'!E50-'Project Managers'!F50,0) -> 0 | H50: {=IF(ISBLANK('Project Managers'!AO50),'Project Managers'!R50,'Project Managers'!AO50)} -> 0 | K50: =IFERROR('Project Managers'!I50-'Project Managers'!J50,0) -> 0 | L50: =IFERROR('Project Managers'!K50/'Project Managers'!I50,0) -> 0 | N50: =IFERROR(IF('Project Managers'!M50-'Project Managers'!I50>0,'Project Managers'!M50-'Project Managers'!I50,0),0) -> 0 | O50: =IFERROR(IF('Project Managers'!M50-'Project Managers'!I50<0,'Project Managers'!M50-'Project Managers'!I50,0),0) -> 0 | P50: =IFERROR('Project Managers'!E50-'Project Managers'!I50,0) -> 1212523 | Q50: =IFERROR(ROUND('Project Managers'!I50/'Project Managers'!E50,4),0) -> 0 | R50: {=IF(ISBLANK('Project Managers'!AP50),IF('Project Managers'!I50<>0,('Project Managers'!I50-'Project Managers'!J50)/'Project Managers'!I50,'Project Managers'!AS50),'Project Managers'!AP50)} -> 0 | T50: 0.2 | U50: =IFERROR(-('Project Managers'!I50-('Project Managers'!J50/(1-'Project Managers'!R50))),0) -> 0 | W50: =IFERROR(-('Project Managers'!I50-('Project Managers'!J50/(1-'Project Managers'!T50))),0) -> 0 | X50: =IFERROR(IF('Project Managers'!AQ50="",1,'Project Managers'!AQ50),0) -> 1 | Z50: 0.02 | AA50: =IFERROR(IF('Project Managers'!Z50='Project Managers'!Q50,0,(('Project Managers'!Z50*'Project Managers'!E50)-'Project Managers'!I50)),0) -> 24250.46 | AB50: =IFERROR(IF('Project Managers'!Z50='Project Managers'!Q50,0,('Project Managers'!AA50-('Project Managers'!AA50*'Project Managers'!L50))),0) -> 24250.46 | AC50: =IFERROR('Project Managers'!AA50-'Project Managers'!AB50,0) -> 0 | AD50: =IFERROR('Project Managers'!AC50/'Project Managers'!AA50,0) -> 0 | AE50: =IFERROR(IF('Project Managers'!Z50<1,1,0),0) -> 1 | AF50: =IFERROR(IF('Project Managers'!AE50=0,0,('Project Managers'!AE50*'Project Managers'!E50)-'Project Managers'!I50-'Project Managers'!AA50),0) -> 1188272.5 | AG50: =IFERROR(IF('Project Managers'!AE50='Project Managers'!V50,0,('Project Managers'!AF50-('Project Managers'!AF50*'Project Managers'!L50))),0) -> 1188272.5 | AH50: =IFERROR('Project Managers'!AF50-'Project Managers'!AG50,0) -> 0 | AI50: =IFERROR('Project Managers'!AH50/'Project Managers'!AF50,0) -> 0 | AK50: =IFERROR(IF('Project Managers'!AJ50=0,0,('Project Managers'!AJ50*'Project Managers'!E50)-'Project Managers'!I50-'Project Managers'!AA50-'Project Managers'!AF50),0) -> 0 | AL50: =IFERROR(IF('Project Managers'!AJ50='Project Managers'!V50,0,('Project Managers'!AK50-('Project Managers'!AK50*'Project Managers'!L50))),0) -> 0 | AM50: =IFERROR('Project Managers'!AK50-'Project Managers'!AL50,0) -> 0 | AN50: =IFERROR('Project Managers'!AM50/'Project Managers'!AK50,0) -> 0
B51: Subtotal of T FERGUSON | C51: - | D51: - | E51: =SUBTOTAL(9,E31:E50) -> 25013123 | F51: =SUBTOTAL(9,F31:F50) -> 20833989 | G51: =SUBTOTAL(9,G31:G50) -> 4179134.4 | H51: {=IF(ISBLANK('Project Managers'!AO51),'Project Managers'!R51,'Project Managers'!AO51)} -> - | I51: =SUBTOTAL(9,I31:I50) -> 21125529 | J51: =SUBTOTAL(9,J31:J50) -> 15503369 | K51: =SUBTOTAL(9,K31:K50) -> 5622160 | L51: =IFERROR('Project Managers'!K51/'Project Managers'!I51,0) -> 0.26613109 | M51: =SUBTOTAL(9,M31:M50) -> 21988338 | N51: =SUBTOTAL(9,N31:N50) -> 1052466 | O51: =SUBTOTAL(9,O31:O50) -> -189656.7 | P51: =SUBTOTAL(9,P31:P50) -> 3887594 | Q51: =IFERROR(ROUND('Project Managers'!I51/'Project Managers'!E51,4),0) -> 0.8446 | R51: - | S51: - | T51: - | U51: =SUBTOTAL(9,U31:U50) -> 275938.61 | V51: =SUBTOTAL(9,V31:V50) -> 162806.29 | W51: =SUBTOTAL(9,W31:W50) -> 524433.75 | X51: - | Y51: - | Z51: - | AA51: =SUBTOTAL(9,AA31:AA50) -> 1402471.1 | AB51: =SUBTOTAL(9,AB31:AB50) -> 1080545.1 | AC51: =IFERROR('Project Managers'!AA51-'Project Managers'!AB51,0) -> 321926.08 | AD51: =IFERROR('Project Managers'!AC51/'Project Managers'!AA51,0) -> 0.22954203 | AE51: =IFERROR(IF('Project Managers'!Z51<1,1,0),0) -> 0 | AF51: =SUBTOTAL(9,AF31:AF50) -> 2485122.9 | AG51: =SUBTOTAL(9,AG31:AG50) -> 2213439.3 | AH51: =SUBTOTAL(9,AH31:AH50) -> 271683.53 | AI51: =IFERROR('Project Managers'!AH51/'Project Managers'!AF51,0) -> 0.10932398 | AJ51: - | AK51: =SUBTOTAL(9,AK31:AK50) -> 0 | AL51: =SUBTOTAL(9,AL31:AL50) -> 0 | AM51: =SUBTOTAL(9,AM31:AM50) -> 0 | AN51: =IFERROR('Project Managers'!AM51/'Project Managers'!AK51,0) -> 0 | AO51: - | AP51: - | AQ51: - | AR51: - | AS51: -
B52: YE ACCRUAL | C52: 999996 | D52: CTX CONST ACCRUAL JOB | E52: 0 | F52: =IFERROR('Project Managers'!E52*(1-'Project Managers'!H52),0) -> 0 | G52: =IFERROR('Project Managers'!E52-'Project Managers'!F52,0) -> 0 | H52: {=IF(ISBLANK('Project Managers'!AO52),'Project Managers'!R52,'Project Managers'!AO52)} -> 0.2 | I52: 0 | J52: 0 | K52: =IFERROR('Project Managers'!I52-'Project Managers'!J52,0) -> 0 | L52: =IFERROR('Project Managers'!K52/'Project Managers'!I52,0) -> 0 | N52: =IFERROR(IF('Project Managers'!M52-'Project Managers'!I52>0,'Project Managers'!M52-'Project Managers'!I52,0),0) -> 0 | O52: =IFERROR(IF('Project Managers'!M52-'Project Managers'!I52<0,'Project Managers'!M52-'Project Managers'!I52,0),0) -> 0 | P52: =IFERROR('Project Managers'!E52-'Project Managers'!I52,0) -> 0 | Q52: =IFERROR(ROUND('Project Managers'!I52/'Project Managers'!E52,4),0) -> 0 | R52: {=IF(ISBLANK('Project Managers'!AP52),IF('Project Managers'!I52<>0,('Project Managers'!I52-'Project Managers'!J52)/'Project Managers'!I52,'Project Managers'!AS52),'Project Managers'!AP52)} -> 0.2 | S52: 0 | U52: =IFERROR(-('Project Managers'!I52-('Project Managers'!J52/(1-'Project Managers'!R52))),0) -> 0 | V52: 0 | W52: =IFERROR(-('Project Managers'!I52-('Project Managers'!J52/(1-'Project Managers'!T52))),0) -> 0 | X52: =IFERROR(IF('Project Managers'!AQ52="",1,'Project Managers'!AQ52),0) -> 1 | Y52: 0 | AA52: =IFERROR(IF('Project Managers'!Z52='Project Managers'!Q52,0,(('Project Managers'!Z52*'Project Managers'!E52)-'Project Managers'!I52)),0) -> 0 | AB52: =IFERROR(IF('Project Managers'!Z52='Project Managers'!Q52,0,('Project Managers'!AA52-('Project Managers'!AA52*'Project Managers'!L52))),0) -> 0 | AC52: =IFERROR('Project Managers'!AA52-'Project Managers'!AB52,0) -> 0 | AD52: =IFERROR('Project Managers'!AC52/'Project Managers'!AA52,0) -> 0 | AE52: =IFERROR(IF('Project Managers'!Z52<1,1,0),0) -> 1 | AF52: =IFERROR(IF('Project Managers'!AE52=0,0,('Project Managers'!AE52*'Project Managers'!E52)-'Project Managers'!I52-'Project Managers'!AA52),0) -> 0 | AG52: =IFERROR(IF('Project Managers'!AE52='Project Managers'!V52,0,('Project Managers'!AF52-('Project Managers'!AF52*'Project Managers'!L52))),0) -> 0 | AH52: =IFERROR('Project Managers'!AF52-'Project Managers'!AG52,0) -> 0 | AI52: =IFERROR('Project Managers'!AH52/'Project Managers'!AF52,0) -> 0 | AK52: =IFERROR(IF('Project Managers'!AJ52=0,0,('Project Managers'!AJ52*'Project Managers'!E52)-'Project Managers'!I52-'Project Managers'!AA52-'Project Managers'!AF52),0) -> 0 | AL52: =IFERROR(IF('Project Managers'!AJ52='Project Managers'!V52,0,('Project Managers'!AK52-('Project Managers'!AK52*'Project Managers'!L52))),0) -> 0 | AM52: =IFERROR('Project Managers'!AK52-'Project Managers'!AL52,0) -> 0 | AN52: =IFERROR('Project Managers'!AM52/'Project Managers'!AK52,0) -> 0 | AS52: 0.2
B53: Subtotal of YE ACCRUAL | C53: - | D53: - | E53: =SUBTOTAL(9,E52) -> 0 | F53: =SUBTOTAL(9,F52) -> 0 | G53: =SUBTOTAL(9,G52) -> 0 | H53: {=IF(ISBLANK('Project Managers'!AO53),'Project Managers'!R53,'Project Managers'!AO53)} -> - | I53: =SUBTOTAL(9,I52) -> 0 | J53: =SUBTOTAL(9,J52) -> 0 | K53: =SUBTOTAL(9,K52) -> 0 | L53: =IFERROR('Project Managers'!K53/'Project Managers'!I53,0) -> 0 | M53: =SUBTOTAL(9,M52) -> 0 | N53: =SUBTOTAL(9,N52) -> 0 | O53: =SUBTOTAL(9,O52) -> 0 | P53: =SUBTOTAL(9,P52) -> 0 | Q53: =IFERROR(ROUND('Project Managers'!I53/'Project Managers'!E53,4),0) -> 0 | R53: - | S53: - | T53: - | U53: =SUBTOTAL(9,U52) -> 0 | V53: =SUBTOTAL(9,V52) -> 0 | W53: =SUBTOTAL(9,W52) -> 0 | X53: - | Y53: - | Z53: - | AA53: =SUBTOTAL(9,AA52) -> 0 | AB53: =SUBTOTAL(9,AB52) -> 0 | AC53: =IFERROR('Project Managers'!AA53-'Project Managers'!AB53,0) -> 0 | AD53: =IFERROR('Project Managers'!AC53/'Project Managers'!AA53,0) -> 0 | AE53: =IFERROR(IF('Project Managers'!Z53<1,1,0),0) -> 0 | AF53: =SUBTOTAL(9,AF52) -> 0 | AG53: =SUBTOTAL(9,AG52) -> 0 | AH53: =SUBTOTAL(9,AH52) -> 0 | AI53: =IFERROR('Project Managers'!AH53/'Project Managers'!AF53,0) -> 0 | AJ53: - | AK53: =SUBTOTAL(9,AK52) -> 0 | AL53: =SUBTOTAL(9,AL52) -> 0 | AM53: =SUBTOTAL(9,AM52) -> 0 | AN53: =IFERROR('Project Managers'!AM53/'Project Managers'!AK53,0) -> 0 | AO53: - | AP53: - | AQ53: - | AR53: - | AS53: -
B54: Grand Total | C54: - | D54: - | E54: =SUBTOTAL(9,E12:E13,E15:E17,E19:E20,E22:E25,E27:E29,E31:E50,E52) -> 1.1833306e+08 | F54: =SUBTOTAL(9,F12:F13,F15:F17,F19:F20,F22:F25,F27:F29,F31:F50,F52) -> 97702072 | G54: =SUBTOTAL(9,G12:G13,G15:G17,G19:G20,G22:G25,G27:G29,G31:G50,G52) -> 20630991 | H54: {=IF(ISBLANK('Project Managers'!AO54),'Project Managers'!R54,'Project Managers'!AO54)} -> - | I54: =SUBTOTAL(9,I12:I13,I15:I17,I19:I20,I22:I25,I27:I29,I31:I50,I52) -> 83449272 | J54: =SUBTOTAL(9,J12:J13,J15:J17,J19:J20,J22:J25,J27:J29,J31:J50,J52) -> 67341287 | K54: =SUBTOTAL(9,K12:K13,K15:K17,K19:K20,K22:K25,K27:K29,K31:K50,K52) -> 16107985 | L54: =IFERROR('Project Managers'!K54/'Project Managers'!I54,0) -> 0.19302727 | M54: =SUBTOTAL(9,M12:M13,M15:M17,M19:M20,M22:M25,M27:M29,M31:M50,M52) -> 86642983 | N54: =SUBTOTAL(9,N12:N13,N15:N17,N19:N20,N22:N25,N27:N29,N31:N50,N52) -> 3642642.8 | O54: =SUBTOTAL(9,O12:O13,O15:O17,O19:O20,O22:O25,O27:O29,O31:O50,O52) -> -448931.32 | P54: =SUBTOTAL(9,P12:P13,P15:P17,P19:P20,P22:P25,P27:P29,P31:P50,P52) -> 34883791 | Q54: =IFERROR(ROUND('Project Managers'!I54/'Project Managers'!E54,4),0) -> 0.7052 | R54: - | S54: - | T54: - | U54: =SUBTOTAL(9,U12:U13,U15:U17,U19:U20,U22:U25,U27:U29,U31:U50,U52) -> 3922768.3 | V54: =SUBTOTAL(9,V12:V13,V15:V17,V19:V20,V22:V25,V27:V29,V31:V50,V52) -> 367645.67 | W54: =SUBTOTAL(9,W12:W13,W15:W17,W19:W20,W22:W25,W27:W29,W31:W50,W52) -> 509684.14 | X54: - | Y54: - | Z54: - | AA54: =SUBTOTAL(9,AA12:AA13,AA15:AA17,AA19:AA20,AA22:AA25,AA27:AA29,AA31:AA50,AA52) -> 4221053.7 | AB54: =SUBTOTAL(9,AB12:AB13,AB15:AB17,AB19:AB20,AB22:AB25,AB27:AB29,AB31:AB50,AB52) -> 3294176.8 | AC54: =IFERROR('Project Managers'!AA54-'Project Managers'!AB54,0) -> 926876.94 | AD54: =IFERROR('Project Managers'!AC54/'Project Managers'!AA54,0) -> 0.21958426 | AE54: =IFERROR(IF('Project Managers'!Z54<1,1,0),0) -> 0 | AF54: =SUBTOTAL(9,AF12:AF13,AF15:AF17,AF19:AF20,AF22:AF25,AF27:AF29,AF31:AF50,AF52) -> 30662737 | AG54: =SUBTOTAL(9,AG12:AG13,AG15:AG17,AG19:AG20,AG22:AG25,AG27:AG29,AG31:AG50,AG52) -> 25652288 | AH54: =SUBTOTAL(9,AH12:AH13,AH15:AH17,AH19:AH20,AH22:AH25,AH27:AH29,AH31:AH50,AH52) -> 5010449.4 | AI54: =IFERROR('Project Managers'!AH54/'Project Managers'!AF54,0) -> 0.16340516 | AJ54: - | AK54: =SUBTOTAL(9,AK12:AK13,AK15:AK17,AK19:AK20,AK22:AK25,AK27:AK29,AK31:AK50,AK52) -> 0 | AL54: =SUBTOTAL(9,AL12:AL13,AL15:AL17,AL19:AL20,AL22:AL25,AL27:AL29,AL31:AL50,AL52) -> 0 | AM54: =SUBTOTAL(9,AM12:AM13,AM15:AM17,AM19:AM20,AM22:AM25,AM27:AM29,AM31:AM50,AM52) -> 0 | AN54: =IFERROR('Project Managers'!AM54/'Project Managers'!AK54,0) -> 0 | AO54: - | AP54: - | AQ54: - | AR54: - | AS54: -

Sheet Divisions
H3: Over and Under Billings
H4: {=EOperiodDate!B4} -> 2025-11-30
E6: Estimated | X6: =YEAR(H4) -> 2025 | AB6: =X6+1 -> 2026 | AG6: =X6+2 -> 2027
B7: {=B15} -> Division | C7: {=C15} -> Job Number | D7: {=D15} -> Description | E7: {=E15} -> Current Contract Amount | F7: {=F15} -> Estimated Cost | G7: {=G15} -> Gross Margin | H7: {=H15} -> GM% | I7: {=I15} -> JTD Earned Revenue | ... W7: {=W15} -> Revised % Complete @ YE | X7: Contract Amount | Y7: Estimated Cost | Z7: Gross Margin | AA7: GM % | AB7: Revised % Complete @ YE | AC7: Contract Amount | AD7: Estimated Cost | AE7: Gross Margin | AF7: GM % | AG7: Revised % Complete @ YE | AH7: Contract Amount | AI7: Estimated Cost | AJ7: Gross Margin | AK7: GM % | AL7: GM % | AM7: {=AM15} -> pmestimatedgmpercentage__custom | AN7: {=AN15} -> percentagecompleteatye__custom | AO7: {=AO15} -> Comments
B15: Division | C15: Job Number | D15: Description | E15: Current Contract Amount | F15: Estimated Cost | G15: Gross Margin | H15: GM% | I15: JTD Earned Revenue | J15: Cost to Date | K15: Gross Margin to Date | L15: GM % | M15: Billed Amount | N15: Over Billing | O15: (Under) Billing | P15: Backlog | Q15: % Complete | R15: PM Estimated GM % | S15: Revised PM Estimated GM % | T15: Potential Profit | U15: Revised Potential Profit | V15: % Complete @ YE | W15: Revised % Complete @ YE | X15: CY Contract Amount | Y15: CY Estimated Cost | Z15: CY Gross Margin | AA15: CY GM % | AB15: CY Revised % Complete | AC15: CY1 Contract Amount | AD15: CY1 Estimated Cost | AE15: CY1 Gross Margin | AF15: CY1GM% | AG15: CY2 Revised % Complete @ YE | AH15: CY2 Contract Amount | AI15: CY2 Estimated Cost | AJ15: CY2 Gross Margin | AK15: CY2 GM % | AL15: estimatedgmpercentage__custom | AM15: pmestimatedgmpercentage__custom | AN15: percentagecompleteatye__custom | AO15: Comments
B16: Central Texas Electrical Construction | C16: 710045 | D16: ZILKER BARTON SPRINGS BAT | E16: 1484896.8 | F16: =IFERROR(Divisions!E16*(1-Divisions!H16),0) -> 1158219.5 | G16: =IFERROR(Divisions!E16-Divisions!F16,0) -> 326677.3 | H16: {=IF(ISBLANK(Divisions!AL16),Divisions!R16,Divisions!AL16)} -> 0.22 | I16: 1484896.8 | J16: 1465800.4 | K16: =IFERROR(Divisions!I16-Divisions!J16,0) -> 19096.46 | L16: =IFERROR(Divisions!K16/Divisions!I16,0) -> 0.012860463 | M16: 1484896.8 | N16: =IFERROR(IF(Divisions!M16-Divisions!I16>0,Divisions!M16-Divisions!I16,0),0) -> 0 | O16: =IFERROR(IF(Divisions!M16-Divisions!I16<0,Divisions!M16-Divisions!I16,0),0) -> 0 | P16: =IFERROR(Divisions!E16-Divisions!I16,0) -> 0 | Q16: =IFERROR(Divisions!I16/Divisions!E16,0) -> 1 | R16: =IFERROR(_xlfn.XLOOKUP(Divisions!C16,'Project Managers'!C:C,'Project Managers'!R:R),0) -> 0.05 | S16: =IFERROR(_xlfn.XLOOKUP(Divisions!C16,'Project Managers'!C:C,'Project Managers'!T:T),0) -> 0.01 | T16: =IFERROR(_xlfn.XLOOKUP(Divisions!C16,'Project Managers'!C:C,'Project Managers'!U:U),0) -> 58050.927 | U16: =IFERROR(_xlfn.XLOOKUP(Divisions!C16,'Project Managers'!C:C,'Project Managers'!W:W),0) -> -4290.3959 | V16: =IFERROR(_xlfn.XLOOKUP(Divisions!C16,'Project Managers'!C:C,'Project Managers'!X:X),0) -> 1 | W16: =IFERROR(_xlfn.XLOOKUP(Divisions!C16,'Project Managers'!C:C,'Project Managers'!Z:Z),0) -> 1 | X16: =IFERROR(_xlfn.XLOOKUP(Divisions!C16,'Project Managers'!C:C,'Project Managers'!AA:AA),0) -> 0 | Y16: =IFERROR(_xlfn.XLOOKUP(Divisions!C16,'Project Managers'!C:C,'Project Managers'!AB:AB),0) -> 0 | Z16: =IFERROR(_xlfn.XLOOKUP(Divisions!C16,'Project Managers'!C:C,'Project Managers'!AC:AC),0) -> 0 | AA16: =IFERROR(_xlfn.XLOOKUP(Divisions!C16,'Project Managers'!C:C,'Project Managers'!AD:AD),0) -> 0 | AB16: =IFERROR(_xlfn.XLOOKUP(Divisions!C16,'Project Managers'!C:C,'Project Managers'!AE:AE),0) -> 0 | AC16: =IFERROR(_xlfn.XLOOKUP(Divisions!C16,'Project Managers'!C:C,'Project Managers'!AF:AF),0) -> 0 | AD16: =IFERROR(_xlfn.XLOOKUP(Divisions!C16,'Project Managers'!C:C,'Project Managers'!AG:AG),0) -> 0 | AE16: =IFERROR(_xlfn.XLOOKUP(Divisions!C16,'Project Managers'!C:C,'Project Managers'!AH:AH),0) -> 0 | AF16: =IFERROR(_xlfn.XLOOKUP(Divisions!C16,'Project Managers'!C:C,'Project Managers'!AI:AI),0) -> 0 | AG16: =IFERROR(_xlfn.XLOOKUP(Divisions!C16,'Project Managers'!C:C,'Project Managers'!AJ:AJ),0) -> 0 | AH16: =IFERROR(_xlfn.XLOOKUP(Divisions!C16,'Project Managers'!C:C,'Project Managers'!AK:AK),0) -> 0 | AI16: =IFERROR(_xlfn.XLOOKUP(Divisions!C16,'Project Managers'!C:C,'Project Managers'!AL:AL),0) -> 0 | AJ16: =IFERROR(_xlfn.XLOOKUP(Divisions!C16,'Project Managers'!C:C,'Project Managers'!AM:AM),0) -> 0 | AK16: =IFERROR(_xlfn.XLOOKUP(Divisions!C16,'Project Managers'!C:C,'Project Managers'!AN:AN),0) -> 0 | AL16: 0.22 | AM16: 0.05 | AO16: =IFERROR(_xlfn.XLOOKUP(Divisions!C16,'Project Managers'!C:C,'Project Managers'!AR:AR),0) -> 0
B17: Central Texas Electrical Construction | C17: 718000 | D17: TFC PARK 35 | E17: 4093979.3 | F17: =IFERROR(Divisions!E17*(1-Divisions!H17),0) -> 3398002.8 | G17: =IFERROR(Divisions!E17-Divisions!F17,0) -> 695976.48 | H17: {=IF(ISBLANK(Divisions!AL17),Divisions!R17,Divisions!AL17)} -> 0.17 | I17: 4093633.3 | J17: 3313579.7 | K17: =IFERROR(Divisions!I17-Divisions!J17,0) -> 780053.59 | L17: =IFERROR(Divisions!K17/Divisions!I17,0) -> 0.19055287 | M17: 4093633.3 | N17: =IFERROR(IF(Divisions!M17-Divisions!I17>0,Divisions!M17-Divisions!I17,0),0) -> 0 | O17: =IFERROR(IF(Divisions!M17-Divisions!I17<0,Divisions!M17-Divisions!I17,0),0) -> 0 | P17: =IFERROR(Divisions!E17-Divisions!I17,0) -> 346 | Q17: =IFERROR(Divisions!I17/Divisions!E17,0) -> 0.99991549 | R17: =IFERROR(_xlfn.XLOOKUP(Divisions!C17,'Project Managers'!C:C,'Project Managers'!R:R),0) -> 0.19 | S17: =IFERROR(_xlfn.XLOOKUP(Divisions!C17,'Project Managers'!C:C,'Project Managers'!T:T),0) -> 0.19 | T17: =IFERROR(_xlfn.XLOOKUP(Divisions!C17,'Project Managers'!C:C,'Project Managers'!U:U),0) -> -2794.1472 | U17: =IFERROR(_xlfn.XLOOKUP(Divisions!C17,'Project Managers'!C:C,'Project Managers'!W:W),0) -> -2794.1472 | V17: =IFERROR(_xlfn.XLOOKUP(Divisions!C17,'Project Managers'!C:C,'Project Managers'!X:X),0) -> 1 | W17: =IFERROR(_xlfn.XLOOKUP(Divisions!C17,'Project Managers'!C:C,'Project Managers'!Z:Z),0) -> 1 | X17: =IFERROR(_xlfn.XLOOKUP(Divisions!C17,'Project Managers'!C:C,'Project Managers'!AA:AA),0) -> 346 | Y17: =IFERROR(_xlfn.XLOOKUP(Divisions!C17,'Project Managers'!C:C,'Project Managers'!AB:AB),0) -> 280.06871 | Z17: =IFERROR(_xlfn.XLOOKUP(Divisions!C17,'Project Managers'!C:C,'Project Managers'!AC:AC),0) -> 65.931294 | AA17: =IFERROR(_xlfn.XLOOKUP(Divisions!C17,'Project Managers'!C:C,'Project Managers'!AD:AD),0) -> 0.19055287 | AB17: =IFERROR(_xlfn.XLOOKUP(Divisions!C17,'Project Managers'!C:C,'Project Managers'!AE:AE),0) -> 0 | AC17: =IFERROR(_xlfn.XLOOKUP(Divisions!C17,'Project Managers'!C:C,'Project Managers'!AF:AF),0) -> 0 | AD17: =IFERROR(_xlfn.XLOOKUP(Divisions!C17,'Project Managers'!C:C,'Project Managers'!AG:AG),0) -> 0 | AE17: =IFERROR(_xlfn.XLOOKUP(Divisions!C17,'Project Managers'!C:C,'Project Managers'!AH:AH),0) -> 0 | AF17: =IFERROR(_xlfn.XLOOKUP(Divisions!C17,'Project Managers'!C:C,'Project Managers'!AI:AI),0) -> 0 | AG17: =IFERROR(_xlfn.XLOOKUP(Divisions!C17,'Project Managers'!C:C,'Project Managers'!AJ:AJ),0) -> 0 | AH17: =IFERROR(_xlfn.XLOOKUP(Divisions!C17,'Project Managers'!C:C,'Project Managers'!AK:AK),0) -> 0 | AI17: =IFERROR(_xlfn.XLOOKUP(Divisions!C17,'Project Managers'!C:C,'Project Managers'!AL:AL),0) -> 0 | AJ17: =IFERROR(_xlfn.XLOOKUP(Divisions!C17,'Project Managers'!C:C,'Project Managers'!AM:AM),0) -> 0 | AK17: =IFERROR(_xlfn.XLOOKUP(Divisions!C17,'Project Managers'!C:C,'Project Managers'!AN:AN),0) -> 0 | AL17: 0.17 | AM17: 0.19 | AO17: =IFERROR(_xlfn.XLOOKUP(Divisions!C17,'Project Managers'!C:C,'Project Managers'!AR:AR),0) -> 0
B18: Central Texas Electrical Construction | C18: 718100 | D18: TESLA 2022 PLASTIC FEEDER | E18: 898831.39 | F18: =IFERROR(Divisions!E18*(1-Divisions!H18),0) -> 728053.43 | G18: =IFERROR(Divisions!E18-Divisions!F18,0) -> 170777.96 | H18: {=IF(ISBLANK(Divisions!AL18),Divisions!R18,Divisions!AL18)} -> 0.19 | I18: 898831.39 | J18: 744578.07 | K18: =IFERROR(Divisions!I18-Divisions!J18,0) -> 154253.32 | L18: =IFERROR(Divisions!K18/Divisions!I18,0) -> 0.17161541 | M18: 898831.39 | N18: =IFERROR(IF(Divisions!M18-Divisions!I18>0,Divisions!M18-Divisions!I18,0),0) -> 0 | O18: =IFERROR(IF(Divisions!M18-Divisions!I18<0,Divisions!M18-Divisions!I18,0),0) -> 0 | P18: =IFERROR(Divisions!E18-Divisions!I18,0) -> 0 | Q18: =IFERROR(Divisions!I18/Divisions!E18,0) -> 1 | R18: =IFERROR(_xlfn.XLOOKUP(Divisions!C18,'Project Managers'!C:C,'Project Managers'!R:R),0) -> 0.17 | S18: =IFERROR(_xlfn.XLOOKUP(Divisions!C18,'Project Managers'!C:C,'Project Managers'!T:T),0) -> 0.07 | T18: =IFERROR(_xlfn.XLOOKUP(Divisions!C18,'Project Managers'!C:C,'Project Managers'!U:U),0) -> -1749.378 | U18: =IFERROR(_xlfn.XLOOKUP(Divisions!C18,'Project Managers'!C:C,'Project Managers'!W:W),0) -> -98209.809 | V18: =IFERROR(_xlfn.XLOOKUP(Divisions!C18,'Project Managers'!C:C,'Project Managers'!X:X),0) -> 1 | W18: =IFERROR(_xlfn.XLOOKUP(Divisions!C18,'Project Managers'!C:C,'Project Managers'!Z:Z),0) -> 1 | X18: =IFERROR(_xlfn.XLOOKUP(Divisions!C18,'Project Managers'!C:C,'Project Managers'!AA:AA),0) -> 0 | Y18: =IFERROR(_xlfn.XLOOKUP(Divisions!C18,'Project Managers'!C:C,'Project Managers'!AB:AB),0) -> 0 | Z18: =IFERROR(_xlfn.XLOOKUP(Divisions!C18,'Project Managers'!C:C,'Project Managers'!AC:AC),0) -> 0 | AA18: =IFERROR(_xlfn.XLOOKUP(Divisions!C18,'Project Managers'!C:C,'Project Managers'!AD:AD),0) -> 0 | AB18: =IFERROR(_xlfn.XLOOKUP(Divisions!C18,'Project Managers'!C:C,'Project Managers'!AE:AE),0) -> 0 | AC18: =IFERROR(_xlfn.XLOOKUP(Divisions!C18,'Project Managers'!C:C,'Project Managers'!AF:AF),0) -> 0 | AD18: =IFERROR(_xlfn.XLOOKUP(Divisions!C18,'Project Managers'!C:C,'Project Managers'!AG:AG),0) -> 0 | AE18: =IFERROR(_xlfn.XLOOKUP(Divisions!C18,'Project Managers'!C:C,'Project Managers'!AH:AH),0) -> 0 | AF18: =IFERROR(_xlfn.XLOOKUP(Divisions!C18,'Project Managers'!C:C,'Project Managers'!AI:AI),0) -> 0 | AG18: =IFERROR(_xlfn.XLOOKUP(Divisions!C18,'Project Managers'!C:C,'Project Managers'!AJ:AJ),0) -> 0 | AH18: =IFERROR(_xlfn.XLOOKUP(Divisions!C18,'Project Managers'!C:C,'Project Managers'!AK:AK),0) -> 0 | AI18: =IFERROR(_xlfn.XLOOKUP(Divisions!C18,'Project Managers'!C:C,'Project Managers'!AL:AL),0) -> 0 | AJ18: =IFERROR(_xlfn.XLOOKUP(Divisions!C18,'Project Managers'!C:C,'Project Managers'!AM:AM),0) -> 0 | AK18: =IFERROR(_xlfn.XLOOKUP(Divisions!C18,'Project Managers'!C:C,'Project Managers'!AN:AN),0) -> 0 | AL18: 0.19 | AM18: 0.17 | AO18: =IFERROR(_xlfn.XLOOKUP(Divisions!C18,'Project Managers'!C:C,'Project Managers'!AR:AR),0) -> 0
B19: Central Texas Electrical Construction | C19: 719500 | D19: SWITCH RR NAP 4 | E19: 20845819 | F19: =IFERROR(Divisions!E19*(1-Divisions!H19),0) -> 16885113 | G19: =IFERROR(Divisions!E19-Divisions!F19,0) -> 3960705.6 | H19: {=IF(ISBLANK(Divisions!AL19),Divisions!R19,Divisions!AL19)} -> 0.19 | I19: 20845819 | J19: 16381247 | K19: =IFERROR(Divisions!I19-Divisions!J19,0) -> 4464572.5 | L19: =IFERROR(Divisions!K19/Divisions!I19,0) -> 0.21417112 | M19: 20845819 | N19: =IFERROR(IF(Divisions!M19-Divisions!I19>0,Divisions!M19-Divisions!I19,0),0) -> 0 | O19: =IFERROR(IF(Divisions!M19-Divisions!I19<0,Divisions!M19-Divisions!I19,0),0) -> 0 | P19: =IFERROR(Divisions!E19-Divisions!I19,0) -> 0 | Q19: =IFERROR(Divisions!I19/Divisions!E19,0) -> 1 | R19: =IFERROR(_xlfn.XLOOKUP(Divisions!C19,'Project Managers'!C:C,'Project Managers'!R:R),0) -> 0.21 | S19: =IFERROR(_xlfn.XLOOKUP(Divisions!C19,'Project Managers'!C:C,'Project Managers'!T:T),0) -> 0.2142 | T19: =IFERROR(_xlfn.XLOOKUP(Divisions!C19,'Project Managers'!C:C,'Project Managers'!U:U),0) -> -110063.92 | U19: =IFERROR(_xlfn.XLOOKUP(Divisions!C19,'Project Managers'!C:C,'Project Managers'!W:W),0) -> 766.02709 | V19: =IFERROR(_xlfn.XLOOKUP(Divisions!C19,'Project Managers'!C:C,'Project Managers'!X:X),0) -> 1 | W19: =IFERROR(_xlfn.XLOOKUP(Divisions!C19,'Project Managers'!C:C,'Project Managers'!Z:Z),0) -> 1 | X19: =IFERROR(_xlfn.XLOOKUP(Divisions!C19,'Project Managers'!C:C,'Project Managers'!AA:AA),0) -> 0 | Y19: =IFERROR(_xlfn.XLOOKUP(Divisions!C19,'Project Managers'!C:C,'Project Managers'!AB:AB),0) -> 0 | Z19: =IFERROR(_xlfn.XLOOKUP(Divisions!C19,'Project Managers'!C:C,'Project Managers'!AC:AC),0) -> 0 | AA19: =IFERROR(_xlfn.XLOOKUP(Divisions!C19,'Project Managers'!C:C,'Project Managers'!AD:AD),0) -> 0 | AB19: =IFERROR(_xlfn.XLOOKUP(Divisions!C19,'Project Managers'!C:C,'Project Managers'!AE:AE),0) -> 0 | AC19: =IFERROR(_xlfn.XLOOKUP(Divisions!C19,'Project Managers'!C:C,'Project Managers'!AF:AF),0) -> 0 | AD19: =IFERROR(_xlfn.XLOOKUP(Divisions!C19,'Project Managers'!C:C,'Project Managers'!AG:AG),0) -> 0 | AE19: =IFERROR(_xlfn.XLOOKUP(Divisions!C19,'Project Managers'!C:C,'Project Managers'!AH:AH),0) -> 0 | AF19: =IFERROR(_xlfn.XLOOKUP(Divisions!C19,'Project Managers'!C:C,'Project Managers'!AI:AI),0) -> 0 | AG19: =IFERROR(_xlfn.XLOOKUP(Divisions!C19,'Project Managers'!C:C,'Project Managers'!AJ:AJ),0) -> 0 | AH19: =IFERROR(_xlfn.XLOOKUP(Divisions!C19,'Project Managers'!C:C,'Project Managers'!AK:AK),0) -> 0 | AI19: =IFERROR(_xlfn.XLOOKUP(Divisions!C19,'Project Managers'!C:C,'Project Managers'!AL:AL),0) -> 0 | AJ19: =IFERROR(_xlfn.XLOOKUP(Divisions!C19,'Project Managers'!C:C,'Project Managers'!AM:AM),0) -> 0 | AK19: =IFERROR(_xlfn.XLOOKUP(Divisions!C19,'Project Managers'!C:C,'Project Managers'!AN:AN),0) -> 0 | AL19: 0.19 | AM19: 0.21 | AO19: =IFERROR(_xlfn.XLOOKUP(Divisions!C19,'Project Managers'!C:C,'Project Managers'!AR:AR),0) -> 0
B20: Central Texas Electrical Construction | C20: 719900 | D20: BLOCKER LANE D14 | E20: 10000 | F20: =IFERROR(Divisions!E20*(1-Divisions!H20),0) -> 10000 | G20: =IFERROR(Divisions!E20-Divisions!F20,0) -> 0 | H20: {=IF(ISBLANK(Divisions!AL20),Divisions!R20,Divisions!AL20)} -> 0 | I20: 6910.28 | J20: 6910.28 | K20: =IFERROR(Divisions!I20-Divisions!J20,0) -> 0 | L20: =IFERROR(Divisions!K20/Divisions!I20,0) -> 0 | N20: =IFERROR(IF(Divisions!M20-Divisions!I20>0,Divisions!M20-Divisions!I20,0),0) -> 0 | O20: =IFERROR(IF(Divisions!M20-Divisions!I20<0,Divisions!M20-Divisions!I20,0),0) -> -6910.28 | P20: =IFERROR(Divisions!E20-Divisions!I20,0) -> 3089.72 | Q20: =IFERROR(Divisions!I20/Divisions!E20,0) -> 0.691028 | R20: =IFERROR(_xlfn.XLOOKUP(Divisions!C20,'Project Managers'!C:C,'Project Managers'!R:R),0) -> 0 | S20: =IFERROR(_xlfn.XLOOKUP(Divisions!C20,'Project Managers'!C:C,'Project Managers'!T:T),0) -> 0.17 | T20: =IFERROR(_xlfn.XLOOKUP(Divisions!C20,'Project Managers'!C:C,'Project Managers'!U:U),0) -> 0 | U20: =IFERROR(_xlfn.XLOOKUP(Divisions!C20,'Project Managers'!C:C,'Project Managers'!W:W),0) -> 1415.3586 | V20: =IFERROR(_xlfn.XLOOKUP(Divisions!C20,'Project Managers'!C:C,'Project Managers'!X:X),0) -> 1 | W20: =IFERROR(_xlfn.XLOOKUP(Divisions!C20,'Project Managers'!C:C,'Project Managers'!Z:Z),0) -> 1 | X20: =IFERROR(_xlfn.XLOOKUP(Divisions!C20,'Project Managers'!C:C,'Project Managers'!AA:AA),0) -> 3089.72 | Y20: =IFERROR(_xlfn.XLOOKUP(Divisions!C20,'Project Managers'!C:C,'Project Managers'!AB:AB),0) -> 3089.72 | Z20: =IFERROR(_xlfn.XLOOKUP(Divisions!C20,'Project Managers'!C:C,'Project Managers'!AC:AC),0) -> 0 | AA20: =IFERROR(_xlfn.XLOOKUP(Divisions!C20,'Project Managers'!C:C,'Project Managers'!AD:AD),0) -> 0 | AB20: =IFERROR(_xlfn.XLOOKUP(Divisions!C20,'Project Managers'!C:C,'Project Managers'!AE:AE),0) -> 0 | AC20: =IFERROR(_xlfn.XLOOKUP(Divisions!C20,'Project Managers'!C:C,'Project Managers'!AF:AF),0) -> 0 | AD20: =IFERROR(_xlfn.XLOOKUP(Divisions!C20,'Project Managers'!C:C,'Project Managers'!AG:AG),0) -> 0 | AE20: =IFERROR(_xlfn.XLOOKUP(Divisions!C20,'Project Managers'!C:C,'Project Managers'!AH:AH),0) -> 0 | AF20: =IFERROR(_xlfn.XLOOKUP(Divisions!C20,'Project Managers'!C:C,'Project Managers'!AI:AI),0) -> 0 | AG20: =IFERROR(_xlfn.XLOOKUP(Divisions!C20,'Project Managers'!C:C,'Project Managers'!AJ:AJ),0) -> 0 | AH20: =IFERROR(_xlfn.XLOOKUP(Divisions!C20,'Project Managers'!C:C,'Project Managers'!AK:AK),0) -> 0 | AI20: =IFERROR(_xlfn.XLOOKUP(Divisions!C20,'Project Managers'!C:C,'Project Managers'!AL:AL),0) -> 0 | AJ20: =IFERROR(_xlfn.XLOOKUP(Divisions!C20,'Project Managers'!C:C,'Project Managers'!AM:AM),0) -> 0 | AK20: =IFERROR(_xlfn.XLOOKUP(Divisions!C20,'Project Managers'!C:C,'Project Managers'!AN:AN),0) -> 0 | AL20: 0 | AM20: 0 | AO20: =IFERROR(_xlfn.XLOOKUP(Divisions!C20,'Project Managers'!C:C,'Project Managers'!AR:AR),0) -> 0
B21: Central Texas Electrical Construction | C21: 720500 | D21: UTFC4 | E21: 972890 | F21: =IFERROR(Divisions!E21*(1-Divisions!H21),0) -> 865872.1 | G21: =IFERROR(Divisions!E21-Divisions!F21,0) -> 107017.9 | H21: {=IF(ISBLANK(Divisions!AL21),Divisions!R21,Divisions!AL21)} -> 0.11 | I21: 972890 | J21: 847449.19 | K21: =IFERROR(Divisions!I21-Divisions!J21,0) -> 125440.81 | L21: =IFERROR(Divisions!K21/Divisions!I21,0) -> 0.12893627 | M21: 972890 | N21: =IFERROR(IF(Divisions!M21-Divisions!I21>0,Divisions!M21-Divisions!I21,0),0) -> 0 | O21: =IFERROR(IF(Divisions!M21-Divisions!I21<0,Divisions!M21-Divisions!I21,0),0) -> 0 | P21: =IFERROR(Divisions!E21-Divisions!I21,0) -> 0 | Q21: =IFERROR(Divisions!I21/Divisions!E21,0) -> 1 | R21: =IFERROR(_xlfn.XLOOKUP(Divisions!C21,'Project Managers'!C:C,'Project Managers'!R:R),0) -> 0.12 | S21: =IFERROR(_xlfn.XLOOKUP(Divisions!C21,'Project Managers'!C:C,'Project Managers'!T:T),0) -> 0.13 | T21: =IFERROR(_xlfn.XLOOKUP(Divisions!C21,'Project Managers'!C:C,'Project Managers'!U:U),0) -> -9879.5568 | U21: =IFERROR(_xlfn.XLOOKUP(Divisions!C21,'Project Managers'!C:C,'Project Managers'!W:W),0) -> 1189.5287 | V21: =IFERROR(_xlfn.XLOOKUP(Divisions!C21,'Project Managers'!C:C,'Project Managers'!X:X),0) -> 1 | W21: =IFERROR(_xlfn.XLOOKUP(Divisions!C21,'Project Managers'!C:C,'Project Managers'!Z:Z),0) -> 1 | X21: =IFERROR(_xlfn.XLOOKUP(Divisions!C21,'Project Managers'!C:C,'Project Managers'!AA:AA),0) -> 0 | Y21: =IFERROR(_xlfn.XLOOKUP(Divisions!C21,'Project Managers'!C:C,'Project Managers'!AB:AB),0) -> 0 | Z21: =IFERROR(_xlfn.XLOOKUP(Divisions!C21,'Project Managers'!C:C,'Project Managers'!AC:AC),0) -> 0 | AA21: =IFERROR(_xlfn.XLOOKUP(Divisions!C21,'Project Managers'!C:C,'Project Managers'!AD:AD),0) -> 0 | AB21: =IFERROR(_xlfn.XLOOKUP(Divisions!C21,'Project Managers'!C:C,'Project Managers'!AE:AE),0) -> 0 | AC21: =IFERROR(_xlfn.XLOOKUP(Divisions!C21,'Project Managers'!C:C,'Project Managers'!AF:AF),0) -> 0 | AD21: =IFERROR(_xlfn.XLOOKUP(Divisions!C21,'Project Managers'!C:C,'Project Managers'!AG:AG),0) -> 0 | AE21: =IFERROR(_xlfn.XLOOKUP(Divisions!C21,'Project Managers'!C:C,'Project Managers'!AH:AH),0) -> 0 | AF21: =IFERROR(_xlfn.XLOOKUP(Divisions!C21,'Project Managers'!C:C,'Project Managers'!AI:AI),0) -> 0 | AG21: =IFERROR(_xlfn.XLOOKUP(Divisions!C21,'Project Managers'!C:C,'Project Managers'!AJ:AJ),0) -> 0 | AH21: =IFERROR(_xlfn.XLOOKUP(Divisions!C21,'Project Managers'!C:C,'Project Managers'!AK:AK),0) -> 0 | AI21: =IFERROR(_xlfn.XLOOKUP(Divisions!C21,'Project Managers'!C:C,'Project Managers'!AL:AL),0) -> 0 | AJ21: =IFERROR(_xlfn.XLOOKUP(Divisions!C21,'Project Managers'!C:C,'Project Managers'!AM:AM),0) -> 0 | AK21: =IFERROR(_xlfn.XLOOKUP(Divisions!C21,'Project Managers'!C:C,'Project Managers'!AN:AN),0) -> 0 | AL21: 0.11 | AM21: 0.12 | AO21: =IFERROR(_xlfn.XLOOKUP(Divisions!C21,'Project Managers'!C:C,'Project Managers'!AR:AR),0) -> 0
B22: Central Texas Electrical Construction | C22: 720900 | D22: TFC GMP4 - BP4- DHNP RENO | E22: 7230488.5 | F22: =IFERROR(Divisions!E22*(1-Divisions!H22),0) -> 6001305.5 | G22: =IFERROR(Divisions!E22-Divisions!F22,0) -> 1229183.1 | H22: {=IF(ISBLANK(Divisions!AL22),Divisions!R22,Divisions!AL22)} -> 0.17 | I22: 5396691.7 | J22: 4063773.8 | K22: =IFERROR(Divisions!I22-Divisions!J22,0) -> 1332917.9 | L22: =IFERROR(Divisions!K22/Divisions!I22,0) -> 0.24698797 | M22: 6079333.9 | N22: =IFERROR(IF(Divisions!M22-Divisions!I22>0,Divisions!M22-Divisions!I22,0),0) -> 682642.21 | O22: =IFERROR(IF(Divisions!M22-Divisions!I22<0,Divisions!M22-Divisions!I22,0),0) -> 0 | P22: =IFERROR(Divisions!E22-Divisions!I22,0) -> 1833796.8 | Q22: =IFERROR(Divisions!I22/Divisions!E22,0) -> 0.74637995 | R22: =IFERROR(_xlfn.XLOOKUP(Divisions!C22,'Project Managers'!C:C,'Project Managers'!R:R),0) -> 0.33 | S22: =IFERROR(_xlfn.XLOOKUP(Divisions!C22,'Project Managers'!C:C,'Project Managers'!T:T),0) -> 0.25 | T22: =IFERROR(_xlfn.XLOOKUP(Divisions!C22,'Project Managers'!C:C,'Project Managers'!U:U),0) -> 668642.31 | U22: =IFERROR(_xlfn.XLOOKUP(Divisions!C22,'Project Managers'!C:C,'Project Managers'!W:W),0) -> 21673.353 | V22: =IFERROR(_xlfn.XLOOKUP(Divisions!C22,'Project Managers'!C:C,'Project Managers'!X:X),0) -> 1 | W22: =IFERROR(_xlfn.XLOOKUP(Divisions!C22,'Project Managers'!C:C,'Project Managers'!Z:Z),0) -> 0.95 | X22: =IFERROR(_xlfn.XLOOKUP(Divisions!C22,'Project Managers'!C:C,'Project Managers'!AA:AA),0) -> 1472272.4 | Y22: =IFERROR(_xlfn.XLOOKUP(Divisions!C22,'Project Managers'!C:C,'Project Managers'!AB:AB),0) -> 1108638.8 | Z22: =IFERROR(_xlfn.XLOOKUP(Divisions!C22,'Project Managers'!C:C,'Project Managers'!AC:AC),0) -> 363633.57 | AA22: =IFERROR(_xlfn.XLOOKUP(Divisions!C22,'Project Managers'!C:C,'Project Managers'!AD:AD),0) -> 0.24698797 | AB22: =IFERROR(_xlfn.XLOOKUP(Divisions!C22,'Project Managers'!C:C,'Project Managers'!AE:AE),0) -> 1 | AC22: =IFERROR(_xlfn.XLOOKUP(Divisions!C22,'Project Managers'!C:C,'Project Managers'!AF:AF),0) -> 361524.43 | AD22: =IFERROR(_xlfn.XLOOKUP(Divisions!C22,'Project Managers'!C:C,'Project Managers'!AG:AG),0) -> 272232.24 | AE22: =IFERROR(_xlfn.XLOOKUP(Divisions!C22,'Project Managers'!C:C,'Project Managers'!AH:AH),0) -> 89292.183 | AF22: =IFERROR(_xlfn.XLOOKUP(Divisions!C22,'Project Managers'!C:C,'Project Managers'!AI:AI),0) -> 0.24698797 | AG22: =IFERROR(_xlfn.XLOOKUP(Divisions!C22,'Project Managers'!C:C,'Project Managers'!AJ:AJ),0) -> 0 | AH22: =IFERROR(_xlfn.XLOOKUP(Divisions!C22,'Project Managers'!C:C,'Project Managers'!AK:AK),0) -> 0 | AI22: =IFERROR(_xlfn.XLOOKUP(Divisions!C22,'Project Managers'!C:C,'Project Managers'!AL:AL),0) -> 0 | AJ22: =IFERROR(_xlfn.XLOOKUP(Divisions!C22,'Project Managers'!C:C,'Project Managers'!AM:AM),0) -> 0 | AK22: =IFERROR(_xlfn.XLOOKUP(Divisions!C22,'Project Managers'!C:C,'Project Managers'!AN:AN),0) -> 0 | AL22: 0.17 | AM22: 0.33 | AO22: =IFERROR(_xlfn.XLOOKUP(Divisions!C22,'Project Managers'!C:C,'Project Managers'!AR:AR),0) -> 0
B23: Central Texas Electrical Construction | C23: 722200 | D23: TITO'S BLOCKER LN W7 | E23: 10801639 | F23: =IFERROR(Divisions!E23*(1-Divisions!H23),0) -> 8857344 | G23: =IFERROR(Divisions!E23-Divisions!F23,0) -> 1944295 | H23: {=IF(ISBLANK(Divisions!AL23),Divisions!R23,Divisions!AL23)} -> 0.18 | I23: 10200547 | J23: 6443807.6 | K23: =IFERROR(Divisions!I23-Divisions!J23,0) -> 3756739.8 | L23: =IFERROR(Divisions!K23/Divisions!I23,0) -> 0.36828806 | M23: 10801639 | N23: =IFERROR(IF(Divisions!M23-Divisions!I23>0,Divisions!M23-Divisions!I23,0),0) -> 601091.62 | O23: =IFERROR(IF(Divisions!M23-Divisions!I23<0,Divisions!M23-Divisions!I23,0),0) -> 0 | P23: =IFERROR(Divisions!E23-Divisions!I23,0) -> 601091.62 | Q23: =IFERROR(Divisions!I23/Divisions!E23,0) -> 0.94435181 | R23: =IFERROR(_xlfn.XLOOKUP(Divisions!C23,'Project Managers'!C:C,'Project Managers'!R:R),0) -> 0.36 | S23: =IFERROR(_xlfn.XLOOKUP(Divisions!C23,'Project Managers'!C:C,'Project Managers'!T:T),0) -> 0.39 | T23: =IFERROR(_xlfn.XLOOKUP(Divisions!C23,'Project Managers'!C:C,'Project Managers'!U:U),0) -> -132098.05 | U23: =IFERROR(_xlfn.XLOOKUP(Divisions!C23,'Project Managers'!C:C,'Project Managers'!W:W),0) -> 363071.59 | V23: =IFERROR(_xlfn.XLOOKUP(Divisions!C23,'Project Managers'!C:C,'Project Managers'!X:X),0) -> 1 | W23: =IFERROR(_xlfn.XLOOKUP(Divisions!C23,'Project Managers'!C:C,'Project Managers'!Z:Z),0) -> 0.98 | X23: =IFERROR(_xlfn.XLOOKUP(Divisions!C23,'Project Managers'!C:C,'Project Managers'!AA:AA),0) -> 385058.84 | Y23: =IFERROR(_xlfn.XLOOKUP(Divisions!C23,'Project Managers'!C:C,'Project Managers'!AB:AB),0) -> 243246.27 | Z23: =IFERROR(_xlfn.XLOOKUP(Divisions!C23,'Project Managers'!C:C,'Project Managers'!AC:AC),0) -> 141812.57 | AA23: =IFERROR(_xlfn.XLOOKUP(Divisions!C23,'Project Managers'!C:C,'Project Managers'!AD:AD),0) -> 0.36828806 | AB23: =IFERROR(_xlfn.XLOOKUP(Divisions!C23,'Project Managers'!C:C,'Project Managers'!AE:AE),0) -> 1 | AC23: =IFERROR(_xlfn.XLOOKUP(Divisions!C23,'Project Managers'!C:C,'Project Managers'!AF:AF),0) -> 216032.78 | AD23: =IFERROR(_xlfn.XLOOKUP(Divisions!C23,'Project Managers'!C:C,'Project Managers'!AG:AG),0) -> 136470.49 | AE23: =IFERROR(_xlfn.XLOOKUP(Divisions!C23,'Project Managers'!C:C,'Project Managers'!AH:AH),0) -> 79562.294 | AF23: =IFERROR(_xlfn.XLOOKUP(Divisions!C23,'Project Managers'!C:C,'Project Managers'!AI:AI),0) -> 0.36828806 | AG23: =IFERROR(_xlfn.XLOOKUP(Divisions!C23,'Project Managers'!C:C,'Project Managers'!AJ:AJ),0) -> 0 | AH23: =IFERROR(_xlfn.XLOOKUP(Divisions!C23,'Project Managers'!C:C,'Project Managers'!AK:AK),0) -> 0 | AI23: =IFERROR(_xlfn.XLOOKUP(Divisions!C23,'Project Managers'!C:C,'Project Managers'!AL:AL),0) -> 0 | AJ23: =IFERROR(_xlfn.XLOOKUP(Divisions!C23,'Project Managers'!C:C,'Project Managers'!AM:AM),0) -> 0 | AK23: =IFERROR(_xlfn.XLOOKUP(Divisions!C23,'Project Managers'!C:C,'Project Managers'!AN:AN),0) -> 0 | AL23: 0.18 | AM23: 0.36 | AO23: =IFERROR(_xlfn.XLOOKUP(Divisions!C23,'Project Managers'!C:C,'Project Managers'!AR:AR),0) -> 0
B24: Central Texas Electrical Construction | C24: 722201 | D24: TITOS D16 | E24: 540613 | F24: =IFERROR(Divisions!E24*(1-Divisions!H24),0) -> 432490.35 | G24: =IFERROR(Divisions!E24-Divisions!F24,0) -> 108122.65 | H24: {=IF(ISBLANK(Divisions!AL24),Divisions!R24,Divisions!AL24)} -> 0.20000009 | I24: 536266.36 | J24: 429013.04 | K24: =IFERROR(Divisions!I24-Divisions!J24,0) -> 107253.32 | L24: =IFERROR(Divisions!K24/Divisions!I24,0) -> 0.20000009 | M24: 540613 | N24: =IFERROR(IF(Divisions!M24-Divisions!I24>0,Divisions!M24-Divisions!I24,0),0) -> 4346.64 | O24: =IFERROR(IF(Divisions!M24-Divisions!I24<0,Divisions!M24-Divisions!I24,0),0) -> 0 | P24: =IFERROR(Divisions!E24-Divisions!I24,0) -> 4346.64 | Q24: =IFERROR(Divisions!I24/Divisions!E24,0) -> 0.99195979 | R24: =IFERROR(_xlfn.XLOOKUP(Divisions!C24,'Project Managers'!C:C,'Project Managers'!R:R),0) -> 0.20000009 | S24: =IFERROR(_xlfn.XLOOKUP(Divisions!C24,'Project Managers'!C:C,'Project Managers'!T:T),0) -> 0.2 | T24: =IFERROR(_xlfn.XLOOKUP(Divisions!C24,'Project Managers'!C:C,'Project Managers'!U:U),0) -> 0 | U24: =IFERROR(_xlfn.XLOOKUP(Divisions!C24,'Project Managers'!C:C,'Project Managers'!W:W),0) -> -0.06 | V24: =IFERROR(_xlfn.XLOOKUP(Divisions!C24,'Project Managers'!C:C,'Project Managers'!X:X),0) -> 1 | W24: =IFERROR(_xlfn.XLOOKUP(Divisions!C24,'Project Managers'!C:C,'Project Managers'!Z:Z),0) -> 0.95 | X24: =IFERROR(_xlfn.XLOOKUP(Divisions!C24,'Project Managers'!C:C,'Project Managers'!AA:AA),0) -> -22684.01 | Y24: =IFERROR(_xlfn.XLOOKUP(Divisions!C24,'Project Managers'!C:C,'Project Managers'!AB:AB),0) -> -18147.206 | Z24: =IFERROR(_xlfn.XLOOKUP(Divisions!C24,'Project Managers'!C:C,'Project Managers'!AC:AC),0) -> -4536.804 | AA24: =IFERROR(_xlfn.XLOOKUP(Divisions!C24,'Project Managers'!C:C,'Project Managers'!AD:AD),0) -> 0.20000009 | AB24: =IFERROR(_xlfn.XLOOKUP(Divisions!C24,'Project Managers'!C:C,'Project Managers'!AE:AE),0) -> 1 | AC24: =IFERROR(_xlfn.XLOOKUP(Divisions!C24,'Project Managers'!C:C,'Project Managers'!AF:AF),0) -> 27030.65 | AD24: =IFERROR(_xlfn.XLOOKUP(Divisions!C24,'Project Managers'!C:C,'Project Managers'!AG:AG),0) -> 21624.518 | AE24: =IFERROR(_xlfn.XLOOKUP(Divisions!C24,'Project Managers'!C:C,'Project Managers'!AH:AH),0) -> 5406.1324 | AF24: =IFERROR(_xlfn.XLOOKUP(Divisions!C24,'Project Managers'!C:C,'Project Managers'!AI:AI),0) -> 0.20000009 | AG24: =IFERROR(_xlfn.XLOOKUP(Divisions!C24,'Project Managers'!C:C,'Project Managers'!AJ:AJ),0) -> 0 | AH24: =IFERROR(_xlfn.XLOOKUP(Divisions!C24,'Project Managers'!C:C,'Project Managers'!AK:AK),0) -> 0 | AI24: =IFERROR(_xlfn.XLOOKUP(Divisions!C24,'Project Managers'!C:C,'Project Managers'!AL:AL),0) -> 0 | AJ24: =IFERROR(_xlfn.XLOOKUP(Divisions!C24,'Project Managers'!C:C,'Project Managers'!AM:AM),0) -> 0 | AK24: =IFERROR(_xlfn.XLOOKUP(Divisions!C24,'Project Managers'!C:C,'Project Managers'!AN:AN),0) -> 0 | AO24: =IFERROR(_xlfn.XLOOKUP(Divisions!C24,'Project Managers'!C:C,'Project Managers'!AR:AR),0) -> 0
B25: Central Texas Electrical Construction | C25: 722202 | D25: TITOS D17 | E25: 540613 | F25: =IFERROR(Divisions!E25*(1-Divisions!H25),0) -> 432490.26 | G25: =IFERROR(Divisions!E25-Divisions!F25,0) -> 108122.74 | H25: {=IF(ISBLANK(Divisions!AL25),Divisions!R25,Divisions!AL25)} -> 0.20000026 | I25: 264539.26 | J25: 211631.34 | K25: =IFERROR(Divisions!I25-Divisions!J25,0) -> 52907.92 | L25: =IFERROR(Divisions!K25/Divisions!I25,0) -> 0.20000026 | M25: 540613 | N25: =IFERROR(IF(Divisions!M25-Divisions!I25>0,Divisions!M25-Divisions!I25,0),0) -> 276073.74 | O25: =IFERROR(IF(Divisions!M25-Divisions!I25<0,Divisions!M25-Divisions!I25,0),0) -> 0 | P25: =IFERROR(Divisions!E25-Divisions!I25,0) -> 276073.74 | Q25: =IFERROR(Divisions!I25/Divisions!E25,0) -> 0.48933204 | R25: =IFERROR(_xlfn.XLOOKUP(Divisions!C25,'Project Managers'!C:C,'Project Managers'!R:R),0) -> 0.20000026 | S25: =IFERROR(_xlfn.XLOOKUP(Divisions!C25,'Project Managers'!C:C,'Project Managers'!T:T),0) -> 0.2 | T25: =IFERROR(_xlfn.XLOOKUP(Divisions!C25,'Project Managers'!C:C,'Project Managers'!U:U),0) -> 0 | U25: =IFERROR(_xlfn.XLOOKUP(Divisions!C25,'Project Managers'!C:C,'Project Managers'!W:W),0) -> -0.085 | V25: =IFERROR(_xlfn.XLOOKUP(Divisions!C25,'Project Managers'!C:C,'Project Managers'!X:X),0) -> 1 | W25: =IFERROR(_xlfn.XLOOKUP(Divisions!C25,'Project Managers'!C:C,'Project Managers'!Z:Z),0) -> 0.95 | X25: =IFERROR(_xlfn.XLOOKUP(Divisions!C25,'Project Managers'!C:C,'Project Managers'!AA:AA),0) -> 249043.09 | Y25: =IFERROR(_xlfn.XLOOKUP(Divisions!C25,'Project Managers'!C:C,'Project Managers'!AB:AB),0) -> 199234.41 | Z25: =IFERROR(_xlfn.XLOOKUP(Divisions!C25,'Project Managers'!C:C,'Project Managers'!AC:AC),0) -> 49808.682 | AA25: =IFERROR(_xlfn.XLOOKUP(Divisions!C25,'Project Managers'!C:C,'Project Managers'!AD:AD),0) -> 0.20000026 | AB25: =IFERROR(_xlfn.XLOOKUP(Divisions!C25,'Project Managers'!C:C,'Project Managers'!AE:AE),0) -> 1 | AC25: =IFERROR(_xlfn.XLOOKUP(Divisions!C25,'Project Managers'!C:C,'Project Managers'!AF:AF),0) -> 27030.65 | AD25: =IFERROR(_xlfn.XLOOKUP(Divisions!C25,'Project Managers'!C:C,'Project Managers'!AG:AG),0) -> 21624.513 | AE25: =IFERROR(_xlfn.XLOOKUP(Divisions!C25,'Project Managers'!C:C,'Project Managers'!AH:AH),0) -> 5406.1369 | AF25: =IFERROR(_xlfn.XLOOKUP(Divisions!C25,'Project Managers'!C:C,'Project Managers'!AI:AI),0) -> 0.20000026 | AG25: =IFERROR(_xlfn.XLOOKUP(Divisions!C25,'Project Managers'!C:C,'Project Managers'!AJ:AJ),0) -> 0 | AH25: =IFERROR(_xlfn.XLOOKUP(Divisions!C25,'Project Managers'!C:C,'Project Managers'!AK:AK),0) -> 0 | AI25: =IFERROR(_xlfn.XLOOKUP(Divisions!C25,'Project Managers'!C:C,'Project Managers'!AL:AL),0) -> 0 | AJ25: =IFERROR(_xlfn.XLOOKUP(Divisions!C25,'Project Managers'!C:C,'Project Managers'!AM:AM),0) -> 0 | AK25: =IFERROR(_xlfn.XLOOKUP(Divisions!C25,'Project Managers'!C:C,'Project Managers'!AN:AN),0) -> 0 | AO25: =IFERROR(_xlfn.XLOOKUP(Divisions!C25,'Project Managers'!C:C,'Project Managers'!AR:AR),0) -> 0
B26: Central Texas Electrical Construction | C26: 722203 | D26: TITOS D18 | E26: 540613 | F26: =IFERROR(Divisions!E26*(1-Divisions!H26),0) -> 432490.38 | G26: =IFERROR(Divisions!E26-Divisions!F26,0) -> 108122.62 | H26: {=IF(ISBLANK(Divisions!AL26),Divisions!R26,Divisions!AL26)} -> 0.20000004 | I26: 529491.34 | J26: 423593.05 | K26: =IFERROR(Divisions!I26-Divisions!J26,0) -> 105898.29 | L26: =IFERROR(Divisions!K26/Divisions!I26,0) -> 0.20000004 | M26: 540613 | N26: =IFERROR(IF(Divisions!M26-Divisions!I26>0,Divisions!M26-Divisions!I26,0),0) -> 11121.66 | O26: =IFERROR(IF(Divisions!M26-Divisions!I26<0,Divisions!M26-Divisions!I26,0),0) -> 0 | P26: =IFERROR(Divisions!E26-Divisions!I26,0) -> 11121.66 | Q26: =IFERROR(Divisions!I26/Divisions!E26,0) -> 0.97942769 | R26: =IFERROR(_xlfn.XLOOKUP(Divisions!C26,'Project Managers'!C:C,'Project Managers'!R:R),0) -> 0.20000004 | S26: =IFERROR(_xlfn.XLOOKUP(Divisions!C26,'Project Managers'!C:C,'Project Managers'!T:T),0) -> 0.2 | T26: =IFERROR(_xlfn.XLOOKUP(Divisions!C26,'Project Managers'!C:C,'Project Managers'!U:U),0) -> 0 | U26: =IFERROR(_xlfn.XLOOKUP(Divisions!C26,'Project Managers'!C:C,'Project Managers'!W:W),0) -> -0.0275 | V26: =IFERROR(_xlfn.XLOOKUP(Divisions!C26,'Project Managers'!C:C,'Project Managers'!X:X),0) -> 1 | W26: =IFERROR(_xlfn.XLOOKUP(Divisions!C26,'Project Managers'!C:C,'Project Managers'!Z:Z),0) -> 0.95 | X26: =IFERROR(_xlfn.XLOOKUP(Divisions!C26,'Project Managers'!C:C,'Project Managers'!AA:AA),0) -> -15908.99 | Y26: =IFERROR(_xlfn.XLOOKUP(Divisions!C26,'Project Managers'!C:C,'Project Managers'!AB:AB),0) -> -12727.191 | Z26: =IFERROR(_xlfn.XLOOKUP(Divisions!C26,'Project Managers'!C:C,'Project Managers'!AC:AC),0) -> -3181.7987 | AA26: =IFERROR(_xlfn.XLOOKUP(Divisions!C26,'Project Managers'!C:C,'Project Managers'!AD:AD),0) -> 0.20000004 | AB26: =IFERROR(_xlfn.XLOOKUP(Divisions!C26,'Project Managers'!C:C,'Project Managers'!AE:AE),0) -> 1 | AC26: =IFERROR(_xlfn.XLOOKUP(Divisions!C26,'Project Managers'!C:C,'Project Managers'!AF:AF),0) -> 27030.65 | AD26: =IFERROR(_xlfn.XLOOKUP(Divisions!C26,'Project Managers'!C:C,'Project Managers'!AG:AG),0) -> 21624.519 | AE26: =IFERROR(_xlfn.XLOOKUP(Divisions!C26,'Project Managers'!C:C,'Project Managers'!AH:AH),0) -> 5406.1311 | AF26: =IFERROR(_xlfn.XLOOKUP(Divisions!C26,'Project Managers'!C:C,'Project Managers'!AI:AI),0) -> 0.20000004 | AG26: =IFERROR(_xlfn.XLOOKUP(Divisions!C26,'Project Managers'!C:C,'Project Managers'!AJ:AJ),0) -> 0 | AH26: =IFERROR(_xlfn.XLOOKUP(Divisions!C26,'Project Managers'!C:C,'Project Managers'!AK:AK),0) -> 0 | AI26: =IFERROR(_xlfn.XLOOKUP(Divisions!C26,'Project Managers'!C:C,'Project Managers'!AL:AL),0) -> 0 | AJ26: =IFERROR(_xlfn.XLOOKUP(Divisions!C26,'Project Managers'!C:C,'Project Managers'!AM:AM),0) -> 0 | AK26: =IFERROR(_xlfn.XLOOKUP(Divisions!C26,'Project Managers'!C:C,'Project Managers'!AN:AN),0) -> 0 | AO26: =IFERROR(_xlfn.XLOOKUP(Divisions!C26,'Project Managers'!C:C,'Project Managers'!AR:AR),0) -> 0
B27: Central Texas Electrical Construction | C27: 722204 | D27: TITOS D19 | E27: 540613 | F27: =IFERROR(Divisions!E27*(1-Divisions!H27),0) -> 432490.36 | G27: =IFERROR(Divisions!E27-Divisions!F27,0) -> 108122.64 | H27: {=IF(ISBLANK(Divisions!AL27),Divisions!R27,Divisions!AL27)} -> 0.20000007 | I27: 511281.68 | J27: 409025.31 | K27: =IFERROR(Divisions!I27-Divisions!J27,0) -> 102256.37 | L27: =IFERROR(Divisions!K27/Divisions!I27,0) -> 0.20000007 | M27: 540613 | N27: =IFERROR(IF(Divisions!M27-Divisions!I27>0,Divisions!M27-Divisions!I27,0),0) -> 29331.32 | O27: =IFERROR(IF(Divisions!M27-Divisions!I27<0,Divisions!M27-Divisions!I27,0),0) -> 0 | P27: =IFERROR(Divisions!E27-Divisions!I27,0) -> 29331.32 | Q27: =IFERROR(Divisions!I27/Divisions!E27,0) -> 0.94574433 | R27: =IFERROR(_xlfn.XLOOKUP(Divisions!C27,'Project Managers'!C:C,'Project Managers'!R:R),0) -> 0.20000007 | S27: =IFERROR(_xlfn.XLOOKUP(Divisions!C27,'Project Managers'!C:C,'Project Managers'!T:T),0) -> 0.2 | T27: =IFERROR(_xlfn.XLOOKUP(Divisions!C27,'Project Managers'!C:C,'Project Managers'!U:U),0) -> -5.8207661e-11 | U27: =IFERROR(_xlfn.XLOOKUP(Divisions!C27,'Project Managers'!C:C,'Project Managers'!W:W),0) -> -0.0425 | V27: =IFERROR(_xlfn.XLOOKUP(Divisions!C27,'Project Managers'!C:C,'Project Managers'!X:X),0) -> 1 | W27: =IFERROR(_xlfn.XLOOKUP(Divisions!C27,'Project Managers'!C:C,'Project Managers'!Z:Z),0) -> 0.95 | X27: =IFERROR(_xlfn.XLOOKUP(Divisions!C27,'Project Managers'!C:C,'Project Managers'!AA:AA),0) -> 2300.67 | Y27: =IFERROR(_xlfn.XLOOKUP(Divisions!C27,'Project Managers'!C:C,'Project Managers'!AB:AB),0) -> 1840.5358 | Z27: =IFERROR(_xlfn.XLOOKUP(Divisions!C27,'Project Managers'!C:C,'Project Managers'!AC:AC),0) -> 460.13415 | AA27: =IFERROR(_xlfn.XLOOKUP(Divisions!C27,'Project Managers'!C:C,'Project Managers'!AD:AD),0) -> 0.20000007 | AB27: =IFERROR(_xlfn.XLOOKUP(Divisions!C27,'Project Managers'!C:C,'Project Managers'!AE:AE),0) -> 1 | AC27: =IFERROR(_xlfn.XLOOKUP(Divisions!C27,'Project Managers'!C:C,'Project Managers'!AF:AF),0) -> 27030.65 | AD27: =IFERROR(_xlfn.XLOOKUP(Divisions!C27,'Project Managers'!C:C,'Project Managers'!AG:AG),0) -> 21624.518 | AE27: =IFERROR(_xlfn.XLOOKUP(Divisions!C27,'Project Managers'!C:C,'Project Managers'!AH:AH),0) -> 5406.1318 | AF27: =IFERROR(_xlfn.XLOOKUP(Divisions!C27,'Project Managers'!C:C,'Project Managers'!AI:AI),0) -> 0.20000007 | AG27: =IFERROR(_xlfn.XLOOKUP(Divisions!C27,'Project Managers'!C:C,'Project Managers'!AJ:AJ),0) -> 0 | AH27: =IFERROR(_xlfn.XLOOKUP(Divisions!C27,'Project Managers'!C:C,'Project Managers'!AK:AK),0) -> 0 | AI27: =IFERROR(_xlfn.XLOOKUP(Divisions!C27,'Project Managers'!C:C,'Project Managers'!AL:AL),0) -> 0 | AJ27: =IFERROR(_xlfn.XLOOKUP(Divisions!C27,'Project Managers'!C:C,'Project Managers'!AM:AM),0) -> 0 | AK27: =IFERROR(_xlfn.XLOOKUP(Divisions!C27,'Project Managers'!C:C,'Project Managers'!AN:AN),0) -> 0 | AO27: =IFERROR(_xlfn.XLOOKUP(Divisions!C27,'Project Managers'!C:C,'Project Managers'!AR:AR),0) -> 0
B28: Central Texas Electrical Construction | C28: 722205 | D28: NEW COMPRESSOR BLDG | E28: 97115 | F28: =IFERROR(Divisions!E28*(1-Divisions!H28),0) -> 63102.676 | G28: =IFERROR(Divisions!E28-Divisions!F28,0) -> 34012.324 | H28: {=IF(ISBLANK(Divisions!AL28),Divisions!R28,Divisions!AL28)} -> 0.35022729 | I28: 71722.08 | J28: 46603.05 | K28: =IFERROR(Divisions!I28-Divisions!J28,0) -> 25119.03 | L28: =IFERROR(Divisions!K28/Divisions!I28,0) -> 0.35022729 | M28: 97115 | N28: =IFERROR(IF(Divisions!M28-Divisions!I28>0,Divisions!M28-Divisions!I28,0),0) -> 25392.92 | O28: =IFERROR(IF(Divisions!M28-Divisions!I28<0,Divisions!M28-Divisions!I28,0),0) -> 0 | P28: =IFERROR(Divisions!E28-Divisions!I28,0) -> 25392.92 | Q28: =IFERROR(Divisions!I28/Divisions!E28,0) -> 0.73852731 | R28: =IFERROR(_xlfn.XLOOKUP(Divisions!C28,'Project Managers'!C:C,'Project Managers'!R:R),0) -> 0.35022729 | S28: =IFERROR(_xlfn.XLOOKUP(Divisions!C28,'Project Managers'!C:C,'Project Managers'!T:T),0) -> 0.35 | T28: =IFERROR(_xlfn.XLOOKUP(Divisions!C28,'Project Managers'!C:C,'Project Managers'!U:U),0) -> 0 | U28: =IFERROR(_xlfn.XLOOKUP(Divisions!C28,'Project Managers'!C:C,'Project Managers'!W:W),0) -> -25.08 | V28: =IFERROR(_xlfn.XLOOKUP(Divisions!C28,'Project Managers'!C:C,'Project Managers'!X:X),0) -> 1 | W28: =IFERROR(_xlfn.XLOOKUP(Divisions!C28,'Project Managers'!C:C,'Project Managers'!Z:Z),0) -> 1 | X28: =IFERROR(_xlfn.XLOOKUP(Divisions!C28,'Project Managers'!C:C,'Project Managers'!AA:AA),0) -> 25392.92 | Y28: =IFERROR(_xlfn.XLOOKUP(Divisions!C28,'Project Managers'!C:C,'Project Managers'!AB:AB),0) -> 16499.626 | Z28: =IFERROR(_xlfn.XLOOKUP(Divisions!C28,'Project Managers'!C:C,'Project Managers'!AC:AC),0) -> 8893.2937 | AA28: =IFERROR(_xlfn.XLOOKUP(Divisions!C28,'Project Managers'!C:C,'Project Managers'!AD:AD),0) -> 0.35022729 | AB28: =IFERROR(_xlfn.XLOOKUP(Divisions!C28,'Project Managers'!C:C,'Project Managers'!AE:AE),0) -> 0 | AC28: =IFERROR(_xlfn.XLOOKUP(Divisions!C28,'Project Managers'!C:C,'Project Managers'!AF:AF),0) -> 0 | AD28: =IFERROR(_xlfn.XLOOKUP(Divisions!C28,'Project Managers'!C:C,'Project Managers'!AG:AG),0) -> 0 | AE28: =IFERROR(_xlfn.XLOOKUP(Divisions!C28,'Project Managers'!C:C,'Project Managers'!AH:AH),0) -> 0 | AF28: =IFERROR(_xlfn.XLOOKUP(Divisions!C28,'Project Managers'!C:C,'Project Managers'!AI:AI),0) -> 0 | AG28: =IFERROR(_xlfn.XLOOKUP(Divisions!C28,'Project Managers'!C:C,'Project Managers'!AJ:AJ),0) -> 0 | AH28: =IFERROR(_xlfn.XLOOKUP(Divisions!C28,'Project Managers'!C:C,'Project Managers'!AK:AK),0) -> 0 | AI28: =IFERROR(_xlfn.XLOOKUP(Divisions!C28,'Project Managers'!C:C,'Project Managers'!AL:AL),0) -> 0 | AJ28: =IFERROR(_xlfn.XLOOKUP(Divisions!C28,'Project Managers'!C:C,'Project Managers'!AM:AM),0) -> 0 | AK28: =IFERROR(_xlfn.XLOOKUP(Divisions!C28,'Project Managers'!C:C,'Project Managers'!AN:AN),0) -> 0 | AO28: =IFERROR(_xlfn.XLOOKUP(Divisions!C28,'Project Managers'!C:C,'Project Managers'!AR:AR),0) -> 0
B29: Central Texas Electrical Construction | C29: 722206 | D29: TITOS GUARD HOUSE 6 | E29: 101940 | F29: =IFERROR(Divisions!E29*(1-Divisions!H29),0) -> 99235.31 | G29: =IFERROR(Divisions!E29-Divisions!F29,0) -> 2704.69 | H29: {=IF(ISBLANK(Divisions!AL29),Divisions!R29,Divisions!AL29)} -> 0.026532176 | I29: 101940 | J29: 99235.31 | K29: =IFERROR(Divisions!I29-Divisions!J29,0) -> 2704.69 | L29: =IFERROR(Divisions!K29/Divisions!I29,0) -> 0.026532176 | M29: 101940 | N29: =IFERROR(IF(Divisions!M29-Divisions!I29>0,Divisions!M29-Divisions!I29,0),0) -> 0 | O29: =IFERROR(IF(Divisions!M29-Divisions!I29<0,Divisions!M29-Divisions!I29,0),0) -> 0 | P29: =IFERROR(Divisions!E29-Divisions!I29,0) -> 0 | Q29: =IFERROR(Divisions!I29/Divisions!E29,0) -> 1 | R29: =IFERROR(_xlfn.XLOOKUP(Divisions!C29,'Project Managers'!C:C,'Project Managers'!R:R),0) -> 0.026532176 | S29: =IFERROR(_xlfn.XLOOKUP(Divisions!C29,'Project Managers'!C:C,'Project Managers'!T:T),0) -> 0.0265 | T29: =IFERROR(_xlfn.XLOOKUP(Divisions!C29,'Project Managers'!C:C,'Project Managers'!U:U),0) -> 0 | U29: =IFERROR(_xlfn.XLOOKUP(Divisions!C29,'Project Managers'!C:C,'Project Managers'!W:W),0) -> -3.3692861 | V29: =IFERROR(_xlfn.XLOOKUP(Divisions!C29,'Project Managers'!C:C,'Project Managers'!X:X),0) -> 1 | W29: =IFERROR(_xlfn.XLOOKUP(Divisions!C29,'Project Managers'!C:C,'Project Managers'!Z:Z),0) -> 1 | X29: =IFERROR(_xlfn.XLOOKUP(Divisions!C29,'Project Managers'!C:C,'Project Managers'!AA:AA),0) -> 0 | Y29: =IFERROR(_xlfn.XLOOKUP(Divisions!C29,'Project Managers'!C:C,'Project Managers'!AB:AB),0) -> 0 | Z29: =IFERROR(_xlfn.XLOOKUP(Divisions!C29,'Project Managers'!C:C,'Project Managers'!AC:AC),0) -> 0 | AA29: =IFERROR(_xlfn.XLOOKUP(Divisions!C29,'Project Managers'!C:C,'Project Managers'!AD:AD),0) -> 0 | AB29: =IFERROR(_xlfn.XLOOKUP(Divisions!C29,'Project Managers'!C:C,'Project Managers'!AE:AE),0) -> 0 | AC29: =IFERROR(_xlfn.XLOOKUP(Divisions!C29,'Project Managers'!C:C,'Project Managers'!AF:AF),0) -> 0 | AD29: =IFERROR(_xlfn.XLOOKUP(Divisions!C29,'Project Managers'!C:C,'Project Managers'!AG:AG),0) -> 0 | AE29: =IFERROR(_xlfn.XLOOKUP(Divisions!C29,'Project Managers'!C:C,'Project Managers'!AH:AH),0) -> 0 | AF29: =IFERROR(_xlfn.XLOOKUP(Divisions!C29,'Project Managers'!C:C,'Project Managers'!AI:AI),0) -> 0 | AG29: =IFERROR(_xlfn.XLOOKUP(Divisions!C29,'Project Managers'!C:C,'Project Managers'!AJ:AJ),0) -> 0 | AH29: =IFERROR(_xlfn.XLOOKUP(Divisions!C29,'Project Managers'!C:C,'Project Managers'!AK:AK),0) -> 0 | AI29: =IFERROR(_xlfn.XLOOKUP(Divisions!C29,'Project Managers'!C:C,'Project Managers'!AL:AL),0) -> 0 | AJ29: =IFERROR(_xlfn.XLOOKUP(Divisions!C29,'Project Managers'!C:C,'Project Managers'!AM:AM),0) -> 0 | AK29: =IFERROR(_xlfn.XLOOKUP(Divisions!C29,'Project Managers'!C:C,'Project Managers'!AN:AN),0) -> 0 | AO29: =IFERROR(_xlfn.XLOOKUP(Divisions!C29,'Project Managers'!C:C,'Project Managers'!AR:AR),0) -> 0
B30: Central Texas Electrical Construction | C30: 722207 | D30: TITOS DUNNAGE AREA DA-1 | E30: 223936.85 | F30: =IFERROR(Divisions!E30*(1-Divisions!H30),0) -> 186614.06 | G30: =IFERROR(Divisions!E30-Divisions!F30,0) -> 37322.786 | H30: {=IF(ISBLANK(Divisions!AL30),Divisions!R30,Divisions!AL30)} -> 0.16666657 | I30: 186692.87 | J30: 155577.41 | K30: =IFERROR(Divisions!I30-Divisions!J30,0) -> 31115.46 | L30: =IFERROR(Divisions!K30/Divisions!I30,0) -> 0.16666657 | M30: 223936.85 | N30: =IFERROR(IF(Divisions!M30-Divisions!I30>0,Divisions!M30-Divisions!I30,0),0) -> 37243.98 | O30: =IFERROR(IF(Divisions!M30-Divisions!I30<0,Divisions!M30-Divisions!I30,0),0) -> 0 | P30: =IFERROR(Divisions!E30-Divisions!I30,0) -> 37243.98 | Q30: =IFERROR(Divisions!I30/Divisions!E30,0) -> 0.83368534 | R30: =IFERROR(_xlfn.XLOOKUP(Divisions!C30,'Project Managers'!C:C,'Project Managers'!R:R),0) -> 0.16666657 | S30: =IFERROR(_xlfn.XLOOKUP(Divisions!C30,'Project Managers'!C:C,'Project Managers'!T:T),0) -> 0.2 | T30: =IFERROR(_xlfn.XLOOKUP(Divisions!C30,'Project Managers'!C:C,'Project Managers'!U:U),0) -> 0 | U30: =IFERROR(_xlfn.XLOOKUP(Divisions!C30,'Project Managers'!C:C,'Project Managers'!W:W),0) -> 7778.8925 | V30: =IFERROR(_xlfn.XLOOKUP(Divisions!C30,'Project Managers'!C:C,'Project Managers'!X:X),0) -> 1 | W30: =IFERROR(_xlfn.XLOOKUP(Divisions!C30,'Project Managers'!C:C,'Project Managers'!Z:Z),0) -> 1 | X30: =IFERROR(_xlfn.XLOOKUP(Divisions!C30,'Project Managers'!C:C,'Project Managers'!AA:AA),0) -> 37243.98 | Y30: =IFERROR(_xlfn.XLOOKUP(Divisions!C30,'Project Managers'!C:C,'Project Managers'!AB:AB),0) -> 31036.654 | Z30: =IFERROR(_xlfn.XLOOKUP(Divisions!C30,'Project Managers'!C:C,'Project Managers'!AC:AC),0) -> 6207.3263 | AA30: =IFERROR(_xlfn.XLOOKUP(Divisions!C30,'Project Managers'!C:C,'Project Managers'!AD:AD),0) -> 0.16666657 | AB30: =IFERROR(_xlfn.XLOOKUP(Divisions!C30,'Project Managers'!C:C,'Project Managers'!AE:AE),0) -> 0 | AC30: =IFERROR(_xlfn.XLOOKUP(Divisions!C30,'Project Managers'!C:C,'Project Managers'!AF:AF),0) -> 0 | AD30: =IFERROR(_xlfn.XLOOKUP(Divisions!C30,'Project Managers'!C:C,'Project Managers'!AG:AG),0) -> 0 | AE30: =IFERROR(_xlfn.XLOOKUP(Divisions!C30,'Project Managers'!C:C,'Project Managers'!AH:AH),0) -> 0 | AF30: =IFERROR(_xlfn.XLOOKUP(Divisions!C30,'Project Managers'!C:C,'Project Managers'!AI:AI),0) -> 0 | AG30: =IFERROR(_xlfn.XLOOKUP(Divisions!C30,'Project Managers'!C:C,'Project Managers'!AJ:AJ),0) -> 0 | AH30: =IFERROR(_xlfn.XLOOKUP(Divisions!C30,'Project Managers'!C:C,'Project Managers'!AK:AK),0) -> 0 | AI30: =IFERROR(_xlfn.XLOOKUP(Divisions!C30,'Project Managers'!C:C,'Project Managers'!AL:AL),0) -> 0 | AJ30: =IFERROR(_xlfn.XLOOKUP(Divisions!C30,'Project Managers'!C:C,'Project Managers'!AM:AM),0) -> 0 | AK30: =IFERROR(_xlfn.XLOOKUP(Divisions!C30,'Project Managers'!C:C,'Project Managers'!AN:AN),0) -> 0 | AO30: =IFERROR(_xlfn.XLOOKUP(Divisions!C30,'Project Managers'!C:C,'Project Managers'!AR:AR),0) -> 0
B31: Central Texas Electrical Construction | C31: 722208 | D31: TITOS AT VAULT EXPANSION | E31: 155587 | F31: =IFERROR(Divisions!E31*(1-Divisions!H31),0) -> 124469.48 | G31: =IFERROR(Divisions!E31-Divisions!F31,0) -> 31117.517 | H31: {=IF(ISBLANK(Divisions!AL31),Divisions!R31,Divisions!AL31)} -> 0.20000075 | I31: 29248.64 | J31: 23398.89 | K31: =IFERROR(Divisions!I31-Divisions!J31,0) -> 5849.75 | L31: =IFERROR(Divisions!K31/Divisions!I31,0) -> 0.20000075 | M31: 29762 | N31: =IFERROR(IF(Divisions!M31-Divisions!I31>0,Divisions!M31-Divisions!I31,0),0) -> 513.36 | O31: =IFERROR(IF(Divisions!M31-Divisions!I31<0,Divisions!M31-Divisions!I31,0),0) -> 0 | P31: =IFERROR(Divisions!E31-Divisions!I31,0) -> 126338.36 | Q31: =IFERROR(Divisions!I31/Divisions!E31,0) -> 0.18798897 | R31: =IFERROR(_xlfn.XLOOKUP(Divisions!C31,'Project Managers'!C:C,'Project Managers'!R:R),0) -> 0.20000075 | S31: =IFERROR(_xlfn.XLOOKUP(Divisions!C31,'Project Managers'!C:C,'Project Managers'!T:T),0) -> 0.2 | T31: =IFERROR(_xlfn.XLOOKUP(Divisions!C31,'Project Managers'!C:C,'Project Managers'!U:U),0) -> -3.6379788e-12 | U31: =IFERROR(_xlfn.XLOOKUP(Divisions!C31,'Project Managers'!C:C,'Project Managers'!W:W),0) -> -0.0275 | V31: =IFERROR(_xlfn.XLOOKUP(Divisions!C31,'Project Managers'!C:C,'Project Managers'!X:X),0) -> 1 | W31: =IFERROR(_xlfn.XLOOKUP(Divisions!C31,'Project Managers'!C:C,'Project Managers'!Z:Z),0) -> 0.2 | X31: =IFERROR(_xlfn.XLOOKUP(Divisions!C31,'Project Managers'!C:C,'Project Managers'!AA:AA),0) -> 1868.76 | Y31: =IFERROR(_xlfn.XLOOKUP(Divisions!C31,'Project Managers'!C:C,'Project Managers'!AB:AB),0) -> 1495.0066 | Z31: =IFERROR(_xlfn.XLOOKUP(Divisions!C31,'Project Managers'!C:C,'Project Managers'!AC:AC),0) -> 373.75341 | AA31: =IFERROR(_xlfn.XLOOKUP(Divisions!C31,'Project Managers'!C:C,'Project Managers'!AD:AD),0) -> 0.20000075 | AB31: =IFERROR(_xlfn.XLOOKUP(Divisions!C31,'Project Managers'!C:C,'Project Managers'!AE:AE),0) -> 1 | AC31: =IFERROR(_xlfn.XLOOKUP(Divisions!C31,'Project Managers'!C:C,'Project Managers'!AF:AF),0) -> 124469.6 | AD31: =IFERROR(_xlfn.XLOOKUP(Divisions!C31,'Project Managers'!C:C,'Project Managers'!AG:AG),0) -> 99575.586 | AE31: =IFERROR(_xlfn.XLOOKUP(Divisions!C31,'Project Managers'!C:C,'Project Managers'!AH:AH),0) -> 24894.014 | AF31: =IFERROR(_xlfn.XLOOKUP(Divisions!C31,'Project Managers'!C:C,'Project Managers'!AI:AI),0) -> 0.20000075 | AG31: =IFERROR(_xlfn.XLOOKUP(Divisions!C31,'Project Managers'!C:C,'Project Managers'!AJ:AJ),0) -> 0 | AH31: =IFERROR(_xlfn.XLOOKUP(Divisions!C31,'Project Managers'!C:C,'Project Managers'!AK:AK),0) -> 0 | AI31: =IFERROR(_xlfn.XLOOKUP(Divisions!C31,'Project Managers'!C:C,'Project Managers'!AL:AL),0) -> 0 | AJ31: =IFERROR(_xlfn.XLOOKUP(Divisions!C31,'Project Managers'!C:C,'Project Managers'!AM:AM),0) -> 0 | AK31: =IFERROR(_xlfn.XLOOKUP(Divisions!C31,'Project Managers'!C:C,'Project Managers'!AN:AN),0) -> 0 | AO31: =IFERROR(_xlfn.XLOOKUP(Divisions!C31,'Project Managers'!C:C,'Project Managers'!AR:AR),0) -> 0
B32: Central Texas Electrical Construction | C32: 722210 | D32: LIBERTY HILL HS #2 | E32: 11473198 | F32: =IFERROR(Divisions!E32*(1-Divisions!H32),0) -> 9522754.3 | G32: =IFERROR(Divisions!E32-Divisions!F32,0) -> 1950443.7 | H32: {=IF(ISBLANK(Divisions!AL32),Divisions!R32,Divisions!AL32)} -> 0.17 | I32: 10565813 | J32: 8976901.2 | K32: =IFERROR(Divisions!I32-Divisions!J32,0) -> 1588911.5 | L32: =IFERROR(Divisions!K32/Divisions!I32,0) -> 0.15038233 | M32: 10673409 | N32: =IFERROR(IF(Divisions!M32-Divisions!I32>0,Divisions!M32-Divisions!I32,0),0) -> 107596.05 | O32: =IFERROR(IF(Divisions!M32-Divisions!I32<0,Divisions!M32-Divisions!I32,0),0) -> 0 | P32: =IFERROR(Divisions!E32-Divisions!I32,0) -> 907385.3 | Q32: =IFERROR(Divisions!I32/Divisions!E32,0) -> 0.92091261 | R32: =IFERROR(_xlfn.XLOOKUP(Divisions!C32,'Project Managers'!C:C,'Project Managers'!R:R),0) -> 0.19 | S32: =IFERROR(_xlfn.XLOOKUP(Divisions!C32,'Project Managers'!C:C,'Project Managers'!T:T),0) -> 0.15 | T32: =IFERROR(_xlfn.XLOOKUP(Divisions!C32,'Project Managers'!C:C,'Project Managers'!U:U),0) -> 516781.36 | U32: =IFERROR(_xlfn.XLOOKUP(Divisions!C32,'Project Managers'!C:C,'Project Managers'!W:W),0) -> -4752.4765 | V32: =IFERROR(_xlfn.XLOOKUP(Divisions!C32,'Project Managers'!C:C,'Project Managers'!X:X),0) -> 1 | W32: =IFERROR(_xlfn.XLOOKUP(Divisions!C32,'Project Managers'!C:C,'Project Managers'!Z:Z),0) -> 0.87 | X32: =IFERROR(_xlfn.XLOOKUP(Divisions!C32,'Project Managers'!C:C,'Project Managers'!AA:AA),0) -> -584130.44 | Y32: =IFERROR(_xlfn.XLOOKUP(Divisions!C32,'Project Managers'!C:C,'Project Managers'!AB:AB),0) -> -496287.54 | Z32: =IFERROR(_xlfn.XLOOKUP(Divisions!C32,'Project Managers'!C:C,'Project Managers'!AC:AC),0) -> -87842.895 | AA32: =IFERROR(_xlfn.XLOOKUP(Divisions!C32,'Project Managers'!C:C,'Project Managers'!AD:AD),0) -> 0.15038233 | AB32: =IFERROR(_xlfn.XLOOKUP(Divisions!C32,'Project Managers'!C:C,'Project Managers'!AE:AE),0) -> 1 | AC32: =IFERROR(_xlfn.XLOOKUP(Divisions!C32,'Project Managers'!C:C,'Project Managers'!AF:AF),0) -> 1491515.7 | AD32: =IFERROR(_xlfn.XLOOKUP(Divisions!C32,'Project Managers'!C:C,'Project Managers'!AG:AG),0) -> 1267218.1 | AE32: =IFERROR(_xlfn.XLOOKUP(Divisions!C32,'Project Managers'!C:C,'Project Managers'!AH:AH),0) -> 224297.61 | AF32: =IFERROR(_xlfn.XLOOKUP(Divisions!C32,'Project Managers'!C:C,'Project Managers'!AI:AI),0) -> 0.15038233 | AG32: =IFERROR(_xlfn.XLOOKUP(Divisions!C32,'Project Managers'!C:C,'Project Managers'!AJ:AJ),0) -> 0 | AH32: =IFERROR(_xlfn.XLOOKUP(Divisions!C32,'Project Managers'!C:C,'Project Managers'!AK:AK),0) -> 0 | AI32: =IFERROR(_xlfn.XLOOKUP(Divisions!C32,'Project Managers'!C:C,'Project Managers'!AL:AL),0) -> 0 | AJ32: =IFERROR(_xlfn.XLOOKUP(Divisions!C32,'Project Managers'!C:C,'Project Managers'!AM:AM),0) -> 0 | AK32: =IFERROR(_xlfn.XLOOKUP(Divisions!C32,'Project Managers'!C:C,'Project Managers'!AN:AN),0) -> 0 | AL32: 0.17 | AM32: 0.19 | AO32: =IFERROR(_xlfn.XLOOKUP(Divisions!C32,'Project Managers'!C:C,'Project Managers'!AR:AR),0) -> 0
B33: Central Texas Electrical Construction | C33: 722280 | D33: HUTTO 1 INITIAL IMPROV | E33: 13617357 | F33: =IFERROR(Divisions!E33*(1-Divisions!H33),0) -> 11438580 | G33: =IFERROR(Divisions!E33-Divisions!F33,0) -> 2178777.1 | H33: {=IF(ISBLANK(Divisions!AL33),Divisions!R33,Divisions!AL33)} -> 0.16 | I33: 13617357 | J33: 12370710 | K33: =IFERROR(Divisions!I33-Divisions!J33,0) -> 1246647.3 | L33: =IFERROR(Divisions!K33/Divisions!I33,0) -> 0.091548405 | M33: 13617357 | N33: =IFERROR(IF(Divisions!M33-Divisions!I33>0,Divisions!M33-Divisions!I33,0),0) -> 0 | O33: =IFERROR(IF(Divisions!M33-Divisions!I33<0,Divisions!M33-Divisions!I33,0),0) -> 0 | P33: =IFERROR(Divisions!E33-Divisions!I33,0) -> 0 | Q33: =IFERROR(Divisions!I33/Divisions!E33,0) -> 1 | R33: =IFERROR(_xlfn.XLOOKUP(Divisions!C33,'Project Managers'!C:C,'Project Managers'!R:R),0) -> 0.23 | S33: =IFERROR(_xlfn.XLOOKUP(Divisions!C33,'Project Managers'!C:C,'Project Managers'!T:T),0) -> 0.085 | T33: =IFERROR(_xlfn.XLOOKUP(Divisions!C33,'Project Managers'!C:C,'Project Managers'!U:U),0) -> 2448499.7 | U33: =IFERROR(_xlfn.XLOOKUP(Divisions!C33,'Project Managers'!C:C,'Project Managers'!W:W),0) -> -97455.699 | V33: =IFERROR(_xlfn.XLOOKUP(Divisions!C33,'Project Managers'!C:C,'Project Managers'!X:X),0) -> 1 | W33: =IFERROR(_xlfn.XLOOKUP(Divisions!C33,'Project Managers'!C:C,'Project Managers'!Z:Z),0) -> 1 | X33: =IFERROR(_xlfn.XLOOKUP(Divisions!C33,'Project Managers'!C:C,'Project Managers'!AA:AA),0) -> 0 | Y33: =IFERROR(_xlfn.XLOOKUP(Divisions!C33,'Project Managers'!C:C,'Project Managers'!AB:AB),0) -> 0 | Z33: =IFERROR(_xlfn.XLOOKUP(Divisions!C33,'Project Managers'!C:C,'Project Managers'!AC:AC),0) -> 0 | AA33: =IFERROR(_xlfn.XLOOKUP(Divisions!C33,'Project Managers'!C:C,'Project Managers'!AD:AD),0) -> 0 | AB33: =IFERROR(_xlfn.XLOOKUP(Divisions!C33,'Project Managers'!C:C,'Project Managers'!AE:AE),0) -> 0 | AC33: =IFERROR(_xlfn.XLOOKUP(Divisions!C33,'Project Managers'!C:C,'Project Managers'!AF:AF),0) -> 0 | AD33: =IFERROR(_xlfn.XLOOKUP(Divisions!C33,'Project Managers'!C:C,'Project Managers'!AG:AG),0) -> 0 | AE33: =IFERROR(_xlfn.XLOOKUP(Divisions!C33,'Project Managers'!C:C,'Project Managers'!AH:AH),0) -> 0 | AF33: =IFERROR(_xlfn.XLOOKUP(Divisions!C33,'Project Managers'!C:C,'Project Managers'!AI:AI),0) -> 0 | AG33: =IFERROR(_xlfn.XLOOKUP(Divisions!C33,'Project Managers'!C:C,'Project Managers'!AJ:AJ),0) -> 0 | AH33: =IFERROR(_xlfn.XLOOKUP(Divisions!C33,'Project Managers'!C:C,'Project Managers'!AK:AK),0) -> 0 | AI33: =IFERROR(_xlfn.XLOOKUP(Divisions!C33,'Project Managers'!C:C,'Project Managers'!AL:AL),0) -> 0 | AJ33: =IFERROR(_xlfn.XLOOKUP(Divisions!C33,'Project Managers'!C:C,'Project Managers'!AM:AM),0) -> 0 | AK33: =IFERROR(_xlfn.XLOOKUP(Divisions!C33,'Project Managers'!C:C,'Project Managers'!AN:AN),0) -> 0 | AL33: 0.16 | AM33: 0.23 | AO33: =IFERROR(_xlfn.XLOOKUP(Divisions!C33,'Project Managers'!C:C,'Project Managers'!AR:AR),0) -> 0
B34: Central Texas Electrical Construction | C34: 722320 | D34: SPACEX DIRECT WORK | E34: 128026.07 | F34: =IFERROR(Divisions!E34*(1-Divisions!H34),0) -> 106193.44 | G34: =IFERROR(Divisions!E34-Divisions!F34,0) -> 21832.631 | H34: {=IF(ISBLANK(Divisions!AL34),Divisions!R34,Divisions!AL34)} -> 0.1705327 | I34: 124814.07 | J34: 103529.19 | K34: =IFERROR(Divisions!I34-Divisions!J34,0) -> 21284.88 | L34: =IFERROR(Divisions!K34/Divisions!I34,0) -> 0.1705327 | M34: 124814.07 | N34: =IFERROR(IF(Divisions!M34-Divisions!I34>0,Divisions!M34-Divisions!I34,0),0) -> 0 | O34: =IFERROR(IF(Divisions!M34-Divisions!I34<0,Divisions!M34-Divisions!I34,0),0) -> 0 | P34: =IFERROR(Divisions!E34-Divisions!I34,0) -> 3212 | Q34: =IFERROR(Divisions!I34/Divisions!E34,0) -> 0.97491136 | R34: =IFERROR(_xlfn.XLOOKUP(Divisions!C34,'Project Managers'!C:C,'Project Managers'!R:R),0) -> 0.1705327 | S34: =IFERROR(_xlfn.XLOOKUP(Divisions!C34,'Project Managers'!C:C,'Project Managers'!T:T),0) -> 0.15 | T34: =IFERROR(_xlfn.XLOOKUP(Divisions!C34,'Project Managers'!C:C,'Project Managers'!U:U),0) -> 0 | U34: =IFERROR(_xlfn.XLOOKUP(Divisions!C34,'Project Managers'!C:C,'Project Managers'!W:W),0) -> -3015.0229 | V34: =IFERROR(_xlfn.XLOOKUP(Divisions!C34,'Project Managers'!C:C,'Project Managers'!X:X),0) -> 1 | W34: =IFERROR(_xlfn.XLOOKUP(Divisions!C34,'Project Managers'!C:C,'Project Managers'!Z:Z),0) -> 1 | X34: =IFERROR(_xlfn.XLOOKUP(Divisions!C34,'Project Managers'!C:C,'Project Managers'!AA:AA),0) -> 3212 | Y34: =IFERROR(_xlfn.XLOOKUP(Divisions!C34,'Project Managers'!C:C,'Project Managers'!AB:AB),0) -> 2664.249 | Z34: =IFERROR(_xlfn.XLOOKUP(Divisions!C34,'Project Managers'!C:C,'Project Managers'!AC:AC),0) -> 547.75102 | AA34: =IFERROR(_xlfn.XLOOKUP(Divisions!C34,'Project Managers'!C:C,'Project Managers'!AD:AD),0) -> 0.1705327 | AB34: =IFERROR(_xlfn.XLOOKUP(Divisions!C34,'Project Managers'!C:C,'Project Managers'!AE:AE),0) -> 0 | AC34: =IFERROR(_xlfn.XLOOKUP(Divisions!C34,'Project Managers'!C:C,'Project Managers'!AF:AF),0) -> 0 | AD34: =IFERROR(_xlfn.XLOOKUP(Divisions!C34,'Project Managers'!C:C,'Project Managers'!AG:AG),0) -> 0 | AE34: =IFERROR(_xlfn.XLOOKUP(Divisions!C34,'Project Managers'!C:C,'Project Managers'!AH:AH),0) -> 0 | AF34: =IFERROR(_xlfn.XLOOKUP(Divisions!C34,'Project Managers'!C:C,'Project Managers'!AI:AI),0) -> 0 | AG34: =IFERROR(_xlfn.XLOOKUP(Divisions!C34,'Project Managers'!C:C,'Project Managers'!AJ:AJ),0) -> 0 | AH34: =IFERROR(_xlfn.XLOOKUP(Divisions!C34,'Project Managers'!C:C,'Project Managers'!AK:AK),0) -> 0 | AI34: =IFERROR(_xlfn.XLOOKUP(Divisions!C34,'Project Managers'!C:C,'Project Managers'!AL:AL),0) -> 0 | AJ34: =IFERROR(_xlfn.XLOOKUP(Divisions!C34,'Project Managers'!C:C,'Project Managers'!AM:AM),0) -> 0 | AK34: =IFERROR(_xlfn.XLOOKUP(Divisions!C34,'Project Managers'!C:C,'Project Managers'!AN:AN),0) -> 0 | AO34: =IFERROR(_xlfn.XLOOKUP(Divisions!C34,'Project Managers'!C:C,'Project Managers'!AR:AR),0) -> 0
B35: Central Texas Electrical Construction | C35: 722330 | D35: WILCO HQ | E35: 8047533.5 | F35: =IFERROR(Divisions!E35*(1-Divisions!H35),0) -> 6679452.8 | G35: =IFERROR(Divisions!E35-Divisions!F35,0) -> 1368080.7 | H35: {=IF(ISBLANK(Divisions!AL35),Divisions!R35,Divisions!AL35)} -> 0.17 | I35: 6563125 | J35: 5446576.6 | K35: =IFERROR(Divisions!I35-Divisions!J35,0) -> 1116548.3 | L35: =IFERROR(Divisions!K35/Divisions!I35,0) -> 0.1701245 | M35: 6409924.4 | N35: =IFERROR(IF(Divisions!M35-Divisions!I35>0,Divisions!M35-Divisions!I35,0),0) -> 0 | O35: =IFERROR(IF(Divisions!M35-Divisions!I35<0,Divisions!M35-Divisions!I35,0),0) -> -153200.51 | P35: =IFERROR(Divisions!E35-Divisions!I35,0) -> 1484408.5 | Q35: =IFERROR(Divisions!I35/Divisions!E35,0) -> 0.81554491 | R35: =IFERROR(_xlfn.XLOOKUP(Divisions!C35,'Project Managers'!C:C,'Project Managers'!R:R),0) -> 0.22 | S35: =IFERROR(_xlfn.XLOOKUP(Divisions!C35,'Project Managers'!C:C,'Project Managers'!T:T),0) -> 0.2 | T35: =IFERROR(_xlfn.XLOOKUP(Divisions!C35,'Project Managers'!C:C,'Project Managers'!U:U),0) -> 419665.6 | U35: =IFERROR(_xlfn.XLOOKUP(Divisions!C35,'Project Managers'!C:C,'Project Managers'!W:W),0) -> 245095.84 | V35: =IFERROR(_xlfn.XLOOKUP(Divisions!C35,'Project Managers'!C:C,'Project Managers'!X:X),0) -> 1 | W35: =IFERROR(_xlfn.XLOOKUP(Divisions!C35,'Project Managers'!C:C,'Project Managers'!Z:Z),0) -> 0.9 | X35: =IFERROR(_xlfn.XLOOKUP(Divisions!C35,'Project Managers'!C:C,'Project Managers'!AA:AA),0) -> 679655.19 | Y35: =IFERROR(_xlfn.XLOOKUP(Divisions!C35,'Project Managers'!C:C,'Project Managers'!AB:AB),0) -> 564029.19 | Z35: =IFERROR(_xlfn.XLOOKUP(Divisions!C35,'Project Managers'!C:C,'Project Managers'!AC:AC),0) -> 115626 | AA35: =IFERROR(_xlfn.XLOOKUP(Divisions!C35,'Project Managers'!C:C,'Project Managers'!AD:AD),0) -> 0.1701245 | AB35: =IFERROR(_xlfn.XLOOKUP(Divisions!C35,'Project Managers'!C:C,'Project Managers'!AE:AE),0) -> 1 | AC35: =IFERROR(_xlfn.XLOOKUP(Divisions!C35,'Project Managers'!C:C,'Project Managers'!AF:AF),0) -> 804753.35 | AD35: =IFERROR(_xlfn.XLOOKUP(Divisions!C35,'Project Managers'!C:C,'Project Managers'!AG:AG),0) -> 667845.09 | AE35: =IFERROR(_xlfn.XLOOKUP(Divisions!C35,'Project Managers'!C:C,'Project Managers'!AH:AH),0) -> 136908.26 | AF35: =IFERROR(_xlfn.XLOOKUP(Divisions!C35,'Project Managers'!C:C,'Project Managers'!AI:AI),0) -> 0.1701245 | AG35: =IFERROR(_xlfn.XLOOKUP(Divisions!C35,'Project Managers'!C:C,'Project Managers'!AJ:AJ),0) -> 0 | AH35: =IFERROR(_xlfn.XLOOKUP(Divisions!C35,'Project Managers'!C:C,'Project Managers'!AK:AK),0) -> 0 | AI35: =IFERROR(_xlfn.XLOOKUP(Divisions!C35,'Project Managers'!C:C,'Project Managers'!AL:AL),0) -> 0 | AJ35: =IFERROR(_xlfn.XLOOKUP(Divisions!C35,'Project Managers'!C:C,'Project Managers'!AM:AM),0) -> 0 | AK35: =IFERROR(_xlfn.XLOOKUP(Divisions!C35,'Project Managers'!C:C,'Project Managers'!AN:AN),0) -> 0 | AL35: 0.17 | AM35: 0.22 | AO35: =IFERROR(_xlfn.XLOOKUP(Divisions!C35,'Project Managers'!C:C,'Project Managers'!AR:AR),0) -> 0
B36: Central Texas Electrical Construction | C36: 722340 | D36: DEL VALLE LIBRARY | E36: 1188326 | F36: =IFERROR(Divisions!E36*(1-Divisions!H36),0) -> 986310.58 | G36: =IFERROR(Divisions!E36-Divisions!F36,0) -> 202015.42 | H36: {=IF(ISBLANK(Divisions!AL36),Divisions!R36,Divisions!AL36)} -> 0.17 | I36: 364066.55 | J36: 316579.52 | K36: =IFERROR(Divisions!I36-Divisions!J36,0) -> 47487.03 | L36: =IFERROR(Divisions!K36/Divisions!I36,0) -> 0.13043503 | M36: 259600 | N36: =IFERROR(IF(Divisions!M36-Divisions!I36>0,Divisions!M36-Divisions!I36,0),0) -> 0 | O36: =IFERROR(IF(Divisions!M36-Divisions!I36<0,Divisions!M36-Divisions!I36,0),0) -> -104466.55 | P36: =IFERROR(Divisions!E36-Divisions!I36,0) -> 824259.45 | Q36: =IFERROR(Divisions!I36/Divisions!E36,0) -> 0.30636925 | R36: =IFERROR(_xlfn.XLOOKUP(Divisions!C36,'Project Managers'!C:C,'Project Managers'!R:R),0) -> 0.18 | S36: =IFERROR(_xlfn.XLOOKUP(Divisions!C36,'Project Managers'!C:C,'Project Managers'!T:T),0) -> 0.13 | T36: =IFERROR(_xlfn.XLOOKUP(Divisions!C36,'Project Managers'!C:C,'Project Managers'!U:U),0) -> 22006.035 | U36: =IFERROR(_xlfn.XLOOKUP(Divisions!C36,'Project Managers'!C:C,'Project Managers'!W:W),0) -> -182.04425 | V36: =IFERROR(_xlfn.XLOOKUP(Divisions!C36,'Project Managers'!C:C,'Project Managers'!X:X),0) -> 1 | W36: =IFERROR(_xlfn.XLOOKUP(Divisions!C36,'Project Managers'!C:C,'Project Managers'!Z:Z),0) -> 0.3 | X36: =IFERROR(_xlfn.XLOOKUP(Divisions!C36,'Project Managers'!C:C,'Project Managers'!AA:AA),0) -> -7568.75 | Y36: =IFERROR(_xlfn.XLOOKUP(Divisions!C36,'Project Managers'!C:C,'Project Managers'!AB:AB),0) -> -6581.5199 | Z36: =IFERROR(_xlfn.XLOOKUP(Divisions!C36,'Project Managers'!C:C,'Project Managers'!AC:AC),0) -> -987.2301 | AA36: =IFERROR(_xlfn.XLOOKUP(Divisions!C36,'Project Managers'!C:C,'Project Managers'!AD:AD),0) -> 0.13043503 | AB36: =IFERROR(_xlfn.XLOOKUP(Divisions!C36,'Project Managers'!C:C,'Project Managers'!AE:AE),0) -> 1 | AC36: =IFERROR(_xlfn.XLOOKUP(Divisions!C36,'Project Managers'!C:C,'Project Managers'!AF:AF),0) -> 831828.2 | AD36: =IFERROR(_xlfn.XLOOKUP(Divisions!C36,'Project Managers'!C:C,'Project Managers'!AG:AG),0) -> 723328.67 | AE36: =IFERROR(_xlfn.XLOOKUP(Divisions!C36,'Project Managers'!C:C,'Project Managers'!AH:AH),0) -> 108499.53 | AF36: =IFERROR(_xlfn.XLOOKUP(Divisions!C36,'Project Managers'!C:C,'Project Managers'!AI:AI),0) -> 0.13043503 | AG36: =IFERROR(_xlfn.XLOOKUP(Divisions!C36,'Project Managers'!C:C,'Project Managers'!AJ:AJ),0) -> 0 | AH36: =IFERROR(_xlfn.XLOOKUP(Divisions!C36,'Project Managers'!C:C,'Project Managers'!AK:AK),0) -> 0 | AI36: =IFERROR(_xlfn.XLOOKUP(Divisions!C36,'Project Managers'!C:C,'Project Managers'!AL:AL),0) -> 0 | AJ36: =IFERROR(_xlfn.XLOOKUP(Divisions!C36,'Project Managers'!C:C,'Project Managers'!AM:AM),0) -> 0 | AK36: =IFERROR(_xlfn.XLOOKUP(Divisions!C36,'Project Managers'!C:C,'Project Managers'!AN:AN),0) -> 0 | AL36: 0.17 | AM36: 0.18 | AO36: =IFERROR(_xlfn.XLOOKUP(Divisions!C36,'Project Managers'!C:C,'Project Managers'!AR:AR),0) -> 0
B37: Central Texas Electrical Construction | C37: 722400 | D37: WILCO JUVENILE JUSTICE | E37: 10936332 | F37: =IFERROR(Divisions!E37*(1-Divisions!H37),0) -> 8858428.7 | G37: =IFERROR(Divisions!E37-Divisions!F37,0) -> 2077903 | H37: {=IF(ISBLANK(Divisions!AL37),Divisions!R37,Divisions!AL37)} -> 0.19 | I37: 2811002.6 | J37: 2342502.2 | K37: =IFERROR(Divisions!I37-Divisions!J37,0) -> 468500.46 | L37: =IFERROR(Divisions!K37/Divisions!I37,0) -> 0.16666667 | M37: 3561220.1 | N37: =IFERROR(IF(Divisions!M37-Divisions!I37>0,Divisions!M37-Divisions!I37,0),0) -> 750217.48 | O37: =IFERROR(IF(Divisions!M37-Divisions!I37<0,Divisions!M37-Divisions!I37,0),0) -> 0 | P37: =IFERROR(Divisions!E37-Divisions!I37,0) -> 8125329.1 | Q37: =IFERROR(Divisions!I37/Divisions!E37,0) -> 0.25703341 | R37: =IFERROR(_xlfn.XLOOKUP(Divisions!C37,'Project Managers'!C:C,'Project Managers'!R:R),0) -> 0.18 | S37: =IFERROR(_xlfn.XLOOKUP(Divisions!C37,'Project Managers'!C:C,'Project Managers'!T:T),0) -> 0.18 | T37: =IFERROR(_xlfn.XLOOKUP(Divisions!C37,'Project Managers'!C:C,'Project Managers'!U:U),0) -> 45707.338 | U37: =IFERROR(_xlfn.XLOOKUP(Divisions!C37,'Project Managers'!C:C,'Project Managers'!W:W),0) -> 45707.338 | V37: =IFERROR(_xlfn.XLOOKUP(Divisions!C37,'Project Managers'!C:C,'Project Managers'!X:X),0) -> 1 | W37: =IFERROR(_xlfn.XLOOKUP(Divisions!C37,'Project Managers'!C:C,'Project Managers'!Z:Z),0) -> 0.26 | X37: =IFERROR(_xlfn.XLOOKUP(Divisions!C37,'Project Managers'!C:C,'Project Managers'!AA:AA),0) -> 32443.6 | Y37: =IFERROR(_xlfn.XLOOKUP(Divisions!C37,'Project Managers'!C:C,'Project Managers'!AB:AB),0) -> 27036.333 | Z37: =IFERROR(_xlfn.XLOOKUP(Divisions!C37,'Project Managers'!C:C,'Project Managers'!AC:AC),0) -> 5407.2668 | AA37: =IFERROR(_xlfn.XLOOKUP(Divisions!C37,'Project Managers'!C:C,'Project Managers'!AD:AD),0) -> 0.16666667 | AB37: =IFERROR(_xlfn.XLOOKUP(Divisions!C37,'Project Managers'!C:C,'Project Managers'!AE:AE),0) -> 1 | AC37: =IFERROR(_xlfn.XLOOKUP(Divisions!C37,'Project Managers'!C:C,'Project Managers'!AF:AF),0) -> 8092885.5 | AD37: =IFERROR(_xlfn.XLOOKUP(Divisions!C37,'Project Managers'!C:C,'Project Managers'!AG:AG),0) -> 6744071.2 | AE37: =IFERROR(_xlfn.XLOOKUP(Divisions!C37,'Project Managers'!C:C,'Project Managers'!AH:AH),0) -> 1348814.3 | AF37: =IFERROR(_xlfn.XLOOKUP(Divisions!C37,'Project Managers'!C:C,'Project Managers'!AI:AI),0) -> 0.16666667 | AG37: =IFERROR(_xlfn.XLOOKUP(Divisions!C37,'Project Managers'!C:C,'Project Managers'!AJ:AJ),0) -> 1 | AH37: =IFERROR(_xlfn.XLOOKUP(Divisions!C37,'Project Managers'!C:C,'Project Managers'!AK:AK),0) -> 0 | AI37: =IFERROR(_xlfn.XLOOKUP(Divisions!C37,'Project Managers'!C:C,'Project Managers'!AL:AL),0) -> 0 | AJ37: =IFERROR(_xlfn.XLOOKUP(Divisions!C37,'Project Managers'!C:C,'Project Managers'!AM:AM),0) -> 0 | AK37: =IFERROR(_xlfn.XLOOKUP(Divisions!C37,'Project Managers'!C:C,'Project Managers'!AN:AN),0) -> 0 | AL37: 0.19 | AM37: 0.18 | AO37: =IFERROR(_xlfn.XLOOKUP(Divisions!C37,'Project Managers'!C:C,'Project Managers'!AR:AR),0) -> 0
B38: Central Texas Electrical Construction | C38: 722420 | D38: UT MAIN BLDG RESTORATION | E38: 3751721 | F38: =IFERROR(Divisions!E38*(1-Divisions!H38),0) -> 3100595.9 | G38: =IFERROR(Divisions!E38-Divisions!F38,0) -> 651125.11 | H38: {=IF(ISBLANK(Divisions!AL38),Divisions!R38,Divisions!AL38)} -> 0.17355371 | I38: 1327737.1 | J38: 1097303.4 | K38: =IFERROR(Divisions!I38-Divisions!J38,0) -> 230433.7 | L38: =IFERROR(Divisions!K38/Divisions!I38,0) -> 0.17355371 | M38: 1172929 | N38: =IFERROR(IF(Divisions!M38-Divisions!I38>0,Divisions!M38-Divisions!I38,0),0) -> 0 | O38: =IFERROR(IF(Divisions!M38-Divisions!I38<0,Divisions!M38-Divisions!I38,0),0) -> -154808.07 | P38: =IFERROR(Divisions!E38-Divisions!I38,0) -> 2423983.9 | Q38: =IFERROR(Divisions!I38/Divisions!E38,0) -> 0.3539008 | R38: =IFERROR(_xlfn.XLOOKUP(Divisions!C38,'Project Managers'!C:C,'Project Managers'!R:R),0) -> 0.17355371 | S38: =IFERROR(_xlfn.XLOOKUP(Divisions!C38,'Project Managers'!C:C,'Project Managers'!T:T),0) -> 0.17 | T38: =IFERROR(_xlfn.XLOOKUP(Divisions!C38,'Project Managers'!C:C,'Project Managers'!U:U),0) -> 0 | U38: =IFERROR(_xlfn.XLOOKUP(Divisions!C38,'Project Managers'!C:C,'Project Managers'!W:W),0) -> -5684.817 | V38: =IFERROR(_xlfn.XLOOKUP(Divisions!C38,'Project Managers'!C:C,'Project Managers'!X:X),0) -> 1 | W38: =IFERROR(_xlfn.XLOOKUP(Divisions!C38,'Project Managers'!C:C,'Project Managers'!Z:Z),0) -> 0.4 | X38: =IFERROR(_xlfn.XLOOKUP(Divisions!C38,'Project Managers'!C:C,'Project Managers'!AA:AA),0) -> 172951.33 | Y38: =IFERROR(_xlfn.XLOOKUP(Divisions!C38,'Project Managers'!C:C,'Project Managers'!AB:AB),0) -> 142934.98 | Z38: =IFERROR(_xlfn.XLOOKUP(Divisions!C38,'Project Managers'!C:C,'Project Managers'!AC:AC),0) -> 30016.346 | AA38: =IFERROR(_xlfn.XLOOKUP(Divisions!C38,'Project Managers'!C:C,'Project Managers'!AD:AD),0) -> 0.17355371 | AB38: =IFERROR(_xlfn.XLOOKUP(Divisions!C38,'Project Managers'!C:C,'Project Managers'!AE:AE),0) -> 1 | AC38: =IFERROR(_xlfn.XLOOKUP(Divisions!C38,'Project Managers'!C:C,'Project Managers'!AF:AF),0) -> 2251032.6 | AD38: =IFERROR(_xlfn.XLOOKUP(Divisions!C38,'Project Managers'!C:C,'Project Managers'!AG:AG),0) -> 1860357.5 | AE38: =IFERROR(_xlfn.XLOOKUP(Divisions!C38,'Project Managers'!C:C,'Project Managers'!AH:AH),0) -> 390675.07 | AF38: =IFERROR(_xlfn.XLOOKUP(Divisions!C38,'Project Managers'!C:C,'Project Managers'!AI:AI),0) -> 0.17355371 | AG38: =IFERROR(_xlfn.XLOOKUP(Divisions!C38,'Project Managers'!C:C,'Project Managers'!AJ:AJ),0) -> 0 | AH38: =IFERROR(_xlfn.XLOOKUP(Divisions!C38,'Project Managers'!C:C,'Project Managers'!AK:AK),0) -> 0 | AI38: =IFERROR(_xlfn.XLOOKUP(Divisions!C38,'Project Managers'!C:C,'Project Managers'!AL:AL),0) -> 0 | AJ38: =IFERROR(_xlfn.XLOOKUP(Divisions!C38,'Project Managers'!C:C,'Project Managers'!AM:AM),0) -> 0 | AK38: =IFERROR(_xlfn.XLOOKUP(Divisions!C38,'Project Managers'!C:C,'Project Managers'!AN:AN),0) -> 0 | AO38: =IFERROR(_xlfn.XLOOKUP(Divisions!C38,'Project Managers'!C:C,'Project Managers'!AR:AR),0) -> 0
B39: Central Texas Electrical Construction | C39: 722450 | D39: VALERO AUSTIN PAC OFFICE | E39: 404338.1 | F39: =IFERROR(Divisions!E39*(1-Divisions!H39),0) -> 337510.95 | G39: =IFERROR(Divisions!E39-Divisions!F39,0) -> 66827.152 | H39: {=IF(ISBLANK(Divisions!AL39),Divisions!R39,Divisions!AL39)} -> 0.16527543 | I39: 395116.39 | J39: 329813.36 | K39: =IFERROR(Divisions!I39-Divisions!J39,0) -> 65303.03 | L39: =IFERROR(Divisions!K39/Divisions!I39,0) -> 0.16527543 | M39: 404338.1 | N39: =IFERROR(IF(Divisions!M39-Divisions!I39>0,Divisions!M39-Divisions!I39,0),0) -> 9221.71 | O39: =IFERROR(IF(Divisions!M39-Divisions!I39<0,Divisions!M39-Divisions!I39,0),0) -> 0 | P39: =IFERROR(Divisions!E39-Divisions!I39,0) -> 9221.71 | Q39: =IFERROR(Divisions!I39/Divisions!E39,0) -> 0.97719307 | R39: =IFERROR(_xlfn.XLOOKUP(Divisions!C39,'Project Managers'!C:C,'Project Managers'!R:R),0) -> 0.16527543 | S39: =IFERROR(_xlfn.XLOOKUP(Divisions!C39,'Project Managers'!C:C,'Project Managers'!T:T),0) -> 0.17 | T39: =IFERROR(_xlfn.XLOOKUP(Divisions!C39,'Project Managers'!C:C,'Project Managers'!U:U),0) -> 0 | U39: =IFERROR(_xlfn.XLOOKUP(Divisions!C39,'Project Managers'!C:C,'Project Managers'!W:W),0) -> 2249.104 | V39: =IFERROR(_xlfn.XLOOKUP(Divisions!C39,'Project Managers'!C:C,'Project Managers'!X:X),0) -> 1 | W39: =IFERROR(_xlfn.XLOOKUP(Divisions!C39,'Project Managers'!C:C,'Project Managers'!Z:Z),0) -> 1 | X39: =IFERROR(_xlfn.XLOOKUP(Divisions!C39,'Project Managers'!C:C,'Project Managers'!AA:AA),0) -> 9221.71 | Y39: =IFERROR(_xlfn.XLOOKUP(Divisions!C39,'Project Managers'!C:C,'Project Managers'!AB:AB),0) -> 7697.5879 | Z39: =IFERROR(_xlfn.XLOOKUP(Divisions!C39,'Project Managers'!C:C,'Project Managers'!AC:AC),0) -> 1524.1221 | AA39: =IFERROR(_xlfn.XLOOKUP(Divisions!C39,'Project Managers'!C:C,'Project Managers'!AD:AD),0) -> 0.16527543 | AB39: =IFERROR(_xlfn.XLOOKUP(Divisions!C39,'Project Managers'!C:C,'Project Managers'!AE:AE),0) -> 0 | AC39: =IFERROR(_xlfn.XLOOKUP(Divisions!C39,'Project Managers'!C:C,'Project Managers'!AF:AF),0) -> 0 | AD39: =IFERROR(_xlfn.XLOOKUP(Divisions!C39,'Project Managers'!C:C,'Project Managers'!AG:AG),0) -> 0 | AE39: =IFERROR(_xlfn.XLOOKUP(Divisions!C39,'Project Managers'!C:C,'Project Managers'!AH:AH),0) -> 0 | AF39: =IFERROR(_xlfn.XLOOKUP(Divisions!C39,'Project Managers'!C:C,'Project Managers'!AI:AI),0) -> 0 | AG39: =IFERROR(_xlfn.XLOOKUP(Divisions!C39,'Project Managers'!C:C,'Project Managers'!AJ:AJ),0) -> 0 | AH39: =IFERROR(_xlfn.XLOOKUP(Divisions!C39,'Project Managers'!C:C,'Project Managers'!AK:AK),0) -> 0 | AI39: =IFERROR(_xlfn.XLOOKUP(Divisions!C39,'Project Managers'!C:C,'Project Managers'!AL:AL),0) -> 0 | AJ39: =IFERROR(_xlfn.XLOOKUP(Divisions!C39,'Project Managers'!C:C,'Project Managers'!AM:AM),0) -> 0 | AK39: =IFERROR(_xlfn.XLOOKUP(Divisions!C39,'Project Managers'!C:C,'Project Managers'!AN:AN),0) -> 0 | AO39: =IFERROR(_xlfn.XLOOKUP(Divisions!C39,'Project Managers'!C:C,'Project Managers'!AR:AR),0) -> 0
